Workbook

Sheet Start Here
A1: START HERE · WHICH TAB DO I NEED?
A2: Every tab has its own blue input cells at the top. Cycle 0 = opening corpus. Calculation rows are tucked away at the bottom of the two main tabs ([+] in the left margin). Click a tab name to jump.
A4: I WANT TO…
A5: Go to | B5: Question it answers | C5: Tax basis
A6: MCX Company vs Personal | B6: Trading MCX gas futures: personally vs a 25.168% company vs company with 1, 2, 3, 4, 5 or 6 family members on payroll — every cycle, in one table | C6: Company 25.168% vs personal slabs
A7: Shipping Engine | B7: (Separate business) BDRY ETF → freight futures under four tax setups, with a ledger of the case you pick | C7: 0% · 25.168% · 31–39%
A8: NG Scenarios | B8: Bull / base / bear paths for MCX natural gas at three starting sizes | C8: Company 25.168%
A9: NG GIFT Bridge | B9: Stay on MCX, switch to GIFT, or run both? | C9: Company 25.168%
A10: NG Risk and Sizing | B10: What do rolls, margin hikes and Kelly sizing do to natural-gas returns? | C10: Company 25.168%
A11: NG Inputs | B11: Shared natural-gas assumptions plus the personal slab tables | C11: —
A12: NG Data | B12: The 123 price legs behind the margin assumptions | C12: —
A13: US ETF Engine | B13: (Separate business) leveraged US ETFs through INDmoney → IBKR | C13: Personal 31–39%
A15: COLOUR CODE
A16: Blue on cream = edit me
A17: Green on mint = linked from another tab — change it at the source
A18: Blue on light-blue = derived
A19: Green bold = result
A21: WHAT CHANGED IN THIS VERSION
A22: 1. MCX tab: one column (and one engine ledger) for every payroll size — Personal, Company, Company + 1 member … + 6 members — so you no longer have to guess how many people are on payroll. The members control is gone.
A23: 2. The ledger dropdown now picks any of those 8 routes; key results list all 8 with the cycle where each overtakes personal.
A24: 3. The members × recycle-ratio grid is kept for the ratio question.

Sheet MCX Company vs Personal
A1: MCX NATURAL-GAS FUTURES · YOU PERSONALLY vs YOUR COMPANY (25.168%) vs COMPANY + 1 … 6 FAMILY MEMBERS ON PAYROLL
A2: Business income from MCX futures (CTT charged ⇒ non-speculative). Change the blue cells; every table reprices. Cycle 0 = opening. The calculation engine is tucked away at the bottom ([+] in the left margin). Money stays in the company.
A4: CONTROLS — this sheet only | U4: Route list
A5: Starting capital (₹ Cr) | B5: 0.6 | C5: Opening trading capital | U5: Personal
A6: Gross return per cycle (on deployed capital) | B6: 1 | C6: Change 100% → 75% and everything reprices | U6: Company
A7: Cycle length (months) | B7: 18 | C7: Spreads each cycle's profit over financial years for personal slab tax | U7: Company + 1 member
A8: Company tax rate (22% + 10% surcharge + 4% cess) | B8: 0.25168 | C8: 0% shows a tax-holiday case | U8: Company + 2 members
A9: Company running cost per cycle (₹ Cr) | B9: 0.05 | C9: Your estimate ≈ ₹5L (statutory audit by a CA is part of it) | U9: Company + 3 members
A10: Personal route running cost per cycle (₹ Cr) | B10: 0 | C10: Laptop + internet ≈ 0 | U10: Company + 4 members
A11: Recycle ratio r (share of salary lent back) | B11: 1 | C11: Rest is spent by the family; the grid below shows the effect | U11: Company + 5 members
A12: Per-person salary cap per YEAR (₹ Cr) | B12: 0.12 | C12: ₹12L/yr — inside the s.87A rebate (assumes no other income) | U12: Company + 6 members
A13: Total salary cap (% of cycle profit) | B13: 0.4 | C13: s.40A(2) prudence limit, not a statutory number
A14: Route shown in the cycle ledger | B14: Company + 3 members | C14: =MATCH(B14,$U$5:$U$12,0) | D14: ◄ route number (1–8)
A15: Deployable-capital ceiling (₹ Cr) | B15: ='NG Inputs'!B9/10000000*'NG Data'!D134 | C15: MCX liquidity ceiling × margin; excess earns the idle yield
A16: Idle-capital yield (liquid fund) | B16: ='NG Inputs'!B10 | C16: From NG Inputs
A17: Salary cap per person per cycle (₹ Cr) | B17: =B12*B7/12 | C17: annual cap × cycle months ÷ 12
A19: KEY RESULTS — corpus at the end of cycle 5, 10 and 20 (₹ Cr), one row per payroll size
A20: Route | B20: After cycle 5 | C20: After cycle 10 | D20: After cycle 20 | E20: Overtakes personal from cycle | F20: Extra vs plain company (cycle 20)
A21: Personal | B21: =INDEX(B33:B53,6) | C21: =INDEX(B33:B53,11) | D21: =INDEX(B33:B53,21) | E21: — | F21: —
A22: Company | B22: =INDEX(C33:C53,6) | C22: =INDEX(C33:C53,11) | D22: =INDEX(C33:C53,21) | E22: =IFERROR(MATCH(1,M33:M53,0)-1,"not within 20") | F22: =D22-$D$22
A23: Company + 1 member | B23: =INDEX(D33:D53,6) | C23: =INDEX(D33:D53,11) | D23: =INDEX(D33:D53,21) | E23: =IFERROR(MATCH(1,N33:N53,0)-1,"not within 20") | F23: =D23-$D$22
A24: Company + 2 members | B24: =INDEX(E33:E53,6) | C24: =INDEX(E33:E53,11) | D24: =INDEX(E33:E53,21) | E24: =IFERROR(MATCH(1,O33:O53,0)-1,"not within 20") | F24: =D24-$D$22
A25: Company + 3 members | B25: =INDEX(F33:F53,6) | C25: =INDEX(F33:F53,11) | D25: =INDEX(F33:F53,21) | E25: =IFERROR(MATCH(1,P33:P53,0)-1,"not within 20") | F25: =D25-$D$22
A26: Company + 4 members | B26: =INDEX(G33:G53,6) | C26: =INDEX(G33:G53,11) | D26: =INDEX(G33:G53,21) | E26: =IFERROR(MATCH(1,Q33:Q53,0)-1,"not within 20") | F26: =D26-$D$22
A27: Company + 5 members | B27: =INDEX(H33:H53,6) | C27: =INDEX(H33:H53,11) | D27: =INDEX(H33:H53,21) | E27: =IFERROR(MATCH(1,R33:R53,0)-1,"not within 20") | F27: =D27-$D$22
A28: Company + 6 members | B28: =INDEX(I33:I53,6) | C28: =INDEX(I33:I53,11) | D28: =INDEX(I33:I53,21) | E28: =IFERROR(MATCH(1,S33:S53,0)-1,"not within 20") | F28: =D28-$D$22
A31: EVERY CYCLE — corpus at the end of each cycle (₹ Cr), one column per payroll size; cycle 0 = opening; best route highlighted
A32: Cycle | B32: Personal | C32: Company | D32: Company + 1 member | E32: Company + 2 members | F32: Company + 3 members | G32: Company + 4 members | H32: Company + 5 members | I32: Company + 6 members | J32: Best route | K32: Company vs personal | L32: Best payroll adds vs company | M32: Co>P? | N32: +1>P? | O32: +2>P? | P32: +3>P? | Q32: +4>P? | R32: +5>P? | S32: +6>P?
A33: 0 | B33: =$B$5 | C33: =$B$5 | D33: =$B$5 | E33: =$B$5 | F33: =$B$5 | G33: =$B$5 | H33: =$B$5 | I33: =$B$5 | J33: =IF(A33=0,"—",INDEX($B$32:$I$32,MATCH(MAX(B33:I33),B33:I33,0))) | K33: =C33-B33 | L33: =MAX(D33:I33)-C33 | M33: =IF(AND($A33>0,C33>$B33),1,0) | N33: =IF(AND($A33>0,D33>$B33),1,0) | O33: =IF(AND($A33>0,E33>$B33),1,0) | P33: =IF(AND($A33>0,F33>$B33),1,0) | Q33: =IF(AND($A33>0,G33>$B33),1,0) | R33: =IF(AND($A33>0,H33>$B33),1,0) | S33: =IF(AND($A33>0,I33>$B33),1,0)
A34: 1 | B34: =K111 | C34: =K136 | D34: =K161 | E34: =K186 | F34: =K211 | G34: =K236 | H34: =K261 | I34: =K286 | J34: =IF(A34=0,"—",INDEX($B$32:$I$32,MATCH(MAX(B34:I34),B34:I34,0))) | K34: =C34-B34 | L34: =MAX(D34:I34)-C34 | M34: =IF(AND($A34>0,C34>$B34),1,0) | N34: =IF(AND($A34>0,D34>$B34),1,0) | O34: =IF(AND($A34>0,E34>$B34),1,0) | P34: =IF(AND($A34>0,F34>$B34),1,0) | Q34: =IF(AND($A34>0,G34>$B34),1,0) | R34: =IF(AND($A34>0,H34>$B34),1,0) | S34: =IF(AND($A34>0,I34>$B34),1,0)
A35: 2 | B35: =K112 | C35: =K137 | D35: =K162 | E35: =K187 | F35: =K212 | G35: =K237 | H35: =K262 | I35: =K287 | J35: =IF(A35=0,"—",INDEX($B$32:$I$32,MATCH(MAX(B35:I35),B35:I35,0))) | K35: =C35-B35 | L35: =MAX(D35:I35)-C35 | M35: =IF(AND($A35>0,C35>$B35),1,0) | N35: =IF(AND($A35>0,D35>$B35),1,0) | O35: =IF(AND($A35>0,E35>$B35),1,0) | P35: =IF(AND($A35>0,F35>$B35),1,0) | Q35: =IF(AND($A35>0,G35>$B35),1,0) | R35: =IF(AND($A35>0,H35>$B35),1,0) | S35: =IF(AND($A35>0,I35>$B35),1,0)
A36: 3 | B36: =K113 | C36: =K138 | D36: =K163 | E36: =K188 | F36: =K213 | G36: =K238 | H36: =K263 | I36: =K288 | J36: =IF(A36=0,"—",INDEX($B$32:$I$32,MATCH(MAX(B36:I36),B36:I36,0))) | K36: =C36-B36 | L36: =MAX(D36:I36)-C36 | M36: =IF(AND($A36>0,C36>$B36),1,0) | N36: =IF(AND($A36>0,D36>$B36),1,0) | O36: =IF(AND($A36>0,E36>$B36),1,0) | P36: =IF(AND($A36>0,F36>$B36),1,0) | Q36: =IF(AND($A36>0,G36>$B36),1,0) | R36: =IF(AND($A36>0,H36>$B36),1,0) | S36: =IF(AND($A36>0,I36>$B36),1,0)
A37: 4 | B37: =K114 | C37: =K139 | D37: =K164 | E37: =K189 | F37: =K214 | G37: =K239 | H37: =K264 | I37: =K289 | J37: =IF(A37=0,"—",INDEX($B$32:$I$32,MATCH(MAX(B37:I37),B37:I37,0))) | K37: =C37-B37 | L37: =MAX(D37:I37)-C37 | M37: =IF(AND($A37>0,C37>$B37),1,0) | N37: =IF(AND($A37>0,D37>$B37),1,0) | O37: =IF(AND($A37>0,E37>$B37),1,0) | P37: =IF(AND($A37>0,F37>$B37),1,0) | Q37: =IF(AND($A37>0,G37>$B37),1,0) | R37: =IF(AND($A37>0,H37>$B37),1,0) | S37: =IF(AND($A37>0,I37>$B37),1,0)
A38: 5 | B38: =K115 | C38: =K140 | D38: =K165 | E38: =K190 | F38: =K215 | G38: =K240 | H38: =K265 | I38: =K290 | J38: =IF(A38=0,"—",INDEX($B$32:$I$32,MATCH(MAX(B38:I38),B38:I38,0))) | K38: =C38-B38 | L38: =MAX(D38:I38)-C38 | M38: =IF(AND($A38>0,C38>$B38),1,0) | N38: =IF(AND($A38>0,D38>$B38),1,0) | O38: =IF(AND($A38>0,E38>$B38),1,0) | P38: =IF(AND($A38>0,F38>$B38),1,0) | Q38: =IF(AND($A38>0,G38>$B38),1,0) | R38: =IF(AND($A38>0,H38>$B38),1,0) | S38: =IF(AND($A38>0,I38>$B38),1,0)
A39: 6 | B39: =K116 | C39: =K141 | D39: =K166 | E39: =K191 | F39: =K216 | G39: =K241 | H39: =K266 | I39: =K291 | J39: =IF(A39=0,"—",INDEX($B$32:$I$32,MATCH(MAX(B39:I39),B39:I39,0))) | K39: =C39-B39 | L39: =MAX(D39:I39)-C39 | M39: =IF(AND($A39>0,C39>$B39),1,0) | N39: =IF(AND($A39>0,D39>$B39),1,0) | O39: =IF(AND($A39>0,E39>$B39),1,0) | P39: =IF(AND($A39>0,F39>$B39),1,0) | Q39: =IF(AND($A39>0,G39>$B39),1,0) | R39: =IF(AND($A39>0,H39>$B39),1,0) | S39: =IF(AND($A39>0,I39>$B39),1,0)
A40: 7 | B40: =K117 | C40: =K142 | D40: =K167 | E40: =K192 | F40: =K217 | G40: =K242 | H40: =K267 | I40: =K292 | J40: =IF(A40=0,"—",INDEX($B$32:$I$32,MATCH(MAX(B40:I40),B40:I40,0))) | K40: =C40-B40 | L40: =MAX(D40:I40)-C40 | M40: =IF(AND($A40>0,C40>$B40),1,0) | N40: =IF(AND($A40>0,D40>$B40),1,0) | O40: =IF(AND($A40>0,E40>$B40),1,0) | P40: =IF(AND($A40>0,F40>$B40),1,0) | Q40: =IF(AND($A40>0,G40>$B40),1,0) | R40: =IF(AND($A40>0,H40>$B40),1,0) | S40: =IF(AND($A40>0,I40>$B40),1,0)
A41: 8 | B41: =K118 | C41: =K143 | D41: =K168 | E41: =K193 | F41: =K218 | G41: =K243 | H41: =K268 | I41: =K293 | J41: =IF(A41=0,"—",INDEX($B$32:$I$32,MATCH(MAX(B41:I41),B41:I41,0))) | K41: =C41-B41 | L41: =MAX(D41:I41)-C41 | M41: =IF(AND($A41>0,C41>$B41),1,0) | N41: =IF(AND($A41>0,D41>$B41),1,0) | O41: =IF(AND($A41>0,E41>$B41),1,0) | P41: =IF(AND($A41>0,F41>$B41),1,0) | Q41: =IF(AND($A41>0,G41>$B41),1,0) | R41: =IF(AND($A41>0,H41>$B41),1,0) | S41: =IF(AND($A41>0,I41>$B41),1,0)
A42: 9 | B42: =K119 | C42: =K144 | D42: =K169 | E42: =K194 | F42: =K219 | G42: =K244 | H42: =K269 | I42: =K294 | J42: =IF(A42=0,"—",INDEX($B$32:$I$32,MATCH(MAX(B42:I42),B42:I42,0))) | K42: =C42-B42 | L42: =MAX(D42:I42)-C42 | M42: =IF(AND($A42>0,C42>$B42),1,0) | N42: =IF(AND($A42>0,D42>$B42),1,0) | O42: =IF(AND($A42>0,E42>$B42),1,0) | P42: =IF(AND($A42>0,F42>$B42),1,0) | Q42: =IF(AND($A42>0,G42>$B42),1,0) | R42: =IF(AND($A42>0,H42>$B42),1,0) | S42: =IF(AND($A42>0,I42>$B42),1,0)
A43: 10 | B43: =K120 | C43: =K145 | D43: =K170 | E43: =K195 | F43: =K220 | G43: =K245 | H43: =K270 | I43: =K295 | J43: =IF(A43=0,"—",INDEX($B$32:$I$32,MATCH(MAX(B43:I43),B43:I43,0))) | K43: =C43-B43 | L43: =MAX(D43:I43)-C43 | M43: =IF(AND($A43>0,C43>$B43),1,0) | N43: =IF(AND($A43>0,D43>$B43),1,0) | O43: =IF(AND($A43>0,E43>$B43),1,0) | P43: =IF(AND($A43>0,F43>$B43),1,0) | Q43: =IF(AND($A43>0,G43>$B43),1,0) | R43: =IF(AND($A43>0,H43>$B43),1,0) | S43: =IF(AND($A43>0,I43>$B43),1,0)
A44: 11 | B44: =K121 | C44: =K146 | D44: =K171 | E44: =K196 | F44: =K221 | G44: =K246 | H44: =K271 | I44: =K296 | J44: =IF(A44=0,"—",INDEX($B$32:$I$32,MATCH(MAX(B44:I44),B44:I44,0))) | K44: =C44-B44 | L44: =MAX(D44:I44)-C44 | M44: =IF(AND($A44>0,C44>$B44),1,0) | N44: =IF(AND($A44>0,D44>$B44),1,0) | O44: =IF(AND($A44>0,E44>$B44),1,0) | P44: =IF(AND($A44>0,F44>$B44),1,0) | Q44: =IF(AND($A44>0,G44>$B44),1,0) | R44: =IF(AND($A44>0,H44>$B44),1,0) | S44: =IF(AND($A44>0,I44>$B44),1,0)
A45: 12 | B45: =K122 | C45: =K147 | D45: =K172 | E45: =K197 | F45: =K222 | G45: =K247 | H45: =K272 | I45: =K297 | J45: =IF(A45=0,"—",INDEX($B$32:$I$32,MATCH(MAX(B45:I45),B45:I45,0))) | K45: =C45-B45 | L45: =MAX(D45:I45)-C45 | M45: =IF(AND($A45>0,C45>$B45),1,0) | N45: =IF(AND($A45>0,D45>$B45),1,0) | O45: =IF(AND($A45>0,E45>$B45),1,0) | P45: =IF(AND($A45>0,F45>$B45),1,0) | Q45: =IF(AND($A45>0,G45>$B45),1,0) | R45: =IF(AND($A45>0,H45>$B45),1,0) | S45: =IF(AND($A45>0,I45>$B45),1,0)
... A53: 20 | B53: =K130 | C53: =K155 | D53: =K180 | E53: =K205 | F53: =K230 | G53: =K255 | H53: =K280 | I53: =K305 | J53: =IF(A53=0,"—",INDEX($B$32:$I$32,MATCH(MAX(B53:I53),B53:I53,0))) | K53: =C53-B53 | L53: =MAX(D53:I53)-C53 | M53: =IF(AND($A53>0,C53>$B53),1,0) | N53: =IF(AND($A53>0,D53>$B53),1,0) | O53: =IF(AND($A53>0,E53>$B53),1,0) | P53: =IF(AND($A53>0,F53>$B53),1,0) | Q53: =IF(AND($A53>0,G53>$B53),1,0) | R53: =IF(AND($A53>0,H53>$B53),1,0) | S53: =IF(AND($A53>0,I53>$B53),1,0)
A55: CYCLE LEDGER OF THE ROUTE YOU PICKED (B14) — read across: where every rupee went
A56: Cycle | B56: Opening corpus ₹ Cr | C56: Gross trading profit ₹ Cr | D56: Running cost ₹ Cr | E56: Salary paid ₹ Cr | F56: Taxable profit ₹ Cr | G56: Tax rate | H56: Tax paid ₹ Cr | I56: Tax saved by payroll ₹ Cr | J56: Family keeps (not lent back) ₹ Cr | K56: Closing corpus ₹ Cr | L56: Cumulative tax paid ₹ Cr | M56: Saved per member ₹ Lakh
A57: 0 | B57: =$B$5 | K57: =$B$5 | L57: 0
A58: 1 | B58: =CHOOSE($C$14,B111,B136,B161,B186,B211,B236,B261,B286) | C58: =CHOOSE($C$14,C111,C136,C161,C186,C211,C236,C261,C286) | D58: =CHOOSE($C$14,D111,D136,D161,D186,D211,D236,D261,D286) | E58: =CHOOSE($C$14,E111,E136,E161,E186,E211,E236,E261,E286) | F58: =CHOOSE($C$14,F111,F136,F161,F186,F211,F236,F261,F286) | G58: =CHOOSE($C$14,G111,G136,G161,G186,G211,G236,G261,G286) | H58: =CHOOSE($C$14,H111,H136,H161,H186,H211,H236,H261,H286) | I58: =CHOOSE($C$14,I111,I136,I161,I186,I211,I236,I261,I286) | ... K58: =CHOOSE($C$14,K111,K136,K161,K186,K211,K236,K261,K286) | L58: =L57+H58 | M58: =IF($C$14>=3,I58*100/($C$14-2),0)
A59: 2 | B59: =CHOOSE($C$14,B112,B137,B162,B187,B212,B237,B262,B287) | C59: =CHOOSE($C$14,C112,C137,C162,C187,C212,C237,C262,C287) | D59: =CHOOSE($C$14,D112,D137,D162,D187,D212,D237,D262,D287) | E59: =CHOOSE($C$14,E112,E137,E162,E187,E212,E237,E262,E287) | F59: =CHOOSE($C$14,F112,F137,F162,F187,F212,F237,F262,F287) | G59: =CHOOSE($C$14,G112,G137,G162,G187,G212,G237,G262,G287) | H59: =CHOOSE($C$14,H112,H137,H162,H187,H212,H237,H262,H287) | I59: =CHOOSE($C$14,I112,I137,I162,I187,I212,I237,I262,I287) | ... K59: =CHOOSE($C$14,K112,K137,K162,K187,K212,K237,K262,K287) | L59: =L58+H59 | M59: =IF($C$14>=3,I59*100/($C$14-2),0)
A60: 3 | B60: =CHOOSE($C$14,B113,B138,B163,B188,B213,B238,B263,B288) | C60: =CHOOSE($C$14,C113,C138,C163,C188,C213,C238,C263,C288) | D60: =CHOOSE($C$14,D113,D138,D163,D188,D213,D238,D263,D288) | E60: =CHOOSE($C$14,E113,E138,E163,E188,E213,E238,E263,E288) | F60: =CHOOSE($C$14,F113,F138,F163,F188,F213,F238,F263,F288) | G60: =CHOOSE($C$14,G113,G138,G163,G188,G213,G238,G263,G288) | H60: =CHOOSE($C$14,H113,H138,H163,H188,H213,H238,H263,H288) | I60: =CHOOSE($C$14,I113,I138,I163,I188,I213,I238,I263,I288) | ... K60: =CHOOSE($C$14,K113,K138,K163,K188,K213,K238,K263,K288) | L60: =L59+H60 | M60: =IF($C$14>=3,I60*100/($C$14-2),0)
A61: 4 | B61: =CHOOSE($C$14,B114,B139,B164,B189,B214,B239,B264,B289) | C61: =CHOOSE($C$14,C114,C139,C164,C189,C214,C239,C264,C289) | D61: =CHOOSE($C$14,D114,D139,D164,D189,D214,D239,D264,D289) | E61: =CHOOSE($C$14,E114,E139,E164,E189,E214,E239,E264,E289) | F61: =CHOOSE($C$14,F114,F139,F164,F189,F214,F239,F264,F289) | G61: =CHOOSE($C$14,G114,G139,G164,G189,G214,G239,G264,G289) | H61: =CHOOSE($C$14,H114,H139,H164,H189,H214,H239,H264,H289) | I61: =CHOOSE($C$14,I114,I139,I164,I189,I214,I239,I264,I289) | ... K61: =CHOOSE($C$14,K114,K139,K164,K189,K214,K239,K264,K289) | L61: =L60+H61 | M61: =IF($C$14>=3,I61*100/($C$14-2),0)
A62: 5 | B62: =CHOOSE($C$14,B115,B140,B165,B190,B215,B240,B265,B290) | C62: =CHOOSE($C$14,C115,C140,C165,C190,C215,C240,C265,C290) | D62: =CHOOSE($C$14,D115,D140,D165,D190,D215,D240,D265,D290) | E62: =CHOOSE($C$14,E115,E140,E165,E190,E215,E240,E265,E290) | F62: =CHOOSE($C$14,F115,F140,F165,F190,F215,F240,F265,F290) | G62: =CHOOSE($C$14,G115,G140,G165,G190,G215,G240,G265,G290) | H62: =CHOOSE($C$14,H115,H140,H165,H190,H215,H240,H265,H290) | I62: =CHOOSE($C$14,I115,I140,I165,I190,I215,I240,I265,I290) | ... K62: =CHOOSE($C$14,K115,K140,K165,K190,K215,K240,K265,K290) | L62: =L61+H62 | M62: =IF($C$14>=3,I62*100/($C$14-2),0)
A63: 6 | B63: =CHOOSE($C$14,B116,B141,B166,B191,B216,B241,B266,B291) | C63: =CHOOSE($C$14,C116,C141,C166,C191,C216,C241,C266,C291) | D63: =CHOOSE($C$14,D116,D141,D166,D191,D216,D241,D266,D291) | E63: =CHOOSE($C$14,E116,E141,E166,E191,E216,E241,E266,E291) | F63: =CHOOSE($C$14,F116,F141,F166,F191,F216,F241,F266,F291) | G63: =CHOOSE($C$14,G116,G141,G166,G191,G216,G241,G266,G291) | H63: =CHOOSE($C$14,H116,H141,H166,H191,H216,H241,H266,H291) | I63: =CHOOSE($C$14,I116,I141,I166,I191,I216,I241,I266,I291) | ... K63: =CHOOSE($C$14,K116,K141,K166,K191,K216,K241,K266,K291) | L63: =L62+H63 | M63: =IF($C$14>=3,I63*100/($C$14-2),0)
A64: 7 | B64: =CHOOSE($C$14,B117,B142,B167,B192,B217,B242,B267,B292) | C64: =CHOOSE($C$14,C117,C142,C167,C192,C217,C242,C267,C292) | D64: =CHOOSE($C$14,D117,D142,D167,D192,D217,D242,D267,D292) | E64: =CHOOSE($C$14,E117,E142,E167,E192,E217,E242,E267,E292) | F64: =CHOOSE($C$14,F117,F142,F167,F192,F217,F242,F267,F292) | G64: =CHOOSE($C$14,G117,G142,G167,G192,G217,G242,G267,G292) | H64: =CHOOSE($C$14,H117,H142,H167,H192,H217,H242,H267,H292) | I64: =CHOOSE($C$14,I117,I142,I167,I192,I217,I242,I267,I292) | ... K64: =CHOOSE($C$14,K117,K142,K167,K192,K217,K242,K267,K292) | L64: =L63+H64 | M64: =IF($C$14>=3,I64*100/($C$14-2),0)
A65: 8 | B65: =CHOOSE($C$14,B118,B143,B168,B193,B218,B243,B268,B293) | C65: =CHOOSE($C$14,C118,C143,C168,C193,C218,C243,C268,C293) | D65: =CHOOSE($C$14,D118,D143,D168,D193,D218,D243,D268,D293) | E65: =CHOOSE($C$14,E118,E143,E168,E193,E218,E243,E268,E293) | F65: =CHOOSE($C$14,F118,F143,F168,F193,F218,F243,F268,F293) | G65: =CHOOSE($C$14,G118,G143,G168,G193,G218,G243,G268,G293) | H65: =CHOOSE($C$14,H118,H143,H168,H193,H218,H243,H268,H293) | I65: =CHOOSE($C$14,I118,I143,I168,I193,I218,I243,I268,I293) | ... K65: =CHOOSE($C$14,K118,K143,K168,K193,K218,K243,K268,K293) | L65: =L64+H65 | M65: =IF($C$14>=3,I65*100/($C$14-2),0)
A66: 9 | B66: =CHOOSE($C$14,B119,B144,B169,B194,B219,B244,B269,B294) | C66: =CHOOSE($C$14,C119,C144,C169,C194,C219,C244,C269,C294) | D66: =CHOOSE($C$14,D119,D144,D169,D194,D219,D244,D269,D294) | E66: =CHOOSE($C$14,E119,E144,E169,E194,E219,E244,E269,E294) | F66: =CHOOSE($C$14,F119,F144,F169,F194,F219,F244,F269,F294) | G66: =CHOOSE($C$14,G119,G144,G169,G194,G219,G244,G269,G294) | H66: =CHOOSE($C$14,H119,H144,H169,H194,H219,H244,H269,H294) | I66: =CHOOSE($C$14,I119,I144,I169,I194,I219,I244,I269,I294) | ... K66: =CHOOSE($C$14,K119,K144,K169,K194,K219,K244,K269,K294) | L66: =L65+H66 | M66: =IF($C$14>=3,I66*100/($C$14-2),0)
A67: 10 | B67: =CHOOSE($C$14,B120,B145,B170,B195,B220,B245,B270,B295) | C67: =CHOOSE($C$14,C120,C145,C170,C195,C220,C245,C270,C295) | D67: =CHOOSE($C$14,D120,D145,D170,D195,D220,D245,D270,D295) | E67: =CHOOSE($C$14,E120,E145,E170,E195,E220,E245,E270,E295) | F67: =CHOOSE($C$14,F120,F145,F170,F195,F220,F245,F270,F295) | G67: =CHOOSE($C$14,G120,G145,G170,G195,G220,G245,G270,G295) | H67: =CHOOSE($C$14,H120,H145,H170,H195,H220,H245,H270,H295) | I67: =CHOOSE($C$14,I120,I145,I170,I195,I220,I245,I270,I295) | ... K67: =CHOOSE($C$14,K120,K145,K170,K195,K220,K245,K270,K295) | L67: =L66+H67 | M67: =IF($C$14>=3,I67*100/($C$14-2),0)
A68: 11 | B68: =CHOOSE($C$14,B121,B146,B171,B196,B221,B246,B271,B296) | C68: =CHOOSE($C$14,C121,C146,C171,C196,C221,C246,C271,C296) | D68: =CHOOSE($C$14,D121,D146,D171,D196,D221,D246,D271,D296) | E68: =CHOOSE($C$14,E121,E146,E171,E196,E221,E246,E271,E296) | F68: =CHOOSE($C$14,F121,F146,F171,F196,F221,F246,F271,F296) | G68: =CHOOSE($C$14,G121,G146,G171,G196,G221,G246,G271,G296) | H68: =CHOOSE($C$14,H121,H146,H171,H196,H221,H246,H271,H296) | I68: =CHOOSE($C$14,I121,I146,I171,I196,I221,I246,I271,I296) | ... K68: =CHOOSE($C$14,K121,K146,K171,K196,K221,K246,K271,K296) | L68: =L67+H68 | M68: =IF($C$14>=3,I68*100/($C$14-2),0)
A69: 12 | B69: =CHOOSE($C$14,B122,B147,B172,B197,B222,B247,B272,B297) | C69: =CHOOSE($C$14,C122,C147,C172,C197,C222,C247,C272,C297) | D69: =CHOOSE($C$14,D122,D147,D172,D197,D222,D247,D272,D297) | E69: =CHOOSE($C$14,E122,E147,E172,E197,E222,E247,E272,E297) | F69: =CHOOSE($C$14,F122,F147,F172,F197,F222,F247,F272,F297) | G69: =CHOOSE($C$14,G122,G147,G172,G197,G222,G247,G272,G297) | H69: =CHOOSE($C$14,H122,H147,H172,H197,H222,H247,H272,H297) | I69: =CHOOSE($C$14,I122,I147,I172,I197,I222,I247,I272,I297) | ... K69: =CHOOSE($C$14,K122,K147,K172,K197,K222,K247,K272,K297) | L69: =L68+H69 | M69: =IF($C$14>=3,I69*100/($C$14-2),0)
... A77: 20 | B77: =CHOOSE($C$14,B130,B155,B180,B205,B230,B255,B280,B305) | C77: =CHOOSE($C$14,C130,C155,C180,C205,C230,C255,C280,C305) | D77: =CHOOSE($C$14,D130,D155,D180,D205,D230,D255,D280,D305) | E77: =CHOOSE($C$14,E130,E155,E180,E205,E230,E255,E280,E305) | F77: =CHOOSE($C$14,F130,F155,F180,F205,F230,F255,F280,F305) | G77: =CHOOSE($C$14,G130,G155,G180,G205,G230,G255,G280,G305) | H77: =CHOOSE($C$14,H130,H155,H180,H205,H230,H255,H280,H305) | I77: =CHOOSE($C$14,I130,I155,I180,I205,I230,I255,I280,I305) | ... K77: =CHOOSE($C$14,K130,K155,K180,K205,K230,K255,K280,K305) | L77: =L76+H77 | M77: =IF($C$14>=3,I77*100/($C$14-2),0)
A78: Total over 20 cycles | C78: =SUM(C58:C77) | D78: =SUM(D58:D77) | E78: =SUM(E58:E77) | H78: =SUM(H58:H77) | I78: =SUM(I58:I77) | J78: =SUM(J58:J77) | K78: =K77 | L78: =L77 | M78: =SUM(M58:M77)
A79: Opening + gross profit − running cost − tax − family keeps = closing corpus, every row. Salary is paid out and lent back (except what the family keeps); its tax saving is the "tax saved by payroll" column.
A81: WHICH RECYCLE RATIO? — corpus at the cycle you choose, for every payroll size (early cycles matter most)
A82: Evaluate at cycle (1–20) | B82: 3 | C82: Each payroll rupee gains (tax rate − (1 − r)); below break-even payroll destroys corpus.
A83: Break-even recycle ratio (1 − company tax) | B83: =1-B8
A85: Members ↓ / recycle ratio → | B85: 0.75 | C85: 0.8 | D85: 0.85 | E85: 0.9 | F85: 0.95 | G85: 1
A86: 0 members | B86: =INDEX(B$311:B$330,$B$82) | C86: =INDEX(C$311:C$330,$B$82) | D86: =INDEX(D$311:D$330,$B$82) | E86: =INDEX(E$311:E$330,$B$82) | F86: =INDEX(F$311:F$330,$B$82) | G86: =INDEX(G$311:G$330,$B$82)
A87: 1 member | B87: =INDEX(H$311:H$330,$B$82) | C87: =INDEX(I$311:I$330,$B$82) | D87: =INDEX(J$311:J$330,$B$82) | E87: =INDEX(K$311:K$330,$B$82) | F87: =INDEX(L$311:L$330,$B$82) | G87: =INDEX(M$311:M$330,$B$82)
A88: 2 members | B88: =INDEX(N$311:N$330,$B$82) | C88: =INDEX(O$311:O$330,$B$82) | D88: =INDEX(P$311:P$330,$B$82) | E88: =INDEX(Q$311:Q$330,$B$82) | F88: =INDEX(R$311:R$330,$B$82) | G88: =INDEX(S$311:S$330,$B$82)
A89: 3 members | B89: =INDEX(T$311:T$330,$B$82) | C89: =INDEX(U$311:U$330,$B$82) | D89: =INDEX(V$311:V$330,$B$82) | E89: =INDEX(W$311:W$330,$B$82) | F89: =INDEX(X$311:X$330,$B$82) | G89: =INDEX(Y$311:Y$330,$B$82)
A90: 4 members | B90: =INDEX(Z$311:Z$330,$B$82) | C90: =INDEX(AA$311:AA$330,$B$82) | D90: =INDEX(AB$311:AB$330,$B$82) | E90: =INDEX(AC$311:AC$330,$B$82) | F90: =INDEX(AD$311:AD$330,$B$82) | G90: =INDEX(AE$311:AE$330,$B$82)
A91: 5 members | B91: =INDEX(AF$311:AF$330,$B$82) | C91: =INDEX(AG$311:AG$330,$B$82) | D91: =INDEX(AH$311:AH$330,$B$82) | E91: =INDEX(AI$311:AI$330,$B$82) | F91: =INDEX(AJ$311:AJ$330,$B$82) | G91: =INDEX(AK$311:AK$330,$B$82)
A92: 6 members | B92: =INDEX(AL$311:AL$330,$B$82) | C92: =INDEX(AM$311:AM$330,$B$82) | D92: =INDEX(AN$311:AN$330,$B$82) | E92: =INDEX(AO$311:AO$330,$B$82) | F92: =INDEX(AP$311:AP$330,$B$82) | G92: =INDEX(AQ$311:AQ$330,$B$82)
A93: Darker green = bigger corpus at that cycle. The 0-member row is the plain company, so the gain from payroll is each cell minus the first row.
A95: CHECKLIST — MCX natural-gas futures in a company
A96: • Allowed: a company can trade MCX futures through a SEBI-registered commodity broker like any client; make sure the objects clause covers commodity derivatives. 25.168% needs the s.115BAA election (Form 10-IC), which is irrevocable.
A97: • Tax character: commodity futures on a recognised exchange where CTT is charged are not speculative (s.43(5)); profit is business income, CTT is deductible, losses carry forward 8 years.
A98: • Audits: a company needs a statutory audit signed by a practising CA every year; a tax audit (s.44AB) applies once turnover (absolute profits + absolute losses on squared-off trades) crosses the threshold. Software prepares filings; the CA signature cannot be automated.
A99: • Payroll: deductible only for real services at market rate (s.37(1); s.40A(2) for relatives). Keep appointment letters, work records, bank-only payments and TDS. ₹12L/yr per member assumes no other income.
A100: • Loan-back: relatives' loans to a private company are outside 'deposits' with a written declaration (Companies (Acceptance of Deposits) Rules 2014). 100% lent back every cycle looks circular and is the likeliest to be challenged. Slabs here follow the new regime for FY2025-26; the Income-tax Act 2025 renumbers sections from 1-Apr-2026 — get CA sign-off.
A107: CALCULATION ENGINE — eight ledgers (personal, company, company + 1…6 members) and the grid calculations (click [+] at the left to open; no need to edit)
A108: PERSONAL
A109: Members | B109: 0
A110: Cycle | B110: Start ₹ Cr | C110: Gross gain ₹ Cr | D110: Running cost ₹ Cr | E110: Salary ₹ Cr | F110: Taxable ₹ Cr | G110: Tax rate | H110: Tax ₹ Cr | I110: Tax saved by payroll ₹ Cr | J110: Net leakage ₹ Cr | K110: End ₹ Cr
A111: 1 | B111: =$B$5 | C111: =(MIN(B111,$B$15)*$B$6+MAX(B111-$B$15,0)*$B$16*$B$7/12) | D111: =$B$10 | E111: 0 | F111: =MAX(C111-D111-E111,0) | G111: =IF(F111>0,H111/F111,0) | H111: =IF((F111*12/$B$7)<='NG Inputs'!$B$32,0,(MAX((F111*12/$B$7)-'NG Inputs'!$A$16,0)*'NG Inputs'!$C$16+MAX((F111*12/$B$7)-'NG Inputs'!$A$17,0)*'NG Inputs'!$C$17+MAX((F111*12/$B$7)-'NG Inputs'!$A$18,0)*'NG Inputs'!$C$18+MAX((F111*12/$B$7)-'NG Inputs'!$A$19,0)*'NG Inputs'!$C$19+MAX((F111*12/$B$7)-'NG Inputs'!$A$20,0)*'NG Inputs'!$C$20+MAX((F111*12/$B$7)-'NG Inputs'!$A$21,0)*'NG Inputs'!$C$21+MAX((F111*12/$B$7)-'NG Inputs'!$A$22,0)*'NG Inputs'!$C$22)*(1+VLOOKUP((F111*12/$B$7),'NG Inputs'!$A$26:$B$29,2,TRUE))*(1+'NG Inputs'!$B$31))*$B$7/12 | I111: 0 | J111: =(1-$B$11)*E111 | K111: =B111+C111-D111-H111-J111
A112: 2 | B112: =K111 | C112: =(MIN(B112,$B$15)*$B$6+MAX(B112-$B$15,0)*$B$16*$B$7/12) | D112: =$B$10 | E112: 0 | F112: =MAX(C112-D112-E112,0) | G112: =IF(F112>0,H112/F112,0) | H112: =IF((F112*12/$B$7)<='NG Inputs'!$B$32,0,(MAX((F112*12/$B$7)-'NG Inputs'!$A$16,0)*'NG Inputs'!$C$16+MAX((F112*12/$B$7)-'NG Inputs'!$A$17,0)*'NG Inputs'!$C$17+MAX((F112*12/$B$7)-'NG Inputs'!$A$18,0)*'NG Inputs'!$C$18+MAX((F112*12/$B$7)-'NG Inputs'!$A$19,0)*'NG Inputs'!$C$19+MAX((F112*12/$B$7)-'NG Inputs'!$A$20,0)*'NG Inputs'!$C$20+MAX((F112*12/$B$7)-'NG Inputs'!$A$21,0)*'NG Inputs'!$C$21+MAX((F112*12/$B$7)-'NG Inputs'!$A$22,0)*'NG Inputs'!$C$22)*(1+VLOOKUP((F112*12/$B$7),'NG Inputs'!$A$26:$B$29,2,TRUE))*(1+'NG Inputs'!$B$31))*$B$7/12 | I112: 0 | J112: =(1-$B$11)*E112 | K112: =B112+C112-D112-H112-J112
A113: 3 | B113: =K112 | C113: =(MIN(B113,$B$15)*$B$6+MAX(B113-$B$15,0)*$B$16*$B$7/12) | D113: =$B$10 | E113: 0 | F113: =MAX(C113-D113-E113,0) | G113: =IF(F113>0,H113/F113,0) | H113: =IF((F113*12/$B$7)<='NG Inputs'!$B$32,0,(MAX((F113*12/$B$7)-'NG Inputs'!$A$16,0)*'NG Inputs'!$C$16+MAX((F113*12/$B$7)-'NG Inputs'!$A$17,0)*'NG Inputs'!$C$17+MAX((F113*12/$B$7)-'NG Inputs'!$A$18,0)*'NG Inputs'!$C$18+MAX((F113*12/$B$7)-'NG Inputs'!$A$19,0)*'NG Inputs'!$C$19+MAX((F113*12/$B$7)-'NG Inputs'!$A$20,0)*'NG Inputs'!$C$20+MAX((F113*12/$B$7)-'NG Inputs'!$A$21,0)*'NG Inputs'!$C$21+MAX((F113*12/$B$7)-'NG Inputs'!$A$22,0)*'NG Inputs'!$C$22)*(1+VLOOKUP((F113*12/$B$7),'NG Inputs'!$A$26:$B$29,2,TRUE))*(1+'NG Inputs'!$B$31))*$B$7/12 | I113: 0 | J113: =(1-$B$11)*E113 | K113: =B113+C113-D113-H113-J113
A114: 4 | B114: =K113 | C114: =(MIN(B114,$B$15)*$B$6+MAX(B114-$B$15,0)*$B$16*$B$7/12) | D114: =$B$10 | E114: 0 | F114: =MAX(C114-D114-E114,0) | G114: =IF(F114>0,H114/F114,0) | H114: =IF((F114*12/$B$7)<='NG Inputs'!$B$32,0,(MAX((F114*12/$B$7)-'NG Inputs'!$A$16,0)*'NG Inputs'!$C$16+MAX((F114*12/$B$7)-'NG Inputs'!$A$17,0)*'NG Inputs'!$C$17+MAX((F114*12/$B$7)-'NG Inputs'!$A$18,0)*'NG Inputs'!$C$18+MAX((F114*12/$B$7)-'NG Inputs'!$A$19,0)*'NG Inputs'!$C$19+MAX((F114*12/$B$7)-'NG Inputs'!$A$20,0)*'NG Inputs'!$C$20+MAX((F114*12/$B$7)-'NG Inputs'!$A$21,0)*'NG Inputs'!$C$21+MAX((F114*12/$B$7)-'NG Inputs'!$A$22,0)*'NG Inputs'!$C$22)*(1+VLOOKUP((F114*12/$B$7),'NG Inputs'!$A$26:$B$29,2,TRUE))*(1+'NG Inputs'!$B$31))*$B$7/12 | I114: 0 | J114: =(1-$B$11)*E114 | K114: =B114+C114-D114-H114-J114
A115: 5 | B115: =K114 | C115: =(MIN(B115,$B$15)*$B$6+MAX(B115-$B$15,0)*$B$16*$B$7/12) | D115: =$B$10 | E115: 0 | F115: =MAX(C115-D115-E115,0) | G115: =IF(F115>0,H115/F115,0) | H115: =IF((F115*12/$B$7)<='NG Inputs'!$B$32,0,(MAX((F115*12/$B$7)-'NG Inputs'!$A$16,0)*'NG Inputs'!$C$16+MAX((F115*12/$B$7)-'NG Inputs'!$A$17,0)*'NG Inputs'!$C$17+MAX((F115*12/$B$7)-'NG Inputs'!$A$18,0)*'NG Inputs'!$C$18+MAX((F115*12/$B$7)-'NG Inputs'!$A$19,0)*'NG Inputs'!$C$19+MAX((F115*12/$B$7)-'NG Inputs'!$A$20,0)*'NG Inputs'!$C$20+MAX((F115*12/$B$7)-'NG Inputs'!$A$21,0)*'NG Inputs'!$C$21+MAX((F115*12/$B$7)-'NG Inputs'!$A$22,0)*'NG Inputs'!$C$22)*(1+VLOOKUP((F115*12/$B$7),'NG Inputs'!$A$26:$B$29,2,TRUE))*(1+'NG Inputs'!$B$31))*$B$7/12 | I115: 0 | J115: =(1-$B$11)*E115 | K115: =B115+C115-D115-H115-J115
A116: 6 | B116: =K115 | C116: =(MIN(B116,$B$15)*$B$6+MAX(B116-$B$15,0)*$B$16*$B$7/12) | D116: =$B$10 | E116: 0 | F116: =MAX(C116-D116-E116,0) | G116: =IF(F116>0,H116/F116,0) | H116: =IF((F116*12/$B$7)<='NG Inputs'!$B$32,0,(MAX((F116*12/$B$7)-'NG Inputs'!$A$16,0)*'NG Inputs'!$C$16+MAX((F116*12/$B$7)-'NG Inputs'!$A$17,0)*'NG Inputs'!$C$17+MAX((F116*12/$B$7)-'NG Inputs'!$A$18,0)*'NG Inputs'!$C$18+MAX((F116*12/$B$7)-'NG Inputs'!$A$19,0)*'NG Inputs'!$C$19+MAX((F116*12/$B$7)-'NG Inputs'!$A$20,0)*'NG Inputs'!$C$20+MAX((F116*12/$B$7)-'NG Inputs'!$A$21,0)*'NG Inputs'!$C$21+MAX((F116*12/$B$7)-'NG Inputs'!$A$22,0)*'NG Inputs'!$C$22)*(1+VLOOKUP((F116*12/$B$7),'NG Inputs'!$A$26:$B$29,2,TRUE))*(1+'NG Inputs'!$B$31))*$B$7/12 | I116: 0 | J116: =(1-$B$11)*E116 | K116: =B116+C116-D116-H116-J116
A117: 7 | B117: =K116 | C117: =(MIN(B117,$B$15)*$B$6+MAX(B117-$B$15,0)*$B$16*$B$7/12) | D117: =$B$10 | E117: 0 | F117: =MAX(C117-D117-E117,0) | G117: =IF(F117>0,H117/F117,0) | H117: =IF((F117*12/$B$7)<='NG Inputs'!$B$32,0,(MAX((F117*12/$B$7)-'NG Inputs'!$A$16,0)*'NG Inputs'!$C$16+MAX((F117*12/$B$7)-'NG Inputs'!$A$17,0)*'NG Inputs'!$C$17+MAX((F117*12/$B$7)-'NG Inputs'!$A$18,0)*'NG Inputs'!$C$18+MAX((F117*12/$B$7)-'NG Inputs'!$A$19,0)*'NG Inputs'!$C$19+MAX((F117*12/$B$7)-'NG Inputs'!$A$20,0)*'NG Inputs'!$C$20+MAX((F117*12/$B$7)-'NG Inputs'!$A$21,0)*'NG Inputs'!$C$21+MAX((F117*12/$B$7)-'NG Inputs'!$A$22,0)*'NG Inputs'!$C$22)*(1+VLOOKUP((F117*12/$B$7),'NG Inputs'!$A$26:$B$29,2,TRUE))*(1+'NG Inputs'!$B$31))*$B$7/12 | I117: 0 | J117: =(1-$B$11)*E117 | K117: =B117+C117-D117-H117-J117
A118: 8 | B118: =K117 | C118: =(MIN(B118,$B$15)*$B$6+MAX(B118-$B$15,0)*$B$16*$B$7/12) | D118: =$B$10 | E118: 0 | F118: =MAX(C118-D118-E118,0) | G118: =IF(F118>0,H118/F118,0) | H118: =IF((F118*12/$B$7)<='NG Inputs'!$B$32,0,(MAX((F118*12/$B$7)-'NG Inputs'!$A$16,0)*'NG Inputs'!$C$16+MAX((F118*12/$B$7)-'NG Inputs'!$A$17,0)*'NG Inputs'!$C$17+MAX((F118*12/$B$7)-'NG Inputs'!$A$18,0)*'NG Inputs'!$C$18+MAX((F118*12/$B$7)-'NG Inputs'!$A$19,0)*'NG Inputs'!$C$19+MAX((F118*12/$B$7)-'NG Inputs'!$A$20,0)*'NG Inputs'!$C$20+MAX((F118*12/$B$7)-'NG Inputs'!$A$21,0)*'NG Inputs'!$C$21+MAX((F118*12/$B$7)-'NG Inputs'!$A$22,0)*'NG Inputs'!$C$22)*(1+VLOOKUP((F118*12/$B$7),'NG Inputs'!$A$26:$B$29,2,TRUE))*(1+'NG Inputs'!$B$31))*$B$7/12 | I118: 0 | J118: =(1-$B$11)*E118 | K118: =B118+C118-D118-H118-J118
A119: 9 | B119: =K118 | C119: =(MIN(B119,$B$15)*$B$6+MAX(B119-$B$15,0)*$B$16*$B$7/12) | D119: =$B$10 | E119: 0 | F119: =MAX(C119-D119-E119,0) | G119: =IF(F119>0,H119/F119,0) | H119: =IF((F119*12/$B$7)<='NG Inputs'!$B$32,0,(MAX((F119*12/$B$7)-'NG Inputs'!$A$16,0)*'NG Inputs'!$C$16+MAX((F119*12/$B$7)-'NG Inputs'!$A$17,0)*'NG Inputs'!$C$17+MAX((F119*12/$B$7)-'NG Inputs'!$A$18,0)*'NG Inputs'!$C$18+MAX((F119*12/$B$7)-'NG Inputs'!$A$19,0)*'NG Inputs'!$C$19+MAX((F119*12/$B$7)-'NG Inputs'!$A$20,0)*'NG Inputs'!$C$20+MAX((F119*12/$B$7)-'NG Inputs'!$A$21,0)*'NG Inputs'!$C$21+MAX((F119*12/$B$7)-'NG Inputs'!$A$22,0)*'NG Inputs'!$C$22)*(1+VLOOKUP((F119*12/$B$7),'NG Inputs'!$A$26:$B$29,2,TRUE))*(1+'NG Inputs'!$B$31))*$B$7/12 | I119: 0 | J119: =(1-$B$11)*E119 | K119: =B119+C119-D119-H119-J119
A120: 10 | B120: =K119 | C120: =(MIN(B120,$B$15)*$B$6+MAX(B120-$B$15,0)*$B$16*$B$7/12) | D120: =$B$10 | E120: 0 | F120: =MAX(C120-D120-E120,0) | G120: =IF(F120>0,H120/F120,0) | H120: =IF((F120*12/$B$7)<='NG Inputs'!$B$32,0,(MAX((F120*12/$B$7)-'NG Inputs'!$A$16,0)*'NG Inputs'!$C$16+MAX((F120*12/$B$7)-'NG Inputs'!$A$17,0)*'NG Inputs'!$C$17+MAX((F120*12/$B$7)-'NG Inputs'!$A$18,0)*'NG Inputs'!$C$18+MAX((F120*12/$B$7)-'NG Inputs'!$A$19,0)*'NG Inputs'!$C$19+MAX((F120*12/$B$7)-'NG Inputs'!$A$20,0)*'NG Inputs'!$C$20+MAX((F120*12/$B$7)-'NG Inputs'!$A$21,0)*'NG Inputs'!$C$21+MAX((F120*12/$B$7)-'NG Inputs'!$A$22,0)*'NG Inputs'!$C$22)*(1+VLOOKUP((F120*12/$B$7),'NG Inputs'!$A$26:$B$29,2,TRUE))*(1+'NG Inputs'!$B$31))*$B$7/12 | I120: 0 | J120: =(1-$B$11)*E120 | K120: =B120+C120-D120-H120-J120
A121: 11 | B121: =K120 | C121: =(MIN(B121,$B$15)*$B$6+MAX(B121-$B$15,0)*$B$16*$B$7/12) | D121: =$B$10 | E121: 0 | F121: =MAX(C121-D121-E121,0) | G121: =IF(F121>0,H121/F121,0) | H121: =IF((F121*12/$B$7)<='NG Inputs'!$B$32,0,(MAX((F121*12/$B$7)-'NG Inputs'!$A$16,0)*'NG Inputs'!$C$16+MAX((F121*12/$B$7)-'NG Inputs'!$A$17,0)*'NG Inputs'!$C$17+MAX((F121*12/$B$7)-'NG Inputs'!$A$18,0)*'NG Inputs'!$C$18+MAX((F121*12/$B$7)-'NG Inputs'!$A$19,0)*'NG Inputs'!$C$19+MAX((F121*12/$B$7)-'NG Inputs'!$A$20,0)*'NG Inputs'!$C$20+MAX((F121*12/$B$7)-'NG Inputs'!$A$21,0)*'NG Inputs'!$C$21+MAX((F121*12/$B$7)-'NG Inputs'!$A$22,0)*'NG Inputs'!$C$22)*(1+VLOOKUP((F121*12/$B$7),'NG Inputs'!$A$26:$B$29,2,TRUE))*(1+'NG Inputs'!$B$31))*$B$7/12 | I121: 0 | J121: =(1-$B$11)*E121 | K121: =B121+C121-D121-H121-J121
A122: 12 | B122: =K121 | C122: =(MIN(B122,$B$15)*$B$6+MAX(B122-$B$15,0)*$B$16*$B$7/12) | D122: =$B$10 | E122: 0 | F122: =MAX(C122-D122-E122,0) | G122: =IF(F122>0,H122/F122,0) | H122: =IF((F122*12/$B$7)<='NG Inputs'!$B$32,0,(MAX((F122*12/$B$7)-'NG Inputs'!$A$16,0)*'NG Inputs'!$C$16+MAX((F122*12/$B$7)-'NG Inputs'!$A$17,0)*'NG Inputs'!$C$17+MAX((F122*12/$B$7)-'NG Inputs'!$A$18,0)*'NG Inputs'!$C$18+MAX((F122*12/$B$7)-'NG Inputs'!$A$19,0)*'NG Inputs'!$C$19+MAX((F122*12/$B$7)-'NG Inputs'!$A$20,0)*'NG Inputs'!$C$20+MAX((F122*12/$B$7)-'NG Inputs'!$A$21,0)*'NG Inputs'!$C$21+MAX((F122*12/$B$7)-'NG Inputs'!$A$22,0)*'NG Inputs'!$C$22)*(1+VLOOKUP((F122*12/$B$7),'NG Inputs'!$A$26:$B$29,2,TRUE))*(1+'NG Inputs'!$B$31))*$B$7/12 | I122: 0 | J122: =(1-$B$11)*E122 | K122: =B122+C122-D122-H122-J122
A123: 13 | B123: =K122 | C123: =(MIN(B123,$B$15)*$B$6+MAX(B123-$B$15,0)*$B$16*$B$7/12) | D123: =$B$10 | E123: 0 | F123: =MAX(C123-D123-E123,0) | G123: =IF(F123>0,H123/F123,0) | H123: =IF((F123*12/$B$7)<='NG Inputs'!$B$32,0,(MAX((F123*12/$B$7)-'NG Inputs'!$A$16,0)*'NG Inputs'!$C$16+MAX((F123*12/$B$7)-'NG Inputs'!$A$17,0)*'NG Inputs'!$C$17+MAX((F123*12/$B$7)-'NG Inputs'!$A$18,0)*'NG Inputs'!$C$18+MAX((F123*12/$B$7)-'NG Inputs'!$A$19,0)*'NG Inputs'!$C$19+MAX((F123*12/$B$7)-'NG Inputs'!$A$20,0)*'NG Inputs'!$C$20+MAX((F123*12/$B$7)-'NG Inputs'!$A$21,0)*'NG Inputs'!$C$21+MAX((F123*12/$B$7)-'NG Inputs'!$A$22,0)*'NG Inputs'!$C$22)*(1+VLOOKUP((F123*12/$B$7),'NG Inputs'!$A$26:$B$29,2,TRUE))*(1+'NG Inputs'!$B$31))*$B$7/12 | I123: 0 | J123: =(1-$B$11)*E123 | K123: =B123+C123-D123-H123-J123
... A130: 20 | B130: =K129 | C130: =(MIN(B130,$B$15)*$B$6+MAX(B130-$B$15,0)*$B$16*$B$7/12) | D130: =$B$10 | E130: 0 | F130: =MAX(C130-D130-E130,0) | G130: =IF(F130>0,H130/F130,0) | H130: =IF((F130*12/$B$7)<='NG Inputs'!$B$32,0,(MAX((F130*12/$B$7)-'NG Inputs'!$A$16,0)*'NG Inputs'!$C$16+MAX((F130*12/$B$7)-'NG Inputs'!$A$17,0)*'NG Inputs'!$C$17+MAX((F130*12/$B$7)-'NG Inputs'!$A$18,0)*'NG Inputs'!$C$18+MAX((F130*12/$B$7)-'NG Inputs'!$A$19,0)*'NG Inputs'!$C$19+MAX((F130*12/$B$7)-'NG Inputs'!$A$20,0)*'NG Inputs'!$C$20+MAX((F130*12/$B$7)-'NG Inputs'!$A$21,0)*'NG Inputs'!$C$21+MAX((F130*12/$B$7)-'NG Inputs'!$A$22,0)*'NG Inputs'!$C$22)*(1+VLOOKUP((F130*12/$B$7),'NG Inputs'!$A$26:$B$29,2,TRUE))*(1+'NG Inputs'!$B$31))*$B$7/12 | I130: 0 | J130: =(1-$B$11)*E130 | K130: =B130+C130-D130-H130-J130
A133: COMPANY
A134: Members | B134: 0
A135: Cycle | B135: Start ₹ Cr | C135: Gross gain ₹ Cr | D135: Running cost ₹ Cr | E135: Salary ₹ Cr | F135: Taxable ₹ Cr | G135: Tax rate | H135: Tax ₹ Cr | I135: Tax saved by payroll ₹ Cr | J135: Net leakage ₹ Cr | K135: End ₹ Cr
A136: 1 | B136: =$B$5 | C136: =(MIN(B136,$B$15)*$B$6+MAX(B136-$B$15,0)*$B$16*$B$7/12) | D136: =$B$9 | E136: =IF(AND($B$134>0,$B$8>0),MIN($B$134*$B$17,$B$13*MAX(C136-D136,0)),0) | F136: =MAX(C136-D136-E136,0) | G136: =$B$8 | H136: =F136*G136 | I136: =MAX(C136-D136,0)*G136-H136 | J136: =(1-$B$11)*E136 | K136: =B136+C136-D136-H136-J136
...

Sheet Shipping Engine
A1: SHIPPING ENGINE · BDRY → SGX/ICE FFA · FOUR TAX CASES (separate business — not MCX)
A2: Change the blue cells; pick which tax case to read in the cycle ledger. Cycle 0 is the opening. The four calculation blocks are tucked away at the bottom (click the [+] in the left margin to open them).
A4: CONTROLS — this sheet only
A5: Starting capital (₹ Cr) | B5: 0.6 | C5: Cycle-1 opening corpus
A6: Gross return per cycle | B6: 0.75 | C6: On deployed capital — your assumption, not data
A7: Cycle length (months) | B7: 18 | C7: <24 ⇒ personal STCG at slabs; ≥24 ⇒ LTCG 12.5% (surcharge capped at 15%)
A8: Company-switch threshold (₹ Cr) | B8: 20 | C8: Case 3 only: personal account becomes a GIFT/IFSC company at this corpus
A9: USD/INR | B9: 94.98
A10: Company tax rate (s.115BAA) | B10: ='NG Inputs'!B4 | C10: Linked to NG Inputs!B4
A11: Company running cost per cycle — full stack (₹ Cr) | B11: 0.5 | C11: Charged only in the GIFT/IFSC company stage; deductible
A12: Lean running cost BEFORE threshold (₹ Cr) | B12: 0 | C12: Case 2 only (company from cycle 1)
A13: BDRY liquidity regime | B13: Current | C13: Current = 90-day mean ($82.7K/day); Hot = freight upswing ($352K/day)
A14: BDRY safe $/day — current | B14: 82683 | C14: bdry_liquidity.csv, 90-day mean of tiered safe liquidity
A15: BDRY safe $/day — hot | B15: 352235 | C15: Top-quartile rolling 90-day windows since 2018
A16: Build window — entry (days) | B16: 45 | C16: 1–1.5 month stretched accumulation
A17: Exit window (days) | B17: 45 | C17: Exit capacity = safe $/day × exit days
A18: FFA capacity per position ($) | B18: 60000000 | C18: SGX/ICE Cape 5TC + Pmx 4TC — verify with your FCM
A19: LTCG base (unlisted foreign ≥24m) | B19: 0.125
A20: STCG top base rate (slab) | B20: 0.3 | C20: New Tax Regime top slab
A21: Health & education cess | B21: 0.04
A22: LTCG surcharge cap | B22: 0.15
A23: Idle-capital yield (liquid fund) | B23: ='NG Inputs'!B10 | C23: Linked to NG Inputs!B10
A24: Family payroll | B24: On | C24: On / Off — company stages of Cases 2 and 3; switches off if company tax = 0
A25: Members on payroll | B25: 3 | C25: 0 to 6
A26: Per-person salary cap per YEAR (₹ Cr) | B26: 0.12 | C26: Equals ₹12L/yr — inside the s.87A rebate zone
A27: Total salary cap (% of cycle profit) | B27: 0.4 | C27: s.40A(2) reasonableness guard
A28: Recycle ratio r (share of salary lent back) | B28: 1 | C28: Below 100% leaks (1−r) × salary out of the company each cycle
A29: Tax case shown in the cycle ledger below | B29: Case 3 · Personal slabs → company at threshold | C29: =MATCH(B29,$A$50:$A$53,0)
A30: DERIVED — capacity and caps
A31: BDRY safe $/day in force | B31: =IF(B13="Hot",B15,B14)
A32: BDRY build capacity (₹ Cr) | B32: =B31*B16*B9/10000000 | C32: safe $/day × build days
A33: BDRY exit capacity (₹ Cr) | B33: =B31*B17*B9/10000000 | C33: safe $/day × exit days
A34: FFA position capacity (₹ Cr) | B34: =B18*B9/10000000
A35: ENTRY ceiling — BDRY (₹ Cr) | B35: =MIN(B32,B33/(1+B6)) | C35: Exit binds: the position grows by (1+gross) before it must be sold
A36: ENTRY ceiling — FFA (₹ Cr) | B36: =B34/(1+B6)
A37: Salary cap per person per cycle (₹ Cr) | B37: =B26*B7/12 | C37: annual cap × cycle months ÷ 12
A38: Max family salary per cycle (₹ Cr) | B38: =B25*B37 | C38: members × per-person cap (before the % of profit cap)
A40: PERSONAL TAX LADDER — New Regime, surcharge on slab income (looked up on each cycle's taxable gain)
A41: Taxable gain ≥ (₹ Cr) | B41: Surcharge | C41: Eff. STCG rate | D41: Eff. LTCG rate (cap applied)
A42: 0 | B42: 0 | C42: =$B$20*(1+B42)*(1+$B$21) | D42: =$B$19*(1+MIN(B42,$B$22))*(1+$B$21) | E42: Top surcharge tier is applied to the whole gain (no marginal relief) — slightly overstates personal tax (conservative).
A43: 0.5 | B43: 0.1 | C43: =$B$20*(1+B43)*(1+$B$21) | D43: =$B$19*(1+MIN(B43,$B$22))*(1+$B$21)
A44: 1 | B44: 0.15 | C44: =$B$20*(1+B44)*(1+$B$21) | D44: =$B$19*(1+MIN(B44,$B$22))*(1+$B$21)
A45: 2 | B45: 0.25 | C45: =$B$20*(1+B45)*(1+$B$21) | D45: =$B$19*(1+MIN(B45,$B$22))*(1+$B$21)
A48: COMPARISON — after 20 cycles
A49: Tax case | B49: Final wealth (₹ Cr) | C49: Final wealth (USD) | D49: Net after-tax CAGR | E49: Total tax (₹ Cr) | F49: Total running cost (₹ Cr) | G49: Family salary paid (₹ Cr) | H49: Tax saved by payroll (₹ Cr) | I49: Net payroll leakage (₹ Cr) | J49: Company from cycle | K49: FFA from cycle | L49: Wealth ÷ Case 2
A50: Case 1 · 0% tax throughout | B50: =Q152 | C50: =R152 | D50: =(Q152/$B$5)^(1/(20*$B$7/12))-1 | E50: =SUM(O133:O152) | F50: =SUM(J133:J152) | G50: =SUM(K133:K152) | H50: =SUMPRODUCT(K133:K152,N133:N152) | I50: =SUM(P133:P152) | J50: =IFERROR(MATCH(1,C133:C152,0),"never") | K50: =IFERROR(MATCH("SGX/ICE FFA blocks",E133:E152,0),"never") | L50: =B50/$B$51
A51: Case 2 · Company flat 25.168% from cycle 1 | B51: =Q177 | C51: =R177 | D51: =(Q177/$B$5)^(1/(20*$B$7/12))-1 | E51: =SUM(O158:O177) | F51: =SUM(J158:J177) | G51: =SUM(K158:K177) | H51: =SUMPRODUCT(K158:K177,N158:N177) | I51: =SUM(P158:P177) | J51: =IFERROR(MATCH(1,C158:C177,0),"never") | K51: =IFERROR(MATCH("SGX/ICE FFA blocks",E158:E177,0),"never") | L51: =B51/$B$51
A52: Case 3 · Personal slabs → company at threshold | B52: =Q202 | C52: =R202 | D52: =(Q202/$B$5)^(1/(20*$B$7/12))-1 | E52: =SUM(O183:O202) | F52: =SUM(J183:J202) | G52: =SUM(K183:K202) | H52: =SUMPRODUCT(K183:K202,N183:N202) | I52: =SUM(P183:P202) | J52: =IFERROR(MATCH(1,C183:C202,0),"never") | K52: =IFERROR(MATCH("SGX/ICE FFA blocks",E183:E202,0),"never") | L52: =B52/$B$51
A53: Case 4 · Personal only (never a company) | B53: =Q227 | C53: =R227 | D53: =(Q227/$B$5)^(1/(20*$B$7/12))-1 | E53: =SUM(O208:O227) | F53: =SUM(J208:J227) | G53: =SUM(K208:K227) | H53: =SUMPRODUCT(K208:K227,N208:N227) | I53: =SUM(P208:P227) | J53: =IFERROR(MATCH(1,C208:C227,0),"never") | K53: =IFERROR(MATCH("SGX/ICE FFA blocks",E208:E227,0),"never") | L53: =B53/$B$51
A54: Money stays inside the company (no exit tax modelled).
A56: EVERY CYCLE, ALL FOUR TAX CASES — corpus at the end of each cycle (₹ Cr)
A57: Cycle | B57: Case 1 · 0% tax | C57: Case 2 · company from start | D57: Case 3 · personal → company | E57: Case 4 · personal only | F57: Best case
A58: 0 | B58: =$B$5 | C58: =$B$5 | D58: =$B$5 | E58: =$B$5 | F58: =IF(A58=0,"—",IF(B58=MAX(B58:E58),"Case 1",IF(C58=MAX(B58:E58),"Case 2",IF(D58=MAX(B58:E58),"Case 3","Case 4"))))
A59: 1 | B59: =Q133 | C59: =Q158 | D59: =Q183 | E59: =Q208 | F59: =IF(A59=0,"—",IF(B59=MAX(B59:E59),"Case 1",IF(C59=MAX(B59:E59),"Case 2",IF(D59=MAX(B59:E59),"Case 3","Case 4"))))
A60: 2 | B60: =Q134 | C60: =Q159 | D60: =Q184 | E60: =Q209 | F60: =IF(A60=0,"—",IF(B60=MAX(B60:E60),"Case 1",IF(C60=MAX(B60:E60),"Case 2",IF(D60=MAX(B60:E60),"Case 3","Case 4"))))
A61: 3 | B61: =Q135 | C61: =Q160 | D61: =Q185 | E61: =Q210 | F61: =IF(A61=0,"—",IF(B61=MAX(B61:E61),"Case 1",IF(C61=MAX(B61:E61),"Case 2",IF(D61=MAX(B61:E61),"Case 3","Case 4"))))
A62: 4 | B62: =Q136 | C62: =Q161 | D62: =Q186 | E62: =Q211 | F62: =IF(A62=0,"—",IF(B62=MAX(B62:E62),"Case 1",IF(C62=MAX(B62:E62),"Case 2",IF(D62=MAX(B62:E62),"Case 3","Case 4"))))
A63: 5 | B63: =Q137 | C63: =Q162 | D63: =Q187 | E63: =Q212 | F63: =IF(A63=0,"—",IF(B63=MAX(B63:E63),"Case 1",IF(C63=MAX(B63:E63),"Case 2",IF(D63=MAX(B63:E63),"Case 3","Case 4"))))
A64: 6 | B64: =Q138 | C64: =Q163 | D64: =Q188 | E64: =Q213 | F64: =IF(A64=0,"—",IF(B64=MAX(B64:E64),"Case 1",IF(C64=MAX(B64:E64),"Case 2",IF(D64=MAX(B64:E64),"Case 3","Case 4"))))
A65: 7 | B65: =Q139 | C65: =Q164 | D65: =Q189 | E65: =Q214 | F65: =IF(A65=0,"—",IF(B65=MAX(B65:E65),"Case 1",IF(C65=MAX(B65:E65),"Case 2",IF(D65=MAX(B65:E65),"Case 3","Case 4"))))
A66: 8 | B66: =Q140 | C66: =Q165 | D66: =Q190 | E66: =Q215 | F66: =IF(A66=0,"—",IF(B66=MAX(B66:E66),"Case 1",IF(C66=MAX(B66:E66),"Case 2",IF(D66=MAX(B66:E66),"Case 3","Case 4"))))
A67: 9 | B67: =Q141 | C67: =Q166 | D67: =Q191 | E67: =Q216 | F67: =IF(A67=0,"—",IF(B67=MAX(B67:E67),"Case 1",IF(C67=MAX(B67:E67),"Case 2",IF(D67=MAX(B67:E67),"Case 3","Case 4"))))
A68: 10 | B68: =Q142 | C68: =Q167 | D68: =Q192 | E68: =Q217 | F68: =IF(A68=0,"—",IF(B68=MAX(B68:E68),"Case 1",IF(C68=MAX(B68:E68),"Case 2",IF(D68=MAX(B68:E68),"Case 3","Case 4"))))
A69: 11 | B69: =Q143 | C69: =Q168 | D69: =Q193 | E69: =Q218 | F69: =IF(A69=0,"—",IF(B69=MAX(B69:E69),"Case 1",IF(C69=MAX(B69:E69),"Case 2",IF(D69=MAX(B69:E69),"Case 3","Case 4"))))
A70: 12 | B70: =Q144 | C70: =Q169 | D70: =Q194 | E70: =Q219 | F70: =IF(A70=0,"—",IF(B70=MAX(B70:E70),"Case 1",IF(C70=MAX(B70:E70),"Case 2",IF(D70=MAX(B70:E70),"Case 3","Case 4"))))
... A78: 20 | B78: =Q152 | C78: =Q177 | D78: =Q202 | E78: =Q227 | F78: =IF(A78=0,"—",IF(B78=MAX(B78:E78),"Case 1",IF(C78=MAX(B78:E78),"Case 2",IF(D78=MAX(B78:E78),"Case 3","Case 4"))))
A80: CYCLE LEDGER OF THE CASE YOU PICKED (B29) — cycle 0 = opening; read across to see where every rupee went
A81: Cycle | B81: Opening corpus ₹ Cr | C81: Wrapper (FEMA gate) | D81: Instrument | E81: Deployed ₹ Cr | F81: Idle ₹ Cr | G81: Gross profit ₹ Cr | H81: Running cost ₹ Cr | I81: Family salary ₹ Cr | J81: Taxable profit ₹ Cr | K81: Tax basis | L81: Tax rate | M81: Tax paid ₹ Cr | N81: Net payroll leakage ₹ Cr | O81: Closing corpus ₹ Cr | P81: Closing USD | Q81: Compliance flag
A82: 0 | C82: Opening | D82: — | O82: =$B$5 | P82: =$B$5*10000000/$B$9
A83: 1 | B83: =CHOOSE($C$29,B133,B158,B183,B208) | C83: =CHOOSE($C$29,D133,D158,D183,D208) | D83: =CHOOSE($C$29,E133,E158,E183,E208) | E83: =CHOOSE($C$29,G133,G158,G183,G208) | F83: =CHOOSE($C$29,H133,H158,H183,H208) | G83: =CHOOSE($C$29,I133,I158,I183,I208) | H83: =CHOOSE($C$29,J133,J158,J183,J208) | I83: =CHOOSE($C$29,K133,K158,K183,K208) | J83: =CHOOSE($C$29,L133,L158,L183,L208) | K83: =CHOOSE($C$29,M133,M158,M183,M208) | L83: =CHOOSE($C$29,N133,N158,N183,N208) | ... Q83: =CHOOSE($C$29,S133,S158,S183,S208)
A84: 2 | B84: =CHOOSE($C$29,B134,B159,B184,B209) | C84: =CHOOSE($C$29,D134,D159,D184,D209) | D84: =CHOOSE($C$29,E134,E159,E184,E209) | E84: =CHOOSE($C$29,G134,G159,G184,G209) | F84: =CHOOSE($C$29,H134,H159,H184,H209) | G84: =CHOOSE($C$29,I134,I159,I184,I209) | H84: =CHOOSE($C$29,J134,J159,J184,J209) | I84: =CHOOSE($C$29,K134,K159,K184,K209) | J84: =CHOOSE($C$29,L134,L159,L184,L209) | K84: =CHOOSE($C$29,M134,M159,M184,M209) | L84: =CHOOSE($C$29,N134,N159,N184,N209) | ... Q84: =CHOOSE($C$29,S134,S159,S184,S209)
A85: 3 | B85: =CHOOSE($C$29,B135,B160,B185,B210) | C85: =CHOOSE($C$29,D135,D160,D185,D210) | D85: =CHOOSE($C$29,E135,E160,E185,E210) | E85: =CHOOSE($C$29,G135,G160,G185,G210) | F85: =CHOOSE($C$29,H135,H160,H185,H210) | G85: =CHOOSE($C$29,I135,I160,I185,I210) | H85: =CHOOSE($C$29,J135,J160,J185,J210) | I85: =CHOOSE($C$29,K135,K160,K185,K210) | J85: =CHOOSE($C$29,L135,L160,L185,L210) | K85: =CHOOSE($C$29,M135,M160,M185,M210) | L85: =CHOOSE($C$29,N135,N160,N185,N210) | ... Q85: =CHOOSE($C$29,S135,S160,S185,S210)
A86: 4 | B86: =CHOOSE($C$29,B136,B161,B186,B211) | C86: =CHOOSE($C$29,D136,D161,D186,D211) | D86: =CHOOSE($C$29,E136,E161,E186,E211) | E86: =CHOOSE($C$29,G136,G161,G186,G211) | F86: =CHOOSE($C$29,H136,H161,H186,H211) | G86: =CHOOSE($C$29,I136,I161,I186,I211) | H86: =CHOOSE($C$29,J136,J161,J186,J211) | I86: =CHOOSE($C$29,K136,K161,K186,K211) | J86: =CHOOSE($C$29,L136,L161,L186,L211) | K86: =CHOOSE($C$29,M136,M161,M186,M211) | L86: =CHOOSE($C$29,N136,N161,N186,N211) | ... Q86: =CHOOSE($C$29,S136,S161,S186,S211)
A87: 5 | B87: =CHOOSE($C$29,B137,B162,B187,B212) | C87: =CHOOSE($C$29,D137,D162,D187,D212) | D87: =CHOOSE($C$29,E137,E162,E187,E212) | E87: =CHOOSE($C$29,G137,G162,G187,G212) | F87: =CHOOSE($C$29,H137,H162,H187,H212) | G87: =CHOOSE($C$29,I137,I162,I187,I212) | H87: =CHOOSE($C$29,J137,J162,J187,J212) | I87: =CHOOSE($C$29,K137,K162,K187,K212) | J87: =CHOOSE($C$29,L137,L162,L187,L212) | K87: =CHOOSE($C$29,M137,M162,M187,M212) | L87: =CHOOSE($C$29,N137,N162,N187,N212) | ... Q87: =CHOOSE($C$29,S137,S162,S187,S212)
A88: 6 | B88: =CHOOSE($C$29,B138,B163,B188,B213) | C88: =CHOOSE($C$29,D138,D163,D188,D213) | D88: =CHOOSE($C$29,E138,E163,E188,E213) | E88: =CHOOSE($C$29,G138,G163,G188,G213) | F88: =CHOOSE($C$29,H138,H163,H188,H213) | G88: =CHOOSE($C$29,I138,I163,I188,I213) | H88: =CHOOSE($C$29,J138,J163,J188,J213) | I88: =CHOOSE($C$29,K138,K163,K188,K213) | J88: =CHOOSE($C$29,L138,L163,L188,L213) | K88: =CHOOSE($C$29,M138,M163,M188,M213) | L88: =CHOOSE($C$29,N138,N163,N188,N213) | ... Q88: =CHOOSE($C$29,S138,S163,S188,S213)
A89: 7 | B89: =CHOOSE($C$29,B139,B164,B189,B214) | C89: =CHOOSE($C$29,D139,D164,D189,D214) | D89: =CHOOSE($C$29,E139,E164,E189,E214) | E89: =CHOOSE($C$29,G139,G164,G189,G214) | F89: =CHOOSE($C$29,H139,H164,H189,H214) | G89: =CHOOSE($C$29,I139,I164,I189,I214) | H89: =CHOOSE($C$29,J139,J164,J189,J214) | I89: =CHOOSE($C$29,K139,K164,K189,K214) | J89: =CHOOSE($C$29,L139,L164,L189,L214) | K89: =CHOOSE($C$29,M139,M164,M189,M214) | L89: =CHOOSE($C$29,N139,N164,N189,N214) | ... Q89: =CHOOSE($C$29,S139,S164,S189,S214)
A90: 8 | B90: =CHOOSE($C$29,B140,B165,B190,B215) | C90: =CHOOSE($C$29,D140,D165,D190,D215) | D90: =CHOOSE($C$29,E140,E165,E190,E215) | E90: =CHOOSE($C$29,G140,G165,G190,G215) | F90: =CHOOSE($C$29,H140,H165,H190,H215) | G90: =CHOOSE($C$29,I140,I165,I190,I215) | H90: =CHOOSE($C$29,J140,J165,J190,J215) | I90: =CHOOSE($C$29,K140,K165,K190,K215) | J90: =CHOOSE($C$29,L140,L165,L190,L215) | K90: =CHOOSE($C$29,M140,M165,M190,M215) | L90: =CHOOSE($C$29,N140,N165,N190,N215) | ... Q90: =CHOOSE($C$29,S140,S165,S190,S215)
A91: 9 | B91: =CHOOSE($C$29,B141,B166,B191,B216) | C91: =CHOOSE($C$29,D141,D166,D191,D216) | D91: =CHOOSE($C$29,E141,E166,E191,E216) | E91: =CHOOSE($C$29,G141,G166,G191,G216) | F91: =CHOOSE($C$29,H141,H166,H191,H216) | G91: =CHOOSE($C$29,I141,I166,I191,I216) | H91: =CHOOSE($C$29,J141,J166,J191,J216) | I91: =CHOOSE($C$29,K141,K166,K191,K216) | J91: =CHOOSE($C$29,L141,L166,L191,L216) | K91: =CHOOSE($C$29,M141,M166,M191,M216) | L91: =CHOOSE($C$29,N141,N166,N191,N216) | ... Q91: =CHOOSE($C$29,S141,S166,S191,S216)
A92: 10 | B92: =CHOOSE($C$29,B142,B167,B192,B217) | C92: =CHOOSE($C$29,D142,D167,D192,D217) | D92: =CHOOSE($C$29,E142,E167,E192,E217) | E92: =CHOOSE($C$29,G142,G167,G192,G217) | F92: =CHOOSE($C$29,H142,H167,H192,H217) | G92: =CHOOSE($C$29,I142,I167,I192,I217) | H92: =CHOOSE($C$29,J142,J167,J192,J217) | I92: =CHOOSE($C$29,K142,K167,K192,K217) | J92: =CHOOSE($C$29,L142,L167,L192,L217) | K92: =CHOOSE($C$29,M142,M167,M192,M217) | L92: =CHOOSE($C$29,N142,N167,N192,N217) | ... Q92: =CHOOSE($C$29,S142,S167,S192,S217)
A93: 11 | B93: =CHOOSE($C$29,B143,B168,B193,B218) | C93: =CHOOSE($C$29,D143,D168,D193,D218) | D93: =CHOOSE($C$29,E143,E168,E193,E218) | E93: =CHOOSE($C$29,G143,G168,G193,G218) | F93: =CHOOSE($C$29,H143,H168,H193,H218) | G93: =CHOOSE($C$29,I143,I168,I193,I218) | H93: =CHOOSE($C$29,J143,J168,J193,J218) | I93: =CHOOSE($C$29,K143,K168,K193,K218) | J93: =CHOOSE($C$29,L143,L168,L193,L218) | K93: =CHOOSE($C$29,M143,M168,M193,M218) | L93: =CHOOSE($C$29,N143,N168,N193,N218) | ... Q93: =CHOOSE($C$29,S143,S168,S193,S218)
A94: 12 | B94: =CHOOSE($C$29,B144,B169,B194,B219) | C94: =CHOOSE($C$29,D144,D169,D194,D219) | D94: =CHOOSE($C$29,E144,E169,E194,E219) | E94: =CHOOSE($C$29,G144,G169,G194,G219) | F94: =CHOOSE($C$29,H144,H169,H194,H219) | G94: =CHOOSE($C$29,I144,I169,I194,I219) | H94: =CHOOSE($C$29,J144,J169,J194,J219) | I94: =CHOOSE($C$29,K144,K169,K194,K219) | J94: =CHOOSE($C$29,L144,L169,L194,L219) | K94: =CHOOSE($C$29,M144,M169,M194,M219) | L94: =CHOOSE($C$29,N144,N169,N194,N219) | ... Q94: =CHOOSE($C$29,S144,S169,S194,S219)
... A102: 20 | B102: =CHOOSE($C$29,B152,B177,B202,B227) | C102: =CHOOSE($C$29,D152,D177,D202,D227) | D102: =CHOOSE($C$29,E152,E177,E202,E227) | E102: =CHOOSE($C$29,G152,G177,G202,G227) | F102: =CHOOSE($C$29,H152,H177,H202,H227) | G102: =CHOOSE($C$29,I152,I177,I202,I227) | H102: =CHOOSE($C$29,J152,J177,J202,J227) | I102: =CHOOSE($C$29,K152,K177,K202,K227) | J102: =CHOOSE($C$29,L152,L177,L202,L227) | K102: =CHOOSE($C$29,M152,M177,M202,M227) | L102: =CHOOSE($C$29,N152,N177,N202,N227) | ... Q102: =CHOOSE($C$29,S152,S177,S202,S227)
A103: Total / end | G103: =SUM(G83:G102) | H103: =SUM(H83:H102) | I103: =SUM(I83:I102) | M103: =SUM(M83:M102) | N103: =SUM(N83:N102) | O103: =O102 | P103: =P102
A104: Opening + gross profit − running cost − tax − payroll leakage = closing corpus, every row.
A106: NOTES — tax & legal (get CA / counsel sign-off)
A107: 1. LRS/individual: US-listed ETFs = unlisted foreign securities; <24m STCG at New-Regime slabs, surcharge 10/15/25% → 39.00% peak; s.48 bars business expenses. ≥24m: LTCG u/s 112 @12.5%, surcharge cap 15% (~14.95% max) — ledger switches on cycle-length input.
A108: 2. FEMA: unlisted Indian co. barred from open-market OPI (OI Rules 2022); GIFT IFSC FIF/unit = person resident outside India. LRS→IFSC-FIF capitalization compliance-sensitive (RBI/IFSCA 2024-25): licensed FME + counsel.
A109: 3. Corporate: s.115BAA 25.168% flat; structural expenses deductible. IFSC s.80LA 10-yr holiday may apply instead (not modelled — conservative).
A110: Approximation: top surcharge tier applied to whole gain (no marginal relief) — slightly overstates individual tax = conservative.
A111: 4. SECTION NUMBERS follow the Income-tax Act 1961. The Income-tax Act 2025 took effect 1-Apr-2026 with renumbered sections; have your CA map each provision for FY 2026-27 onward.
A112: 5. s.87A: the new-regime rebate (income up to ₹12L) offsets slab-rate tax only — not special-rate income. Family salary qualifies; capital gains in their hands do not.
A113: 6. PAYROLL: salary must be for real, documented services at market rate (s.37(1) / s.40A(2)). Lending 100% back every cycle is the most scrutiny-prone setting. Pay by bank transfer only (s.269SS/269T) and deduct TDS where due.
A114: 7. LRS: individual investment remittances attract 20% TCS above ₹10L per PAN per FY and are capped (USD 250,000 per FY); LRS bars margin/derivative trading abroad — hence the compliance flag on FFA cycles run through an individual.
A115: 8. COMPANY SWITCH (Case 3): moving a personal foreign portfolio into a company is not free of tax or FEMA process (LRS caps, ODI/OPI rules). The model treats it as frictionless — structure it before you reach the threshold.
A116: Capacity = tier-safe $/day × build days. Current: $82.7K/day → $3.72M ≈ ₹35.3 Cr at 45d. Your "$3M when heated" holds: 36 build days at current liquidity, ~9 days in HOT regimes ($352K/day; Jul-2021 peak $663K/day → ~$29.8M).
... A130: CASE 1 · 0% TAX THROUGHOUT — Benchmark: s.80LA IFSC holiday / NRI / tax-free
A131: Tax mode | B131: 1
A132: Cycle | B132: Start ₹ Cr | C132: Company? (1/0) | D132: Wrapper (FEMA gate) | E132: Instrument | F132: Capacity ₹ Cr | G132: Deployed ₹ Cr | H132: Idle ₹ Cr | I132: Gross gain ₹ Cr | J132: Running cost ₹ Cr | K132: Family salary ₹ Cr | L132: Taxable ₹ Cr | M132: Tax basis | N132: Eff. tax rate | O132: Tax ₹ Cr | P132: Net payroll leakage ₹ Cr | Q132: End ₹ Cr | R132: End USD | S132: Compliance flag
A133: 1 | B133: =$B$5 | C133: =IF($B$131=2,1,IF($B$131=4,0,IF(B133>=$B$8,1,0))) | D133: =IF(C133=1,IF($B$131=2,"Company (115BAA)","GIFT FIF (IFSC) Corp"),IF($B$131=1,"Individual / NRI (0%)","Individual LRS")) | E133: =IF(B133>$B$35,"SGX/ICE FFA blocks","BDRY (45-day iceberg)") | F133: =IF(B133>$B$35,$B$36,$B$35) | G133: =MIN(B133,F133) | H133: =B133-G133 | I133: =G133*$B$6+H133*$B$23*$B$7/12 | J133: =IF(C133=1,IF(B133>=$B$8,$B$11,$B$12),0) | K133: =IF(AND($B$24="On",C133=1,$B$131<>1,$B$10>0),MIN($B$38,$B$27*MAX(I133-J133,0)),0) | L133: =MAX(I133-J133-K133,0) | M133: =IF($B$131=1,"0% (exempt)",IF(C133=1,"115BAA company",IF($B$7>=24,"LTCG 112","STCG @ slab"))) | N133: =IF($B$131=1,0,IF(C133=1,$B$10,IF($B$7>=24,$B$19*(1+MIN(VLOOKUP(L133,$A$42:$B$45,2,TRUE),$B$22))*(1+$B$21),$B$20*(1+VLOOKUP(L133,$A$42:$B$45,2,TRUE))*(1+$B$21)))) | O133: =L133*N133 | P133: =(1-$B$28)*K133 | Q133: =B133+I133-J133-O133-P133 | R133: =Q133*10000000/$B$9 | S133: =IF(AND(C133=0,E133="SGX/ICE FFA blocks"),"⚠ FFA derivatives need a corporate/IFSC wrapper — not via personal LRS","")
A134: 2 | B134: =Q133 | C134: =IF($B$131=2,1,IF($B$131=4,0,IF(B134>=$B$8,1,0))) | D134: =IF(C134=1,IF($B$131=2,"Company (115BAA)","GIFT FIF (IFSC) Corp"),IF($B$131=1,"Individual / NRI (0%)","Individual LRS")) | E134: =IF(B134>$B$35,"SGX/ICE FFA blocks","BDRY (45-day iceberg)") | F134: =IF(B134>$B$35,$B$36,$B$35) | G134: =MIN(B134,F134) | H134: =B134-G134 | I134: =G134*$B$6+H134*$B$23*$B$7/12 | J134: =IF(C134=1,IF(B134>=$B$8,$B$11,$B$12),0) | K134: =IF(AND($B$24="On",C134=1,$B$131<>1,$B$10>0),MIN($B$38,$B$27*MAX(I134-J134,0)),0) | L134: =MAX(I134-J134-K134,0) | M134: =IF($B$131=1,"0% (exempt)",IF(C134=1,"115BAA company",IF($B$7>=24,"LTCG 112","STCG @ slab"))) | N134: =IF($B$131=1,0,IF(C134=1,$B$10,IF($B$7>=24,$B$19*(1+MIN(VLOOKUP(L134,$A$42:$B$45,2,TRUE),$B$22))*(1+$B$21),$B$20*(1+VLOOKUP(L134,$A$42:$B$45,2,TRUE))*(1+$B$21)))) | O134: =L134*N134 | P134: =(1-$B$28)*K134 | Q134: =B134+I134-J134-O134-P134 | R134: =Q134*10000000/$B$9 | S134: =IF(AND(C134=0,E134="SGX/ICE FFA blocks"),"⚠ FFA derivatives need a corporate/IFSC wrapper — not via personal LRS","")
...

Sheet NG Scenarios
A1: REBUILT SCENARIOS · BULL / BASE / BEAR
A2: Per-trade tax, dynamic PDF-bucket margins, costs, slippage, ₹378 Cr ceiling. K'=K+min(dep·K/m,Nmax)·(move−roll−txn−slip)·(1−tax)+idle·yield·(1−tax).
A3: Starting capital bases → | C3: 2000000 | D3: 7500000 | E3: 20000000 | F3: ◄ Edit these to rescale every scenario & the expense schedule. Cells: C3=Base1, D3=Base2, E3=Base3
A4: Scenario | B4: Move % | C4: Margin % | D4: Calls/yr | E4: Gross ROC/call | F4: Rationale
A5: BULL | B5: 0.3 | C5: ='NG Data'!D135 | D5: 2 | E5: =B5/C5 | F5: Catch 2 legs/yr, capture first 30% of a ≥30% swing; margin = PDF ≥30%-bucket avg (25.9%)
A6: BASE | B6: 0.25 | C6: ='NG Data'!D134 | D6: 2 | E6: =B6/C6 | F6: TRUE BASE: 25% move (7-11×/yr, 2020-26) at the 25-30% bucket avg margin 27.3% — NOT 22%. (v9: move corrected 18%→25% to match this rationale and NG Risk and Sizing / NG GIFT Bridge.)
A7: BEAR | B7: 0.15 | C7: 0.28 | D7: 1 | E7: =B7/C7 | F7: 1 catch/yr of a 15% move in an elevated-margin regime (2022-style / Nov-26 fwd 29.7%)
A9: Expense schedule (₹) — blue, scales with each starting-capital base above (C3/D3/E3)
A10: Year | B10: =IF($C$3>=10000000,"₹"&TEXT($C$3/10000000,"0.##")&"Cr","₹"&TEXT($C$3/100000,"0.##")&"L")&" start" | C10: =IF($D$3>=10000000,"₹"&TEXT($D$3/10000000,"0.##")&"Cr","₹"&TEXT($D$3/100000,"0.##")&"L")&" start" | D10: =IF($E$3>=10000000,"₹"&TEXT($E$3/10000000,"0.##")&"Cr","₹"&TEXT($E$3/100000,"0.##")&"L")&" start"
A11: 1 | B11: =ROUND(0.01*$C$3,0) | C11: =ROUND(0.01*$D$3,0) | D11: =ROUND(0.01*$E$3,0)
A12: 2 | B12: =ROUND(0.01*$C$3,0) | C12: =ROUND(0.01*$D$3,0) | D12: =ROUND(0.01*$E$3,0)
A13: 3 | B13: =ROUND(0.025*$C$3,0) | C13: =ROUND(0.025*$D$3,0) | D13: =ROUND(0.025*$E$3,0)
A14: 4 | B14: =ROUND(0.025*$C$3,0) | C14: =ROUND(0.025*$D$3,0) | D14: =ROUND(0.025*$E$3,0)
A15: 5 | B15: =ROUND(0.05*$C$3,0) | C15: =ROUND(0.05*$D$3,0) | D15: =ROUND(0.05*$E$3,0)
A16: 6 | B16: =ROUND(0.05*$C$3,0) | C16: =ROUND(0.05*$D$3,0) | D16: =ROUND(0.05*$E$3,0)
A17: 7 | B17: =ROUND(0.05*$C$3,0) | C17: =ROUND(0.05*$D$3,0) | D17: =ROUND(0.05*$E$3,0)
A18: 8 | B18: =ROUND(0.1*$C$3,0) | C18: =ROUND(0.1*$D$3,0) | D18: =ROUND(0.1*$E$3,0)
A19: 9 | B19: =ROUND(0.1*$C$3,0) | C19: =ROUND(0.1*$D$3,0) | D19: =ROUND(0.1*$E$3,0)
A20: 10 | B20: =ROUND(0.1*$C$3,0) | C20: =ROUND(0.1*$D$3,0) | D20: =ROUND(0.1*$E$3,0)
A21: 11 | B21: =ROUND(0.1*$C$3,0) | C21: =ROUND(0.1*$D$3,0) | D21: =ROUND(0.1*$E$3,0)
A22: 12 | B22: =ROUND(0.1*$C$3,0) | C22: =ROUND(0.1*$D$3,0) | D22: =ROUND(0.1*$E$3,0)
A23: 13 | B23: =ROUND(0.1*$C$3,0) | C23: =ROUND(0.1*$D$3,0) | D23: =ROUND(0.1*$E$3,0)
A24: 14 | B24: =ROUND(0.1*$C$3,0) | C24: =ROUND(0.1*$D$3,0) | D24: =ROUND(0.1*$E$3,0)
A25: 15 | B25: =ROUND(0.1*$C$3,0) | C25: =ROUND(0.1*$D$3,0) | D25: =ROUND(0.1*$E$3,0)
A27: TRADE-BY-TRADE LEDGER — 15 years × calls; even call # = year end (expense applied)
A28: Call # | B28: Year | C28: ="BULL "&IF($C$3>=10000000,"₹"&TEXT($C$3/10000000,"0.##")&"Cr","₹"&TEXT($C$3/100000,"0.##")&"L") | D28: ="BULL "&IF($D$3>=10000000,"₹"&TEXT($D$3/10000000,"0.##")&"Cr","₹"&TEXT($D$3/100000,"0.##")&"L") | E28: ="BULL "&IF($E$3>=10000000,"₹"&TEXT($E$3/10000000,"0.##")&"Cr","₹"&TEXT($E$3/100000,"0.##")&"L") | F28: ="BASE "&IF($C$3>=10000000,"₹"&TEXT($C$3/10000000,"0.##")&"Cr","₹"&TEXT($C$3/100000,"0.##")&"L") | G28: ="BASE "&IF($D$3>=10000000,"₹"&TEXT($D$3/10000000,"0.##")&"Cr","₹"&TEXT($D$3/100000,"0.##")&"L") | H28: ="BASE "&IF($E$3>=10000000,"₹"&TEXT($E$3/10000000,"0.##")&"Cr","₹"&TEXT($E$3/100000,"0.##")&"L") | I28: ="BEAR "&IF($C$3>=10000000,"₹"&TEXT($C$3/10000000,"0.##")&"Cr","₹"&TEXT($C$3/100000,"0.##")&"L") | J28: ="BEAR "&IF($D$3>=10000000,"₹"&TEXT($D$3/10000000,"0.##")&"Cr","₹"&TEXT($D$3/100000,"0.##")&"L") | K28: ="BEAR "&IF($E$3>=10000000,"₹"&TEXT($E$3/10000000,"0.##")&"Cr","₹"&TEXT($E$3/100000,"0.##")&"L")
A29: 1 | B29: =ROUNDUP(A29/2,0) | C29: =$C$3+IF(OR($D$5=2,MOD(A29,2)=1),1,0)*(MIN('NG Inputs'!$B$12*$C$3/$C$5,'NG Inputs'!$B$9)*($B$5-'NG Inputs'!$B$5-'NG Inputs'!$B$6-2*'NG Inputs'!$B$7*SQRT(MIN('NG Inputs'!$B$12*$C$3/$C$5,'NG Inputs'!$B$9)/'NG Inputs'!$B$8))+MAX($C$3-MIN('NG Inputs'!$B$12*$C$3/$C$5,'NG Inputs'!$B$9)*$C$5,0)*'NG Inputs'!$B$10/$D$5)*(1-'NG Inputs'!$B$4)+IF($D$5=1,(1-IF(OR($D$5=2,MOD(A29,2)=1),1,0))*$C$3*'NG Inputs'!$B$10*(1-'NG Inputs'!$B$4)/2,0)-IF(MOD(A29,2)=0,INDEX($B$11:$D$25,B29,1)*(1-'NG Inputs'!$B$4),0) | D29: =$D$3+IF(OR($D$5=2,MOD(A29,2)=1),1,0)*(MIN('NG Inputs'!$B$12*$D$3/$C$5,'NG Inputs'!$B$9)*($B$5-'NG Inputs'!$B$5-'NG Inputs'!$B$6-2*'NG Inputs'!$B$7*SQRT(MIN('NG Inputs'!$B$12*$D$3/$C$5,'NG Inputs'!$B$9)/'NG Inputs'!$B$8))+MAX($D$3-MIN('NG Inputs'!$B$12*$D$3/$C$5,'NG Inputs'!$B$9)*$C$5,0)*'NG Inputs'!$B$10/$D$5)*(1-'NG Inputs'!$B$4)+IF($D$5=1,(1-IF(OR($D$5=2,MOD(A29,2)=1),1,0))*$D$3*'NG Inputs'!$B$10*(1-'NG Inputs'!$B$4)/2,0)-IF(MOD(A29,2)=0,INDEX($B$11:$D$25,B29,2)*(1-'NG Inputs'!$B$4),0) | E29: =$E$3+IF(OR($D$5=2,MOD(A29,2)=1),1,0)*(MIN('NG Inputs'!$B$12*$E$3/$C$5,'NG Inputs'!$B$9)*($B$5-'NG Inputs'!$B$5-'NG Inputs'!$B$6-2*'NG Inputs'!$B$7*SQRT(MIN('NG Inputs'!$B$12*$E$3/$C$5,'NG Inputs'!$B$9)/'NG Inputs'!$B$8))+MAX($E$3-MIN('NG Inputs'!$B$12*$E$3/$C$5,'NG Inputs'!$B$9)*$C$5,0)*'NG Inputs'!$B$10/$D$5)*(1-'NG Inputs'!$B$4)+IF($D$5=1,(1-IF(OR($D$5=2,MOD(A29,2)=1),1,0))*$E$3*'NG Inputs'!$B$10*(1-'NG Inputs'!$B$4)/2,0)-IF(MOD(A29,2)=0,INDEX($B$11:$D$25,B29,3)*(1-'NG Inputs'!$B$4),0) | F29: =$C$3+IF(OR($D$6=2,MOD(A29,2)=1),1,0)*(MIN('NG Inputs'!$B$12*$C$3/$C$6,'NG Inputs'!$B$9)*($B$6-'NG Inputs'!$B$5-'NG Inputs'!$B$6-2*'NG Inputs'!$B$7*SQRT(MIN('NG Inputs'!$B$12*$C$3/$C$6,'NG Inputs'!$B$9)/'NG Inputs'!$B$8))+MAX($C$3-MIN('NG Inputs'!$B$12*$C$3/$C$6,'NG Inputs'!$B$9)*$C$6,0)*'NG Inputs'!$B$10/$D$6)*(1-'NG Inputs'!$B$4)+IF($D$6=1,(1-IF(OR($D$6=2,MOD(A29,2)=1),1,0))*$C$3*'NG Inputs'!$B$10*(1-'NG Inputs'!$B$4)/2,0)-IF(MOD(A29,2)=0,INDEX($B$11:$D$25,B29,1)*(1-'NG Inputs'!$B$4),0) | G29: =$D$3+IF(OR($D$6=2,MOD(A29,2)=1),1,0)*(MIN('NG Inputs'!$B$12*$D$3/$C$6,'NG Inputs'!$B$9)*($B$6-'NG Inputs'!$B$5-'NG Inputs'!$B$6-2*'NG Inputs'!$B$7*SQRT(MIN('NG Inputs'!$B$12*$D$3/$C$6,'NG Inputs'!$B$9)/'NG Inputs'!$B$8))+MAX($D$3-MIN('NG Inputs'!$B$12*$D$3/$C$6,'NG Inputs'!$B$9)*$C$6,0)*'NG Inputs'!$B$10/$D$6)*(1-'NG Inputs'!$B$4)+IF($D$6=1,(1-IF(OR($D$6=2,MOD(A29,2)=1),1,0))*$D$3*'NG Inputs'!$B$10*(1-'NG Inputs'!$B$4)/2,0)-IF(MOD(A29,2)=0,INDEX($B$11:$D$25,B29,2)*(1-'NG Inputs'!$B$4),0) | H29: =$E$3+IF(OR($D$6=2,MOD(A29,2)=1),1,0)*(MIN('NG Inputs'!$B$12*$E$3/$C$6,'NG Inputs'!$B$9)*($B$6-'NG Inputs'!$B$5-'NG Inputs'!$B$6-2*'NG Inputs'!$B$7*SQRT(MIN('NG Inputs'!$B$12*$E$3/$C$6,'NG Inputs'!$B$9)/'NG Inputs'!$B$8))+MAX($E$3-MIN('NG Inputs'!$B$12*$E$3/$C$6,'NG Inputs'!$B$9)*$C$6,0)*'NG Inputs'!$B$10/$D$6)*(1-'NG Inputs'!$B$4)+IF($D$6=1,(1-IF(OR($D$6=2,MOD(A29,2)=1),1,0))*$E$3*'NG Inputs'!$B$10*(1-'NG Inputs'!$B$4)/2,0)-IF(MOD(A29,2)=0,INDEX($B$11:$D$25,B29,3)*(1-'NG Inputs'!$B$4),0) | I29: =$C$3+IF(OR($D$7=2,MOD(A29,2)=1),1,0)*(MIN('NG Inputs'!$B$12*$C$3/$C$7,'NG Inputs'!$B$9)*($B$7-'NG Inputs'!$B$5-'NG Inputs'!$B$6-2*'NG Inputs'!$B$7*SQRT(MIN('NG Inputs'!$B$12*$C$3/$C$7,'NG Inputs'!$B$9)/'NG Inputs'!$B$8))+MAX($C$3-MIN('NG Inputs'!$B$12*$C$3/$C$7,'NG Inputs'!$B$9)*$C$7,0)*'NG Inputs'!$B$10/$D$7)*(1-'NG Inputs'!$B$4)+IF($D$7=1,(1-IF(OR($D$7=2,MOD(A29,2)=1),1,0))*$C$3*'NG Inputs'!$B$10*(1-'NG Inputs'!$B$4)/2,0)-IF(MOD(A29,2)=0,INDEX($B$11:$D$25,B29,1)*(1-'NG Inputs'!$B$4),0) | J29: =$D$3+IF(OR($D$7=2,MOD(A29,2)=1),1,0)*(MIN('NG Inputs'!$B$12*$D$3/$C$7,'NG Inputs'!$B$9)*($B$7-'NG Inputs'!$B$5-'NG Inputs'!$B$6-2*'NG Inputs'!$B$7*SQRT(MIN('NG Inputs'!$B$12*$D$3/$C$7,'NG Inputs'!$B$9)/'NG Inputs'!$B$8))+MAX($D$3-MIN('NG Inputs'!$B$12*$D$3/$C$7,'NG Inputs'!$B$9)*$C$7,0)*'NG Inputs'!$B$10/$D$7)*(1-'NG Inputs'!$B$4)+IF($D$7=1,(1-IF(OR($D$7=2,MOD(A29,2)=1),1,0))*$D$3*'NG Inputs'!$B$10*(1-'NG Inputs'!$B$4)/2,0)-IF(MOD(A29,2)=0,INDEX($B$11:$D$25,B29,2)*(1-'NG Inputs'!$B$4),0) | K29: =$E$3+IF(OR($D$7=2,MOD(A29,2)=1),1,0)*(MIN('NG Inputs'!$B$12*$E$3/$C$7,'NG Inputs'!$B$9)*($B$7-'NG Inputs'!$B$5-'NG Inputs'!$B$6-2*'NG Inputs'!$B$7*SQRT(MIN('NG Inputs'!$B$12*$E$3/$C$7,'NG Inputs'!$B$9)/'NG Inputs'!$B$8))+MAX($E$3-MIN('NG Inputs'!$B$12*$E$3/$C$7,'NG Inputs'!$B$9)*$C$7,0)*'NG Inputs'!$B$10/$D$7)*(1-'NG Inputs'!$B$4)+IF($D$7=1,(1-IF(OR($D$7=2,MOD(A29,2)=1),1,0))*$E$3*'NG Inputs'!$B$10*(1-'NG Inputs'!$B$4)/2,0)-IF(MOD(A29,2)=0,INDEX($B$11:$D$25,B29,3)*(1-'NG Inputs'!$B$4),0)
A30: 2 | B30: =ROUNDUP(A30/2,0) | C30: =C29+IF(OR($D$5=2,MOD(A30,2)=1),1,0)*(MIN('NG Inputs'!$B$12*C29/$C$5,'NG Inputs'!$B$9)*($B$5-'NG Inputs'!$B$5-'NG Inputs'!$B$6-2*'NG Inputs'!$B$7*SQRT(MIN('NG Inputs'!$B$12*C29/$C$5,'NG Inputs'!$B$9)/'NG Inputs'!$B$8))+MAX(C29-MIN('NG Inputs'!$B$12*C29/$C$5,'NG Inputs'!$B$9)*$C$5,0)*'NG Inputs'!$B$10/$D$5)*(1-'NG Inputs'!$B$4)+IF($D$5=1,(1-IF(OR($D$5=2,MOD(A30,2)=1),1,0))*C29*'NG Inputs'!$B$10*(1-'NG Inputs'!$B$4)/2,0)-IF(MOD(A30,2)=0,INDEX($B$11:$D$25,B30,1)*(1-'NG Inputs'!$B$4),0) | D30: =D29+IF(OR($D$5=2,MOD(A30,2)=1),1,0)*(MIN('NG Inputs'!$B$12*D29/$C$5,'NG Inputs'!$B$9)*($B$5-'NG Inputs'!$B$5-'NG Inputs'!$B$6-2*'NG Inputs'!$B$7*SQRT(MIN('NG Inputs'!$B$12*D29/$C$5,'NG Inputs'!$B$9)/'NG Inputs'!$B$8))+MAX(D29-MIN('NG Inputs'!$B$12*D29/$C$5,'NG Inputs'!$B$9)*$C$5,0)*'NG Inputs'!$B$10/$D$5)*(1-'NG Inputs'!$B$4)+IF($D$5=1,(1-IF(OR($D$5=2,MOD(A30,2)=1),1,0))*D29*'NG Inputs'!$B$10*(1-'NG Inputs'!$B$4)/2,0)-IF(MOD(A30,2)=0,INDEX($B$11:$D$25,B30,2)*(1-'NG Inputs'!$B$4),0) | E30: =E29+IF(OR($D$5=2,MOD(A30,2)=1),1,0)*(MIN('NG Inputs'!$B$12*E29/$C$5,'NG Inputs'!$B$9)*($B$5-'NG Inputs'!$B$5-'NG Inputs'!$B$6-2*'NG Inputs'!$B$7*SQRT(MIN('NG Inputs'!$B$12*E29/$C$5,'NG Inputs'!$B$9)/'NG Inputs'!$B$8))+MAX(E29-MIN('NG Inputs'!$B$12*E29/$C$5,'NG Inputs'!$B$9)*$C$5,0)*'NG Inputs'!$B$10/$D$5)*(1-'NG Inputs'!$B$4)+IF($D$5=1,(1-IF(OR($D$5=2,MOD(A30,2)=1),1,0))*E29*'NG Inputs'!$B$10*(1-'NG Inputs'!$B$4)/2,0)-IF(MOD(A30,2)=0,INDEX($B$11:$D$25,B30,3)*(1-'NG Inputs'!$B$4),0) | F30: =F29+IF(OR($D$6=2,MOD(A30,2)=1),1,0)*(MIN('NG Inputs'!$B$12*F29/$C$6,'NG Inputs'!$B$9)*($B$6-'NG Inputs'!$B$5-'NG Inputs'!$B$6-2*'NG Inputs'!$B$7*SQRT(MIN('NG Inputs'!$B$12*F29/$C$6,'NG Inputs'!$B$9)/'NG Inputs'!$B$8))+MAX(F29-MIN('NG Inputs'!$B$12*F29/$C$6,'NG Inputs'!$B$9)*$C$6,0)*'NG Inputs'!$B$10/$D$6)*(1-'NG Inputs'!$B$4)+IF($D$6=1,(1-IF(OR($D$6=2,MOD(A30,2)=1),1,0))*F29*'NG Inputs'!$B$10*(1-'NG Inputs'!$B$4)/2,0)-IF(MOD(A30,2)=0,INDEX($B$11:$D$25,B30,1)*(1-'NG Inputs'!$B$4),0) | G30: =G29+IF(OR($D$6=2,MOD(A30,2)=1),1,0)*(MIN('NG Inputs'!$B$12*G29/$C$6,'NG Inputs'!$B$9)*($B$6-'NG Inputs'!$B$5-'NG Inputs'!$B$6-2*'NG Inputs'!$B$7*SQRT(MIN('NG Inputs'!$B$12*G29/$C$6,'NG Inputs'!$B$9)/'NG Inputs'!$B$8))+MAX(G29-MIN('NG Inputs'!$B$12*G29/$C$6,'NG Inputs'!$B$9)*$C$6,0)*'NG Inputs'!$B$10/$D$6)*(1-'NG Inputs'!$B$4)+IF($D$6=1,(1-IF(OR($D$6=2,MOD(A30,2)=1),1,0))*G29*'NG Inputs'!$B$10*(1-'NG Inputs'!$B$4)/2,0)-IF(MOD(A30,2)=0,INDEX($B$11:$D$25,B30,2)*(1-'NG Inputs'!$B$4),0) | H30: =H29+IF(OR($D$6=2,MOD(A30,2)=1),1,0)*(MIN('NG Inputs'!$B$12*H29/$C$6,'NG Inputs'!$B$9)*($B$6-'NG Inputs'!$B$5-'NG Inputs'!$B$6-2*'NG Inputs'!$B$7*SQRT(MIN('NG Inputs'!$B$12*H29/$C$6,'NG Inputs'!$B$9)/'NG Inputs'!$B$8))+MAX(H29-MIN('NG Inputs'!$B$12*H29/$C$6,'NG Inputs'!$B$9)*$C$6,0)*'NG Inputs'!$B$10/$D$6)*(1-'NG Inputs'!$B$4)+IF($D$6=1,(1-IF(OR($D$6=2,MOD(A30,2)=1),1,0))*H29*'NG Inputs'!$B$10*(1-'NG Inputs'!$B$4)/2,0)-IF(MOD(A30,2)=0,INDEX($B$11:$D$25,B30,3)*(1-'NG Inputs'!$B$4),0) | I30: =I29+IF(OR($D$7=2,MOD(A30,2)=1),1,0)*(MIN('NG Inputs'!$B$12*I29/$C$7,'NG Inputs'!$B$9)*($B$7-'NG Inputs'!$B$5-'NG Inputs'!$B$6-2*'NG Inputs'!$B$7*SQRT(MIN('NG Inputs'!$B$12*I29/$C$7,'NG Inputs'!$B$9)/'NG Inputs'!$B$8))+MAX(I29-MIN('NG Inputs'!$B$12*I29/$C$7,'NG Inputs'!$B$9)*$C$7,0)*'NG Inputs'!$B$10/$D$7)*(1-'NG Inputs'!$B$4)+IF($D$7=1,(1-IF(OR($D$7=2,MOD(A30,2)=1),1,0))*I29*'NG Inputs'!$B$10*(1-'NG Inputs'!$B$4)/2,0)-IF(MOD(A30,2)=0,INDEX($B$11:$D$25,B30,1)*(1-'NG Inputs'!$B$4),0) | J30: =J29+IF(OR($D$7=2,MOD(A30,2)=1),1,0)*(MIN('NG Inputs'!$B$12*J29/$C$7,'NG Inputs'!$B$9)*($B$7-'NG Inputs'!$B$5-'NG Inputs'!$B$6-2*'NG Inputs'!$B$7*SQRT(MIN('NG Inputs'!$B$12*J29/$C$7,'NG Inputs'!$B$9)/'NG Inputs'!$B$8))+MAX(J29-MIN('NG Inputs'!$B$12*J29/$C$7,'NG Inputs'!$B$9)*$C$7,0)*'NG Inputs'!$B$10/$D$7)*(1-'NG Inputs'!$B$4)+IF($D$7=1,(1-IF(OR($D$7=2,MOD(A30,2)=1),1,0))*J29*'NG Inputs'!$B$10*(1-'NG Inputs'!$B$4)/2,0)-IF(MOD(A30,2)=0,INDEX($B$11:$D$25,B30,2)*(1-'NG Inputs'!$B$4),0) | K30: =K29+IF(OR($D$7=2,MOD(A30,2)=1),1,0)*(MIN('NG Inputs'!$B$12*K29/$C$7,'NG Inputs'!$B$9)*($B$7-'NG Inputs'!$B$5-'NG Inputs'!$B$6-2*'NG Inputs'!$B$7*SQRT(MIN('NG Inputs'!$B$12*K29/$C$7,'NG Inputs'!$B$9)/'NG Inputs'!$B$8))+MAX(K29-MIN('NG Inputs'!$B$12*K29/$C$7,'NG Inputs'!$B$9)*$C$7,0)*'NG Inputs'!$B$10/$D$7)*(1-'NG Inputs'!$B$4)+IF($D$7=1,(1-IF(OR($D$7=2,MOD(A30,2)=1),1,0))*K29*'NG Inputs'!$B$10*(1-'NG Inputs'!$B$4)/2,0)-IF(MOD(A30,2)=0,INDEX($B$11:$D$25,B30,3)*(1-'NG Inputs'!$B$4),0)
A31: 3 | B31: =ROUNDUP(A31/2,0) | C31: =C30+IF(OR($D$5=2,MOD(A31,2)=1),1,0)*(MIN('NG Inputs'!$B$12*C30/$C$5,'NG Inputs'!$B$9)*($B$5-'NG Inputs'!$B$5-'NG Inputs'!$B$6-2*'NG Inputs'!$B$7*SQRT(MIN('NG Inputs'!$B$12*C30/$C$5,'NG Inputs'!$B$9)/'NG Inputs'!$B$8))+MAX(C30-MIN('NG Inputs'!$B$12*C30/$C$5,'NG Inputs'!$B$9)*$C$5,0)*'NG Inputs'!$B$10/$D$5)*(1-'NG Inputs'!$B$4)+IF($D$5=1,(1-IF(OR($D$5=2,MOD(A31,2)=1),1,0))*C30*'NG Inputs'!$B$10*(1-'NG Inputs'!$B$4)/2,0)-IF(MOD(A31,2)=0,INDEX($B$11:$D$25,B31,1)*(1-'NG Inputs'!$B$4),0) | D31: =D30+IF(OR($D$5=2,MOD(A31,2)=1),1,0)*(MIN('NG Inputs'!$B$12*D30/$C$5,'NG Inputs'!$B$9)*($B$5-'NG Inputs'!$B$5-'NG Inputs'!$B$6-2*'NG Inputs'!$B$7*SQRT(MIN('NG Inputs'!$B$12*D30/$C$5,'NG Inputs'!$B$9)/'NG Inputs'!$B$8))+MAX(D30-MIN('NG Inputs'!$B$12*D30/$C$5,'NG Inputs'!$B$9)*$C$5,0)*'NG Inputs'!$B$10/$D$5)*(1-'NG Inputs'!$B$4)+IF($D$5=1,(1-IF(OR($D$5=2,MOD(A31,2)=1),1,0))*D30*'NG Inputs'!$B$10*(1-'NG Inputs'!$B$4)/2,0)-IF(MOD(A31,2)=0,INDEX($B$11:$D$25,B31,2)*(1-'NG Inputs'!$B$4),0) | E31: =E30+IF(OR($D$5=2,MOD(A31,2)=1),1,0)*(MIN('NG Inputs'!$B$12*E30/$C$5,'NG Inputs'!$B$9)*($B$5-'NG Inputs'!$B$5-'NG Inputs'!$B$6-2*'NG Inputs'!$B$7*SQRT(MIN('NG Inputs'!$B$12*E30/$C$5,'NG Inputs'!$B$9)/'NG Inputs'!$B$8))+MAX(E30-MIN('NG Inputs'!$B$12*E30/$C$5,'NG Inputs'!$B$9)*$C$5,0)*'NG Inputs'!$B$10/$D$5)*(1-'NG Inputs'!$B$4)+IF($D$5=1,(1-IF(OR($D$5=2,MOD(A31,2)=1),1,0))*E30*'NG Inputs'!$B$10*(1-'NG Inputs'!$B$4)/2,0)-IF(MOD(A31,2)=0,INDEX($B$11:$D$25,B31,3)*(1-'NG Inputs'!$B$4),0) | F31: =F30+IF(OR($D$6=2,MOD(A31,2)=1),1,0)*(MIN('NG Inputs'!$B$12*F30/$C$6,'NG Inputs'!$B$9)*($B$6-'NG Inputs'!$B$5-'NG Inputs'!$B$6-2*'NG Inputs'!$B$7*SQRT(MIN('NG Inputs'!$B$12*F30/$C$6,'NG Inputs'!$B$9)/'NG Inputs'!$B$8))+MAX(F30-MIN('NG Inputs'!$B$12*F30/$C$6,'NG Inputs'!$B$9)*$C$6,0)*'NG Inputs'!$B$10/$D$6)*(1-'NG Inputs'!$B$4)+IF($D$6=1,(1-IF(OR($D$6=2,MOD(A31,2)=1),1,0))*F30*'NG Inputs'!$B$10*(1-'NG Inputs'!$B$4)/2,0)-IF(MOD(A31,2)=0,INDEX($B$11:$D$25,B31,1)*(1-'NG Inputs'!$B$4),0) | G31: =G30+IF(OR($D$6=2,MOD(A31,2)=1),1,0)*(MIN('NG Inputs'!$B$12*G30/$C$6,'NG Inputs'!$B$9)*($B$6-'NG Inputs'!$B$5-'NG Inputs'!$B$6-2*'NG Inputs'!$B$7*SQRT(MIN('NG Inputs'!$B$12*G30/$C$6,'NG Inputs'!$B$9)/'NG Inputs'!$B$8))+MAX(G30-MIN('NG Inputs'!$B$12*G30/$C$6,'NG Inputs'!$B$9)*$C$6,0)*'NG Inputs'!$B$10/$D$6)*(1-'NG Inputs'!$B$4)+IF($D$6=1,(1-IF(OR($D$6=2,MOD(A31,2)=1),1,0))*G30*'NG Inputs'!$B$10*(1-'NG Inputs'!$B$4)/2,0)-IF(MOD(A31,2)=0,INDEX($B$11:$D$25,B31,2)*(1-'NG Inputs'!$B$4),0) | H31: =H30+IF(OR($D$6=2,MOD(A31,2)=1),1,0)*(MIN('NG Inputs'!$B$12*H30/$C$6,'NG Inputs'!$B$9)*($B$6-'NG Inputs'!$B$5-'NG Inputs'!$B$6-2*'NG Inputs'!$B$7*SQRT(MIN('NG Inputs'!$B$12*H30/$C$6,'NG Inputs'!$B$9)/'NG Inputs'!$B$8))+MAX(H30-MIN('NG Inputs'!$B$12*H30/$C$6,'NG Inputs'!$B$9)*$C$6,0)*'NG Inputs'!$B$10/$D$6)*(1-'NG Inputs'!$B$4)+IF($D$6=1,(1-IF(OR($D$6=2,MOD(A31,2)=1),1,0))*H30*'NG Inputs'!$B$10*(1-'NG Inputs'!$B$4)/2,0)-IF(MOD(A31,2)=0,INDEX($B$11:$D$25,B31,3)*(1-'NG Inputs'!$B$4),0) | I31: =I30+IF(OR($D$7=2,MOD(A31,2)=1),1,0)*(MIN('NG Inputs'!$B$12*I30/$C$7,'NG Inputs'!$B$9)*($B$7-'NG Inputs'!$B$5-'NG Inputs'!$B$6-2*'NG Inputs'!$B$7*SQRT(MIN('NG Inputs'!$B$12*I30/$C$7,'NG Inputs'!$B$9)/'NG Inputs'!$B$8))+MAX(I30-MIN('NG Inputs'!$B$12*I30/$C$7,'NG Inputs'!$B$9)*$C$7,0)*'NG Inputs'!$B$10/$D$7)*(1-'NG Inputs'!$B$4)+IF($D$7=1,(1-IF(OR($D$7=2,MOD(A31,2)=1),1,0))*I30*'NG Inputs'!$B$10*(1-'NG Inputs'!$B$4)/2,0)-IF(MOD(A31,2)=0,INDEX($B$11:$D$25,B31,1)*(1-'NG Inputs'!$B$4),0) | J31: =J30+IF(OR($D$7=2,MOD(A31,2)=1),1,0)*(MIN('NG Inputs'!$B$12*J30/$C$7,'NG Inputs'!$B$9)*($B$7-'NG Inputs'!$B$5-'NG Inputs'!$B$6-2*'NG Inputs'!$B$7*SQRT(MIN('NG Inputs'!$B$12*J30/$C$7,'NG Inputs'!$B$9)/'NG Inputs'!$B$8))+MAX(J30-MIN('NG Inputs'!$B$12*J30/$C$7,'NG Inputs'!$B$9)*$C$7,0)*'NG Inputs'!$B$10/$D$7)*(1-'NG Inputs'!$B$4)+IF($D$7=1,(1-IF(OR($D$7=2,MOD(A31,2)=1),1,0))*J30*'NG Inputs'!$B$10*(1-'NG Inputs'!$B$4)/2,0)-IF(MOD(A31,2)=0,INDEX($B$11:$D$25,B31,2)*(1-'NG Inputs'!$B$4),0) | K31: =K30+IF(OR($D$7=2,MOD(A31,2)=1),1,0)*(MIN('NG Inputs'!$B$12*K30/$C$7,'NG Inputs'!$B$9)*($B$7-'NG Inputs'!$B$5-'NG Inputs'!$B$6-2*'NG Inputs'!$B$7*SQRT(MIN('NG Inputs'!$B$12*K30/$C$7,'NG Inputs'!$B$9)/'NG Inputs'!$B$8))+MAX(K30-MIN('NG Inputs'!$B$12*K30/$C$7,'NG Inputs'!$B$9)*$C$7,0)*'NG Inputs'!$B$10/$D$7)*(1-'NG Inputs'!$B$4)+IF($D$7=1,(1-IF(OR($D$7=2,MOD(A31,2)=1),1,0))*K30*'NG Inputs'!$B$10*(1-'NG Inputs'!$B$4)/2,0)-IF(MOD(A31,2)=0,INDEX($B$11:$D$25,B31,3)*(1-'NG Inputs'!$B$4),0)
A32: 4 | B32: =ROUNDUP(A32/2,0) | C32: =C31+IF(OR($D$5=2,MOD(A32,2)=1),1,0)*(MIN('NG Inputs'!$B$12*C31/$C$5,'NG Inputs'!$B$9)*($B$5-'NG Inputs'!$B$5-'NG Inputs'!$B$6-2*'NG Inputs'!$B$7*SQRT(MIN('NG Inputs'!$B$12*C31/$C$5,'NG Inputs'!$B$9)/'NG Inputs'!$B$8))+MAX(C31-MIN('NG Inputs'!$B$12*C31/$C$5,'NG Inputs'!$B$9)*$C$5,0)*'NG Inputs'!$B$10/$D$5)*(1-'NG Inputs'!$B$4)+IF($D$5=1,(1-IF(OR($D$5=2,MOD(A32,2)=1),1,0))*C31*'NG Inputs'!$B$10*(1-'NG Inputs'!$B$4)/2,0)-IF(MOD(A32,2)=0,INDEX($B$11:$D$25,B32,1)*(1-'NG Inputs'!$B$4),0) | D32: =D31+IF(OR($D$5=2,MOD(A32,2)=1),1,0)*(MIN('NG Inputs'!$B$12*D31/$C$5,'NG Inputs'!$B$9)*($B$5-'NG Inputs'!$B$5-'NG Inputs'!$B$6-2*'NG Inputs'!$B$7*SQRT(MIN('NG Inputs'!$B$12*D31/$C$5,'NG Inputs'!$B$9)/'NG Inputs'!$B$8))+MAX(D31-MIN('NG Inputs'!$B$12*D31/$C$5,'NG Inputs'!$B$9)*$C$5,0)*'NG Inputs'!$B$10/$D$5)*(1-'NG Inputs'!$B$4)+IF($D$5=1,(1-IF(OR($D$5=2,MOD(A32,2)=1),1,0))*D31*'NG Inputs'!$B$10*(1-'NG Inputs'!$B$4)/2,0)-IF(MOD(A32,2)=0,INDEX($B$11:$D$25,B32,2)*(1-'NG Inputs'!$B$4),0) | E32: =E31+IF(OR($D$5=2,MOD(A32,2)=1),1,0)*(MIN('NG Inputs'!$B$12*E31/$C$5,'NG Inputs'!$B$9)*($B$5-'NG Inputs'!$B$5-'NG Inputs'!$B$6-2*'NG Inputs'!$B$7*SQRT(MIN('NG Inputs'!$B$12*E31/$C$5,'NG Inputs'!$B$9)/'NG Inputs'!$B$8))+MAX(E31-MIN('NG Inputs'!$B$12*E31/$C$5,'NG Inputs'!$B$9)*$C$5,0)*'NG Inputs'!$B$10/$D$5)*(1-'NG Inputs'!$B$4)+IF($D$5=1,(1-IF(OR($D$5=2,MOD(A32,2)=1),1,0))*E31*'NG Inputs'!$B$10*(1-'NG Inputs'!$B$4)/2,0)-IF(MOD(A32,2)=0,INDEX($B$11:$D$25,B32,3)*(1-'NG Inputs'!$B$4),0) | F32: =F31+IF(OR($D$6=2,MOD(A32,2)=1),1,0)*(MIN('NG Inputs'!$B$12*F31/$C$6,'NG Inputs'!$B$9)*($B$6-'NG Inputs'!$B$5-'NG Inputs'!$B$6-2*'NG Inputs'!$B$7*SQRT(MIN('NG Inputs'!$B$12*F31/$C$6,'NG Inputs'!$B$9)/'NG Inputs'!$B$8))+MAX(F31-MIN('NG Inputs'!$B$12*F31/$C$6,'NG Inputs'!$B$9)*$C$6,0)*'NG Inputs'!$B$10/$D$6)*(1-'NG Inputs'!$B$4)+IF($D$6=1,(1-IF(OR($D$6=2,MOD(A32,2)=1),1,0))*F31*'NG Inputs'!$B$10*(1-'NG Inputs'!$B$4)/2,0)-IF(MOD(A32,2)=0,INDEX($B$11:$D$25,B32,1)*(1-'NG Inputs'!$B$4),0) | G32: =G31+IF(OR($D$6=2,MOD(A32,2)=1),1,0)*(MIN('NG Inputs'!$B$12*G31/$C$6,'NG Inputs'!$B$9)*($B$6-'NG Inputs'!$B$5-'NG Inputs'!$B$6-2*'NG Inputs'!$B$7*SQRT(MIN('NG Inputs'!$B$12*G31/$C$6,'NG Inputs'!$B$9)/'NG Inputs'!$B$8))+MAX(G31-MIN('NG Inputs'!$B$12*G31/$C$6,'NG Inputs'!$B$9)*$C$6,0)*'NG Inputs'!$B$10/$D$6)*(1-'NG Inputs'!$B$4)+IF($D$6=1,(1-IF(OR($D$6=2,MOD(A32,2)=1),1,0))*G31*'NG Inputs'!$B$10*(1-'NG Inputs'!$B$4)/2,0)-IF(MOD(A32,2)=0,INDEX($B$11:$D$25,B32,2)*(1-'NG Inputs'!$B$4),0) | H32: =H31+IF(OR($D$6=2,MOD(A32,2)=1),1,0)*(MIN('NG Inputs'!$B$12*H31/$C$6,'NG Inputs'!$B$9)*($B$6-'NG Inputs'!$B$5-'NG Inputs'!$B$6-2*'NG Inputs'!$B$7*SQRT(MIN('NG Inputs'!$B$12*H31/$C$6,'NG Inputs'!$B$9)/'NG Inputs'!$B$8))+MAX(H31-MIN('NG Inputs'!$B$12*H31/$C$6,'NG Inputs'!$B$9)*$C$6,0)*'NG Inputs'!$B$10/$D$6)*(1-'NG Inputs'!$B$4)+IF($D$6=1,(1-IF(OR($D$6=2,MOD(A32,2)=1),1,0))*H31*'NG Inputs'!$B$10*(1-'NG Inputs'!$B$4)/2,0)-IF(MOD(A32,2)=0,INDEX($B$11:$D$25,B32,3)*(1-'NG Inputs'!$B$4),0) | I32: =I31+IF(OR($D$7=2,MOD(A32,2)=1),1,0)*(MIN('NG Inputs'!$B$12*I31/$C$7,'NG Inputs'!$B$9)*($B$7-'NG Inputs'!$B$5-'NG Inputs'!$B$6-2*'NG Inputs'!$B$7*SQRT(MIN('NG Inputs'!$B$12*I31/$C$7,'NG Inputs'!$B$9)/'NG Inputs'!$B$8))+MAX(I31-MIN('NG Inputs'!$B$12*I31/$C$7,'NG Inputs'!$B$9)*$C$7,0)*'NG Inputs'!$B$10/$D$7)*(1-'NG Inputs'!$B$4)+IF($D$7=1,(1-IF(OR($D$7=2,MOD(A32,2)=1),1,0))*I31*'NG Inputs'!$B$10*(1-'NG Inputs'!$B$4)/2,0)-IF(MOD(A32,2)=0,INDEX($B$11:$D$25,B32,1)*(1-'NG Inputs'!$B$4),0) | J32: =J31+IF(OR($D$7=2,MOD(A32,2)=1),1,0)*(MIN('NG Inputs'!$B$12*J31/$C$7,'NG Inputs'!$B$9)*($B$7-'NG Inputs'!$B$5-'NG Inputs'!$B$6-2*'NG Inputs'!$B$7*SQRT(MIN('NG Inputs'!$B$12*J31/$C$7,'NG Inputs'!$B$9)/'NG Inputs'!$B$8))+MAX(J31-MIN('NG Inputs'!$B$12*J31/$C$7,'NG Inputs'!$B$9)*$C$7,0)*'NG Inputs'!$B$10/$D$7)*(1-'NG Inputs'!$B$4)+IF($D$7=1,(1-IF(OR($D$7=2,MOD(A32,2)=1),1,0))*J31*'NG Inputs'!$B$10*(1-'NG Inputs'!$B$4)/2,0)-IF(MOD(A32,2)=0,INDEX($B$11:$D$25,B32,2)*(1-'NG Inputs'!$B$4),0) | K32: =K31+IF(OR($D$7=2,MOD(A32,2)=1),1,0)*(MIN('NG Inputs'!$B$12*K31/$C$7,'NG Inputs'!$B$9)*($B$7-'NG Inputs'!$B$5-'NG Inputs'!$B$6-2*'NG Inputs'!$B$7*SQRT(MIN('NG Inputs'!$B$12*K31/$C$7,'NG Inputs'!$B$9)/'NG Inputs'!$B$8))+MAX(K31-MIN('NG Inputs'!$B$12*K31/$C$7,'NG Inputs'!$B$9)*$C$7,0)*'NG Inputs'!$B$10/$D$7)*(1-'NG Inputs'!$B$4)+IF($D$7=1,(1-IF(OR($D$7=2,MOD(A32,2)=1),1,0))*K31*'NG Inputs'!$B$10*(1-'NG Inputs'!$B$4)/2,0)-IF(MOD(A32,2)=0,INDEX($B$11:$D$25,B32,3)*(1-'NG Inputs'!$B$4),0)
A33: 5 | B33: =ROUNDUP(A33/2,0) | C33: =C32+IF(OR($D$5=2,MOD(A33,2)=1),1,0)*(MIN('NG Inputs'!$B$12*C32/$C$5,'NG Inputs'!$B$9)*($B$5-'NG Inputs'!$B$5-'NG Inputs'!$B$6-2*'NG Inputs'!$B$7*SQRT(MIN('NG Inputs'!$B$12*C32/$C$5,'NG Inputs'!$B$9)/'NG Inputs'!$B$8))+MAX(C32-MIN('NG Inputs'!$B$12*C32/$C$5,'NG Inputs'!$B$9)*$C$5,0)*'NG Inputs'!$B$10/$D$5)*(1-'NG Inputs'!$B$4)+IF($D$5=1,(1-IF(OR($D$5=2,MOD(A33,2)=1),1,0))*C32*'NG Inputs'!$B$10*(1-'NG Inputs'!$B$4)/2,0)-IF(MOD(A33,2)=0,INDEX($B$11:$D$25,B33,1)*(1-'NG Inputs'!$B$4),0) | D33: =D32+IF(OR($D$5=2,MOD(A33,2)=1),1,0)*(MIN('NG Inputs'!$B$12*D32/$C$5,'NG Inputs'!$B$9)*($B$5-'NG Inputs'!$B$5-'NG Inputs'!$B$6-2*'NG Inputs'!$B$7*SQRT(MIN('NG Inputs'!$B$12*D32/$C$5,'NG Inputs'!$B$9)/'NG Inputs'!$B$8))+MAX(D32-MIN('NG Inputs'!$B$12*D32/$C$5,'NG Inputs'!$B$9)*$C$5,0)*'NG Inputs'!$B$10/$D$5)*(1-'NG Inputs'!$B$4)+IF($D$5=1,(1-IF(OR($D$5=2,MOD(A33,2)=1),1,0))*D32*'NG Inputs'!$B$10*(1-'NG Inputs'!$B$4)/2,0)-IF(MOD(A33,2)=0,INDEX($B$11:$D$25,B33,2)*(1-'NG Inputs'!$B$4),0) | E33: =E32+IF(OR($D$5=2,MOD(A33,2)=1),1,0)*(MIN('NG Inputs'!$B$12*E32/$C$5,'NG Inputs'!$B$9)*($B$5-'NG Inputs'!$B$5-'NG Inputs'!$B$6-2*'NG Inputs'!$B$7*SQRT(MIN('NG Inputs'!$B$12*E32/$C$5,'NG Inputs'!$B$9)/'NG Inputs'!$B$8))+MAX(E32-MIN('NG Inputs'!$B$12*E32/$C$5,'NG Inputs'!$B$9)*$C$5,0)*'NG Inputs'!$B$10/$D$5)*(1-'NG Inputs'!$B$4)+IF($D$5=1,(1-IF(OR($D$5=2,MOD(A33,2)=1),1,0))*E32*'NG Inputs'!$B$10*(1-'NG Inputs'!$B$4)/2,0)-IF(MOD(A33,2)=0,INDEX($B$11:$D$25,B33,3)*(1-'NG Inputs'!$B$4),0) | F33: =F32+IF(OR($D$6=2,MOD(A33,2)=1),1,0)*(MIN('NG Inputs'!$B$12*F32/$C$6,'NG Inputs'!$B$9)*($B$6-'NG Inputs'!$B$5-'NG Inputs'!$B$6-2*'NG Inputs'!$B$7*SQRT(MIN('NG Inputs'!$B$12*F32/$C$6,'NG Inputs'!$B$9)/'NG Inputs'!$B$8))+MAX(F32-MIN('NG Inputs'!$B$12*F32/$C$6,'NG Inputs'!$B$9)*$C$6,0)*'NG Inputs'!$B$10/$D$6)*(1-'NG Inputs'!$B$4)+IF($D$6=1,(1-IF(OR($D$6=2,MOD(A33,2)=1),1,0))*F32*'NG Inputs'!$B$10*(1-'NG Inputs'!$B$4)/2,0)-IF(MOD(A33,2)=0,INDEX($B$11:$D$25,B33,1)*(1-'NG Inputs'!$B$4),0) | G33: =G32+IF(OR($D$6=2,MOD(A33,2)=1),1,0)*(MIN('NG Inputs'!$B$12*G32/$C$6,'NG Inputs'!$B$9)*($B$6-'NG Inputs'!$B$5-'NG Inputs'!$B$6-2*'NG Inputs'!$B$7*SQRT(MIN('NG Inputs'!$B$12*G32/$C$6,'NG Inputs'!$B$9)/'NG Inputs'!$B$8))+MAX(G32-MIN('NG Inputs'!$B$12*G32/$C$6,'NG Inputs'!$B$9)*$C$6,0)*'NG Inputs'!$B$10/$D$6)*(1-'NG Inputs'!$B$4)+IF($D$6=1,(1-IF(OR($D$6=2,MOD(A33,2)=1),1,0))*G32*'NG Inputs'!$B$10*(1-'NG Inputs'!$B$4)/2,0)-IF(MOD(A33,2)=0,INDEX($B$11:$D$25,B33,2)*(1-'NG Inputs'!$B$4),0) | H33: =H32+IF(OR($D$6=2,MOD(A33,2)=1),1,0)*(MIN('NG Inputs'!$B$12*H32/$C$6,'NG Inputs'!$B$9)*($B$6-'NG Inputs'!$B$5-'NG Inputs'!$B$6-2*'NG Inputs'!$B$7*SQRT(MIN('NG Inputs'!$B$12*H32/$C$6,'NG Inputs'!$B$9)/'NG Inputs'!$B$8))+MAX(H32-MIN('NG Inputs'!$B$12*H32/$C$6,'NG Inputs'!$B$9)*$C$6,0)*'NG Inputs'!$B$10/$D$6)*(1-'NG Inputs'!$B$4)+IF($D$6=1,(1-IF(OR($D$6=2,MOD(A33,2)=1),1,0))*H32*'NG Inputs'!$B$10*(1-'NG Inputs'!$B$4)/2,0)-IF(MOD(A33,2)=0,INDEX($B$11:$D$25,B33,3)*(1-'NG Inputs'!$B$4),0) | I33: =I32+IF(OR($D$7=2,MOD(A33,2)=1),1,0)*(MIN('NG Inputs'!$B$12*I32/$C$7,'NG Inputs'!$B$9)*($B$7-'NG Inputs'!$B$5-'NG Inputs'!$B$6-2*'NG Inputs'!$B$7*SQRT(MIN('NG Inputs'!$B$12*I32/$C$7,'NG Inputs'!$B$9)/'NG Inputs'!$B$8))+MAX(I32-MIN('NG Inputs'!$B$12*I32/$C$7,'NG Inputs'!$B$9)*$C$7,0)*'NG Inputs'!$B$10/$D$7)*(1-'NG Inputs'!$B$4)+IF($D$7=1,(1-IF(OR($D$7=2,MOD(A33,2)=1),1,0))*I32*'NG Inputs'!$B$10*(1-'NG Inputs'!$B$4)/2,0)-IF(MOD(A33,2)=0,INDEX($B$11:$D$25,B33,1)*(1-'NG Inputs'!$B$4),0) | J33: =J32+IF(OR($D$7=2,MOD(A33,2)=1),1,0)*(MIN('NG Inputs'!$B$12*J32/$C$7,'NG Inputs'!$B$9)*($B$7-'NG Inputs'!$B$5-'NG Inputs'!$B$6-2*'NG Inputs'!$B$7*SQRT(MIN('NG Inputs'!$B$12*J32/$C$7,'NG Inputs'!$B$9)/'NG Inputs'!$B$8))+MAX(J32-MIN('NG Inputs'!$B$12*J32/$C$7,'NG Inputs'!$B$9)*$C$7,0)*'NG Inputs'!$B$10/$D$7)*(1-'NG Inputs'!$B$4)+IF($D$7=1,(1-IF(OR($D$7=2,MOD(A33,2)=1),1,0))*J32*'NG Inputs'!$B$10*(1-'NG Inputs'!$B$4)/2,0)-IF(MOD(A33,2)=0,INDEX($B$11:$D$25,B33,2)*(1-'NG Inputs'!$B$4),0) | K33: =K32+IF(OR($D$7=2,MOD(A33,2)=1),1,0)*(MIN('NG Inputs'!$B$12*K32/$C$7,'NG Inputs'!$B$9)*($B$7-'NG Inputs'!$B$5-'NG Inputs'!$B$6-2*'NG Inputs'!$B$7*SQRT(MIN('NG Inputs'!$B$12*K32/$C$7,'NG Inputs'!$B$9)/'NG Inputs'!$B$8))+MAX(K32-MIN('NG Inputs'!$B$12*K32/$C$7,'NG Inputs'!$B$9)*$C$7,0)*'NG Inputs'!$B$10/$D$7)*(1-'NG Inputs'!$B$4)+IF($D$7=1,(1-IF(OR($D$7=2,MOD(A33,2)=1),1,0))*K32*'NG Inputs'!$B$10*(1-'NG Inputs'!$B$4)/2,0)-IF(MOD(A33,2)=0,INDEX($B$11:$D$25,B33,3)*(1-'NG Inputs'!$B$4),0)
A34: 6 | B34: =ROUNDUP(A34/2,0) | C34: =C33+IF(OR($D$5=2,MOD(A34,2)=1),1,0)*(MIN('NG Inputs'!$B$12*C33/$C$5,'NG Inputs'!$B$9)*($B$5-'NG Inputs'!$B$5-'NG Inputs'!$B$6-2*'NG Inputs'!$B$7*SQRT(MIN('NG Inputs'!$B$12*C33/$C$5,'NG Inputs'!$B$9)/'NG Inputs'!$B$8))+MAX(C33-MIN('NG Inputs'!$B$12*C33/$C$5,'NG Inputs'!$B$9)*$C$5,0)*'NG Inputs'!$B$10/$D$5)*(1-'NG Inputs'!$B$4)+IF($D$5=1,(1-IF(OR($D$5=2,MOD(A34,2)=1),1,0))*C33*'NG Inputs'!$B$10*(1-'NG Inputs'!$B$4)/2,0)-IF(MOD(A34,2)=0,INDEX($B$11:$D$25,B34,1)*(1-'NG Inputs'!$B$4),0) | D34: =D33+IF(OR($D$5=2,MOD(A34,2)=1),1,0)*(MIN('NG Inputs'!$B$12*D33/$C$5,'NG Inputs'!$B$9)*($B$5-'NG Inputs'!$B$5-'NG Inputs'!$B$6-2*'NG Inputs'!$B$7*SQRT(MIN('NG Inputs'!$B$12*D33/$C$5,'NG Inputs'!$B$9)/'NG Inputs'!$B$8))+MAX(D33-MIN('NG Inputs'!$B$12*D33/$C$5,'NG Inputs'!$B$9)*$C$5,0)*'NG Inputs'!$B$10/$D$5)*(1-'NG Inputs'!$B$4)+IF($D$5=1,(1-IF(OR($D$5=2,MOD(A34,2)=1),1,0))*D33*'NG Inputs'!$B$10*(1-'NG Inputs'!$B$4)/2,0)-IF(MOD(A34,2)=0,INDEX($B$11:$D$25,B34,2)*(1-'NG Inputs'!$B$4),0) | E34: =E33+IF(OR($D$5=2,MOD(A34,2)=1),1,0)*(MIN('NG Inputs'!$B$12*E33/$C$5,'NG Inputs'!$B$9)*($B$5-'NG Inputs'!$B$5-'NG Inputs'!$B$6-2*'NG Inputs'!$B$7*SQRT(MIN('NG Inputs'!$B$12*E33/$C$5,'NG Inputs'!$B$9)/'NG Inputs'!$B$8))+MAX(E33-MIN('NG Inputs'!$B$12*E33/$C$5,'NG Inputs'!$B$9)*$C$5,0)*'NG Inputs'!$B$10/$D$5)*(1-'NG Inputs'!$B$4)+IF($D$5=1,(1-IF(OR($D$5=2,MOD(A34,2)=1),1,0))*E33*'NG Inputs'!$B$10*(1-'NG Inputs'!$B$4)/2,0)-IF(MOD(A34,2)=0,INDEX($B$11:$D$25,B34,3)*(1-'NG Inputs'!$B$4),0) | F34: =F33+IF(OR($D$6=2,MOD(A34,2)=1),1,0)*(MIN('NG Inputs'!$B$12*F33/$C$6,'NG Inputs'!$B$9)*($B$6-'NG Inputs'!$B$5-'NG Inputs'!$B$6-2*'NG Inputs'!$B$7*SQRT(MIN('NG Inputs'!$B$12*F33/$C$6,'NG Inputs'!$B$9)/'NG Inputs'!$B$8))+MAX(F33-MIN('NG Inputs'!$B$12*F33/$C$6,'NG Inputs'!$B$9)*$C$6,0)*'NG Inputs'!$B$10/$D$6)*(1-'NG Inputs'!$B$4)+IF($D$6=1,(1-IF(OR($D$6=2,MOD(A34,2)=1),1,0))*F33*'NG Inputs'!$B$10*(1-'NG Inputs'!$B$4)/2,0)-IF(MOD(A34,2)=0,INDEX($B$11:$D$25,B34,1)*(1-'NG Inputs'!$B$4),0) | G34: =G33+IF(OR($D$6=2,MOD(A34,2)=1),1,0)*(MIN('NG Inputs'!$B$12*G33/$C$6,'NG Inputs'!$B$9)*($B$6-'NG Inputs'!$B$5-'NG Inputs'!$B$6-2*'NG Inputs'!$B$7*SQRT(MIN('NG Inputs'!$B$12*G33/$C$6,'NG Inputs'!$B$9)/'NG Inputs'!$B$8))+MAX(G33-MIN('NG Inputs'!$B$12*G33/$C$6,'NG Inputs'!$B$9)*$C$6,0)*'NG Inputs'!$B$10/$D$6)*(1-'NG Inputs'!$B$4)+IF($D$6=1,(1-IF(OR($D$6=2,MOD(A34,2)=1),1,0))*G33*'NG Inputs'!$B$10*(1-'NG Inputs'!$B$4)/2,0)-IF(MOD(A34,2)=0,INDEX($B$11:$D$25,B34,2)*(1-'NG Inputs'!$B$4),0) | H34: =H33+IF(OR($D$6=2,MOD(A34,2)=1),1,0)*(MIN('NG Inputs'!$B$12*H33/$C$6,'NG Inputs'!$B$9)*($B$6-'NG Inputs'!$B$5-'NG Inputs'!$B$6-2*'NG Inputs'!$B$7*SQRT(MIN('NG Inputs'!$B$12*H33/$C$6,'NG Inputs'!$B$9)/'NG Inputs'!$B$8))+MAX(H33-MIN('NG Inputs'!$B$12*H33/$C$6,'NG Inputs'!$B$9)*$C$6,0)*'NG Inputs'!$B$10/$D$6)*(1-'NG Inputs'!$B$4)+IF($D$6=1,(1-IF(OR($D$6=2,MOD(A34,2)=1),1,0))*H33*'NG Inputs'!$B$10*(1-'NG Inputs'!$B$4)/2,0)-IF(MOD(A34,2)=0,INDEX($B$11:$D$25,B34,3)*(1-'NG Inputs'!$B$4),0) | I34: =I33+IF(OR($D$7=2,MOD(A34,2)=1),1,0)*(MIN('NG Inputs'!$B$12*I33/$C$7,'NG Inputs'!$B$9)*($B$7-'NG Inputs'!$B$5-'NG Inputs'!$B$6-2*'NG Inputs'!$B$7*SQRT(MIN('NG Inputs'!$B$12*I33/$C$7,'NG Inputs'!$B$9)/'NG Inputs'!$B$8))+MAX(I33-MIN('NG Inputs'!$B$12*I33/$C$7,'NG Inputs'!$B$9)*$C$7,0)*'NG Inputs'!$B$10/$D$7)*(1-'NG Inputs'!$B$4)+IF($D$7=1,(1-IF(OR($D$7=2,MOD(A34,2)=1),1,0))*I33*'NG Inputs'!$B$10*(1-'NG Inputs'!$B$4)/2,0)-IF(MOD(A34,2)=0,INDEX($B$11:$D$25,B34,1)*(1-'NG Inputs'!$B$4),0) | J34: =J33+IF(OR($D$7=2,MOD(A34,2)=1),1,0)*(MIN('NG Inputs'!$B$12*J33/$C$7,'NG Inputs'!$B$9)*($B$7-'NG Inputs'!$B$5-'NG Inputs'!$B$6-2*'NG Inputs'!$B$7*SQRT(MIN('NG Inputs'!$B$12*J33/$C$7,'NG Inputs'!$B$9)/'NG Inputs'!$B$8))+MAX(J33-MIN('NG Inputs'!$B$12*J33/$C$7,'NG Inputs'!$B$9)*$C$7,0)*'NG Inputs'!$B$10/$D$7)*(1-'NG Inputs'!$B$4)+IF($D$7=1,(1-IF(OR($D$7=2,MOD(A34,2)=1),1,0))*J33*'NG Inputs'!$B$10*(1-'NG Inputs'!$B$4)/2,0)-IF(MOD(A34,2)=0,INDEX($B$11:$D$25,B34,2)*(1-'NG Inputs'!$B$4),0) | K34: =K33+IF(OR($D$7=2,MOD(A34,2)=1),1,0)*(MIN('NG Inputs'!$B$12*K33/$C$7,'NG Inputs'!$B$9)*($B$7-'NG Inputs'!$B$5-'NG Inputs'!$B$6-2*'NG Inputs'!$B$7*SQRT(MIN('NG Inputs'!$B$12*K33/$C$7,'NG Inputs'!$B$9)/'NG Inputs'!$B$8))+MAX(K33-MIN('NG Inputs'!$B$12*K33/$C$7,'NG Inputs'!$B$9)*$C$7,0)*'NG Inputs'!$B$10/$D$7)*(1-'NG Inputs'!$B$4)+IF($D$7=1,(1-IF(OR($D$7=2,MOD(A34,2)=1),1,0))*K33*'NG Inputs'!$B$10*(1-'NG Inputs'!$B$4)/2,0)-IF(MOD(A34,2)=0,INDEX($B$11:$D$25,B34,3)*(1-'NG Inputs'!$B$4),0)
A35: 7 | B35: =ROUNDUP(A35/2,0) | C35: =C34+IF(OR($D$5=2,MOD(A35,2)=1),1,0)*(MIN('NG Inputs'!$B$12*C34/$C$5,'NG Inputs'!$B$9)*($B$5-'NG Inputs'!$B$5-'NG Inputs'!$B$6-2*'NG Inputs'!$B$7*SQRT(MIN('NG Inputs'!$B$12*C34/$C$5,'NG Inputs'!$B$9)/'NG Inputs'!$B$8))+MAX(C34-MIN('NG Inputs'!$B$12*C34/$C$5,'NG Inputs'!$B$9)*$C$5,0)*'NG Inputs'!$B$10/$D$5)*(1-'NG Inputs'!$B$4)+IF($D$5=1,(1-IF(OR($D$5=2,MOD(A35,2)=1),1,0))*C34*'NG Inputs'!$B$10*(1-'NG Inputs'!$B$4)/2,0)-IF(MOD(A35,2)=0,INDEX($B$11:$D$25,B35,1)*(1-'NG Inputs'!$B$4),0) | D35: =D34+IF(OR($D$5=2,MOD(A35,2)=1),1,0)*(MIN('NG Inputs'!$B$12*D34/$C$5,'NG Inputs'!$B$9)*($B$5-'NG Inputs'!$B$5-'NG Inputs'!$B$6-2*'NG Inputs'!$B$7*SQRT(MIN('NG Inputs'!$B$12*D34/$C$5,'NG Inputs'!$B$9)/'NG Inputs'!$B$8))+MAX(D34-MIN('NG Inputs'!$B$12*D34/$C$5,'NG Inputs'!$B$9)*$C$5,0)*'NG Inputs'!$B$10/$D$5)*(1-'NG Inputs'!$B$4)+IF($D$5=1,(1-IF(OR($D$5=2,MOD(A35,2)=1),1,0))*D34*'NG Inputs'!$B$10*(1-'NG Inputs'!$B$4)/2,0)-IF(MOD(A35,2)=0,INDEX($B$11:$D$25,B35,2)*(1-'NG Inputs'!$B$4),0) | E35: =E34+IF(OR($D$5=2,MOD(A35,2)=1),1,0)*(MIN('NG Inputs'!$B$12*E34/$C$5,'NG Inputs'!$B$9)*($B$5-'NG Inputs'!$B$5-'NG Inputs'!$B$6-2*'NG Inputs'!$B$7*SQRT(MIN('NG Inputs'!$B$12*E34/$C$5,'NG Inputs'!$B$9)/'NG Inputs'!$B$8))+MAX(E34-MIN('NG Inputs'!$B$12*E34/$C$5,'NG Inputs'!$B$9)*$C$5,0)*'NG Inputs'!$B$10/$D$5)*(1-'NG Inputs'!$B$4)+IF($D$5=1,(1-IF(OR($D$5=2,MOD(A35,2)=1),1,0))*E34*'NG Inputs'!$B$10*(1-'NG Inputs'!$B$4)/2,0)-IF(MOD(A35,2)=0,INDEX($B$11:$D$25,B35,3)*(1-'NG Inputs'!$B$4),0) | F35: =F34+IF(OR($D$6=2,MOD(A35,2)=1),1,0)*(MIN('NG Inputs'!$B$12*F34/$C$6,'NG Inputs'!$B$9)*($B$6-'NG Inputs'!$B$5-'NG Inputs'!$B$6-2*'NG Inputs'!$B$7*SQRT(MIN('NG Inputs'!$B$12*F34/$C$6,'NG Inputs'!$B$9)/'NG Inputs'!$B$8))+MAX(F34-MIN('NG Inputs'!$B$12*F34/$C$6,'NG Inputs'!$B$9)*$C$6,0)*'NG Inputs'!$B$10/$D$6)*(1-'NG Inputs'!$B$4)+IF($D$6=1,(1-IF(OR($D$6=2,MOD(A35,2)=1),1,0))*F34*'NG Inputs'!$B$10*(1-'NG Inputs'!$B$4)/2,0)-IF(MOD(A35,2)=0,INDEX($B$11:$D$25,B35,1)*(1-'NG Inputs'!$B$4),0) | G35: =G34+IF(OR($D$6=2,MOD(A35,2)=1),1,0)*(MIN('NG Inputs'!$B$12*G34/$C$6,'NG Inputs'!$B$9)*($B$6-'NG Inputs'!$B$5-'NG Inputs'!$B$6-2*'NG Inputs'!$B$7*SQRT(MIN('NG Inputs'!$B$12*G34/$C$6,'NG Inputs'!$B$9)/'NG Inputs'!$B$8))+MAX(G34-MIN('NG Inputs'!$B$12*G34/$C$6,'NG Inputs'!$B$9)*$C$6,0)*'NG Inputs'!$B$10/$D$6)*(1-'NG Inputs'!$B$4)+IF($D$6=1,(1-IF(OR($D$6=2,MOD(A35,2)=1),1,0))*G34*'NG Inputs'!$B$10*(1-'NG Inputs'!$B$4)/2,0)-IF(MOD(A35,2)=0,INDEX($B$11:$D$25,B35,2)*(1-'NG Inputs'!$B$4),0) | H35: =H34+IF(OR($D$6=2,MOD(A35,2)=1),1,0)*(MIN('NG Inputs'!$B$12*H34/$C$6,'NG Inputs'!$B$9)*($B$6-'NG Inputs'!$B$5-'NG Inputs'!$B$6-2*'NG Inputs'!$B$7*SQRT(MIN('NG Inputs'!$B$12*H34/$C$6,'NG Inputs'!$B$9)/'NG Inputs'!$B$8))+MAX(H34-MIN('NG Inputs'!$B$12*H34/$C$6,'NG Inputs'!$B$9)*$C$6,0)*'NG Inputs'!$B$10/$D$6)*(1-'NG Inputs'!$B$4)+IF($D$6=1,(1-IF(OR($D$6=2,MOD(A35,2)=1),1,0))*H34*'NG Inputs'!$B$10*(1-'NG Inputs'!$B$4)/2,0)-IF(MOD(A35,2)=0,INDEX($B$11:$D$25,B35,3)*(1-'NG Inputs'!$B$4),0) | I35: =I34+IF(OR($D$7=2,MOD(A35,2)=1),1,0)*(MIN('NG Inputs'!$B$12*I34/$C$7,'NG Inputs'!$B$9)*($B$7-'NG Inputs'!$B$5-'NG Inputs'!$B$6-2*'NG Inputs'!$B$7*SQRT(MIN('NG Inputs'!$B$12*I34/$C$7,'NG Inputs'!$B$9)/'NG Inputs'!$B$8))+MAX(I34-MIN('NG Inputs'!$B$12*I34/$C$7,'NG Inputs'!$B$9)*$C$7,0)*'NG Inputs'!$B$10/$D$7)*(1-'NG Inputs'!$B$4)+IF($D$7=1,(1-IF(OR($D$7=2,MOD(A35,2)=1),1,0))*I34*'NG Inputs'!$B$10*(1-'NG Inputs'!$B$4)/2,0)-IF(MOD(A35,2)=0,INDEX($B$11:$D$25,B35,1)*(1-'NG Inputs'!$B$4),0) | J35: =J34+IF(OR($D$7=2,MOD(A35,2)=1),1,0)*(MIN('NG Inputs'!$B$12*J34/$C$7,'NG Inputs'!$B$9)*($B$7-'NG Inputs'!$B$5-'NG Inputs'!$B$6-2*'NG Inputs'!$B$7*SQRT(MIN('NG Inputs'!$B$12*J34/$C$7,'NG Inputs'!$B$9)/'NG Inputs'!$B$8))+MAX(J34-MIN('NG Inputs'!$B$12*J34/$C$7,'NG Inputs'!$B$9)*$C$7,0)*'NG Inputs'!$B$10/$D$7)*(1-'NG Inputs'!$B$4)+IF($D$7=1,(1-IF(OR($D$7=2,MOD(A35,2)=1),1,0))*J34*'NG Inputs'!$B$10*(1-'NG Inputs'!$B$4)/2,0)-IF(MOD(A35,2)=0,INDEX($B$11:$D$25,B35,2)*(1-'NG Inputs'!$B$4),0) | K35: =K34+IF(OR($D$7=2,MOD(A35,2)=1),1,0)*(MIN('NG Inputs'!$B$12*K34/$C$7,'NG Inputs'!$B$9)*($B$7-'NG Inputs'!$B$5-'NG Inputs'!$B$6-2*'NG Inputs'!$B$7*SQRT(MIN('NG Inputs'!$B$12*K34/$C$7,'NG Inputs'!$B$9)/'NG Inputs'!$B$8))+MAX(K34-MIN('NG Inputs'!$B$12*K34/$C$7,'NG Inputs'!$B$9)*$C$7,0)*'NG Inputs'!$B$10/$D$7)*(1-'NG Inputs'!$B$4)+IF($D$7=1,(1-IF(OR($D$7=2,MOD(A35,2)=1),1,0))*K34*'NG Inputs'!$B$10*(1-'NG Inputs'!$B$4)/2,0)-IF(MOD(A35,2)=0,INDEX($B$11:$D$25,B35,3)*(1-'NG Inputs'!$B$4),0)
A36: 8 | B36: =ROUNDUP(A36/2,0) | C36: =C35+IF(OR($D$5=2,MOD(A36,2)=1),1,0)*(MIN('NG Inputs'!$B$12*C35/$C$5,'NG Inputs'!$B$9)*($B$5-'NG Inputs'!$B$5-'NG Inputs'!$B$6-2*'NG Inputs'!$B$7*SQRT(MIN('NG Inputs'!$B$12*C35/$C$5,'NG Inputs'!$B$9)/'NG Inputs'!$B$8))+MAX(C35-MIN('NG Inputs'!$B$12*C35/$C$5,'NG Inputs'!$B$9)*$C$5,0)*'NG Inputs'!$B$10/$D$5)*(1-'NG Inputs'!$B$4)+IF($D$5=1,(1-IF(OR($D$5=2,MOD(A36,2)=1),1,0))*C35*'NG Inputs'!$B$10*(1-'NG Inputs'!$B$4)/2,0)-IF(MOD(A36,2)=0,INDEX($B$11:$D$25,B36,1)*(1-'NG Inputs'!$B$4),0) | D36: =D35+IF(OR($D$5=2,MOD(A36,2)=1),1,0)*(MIN('NG Inputs'!$B$12*D35/$C$5,'NG Inputs'!$B$9)*($B$5-'NG Inputs'!$B$5-'NG Inputs'!$B$6-2*'NG Inputs'!$B$7*SQRT(MIN('NG Inputs'!$B$12*D35/$C$5,'NG Inputs'!$B$9)/'NG Inputs'!$B$8))+MAX(D35-MIN('NG Inputs'!$B$12*D35/$C$5,'NG Inputs'!$B$9)*$C$5,0)*'NG Inputs'!$B$10/$D$5)*(1-'NG Inputs'!$B$4)+IF($D$5=1,(1-IF(OR($D$5=2,MOD(A36,2)=1),1,0))*D35*'NG Inputs'!$B$10*(1-'NG Inputs'!$B$4)/2,0)-IF(MOD(A36,2)=0,INDEX($B$11:$D$25,B36,2)*(1-'NG Inputs'!$B$4),0) | E36: =E35+IF(OR($D$5=2,MOD(A36,2)=1),1,0)*(MIN('NG Inputs'!$B$12*E35/$C$5,'NG Inputs'!$B$9)*($B$5-'NG Inputs'!$B$5-'NG Inputs'!$B$6-2*'NG Inputs'!$B$7*SQRT(MIN('NG Inputs'!$B$12*E35/$C$5,'NG Inputs'!$B$9)/'NG Inputs'!$B$8))+MAX(E35-MIN('NG Inputs'!$B$12*E35/$C$5,'NG Inputs'!$B$9)*$C$5,0)*'NG Inputs'!$B$10/$D$5)*(1-'NG Inputs'!$B$4)+IF($D$5=1,(1-IF(OR($D$5=2,MOD(A36,2)=1),1,0))*E35*'NG Inputs'!$B$10*(1-'NG Inputs'!$B$4)/2,0)-IF(MOD(A36,2)=0,INDEX($B$11:$D$25,B36,3)*(1-'NG Inputs'!$B$4),0) | F36: =F35+IF(OR($D$6=2,MOD(A36,2)=1),1,0)*(MIN('NG Inputs'!$B$12*F35/$C$6,'NG Inputs'!$B$9)*($B$6-'NG Inputs'!$B$5-'NG Inputs'!$B$6-2*'NG Inputs'!$B$7*SQRT(MIN('NG Inputs'!$B$12*F35/$C$6,'NG Inputs'!$B$9)/'NG Inputs'!$B$8))+MAX(F35-MIN('NG Inputs'!$B$12*F35/$C$6,'NG Inputs'!$B$9)*$C$6,0)*'NG Inputs'!$B$10/$D$6)*(1-'NG Inputs'!$B$4)+IF($D$6=1,(1-IF(OR($D$6=2,MOD(A36,2)=1),1,0))*F35*'NG Inputs'!$B$10*(1-'NG Inputs'!$B$4)/2,0)-IF(MOD(A36,2)=0,INDEX($B$11:$D$25,B36,1)*(1-'NG Inputs'!$B$4),0) | G36: =G35+IF(OR($D$6=2,MOD(A36,2)=1),1,0)*(MIN('NG Inputs'!$B$12*G35/$C$6,'NG Inputs'!$B$9)*($B$6-'NG Inputs'!$B$5-'NG Inputs'!$B$6-2*'NG Inputs'!$B$7*SQRT(MIN('NG Inputs'!$B$12*G35/$C$6,'NG Inputs'!$B$9)/'NG Inputs'!$B$8))+MAX(G35-MIN('NG Inputs'!$B$12*G35/$C$6,'NG Inputs'!$B$9)*$C$6,0)*'NG Inputs'!$B$10/$D$6)*(1-'NG Inputs'!$B$4)+IF($D$6=1,(1-IF(OR($D$6=2,MOD(A36,2)=1),1,0))*G35*'NG Inputs'!$B$10*(1-'NG Inputs'!$B$4)/2,0)-IF(MOD(A36,2)=0,INDEX($B$11:$D$25,B36,2)*(1-'NG Inputs'!$B$4),0) | H36: =H35+IF(OR($D$6=2,MOD(A36,2)=1),1,0)*(MIN('NG Inputs'!$B$12*H35/$C$6,'NG Inputs'!$B$9)*($B$6-'NG Inputs'!$B$5-'NG Inputs'!$B$6-2*'NG Inputs'!$B$7*SQRT(MIN('NG Inputs'!$B$12*H35/$C$6,'NG Inputs'!$B$9)/'NG Inputs'!$B$8))+MAX(H35-MIN('NG Inputs'!$B$12*H35/$C$6,'NG Inputs'!$B$9)*$C$6,0)*'NG Inputs'!$B$10/$D$6)*(1-'NG Inputs'!$B$4)+IF($D$6=1,(1-IF(OR($D$6=2,MOD(A36,2)=1),1,0))*H35*'NG Inputs'!$B$10*(1-'NG Inputs'!$B$4)/2,0)-IF(MOD(A36,2)=0,INDEX($B$11:$D$25,B36,3)*(1-'NG Inputs'!$B$4),0) | I36: =I35+IF(OR($D$7=2,MOD(A36,2)=1),1,0)*(MIN('NG Inputs'!$B$12*I35/$C$7,'NG Inputs'!$B$9)*($B$7-'NG Inputs'!$B$5-'NG Inputs'!$B$6-2*'NG Inputs'!$B$7*SQRT(MIN('NG Inputs'!$B$12*I35/$C$7,'NG Inputs'!$B$9)/'NG Inputs'!$B$8))+MAX(I35-MIN('NG Inputs'!$B$12*I35/$C$7,'NG Inputs'!$B$9)*$C$7,0)*'NG Inputs'!$B$10/$D$7)*(1-'NG Inputs'!$B$4)+IF($D$7=1,(1-IF(OR($D$7=2,MOD(A36,2)=1),1,0))*I35*'NG Inputs'!$B$10*(1-'NG Inputs'!$B$4)/2,0)-IF(MOD(A36,2)=0,INDEX($B$11:$D$25,B36,1)*(1-'NG Inputs'!$B$4),0) | J36: =J35+IF(OR($D$7=2,MOD(A36,2)=1),1,0)*(MIN('NG Inputs'!$B$12*J35/$C$7,'NG Inputs'!$B$9)*($B$7-'NG Inputs'!$B$5-'NG Inputs'!$B$6-2*'NG Inputs'!$B$7*SQRT(MIN('NG Inputs'!$B$12*J35/$C$7,'NG Inputs'!$B$9)/'NG Inputs'!$B$8))+MAX(J35-MIN('NG Inputs'!$B$12*J35/$C$7,'NG Inputs'!$B$9)*$C$7,0)*'NG Inputs'!$B$10/$D$7)*(1-'NG Inputs'!$B$4)+IF($D$7=1,(1-IF(OR($D$7=2,MOD(A36,2)=1),1,0))*J35*'NG Inputs'!$B$10*(1-'NG Inputs'!$B$4)/2,0)-IF(MOD(A36,2)=0,INDEX($B$11:$D$25,B36,2)*(1-'NG Inputs'!$B$4),0) | K36: =K35+IF(OR($D$7=2,MOD(A36,2)=1),1,0)*(MIN('NG Inputs'!$B$12*K35/$C$7,'NG Inputs'!$B$9)*($B$7-'NG Inputs'!$B$5-'NG Inputs'!$B$6-2*'NG Inputs'!$B$7*SQRT(MIN('NG Inputs'!$B$12*K35/$C$7,'NG Inputs'!$B$9)/'NG Inputs'!$B$8))+MAX(K35-MIN('NG Inputs'!$B$12*K35/$C$7,'NG Inputs'!$B$9)*$C$7,0)*'NG Inputs'!$B$10/$D$7)*(1-'NG Inputs'!$B$4)+IF($D$7=1,(1-IF(OR($D$7=2,MOD(A36,2)=1),1,0))*K35*'NG Inputs'!$B$10*(1-'NG Inputs'!$B$4)/2,0)-IF(MOD(A36,2)=0,INDEX($B$11:$D$25,B36,3)*(1-'NG Inputs'!$B$4),0)
A37: 9 | B37: =ROUNDUP(A37/2,0) | C37: =C36+IF(OR($D$5=2,MOD(A37,2)=1),1,0)*(MIN('NG Inputs'!$B$12*C36/$C$5,'NG Inputs'!$B$9)*($B$5-'NG Inputs'!$B$5-'NG Inputs'!$B$6-2*'NG Inputs'!$B$7*SQRT(MIN('NG Inputs'!$B$12*C36/$C$5,'NG Inputs'!$B$9)/'NG Inputs'!$B$8))+MAX(C36-MIN('NG Inputs'!$B$12*C36/$C$5,'NG Inputs'!$B$9)*$C$5,0)*'NG Inputs'!$B$10/$D$5)*(1-'NG Inputs'!$B$4)+IF($D$5=1,(1-IF(OR($D$5=2,MOD(A37,2)=1),1,0))*C36*'NG Inputs'!$B$10*(1-'NG Inputs'!$B$4)/2,0)-IF(MOD(A37,2)=0,INDEX($B$11:$D$25,B37,1)*(1-'NG Inputs'!$B$4),0) | D37: =D36+IF(OR($D$5=2,MOD(A37,2)=1),1,0)*(MIN('NG Inputs'!$B$12*D36/$C$5,'NG Inputs'!$B$9)*($B$5-'NG Inputs'!$B$5-'NG Inputs'!$B$6-2*'NG Inputs'!$B$7*SQRT(MIN('NG Inputs'!$B$12*D36/$C$5,'NG Inputs'!$B$9)/'NG Inputs'!$B$8))+MAX(D36-MIN('NG Inputs'!$B$12*D36/$C$5,'NG Inputs'!$B$9)*$C$5,0)*'NG Inputs'!$B$10/$D$5)*(1-'NG Inputs'!$B$4)+IF($D$5=1,(1-IF(OR($D$5=2,MOD(A37,2)=1),1,0))*D36*'NG Inputs'!$B$10*(1-'NG Inputs'!$B$4)/2,0)-IF(MOD(A37,2)=0,INDEX($B$11:$D$25,B37,2)*(1-'NG Inputs'!$B$4),0) | E37: =E36+IF(OR($D$5=2,MOD(A37,2)=1),1,0)*(MIN('NG Inputs'!$B$12*E36/$C$5,'NG Inputs'!$B$9)*($B$5-'NG Inputs'!$B$5-'NG Inputs'!$B$6-2*'NG Inputs'!$B$7*SQRT(MIN('NG Inputs'!$B$12*E36/$C$5,'NG Inputs'!$B$9)/'NG Inputs'!$B$8))+MAX(E36-MIN('NG Inputs'!$B$12*E36/$C$5,'NG Inputs'!$B$9)*$C$5,0)*'NG Inputs'!$B$10/$D$5)*(1-'NG Inputs'!$B$4)+IF($D$5=1,(1-IF(OR($D$5=2,MOD(A37,2)=1),1,0))*E36*'NG Inputs'!$B$10*(1-'NG Inputs'!$B$4)/2,0)-IF(MOD(A37,2)=0,INDEX($B$11:$D$25,B37,3)*(1-'NG Inputs'!$B$4),0) | F37: =F36+IF(OR($D$6=2,MOD(A37,2)=1),1,0)*(MIN('NG Inputs'!$B$12*F36/$C$6,'NG Inputs'!$B$9)*($B$6-'NG Inputs'!$B$5-'NG Inputs'!$B$6-2*'NG Inputs'!$B$7*SQRT(MIN('NG Inputs'!$B$12*F36/$C$6,'NG Inputs'!$B$9)/'NG Inputs'!$B$8))+MAX(F36-MIN('NG Inputs'!$B$12*F36/$C$6,'NG Inputs'!$B$9)*$C$6,0)*'NG Inputs'!$B$10/$D$6)*(1-'NG Inputs'!$B$4)+IF($D$6=1,(1-IF(OR($D$6=2,MOD(A37,2)=1),1,0))*F36*'NG Inputs'!$B$10*(1-'NG Inputs'!$B$4)/2,0)-IF(MOD(A37,2)=0,INDEX($B$11:$D$25,B37,1)*(1-'NG Inputs'!$B$4),0) | G37: =G36+IF(OR($D$6=2,MOD(A37,2)=1),1,0)*(MIN('NG Inputs'!$B$12*G36/$C$6,'NG Inputs'!$B$9)*($B$6-'NG Inputs'!$B$5-'NG Inputs'!$B$6-2*'NG Inputs'!$B$7*SQRT(MIN('NG Inputs'!$B$12*G36/$C$6,'NG Inputs'!$B$9)/'NG Inputs'!$B$8))+MAX(G36-MIN('NG Inputs'!$B$12*G36/$C$6,'NG Inputs'!$B$9)*$C$6,0)*'NG Inputs'!$B$10/$D$6)*(1-'NG Inputs'!$B$4)+IF($D$6=1,(1-IF(OR($D$6=2,MOD(A37,2)=1),1,0))*G36*'NG Inputs'!$B$10*(1-'NG Inputs'!$B$4)/2,0)-IF(MOD(A37,2)=0,INDEX($B$11:$D$25,B37,2)*(1-'NG Inputs'!$B$4),0) | H37: =H36+IF(OR($D$6=2,MOD(A37,2)=1),1,0)*(MIN('NG Inputs'!$B$12*H36/$C$6,'NG Inputs'!$B$9)*($B$6-'NG Inputs'!$B$5-'NG Inputs'!$B$6-2*'NG Inputs'!$B$7*SQRT(MIN('NG Inputs'!$B$12*H36/$C$6,'NG Inputs'!$B$9)/'NG Inputs'!$B$8))+MAX(H36-MIN('NG Inputs'!$B$12*H36/$C$6,'NG Inputs'!$B$9)*$C$6,0)*'NG Inputs'!$B$10/$D$6)*(1-'NG Inputs'!$B$4)+IF($D$6=1,(1-IF(OR($D$6=2,MOD(A37,2)=1),1,0))*H36*'NG Inputs'!$B$10*(1-'NG Inputs'!$B$4)/2,0)-IF(MOD(A37,2)=0,INDEX($B$11:$D$25,B37,3)*(1-'NG Inputs'!$B$4),0) | I37: =I36+IF(OR($D$7=2,MOD(A37,2)=1),1,0)*(MIN('NG Inputs'!$B$12*I36/$C$7,'NG Inputs'!$B$9)*($B$7-'NG Inputs'!$B$5-'NG Inputs'!$B$6-2*'NG Inputs'!$B$7*SQRT(MIN('NG Inputs'!$B$12*I36/$C$7,'NG Inputs'!$B$9)/'NG Inputs'!$B$8))+MAX(I36-MIN('NG Inputs'!$B$12*I36/$C$7,'NG Inputs'!$B$9)*$C$7,0)*'NG Inputs'!$B$10/$D$7)*(1-'NG Inputs'!$B$4)+IF($D$7=1,(1-IF(OR($D$7=2,MOD(A37,2)=1),1,0))*I36*'NG Inputs'!$B$10*(1-'NG Inputs'!$B$4)/2,0)-IF(MOD(A37,2)=0,INDEX($B$11:$D$25,B37,1)*(1-'NG Inputs'!$B$4),0) | J37: =J36+IF(OR($D$7=2,MOD(A37,2)=1),1,0)*(MIN('NG Inputs'!$B$12*J36/$C$7,'NG Inputs'!$B$9)*($B$7-'NG Inputs'!$B$5-'NG Inputs'!$B$6-2*'NG Inputs'!$B$7*SQRT(MIN('NG Inputs'!$B$12*J36/$C$7,'NG Inputs'!$B$9)/'NG Inputs'!$B$8))+MAX(J36-MIN('NG Inputs'!$B$12*J36/$C$7,'NG Inputs'!$B$9)*$C$7,0)*'NG Inputs'!$B$10/$D$7)*(1-'NG Inputs'!$B$4)+IF($D$7=1,(1-IF(OR($D$7=2,MOD(A37,2)=1),1,0))*J36*'NG Inputs'!$B$10*(1-'NG Inputs'!$B$4)/2,0)-IF(MOD(A37,2)=0,INDEX($B$11:$D$25,B37,2)*(1-'NG Inputs'!$B$4),0) | K37: =K36+IF(OR($D$7=2,MOD(A37,2)=1),1,0)*(MIN('NG Inputs'!$B$12*K36/$C$7,'NG Inputs'!$B$9)*($B$7-'NG Inputs'!$B$5-'NG Inputs'!$B$6-2*'NG Inputs'!$B$7*SQRT(MIN('NG Inputs'!$B$12*K36/$C$7,'NG Inputs'!$B$9)/'NG Inputs'!$B$8))+MAX(K36-MIN('NG Inputs'!$B$12*K36/$C$7,'NG Inputs'!$B$9)*$C$7,0)*'NG Inputs'!$B$10/$D$7)*(1-'NG Inputs'!$B$4)+IF($D$7=1,(1-IF(OR($D$7=2,MOD(A37,2)=1),1,0))*K36*'NG Inputs'!$B$10*(1-'NG Inputs'!$B$4)/2,0)-IF(MOD(A37,2)=0,INDEX($B$11:$D$25,B37,3)*(1-'NG Inputs'!$B$4),0)
A38: 10 | B38: =ROUNDUP(A38/2,0) | C38: =C37+IF(OR($D$5=2,MOD(A38,2)=1),1,0)*(MIN('NG Inputs'!$B$12*C37/$C$5,'NG Inputs'!$B$9)*($B$5-'NG Inputs'!$B$5-'NG Inputs'!$B$6-2*'NG Inputs'!$B$7*SQRT(MIN('NG Inputs'!$B$12*C37/$C$5,'NG Inputs'!$B$9)/'NG Inputs'!$B$8))+MAX(C37-MIN('NG Inputs'!$B$12*C37/$C$5,'NG Inputs'!$B$9)*$C$5,0)*'NG Inputs'!$B$10/$D$5)*(1-'NG Inputs'!$B$4)+IF($D$5=1,(1-IF(OR($D$5=2,MOD(A38,2)=1),1,0))*C37*'NG Inputs'!$B$10*(1-'NG Inputs'!$B$4)/2,0)-IF(MOD(A38,2)=0,INDEX($B$11:$D$25,B38,1)*(1-'NG Inputs'!$B$4),0) | D38: =D37+IF(OR($D$5=2,MOD(A38,2)=1),1,0)*(MIN('NG Inputs'!$B$12*D37/$C$5,'NG Inputs'!$B$9)*($B$5-'NG Inputs'!$B$5-'NG Inputs'!$B$6-2*'NG Inputs'!$B$7*SQRT(MIN('NG Inputs'!$B$12*D37/$C$5,'NG Inputs'!$B$9)/'NG Inputs'!$B$8))+MAX(D37-MIN('NG Inputs'!$B$12*D37/$C$5,'NG Inputs'!$B$9)*$C$5,0)*'NG Inputs'!$B$10/$D$5)*(1-'NG Inputs'!$B$4)+IF($D$5=1,(1-IF(OR($D$5=2,MOD(A38,2)=1),1,0))*D37*'NG Inputs'!$B$10*(1-'NG Inputs'!$B$4)/2,0)-IF(MOD(A38,2)=0,INDEX($B$11:$D$25,B38,2)*(1-'NG Inputs'!$B$4),0) | E38: =E37+IF(OR($D$5=2,MOD(A38,2)=1),1,0)*(MIN('NG Inputs'!$B$12*E37/$C$5,'NG Inputs'!$B$9)*($B$5-'NG Inputs'!$B$5-'NG Inputs'!$B$6-2*'NG Inputs'!$B$7*SQRT(MIN('NG Inputs'!$B$12*E37/$C$5,'NG Inputs'!$B$9)/'NG Inputs'!$B$8))+MAX(E37-MIN('NG Inputs'!$B$12*E37/$C$5,'NG Inputs'!$B$9)*$C$5,0)*'NG Inputs'!$B$10/$D$5)*(1-'NG Inputs'!$B$4)+IF($D$5=1,(1-IF(OR($D$5=2,MOD(A38,2)=1),1,0))*E37*'NG Inputs'!$B$10*(1-'NG Inputs'!$B$4)/2,0)-IF(MOD(A38,2)=0,INDEX($B$11:$D$25,B38,3)*(1-'NG Inputs'!$B$4),0) | F38: =F37+IF(OR($D$6=2,MOD(A38,2)=1),1,0)*(MIN('NG Inputs'!$B$12*F37/$C$6,'NG Inputs'!$B$9)*($B$6-'NG Inputs'!$B$5-'NG Inputs'!$B$6-2*'NG Inputs'!$B$7*SQRT(MIN('NG Inputs'!$B$12*F37/$C$6,'NG Inputs'!$B$9)/'NG Inputs'!$B$8))+MAX(F37-MIN('NG Inputs'!$B$12*F37/$C$6,'NG Inputs'!$B$9)*$C$6,0)*'NG Inputs'!$B$10/$D$6)*(1-'NG Inputs'!$B$4)+IF($D$6=1,(1-IF(OR($D$6=2,MOD(A38,2)=1),1,0))*F37*'NG Inputs'!$B$10*(1-'NG Inputs'!$B$4)/2,0)-IF(MOD(A38,2)=0,INDEX($B$11:$D$25,B38,1)*(1-'NG Inputs'!$B$4),0) | G38: =G37+IF(OR($D$6=2,MOD(A38,2)=1),1,0)*(MIN('NG Inputs'!$B$12*G37/$C$6,'NG Inputs'!$B$9)*($B$6-'NG Inputs'!$B$5-'NG Inputs'!$B$6-2*'NG Inputs'!$B$7*SQRT(MIN('NG Inputs'!$B$12*G37/$C$6,'NG Inputs'!$B$9)/'NG Inputs'!$B$8))+MAX(G37-MIN('NG Inputs'!$B$12*G37/$C$6,'NG Inputs'!$B$9)*$C$6,0)*'NG Inputs'!$B$10/$D$6)*(1-'NG Inputs'!$B$4)+IF($D$6=1,(1-IF(OR($D$6=2,MOD(A38,2)=1),1,0))*G37*'NG Inputs'!$B$10*(1-'NG Inputs'!$B$4)/2,0)-IF(MOD(A38,2)=0,INDEX($B$11:$D$25,B38,2)*(1-'NG Inputs'!$B$4),0) | H38: =H37+IF(OR($D$6=2,MOD(A38,2)=1),1,0)*(MIN('NG Inputs'!$B$12*H37/$C$6,'NG Inputs'!$B$9)*($B$6-'NG Inputs'!$B$5-'NG Inputs'!$B$6-2*'NG Inputs'!$B$7*SQRT(MIN('NG Inputs'!$B$12*H37/$C$6,'NG Inputs'!$B$9)/'NG Inputs'!$B$8))+MAX(H37-MIN('NG Inputs'!$B$12*H37/$C$6,'NG Inputs'!$B$9)*$C$6,0)*'NG Inputs'!$B$10/$D$6)*(1-'NG Inputs'!$B$4)+IF($D$6=1,(1-IF(OR($D$6=2,MOD(A38,2)=1),1,0))*H37*'NG Inputs'!$B$10*(1-'NG Inputs'!$B$4)/2,0)-IF(MOD(A38,2)=0,INDEX($B$11:$D$25,B38,3)*(1-'NG Inputs'!$B$4),0) | I38: =I37+IF(OR($D$7=2,MOD(A38,2)=1),1,0)*(MIN('NG Inputs'!$B$12*I37/$C$7,'NG Inputs'!$B$9)*($B$7-'NG Inputs'!$B$5-'NG Inputs'!$B$6-2*'NG Inputs'!$B$7*SQRT(MIN('NG Inputs'!$B$12*I37/$C$7,'NG Inputs'!$B$9)/'NG Inputs'!$B$8))+MAX(I37-MIN('NG Inputs'!$B$12*I37/$C$7,'NG Inputs'!$B$9)*$C$7,0)*'NG Inputs'!$B$10/$D$7)*(1-'NG Inputs'!$B$4)+IF($D$7=1,(1-IF(OR($D$7=2,MOD(A38,2)=1),1,0))*I37*'NG Inputs'!$B$10*(1-'NG Inputs'!$B$4)/2,0)-IF(MOD(A38,2)=0,INDEX($B$11:$D$25,B38,1)*(1-'NG Inputs'!$B$4),0) | J38: =J37+IF(OR($D$7=2,MOD(A38,2)=1),1,0)*(MIN('NG Inputs'!$B$12*J37/$C$7,'NG Inputs'!$B$9)*($B$7-'NG Inputs'!$B$5-'NG Inputs'!$B$6-2*'NG Inputs'!$B$7*SQRT(MIN('NG Inputs'!$B$12*J37/$C$7,'NG Inputs'!$B$9)/'NG Inputs'!$B$8))+MAX(J37-MIN('NG Inputs'!$B$12*J37/$C$7,'NG Inputs'!$B$9)*$C$7,0)*'NG Inputs'!$B$10/$D$7)*(1-'NG Inputs'!$B$4)+IF($D$7=1,(1-IF(OR($D$7=2,MOD(A38,2)=1),1,0))*J37*'NG Inputs'!$B$10*(1-'NG Inputs'!$B$4)/2,0)-IF(MOD(A38,2)=0,INDEX($B$11:$D$25,B38,2)*(1-'NG Inputs'!$B$4),0) | K38: =K37+IF(OR($D$7=2,MOD(A38,2)=1),1,0)*(MIN('NG Inputs'!$B$12*K37/$C$7,'NG Inputs'!$B$9)*($B$7-'NG Inputs'!$B$5-'NG Inputs'!$B$6-2*'NG Inputs'!$B$7*SQRT(MIN('NG Inputs'!$B$12*K37/$C$7,'NG Inputs'!$B$9)/'NG Inputs'!$B$8))+MAX(K37-MIN('NG Inputs'!$B$12*K37/$C$7,'NG Inputs'!$B$9)*$C$7,0)*'NG Inputs'!$B$10/$D$7)*(1-'NG Inputs'!$B$4)+IF($D$7=1,(1-IF(OR($D$7=2,MOD(A38,2)=1),1,0))*K37*'NG Inputs'!$B$10*(1-'NG Inputs'!$B$4)/2,0)-IF(MOD(A38,2)=0,INDEX($B$11:$D$25,B38,3)*(1-'NG Inputs'!$B$4),0)
A39: 11 | B39: =ROUNDUP(A39/2,0) | C39: =C38+IF(OR($D$5=2,MOD(A39,2)=1),1,0)*(MIN('NG Inputs'!$B$12*C38/$C$5,'NG Inputs'!$B$9)*($B$5-'NG Inputs'!$B$5-'NG Inputs'!$B$6-2*'NG Inputs'!$B$7*SQRT(MIN('NG Inputs'!$B$12*C38/$C$5,'NG Inputs'!$B$9)/'NG Inputs'!$B$8))+MAX(C38-MIN('NG Inputs'!$B$12*C38/$C$5,'NG Inputs'!$B$9)*$C$5,0)*'NG Inputs'!$B$10/$D$5)*(1-'NG Inputs'!$B$4)+IF($D$5=1,(1-IF(OR($D$5=2,MOD(A39,2)=1),1,0))*C38*'NG Inputs'!$B$10*(1-'NG Inputs'!$B$4)/2,0)-IF(MOD(A39,2)=0,INDEX($B$11:$D$25,B39,1)*(1-'NG Inputs'!$B$4),0) | D39: =D38+IF(OR($D$5=2,MOD(A39,2)=1),1,0)*(MIN('NG Inputs'!$B$12*D38/$C$5,'NG Inputs'!$B$9)*($B$5-'NG Inputs'!$B$5-'NG Inputs'!$B$6-2*'NG Inputs'!$B$7*SQRT(MIN('NG Inputs'!$B$12*D38/$C$5,'NG Inputs'!$B$9)/'NG Inputs'!$B$8))+MAX(D38-MIN('NG Inputs'!$B$12*D38/$C$5,'NG Inputs'!$B$9)*$C$5,0)*'NG Inputs'!$B$10/$D$5)*(1-'NG Inputs'!$B$4)+IF($D$5=1,(1-IF(OR($D$5=2,MOD(A39,2)=1),1,0))*D38*'NG Inputs'!$B$10*(1-'NG Inputs'!$B$4)/2,0)-IF(MOD(A39,2)=0,INDEX($B$11:$D$25,B39,2)*(1-'NG Inputs'!$B$4),0) | E39: =E38+IF(OR($D$5=2,MOD(A39,2)=1),1,0)*(MIN('NG Inputs'!$B$12*E38/$C$5,'NG Inputs'!$B$9)*($B$5-'NG Inputs'!$B$5-'NG Inputs'!$B$6-2*'NG Inputs'!$B$7*SQRT(MIN('NG Inputs'!$B$12*E38/$C$5,'NG Inputs'!$B$9)/'NG Inputs'!$B$8))+MAX(E38-MIN('NG Inputs'!$B$12*E38/$C$5,'NG Inputs'!$B$9)*$C$5,0)*'NG Inputs'!$B$10/$D$5)*(1-'NG Inputs'!$B$4)+IF($D$5=1,(1-IF(OR($D$5=2,MOD(A39,2)=1),1,0))*E38*'NG Inputs'!$B$10*(1-'NG Inputs'!$B$4)/2,0)-IF(MOD(A39,2)=0,INDEX($B$11:$D$25,B39,3)*(1-'NG Inputs'!$B$4),0) | F39: =F38+IF(OR($D$6=2,MOD(A39,2)=1),1,0)*(MIN('NG Inputs'!$B$12*F38/$C$6,'NG Inputs'!$B$9)*($B$6-'NG Inputs'!$B$5-'NG Inputs'!$B$6-2*'NG Inputs'!$B$7*SQRT(MIN('NG Inputs'!$B$12*F38/$C$6,'NG Inputs'!$B$9)/'NG Inputs'!$B$8))+MAX(F38-MIN('NG Inputs'!$B$12*F38/$C$6,'NG Inputs'!$B$9)*$C$6,0)*'NG Inputs'!$B$10/$D$6)*(1-'NG Inputs'!$B$4)+IF($D$6=1,(1-IF(OR($D$6=2,MOD(A39,2)=1),1,0))*F38*'NG Inputs'!$B$10*(1-'NG Inputs'!$B$4)/2,0)-IF(MOD(A39,2)=0,INDEX($B$11:$D$25,B39,1)*(1-'NG Inputs'!$B$4),0) | G39: =G38+IF(OR($D$6=2,MOD(A39,2)=1),1,0)*(MIN('NG Inputs'!$B$12*G38/$C$6,'NG Inputs'!$B$9)*($B$6-'NG Inputs'!$B$5-'NG Inputs'!$B$6-2*'NG Inputs'!$B$7*SQRT(MIN('NG Inputs'!$B$12*G38/$C$6,'NG Inputs'!$B$9)/'NG Inputs'!$B$8))+MAX(G38-MIN('NG Inputs'!$B$12*G38/$C$6,'NG Inputs'!$B$9)*$C$6,0)*'NG Inputs'!$B$10/$D$6)*(1-'NG Inputs'!$B$4)+IF($D$6=1,(1-IF(OR($D$6=2,MOD(A39,2)=1),1,0))*G38*'NG Inputs'!$B$10*(1-'NG Inputs'!$B$4)/2,0)-IF(MOD(A39,2)=0,INDEX($B$11:$D$25,B39,2)*(1-'NG Inputs'!$B$4),0) | H39: =H38+IF(OR($D$6=2,MOD(A39,2)=1),1,0)*(MIN('NG Inputs'!$B$12*H38/$C$6,'NG Inputs'!$B$9)*($B$6-'NG Inputs'!$B$5-'NG Inputs'!$B$6-2*'NG Inputs'!$B$7*SQRT(MIN('NG Inputs'!$B$12*H38/$C$6,'NG Inputs'!$B$9)/'NG Inputs'!$B$8))+MAX(H38-MIN('NG Inputs'!$B$12*H38/$C$6,'NG Inputs'!$B$9)*$C$6,0)*'NG Inputs'!$B$10/$D$6)*(1-'NG Inputs'!$B$4)+IF($D$6=1,(1-IF(OR($D$6=2,MOD(A39,2)=1),1,0))*H38*'NG Inputs'!$B$10*(1-'NG Inputs'!$B$4)/2,0)-IF(MOD(A39,2)=0,INDEX($B$11:$D$25,B39,3)*(1-'NG Inputs'!$B$4),0) | I39: =I38+IF(OR($D$7=2,MOD(A39,2)=1),1,0)*(MIN('NG Inputs'!$B$12*I38/$C$7,'NG Inputs'!$B$9)*($B$7-'NG Inputs'!$B$5-'NG Inputs'!$B$6-2*'NG Inputs'!$B$7*SQRT(MIN('NG Inputs'!$B$12*I38/$C$7,'NG Inputs'!$B$9)/'NG Inputs'!$B$8))+MAX(I38-MIN('NG Inputs'!$B$12*I38/$C$7,'NG Inputs'!$B$9)*$C$7,0)*'NG Inputs'!$B$10/$D$7)*(1-'NG Inputs'!$B$4)+IF($D$7=1,(1-IF(OR($D$7=2,MOD(A39,2)=1),1,0))*I38*'NG Inputs'!$B$10*(1-'NG Inputs'!$B$4)/2,0)-IF(MOD(A39,2)=0,INDEX($B$11:$D$25,B39,1)*(1-'NG Inputs'!$B$4),0) | J39: =J38+IF(OR($D$7=2,MOD(A39,2)=1),1,0)*(MIN('NG Inputs'!$B$12*J38/$C$7,'NG Inputs'!$B$9)*($B$7-'NG Inputs'!$B$5-'NG Inputs'!$B$6-2*'NG Inputs'!$B$7*SQRT(MIN('NG Inputs'!$B$12*J38/$C$7,'NG Inputs'!$B$9)/'NG Inputs'!$B$8))+MAX(J38-MIN('NG Inputs'!$B$12*J38/$C$7,'NG Inputs'!$B$9)*$C$7,0)*'NG Inputs'!$B$10/$D$7)*(1-'NG Inputs'!$B$4)+IF($D$7=1,(1-IF(OR($D$7=2,MOD(A39,2)=1),1,0))*J38*'NG Inputs'!$B$10*(1-'NG Inputs'!$B$4)/2,0)-IF(MOD(A39,2)=0,INDEX($B$11:$D$25,B39,2)*(1-'NG Inputs'!$B$4),0) | K39: =K38+IF(OR($D$7=2,MOD(A39,2)=1),1,0)*(MIN('NG Inputs'!$B$12*K38/$C$7,'NG Inputs'!$B$9)*($B$7-'NG Inputs'!$B$5-'NG Inputs'!$B$6-2*'NG Inputs'!$B$7*SQRT(MIN('NG Inputs'!$B$12*K38/$C$7,'NG Inputs'!$B$9)/'NG Inputs'!$B$8))+MAX(K38-MIN('NG Inputs'!$B$12*K38/$C$7,'NG Inputs'!$B$9)*$C$7,0)*'NG Inputs'!$B$10/$D$7)*(1-'NG Inputs'!$B$4)+IF($D$7=1,(1-IF(OR($D$7=2,MOD(A39,2)=1),1,0))*K38*'NG Inputs'!$B$10*(1-'NG Inputs'!$B$4)/2,0)-IF(MOD(A39,2)=0,INDEX($B$11:$D$25,B39,3)*(1-'NG Inputs'!$B$4),0)
A40: 12 | B40: =ROUNDUP(A40/2,0) | C40: =C39+IF(OR($D$5=2,MOD(A40,2)=1),1,0)*(MIN('NG Inputs'!$B$12*C39/$C$5,'NG Inputs'!$B$9)*($B$5-'NG Inputs'!$B$5-'NG Inputs'!$B$6-2*'NG Inputs'!$B$7*SQRT(MIN('NG Inputs'!$B$12*C39/$C$5,'NG Inputs'!$B$9)/'NG Inputs'!$B$8))+MAX(C39-MIN('NG Inputs'!$B$12*C39/$C$5,'NG Inputs'!$B$9)*$C$5,0)*'NG Inputs'!$B$10/$D$5)*(1-'NG Inputs'!$B$4)+IF($D$5=1,(1-IF(OR($D$5=2,MOD(A40,2)=1),1,0))*C39*'NG Inputs'!$B$10*(1-'NG Inputs'!$B$4)/2,0)-IF(MOD(A40,2)=0,INDEX($B$11:$D$25,B40,1)*(1-'NG Inputs'!$B$4),0) | D40: =D39+IF(OR($D$5=2,MOD(A40,2)=1),1,0)*(MIN('NG Inputs'!$B$12*D39/$C$5,'NG Inputs'!$B$9)*($B$5-'NG Inputs'!$B$5-'NG Inputs'!$B$6-2*'NG Inputs'!$B$7*SQRT(MIN('NG Inputs'!$B$12*D39/$C$5,'NG Inputs'!$B$9)/'NG Inputs'!$B$8))+MAX(D39-MIN('NG Inputs'!$B$12*D39/$C$5,'NG Inputs'!$B$9)*$C$5,0)*'NG Inputs'!$B$10/$D$5)*(1-'NG Inputs'!$B$4)+IF($D$5=1,(1-IF(OR($D$5=2,MOD(A40,2)=1),1,0))*D39*'NG Inputs'!$B$10*(1-'NG Inputs'!$B$4)/2,0)-IF(MOD(A40,2)=0,INDEX($B$11:$D$25,B40,2)*(1-'NG Inputs'!$B$4),0) | E40: =E39+IF(OR($D$5=2,MOD(A40,2)=1),1,0)*(MIN('NG Inputs'!$B$12*E39/$C$5,'NG Inputs'!$B$9)*($B$5-'NG Inputs'!$B$5-'NG Inputs'!$B$6-2*'NG Inputs'!$B$7*SQRT(MIN('NG Inputs'!$B$12*E39/$C$5,'NG Inputs'!$B$9)/'NG Inputs'!$B$8))+MAX(E39-MIN('NG Inputs'!$B$12*E39/$C$5,'NG Inputs'!$B$9)*$C$5,0)*'NG Inputs'!$B$10/$D$5)*(1-'NG Inputs'!$B$4)+IF($D$5=1,(1-IF(OR($D$5=2,MOD(A40,2)=1),1,0))*E39*'NG Inputs'!$B$10*(1-'NG Inputs'!$B$4)/2,0)-IF(MOD(A40,2)=0,INDEX($B$11:$D$25,B40,3)*(1-'NG Inputs'!$B$4),0) | F40: =F39+IF(OR($D$6=2,MOD(A40,2)=1),1,0)*(MIN('NG Inputs'!$B$12*F39/$C$6,'NG Inputs'!$B$9)*($B$6-'NG Inputs'!$B$5-'NG Inputs'!$B$6-2*'NG Inputs'!$B$7*SQRT(MIN('NG Inputs'!$B$12*F39/$C$6,'NG Inputs'!$B$9)/'NG Inputs'!$B$8))+MAX(F39-MIN('NG Inputs'!$B$12*F39/$C$6,'NG Inputs'!$B$9)*$C$6,0)*'NG Inputs'!$B$10/$D$6)*(1-'NG Inputs'!$B$4)+IF($D$6=1,(1-IF(OR($D$6=2,MOD(A40,2)=1),1,0))*F39*'NG Inputs'!$B$10*(1-'NG Inputs'!$B$4)/2,0)-IF(MOD(A40,2)=0,INDEX($B$11:$D$25,B40,1)*(1-'NG Inputs'!$B$4),0) | G40: =G39+IF(OR($D$6=2,MOD(A40,2)=1),1,0)*(MIN('NG Inputs'!$B$12*G39/$C$6,'NG Inputs'!$B$9)*($B$6-'NG Inputs'!$B$5-'NG Inputs'!$B$6-2*'NG Inputs'!$B$7*SQRT(MIN('NG Inputs'!$B$12*G39/$C$6,'NG Inputs'!$B$9)/'NG Inputs'!$B$8))+MAX(G39-MIN('NG Inputs'!$B$12*G39/$C$6,'NG Inputs'!$B$9)*$C$6,0)*'NG Inputs'!$B$10/$D$6)*(1-'NG Inputs'!$B$4)+IF($D$6=1,(1-IF(OR($D$6=2,MOD(A40,2)=1),1,0))*G39*'NG Inputs'!$B$10*(1-'NG Inputs'!$B$4)/2,0)-IF(MOD(A40,2)=0,INDEX($B$11:$D$25,B40,2)*(1-'NG Inputs'!$B$4),0) | H40: =H39+IF(OR($D$6=2,MOD(A40,2)=1),1,0)*(MIN('NG Inputs'!$B$12*H39/$C$6,'NG Inputs'!$B$9)*($B$6-'NG Inputs'!$B$5-'NG Inputs'!$B$6-2*'NG Inputs'!$B$7*SQRT(MIN('NG Inputs'!$B$12*H39/$C$6,'NG Inputs'!$B$9)/'NG Inputs'!$B$8))+MAX(H39-MIN('NG Inputs'!$B$12*H39/$C$6,'NG Inputs'!$B$9)*$C$6,0)*'NG Inputs'!$B$10/$D$6)*(1-'NG Inputs'!$B$4)+IF($D$6=1,(1-IF(OR($D$6=2,MOD(A40,2)=1),1,0))*H39*'NG Inputs'!$B$10*(1-'NG Inputs'!$B$4)/2,0)-IF(MOD(A40,2)=0,INDEX($B$11:$D$25,B40,3)*(1-'NG Inputs'!$B$4),0) | I40: =I39+IF(OR($D$7=2,MOD(A40,2)=1),1,0)*(MIN('NG Inputs'!$B$12*I39/$C$7,'NG Inputs'!$B$9)*($B$7-'NG Inputs'!$B$5-'NG Inputs'!$B$6-2*'NG Inputs'!$B$7*SQRT(MIN('NG Inputs'!$B$12*I39/$C$7,'NG Inputs'!$B$9)/'NG Inputs'!$B$8))+MAX(I39-MIN('NG Inputs'!$B$12*I39/$C$7,'NG Inputs'!$B$9)*$C$7,0)*'NG Inputs'!$B$10/$D$7)*(1-'NG Inputs'!$B$4)+IF($D$7=1,(1-IF(OR($D$7=2,MOD(A40,2)=1),1,0))*I39*'NG Inputs'!$B$10*(1-'NG Inputs'!$B$4)/2,0)-IF(MOD(A40,2)=0,INDEX($B$11:$D$25,B40,1)*(1-'NG Inputs'!$B$4),0) | J40: =J39+IF(OR($D$7=2,MOD(A40,2)=1),1,0)*(MIN('NG Inputs'!$B$12*J39/$C$7,'NG Inputs'!$B$9)*($B$7-'NG Inputs'!$B$5-'NG Inputs'!$B$6-2*'NG Inputs'!$B$7*SQRT(MIN('NG Inputs'!$B$12*J39/$C$7,'NG Inputs'!$B$9)/'NG Inputs'!$B$8))+MAX(J39-MIN('NG Inputs'!$B$12*J39/$C$7,'NG Inputs'!$B$9)*$C$7,0)*'NG Inputs'!$B$10/$D$7)*(1-'NG Inputs'!$B$4)+IF($D$7=1,(1-IF(OR($D$7=2,MOD(A40,2)=1),1,0))*J39*'NG Inputs'!$B$10*(1-'NG Inputs'!$B$4)/2,0)-IF(MOD(A40,2)=0,INDEX($B$11:$D$25,B40,2)*(1-'NG Inputs'!$B$4),0) | K40: =K39+IF(OR($D$7=2,MOD(A40,2)=1),1,0)*(MIN('NG Inputs'!$B$12*K39/$C$7,'NG Inputs'!$B$9)*($B$7-'NG Inputs'!$B$5-'NG Inputs'!$B$6-2*'NG Inputs'!$B$7*SQRT(MIN('NG Inputs'!$B$12*K39/$C$7,'NG Inputs'!$B$9)/'NG Inputs'!$B$8))+MAX(K39-MIN('NG Inputs'!$B$12*K39/$C$7,'NG Inputs'!$B$9)*$C$7,0)*'NG Inputs'!$B$10/$D$7)*(1-'NG Inputs'!$B$4)+IF($D$7=1,(1-IF(OR($D$7=2,MOD(A40,2)=1),1,0))*K39*'NG Inputs'!$B$10*(1-'NG Inputs'!$B$4)/2,0)-IF(MOD(A40,2)=0,INDEX($B$11:$D$25,B40,3)*(1-'NG Inputs'!$B$4),0)
A41: 13 | B41: =ROUNDUP(A41/2,0) | C41: =C40+IF(OR($D$5=2,MOD(A41,2)=1),1,0)*(MIN('NG Inputs'!$B$12*C40/$C$5,'NG Inputs'!$B$9)*($B$5-'NG Inputs'!$B$5-'NG Inputs'!$B$6-2*'NG Inputs'!$B$7*SQRT(MIN('NG Inputs'!$B$12*C40/$C$5,'NG Inputs'!$B$9)/'NG Inputs'!$B$8))+MAX(C40-MIN('NG Inputs'!$B$12*C40/$C$5,'NG Inputs'!$B$9)*$C$5,0)*'NG Inputs'!$B$10/$D$5)*(1-'NG Inputs'!$B$4)+IF($D$5=1,(1-IF(OR($D$5=2,MOD(A41,2)=1),1,0))*C40*'NG Inputs'!$B$10*(1-'NG Inputs'!$B$4)/2,0)-IF(MOD(A41,2)=0,INDEX($B$11:$D$25,B41,1)*(1-'NG Inputs'!$B$4),0) | D41: =D40+IF(OR($D$5=2,MOD(A41,2)=1),1,0)*(MIN('NG Inputs'!$B$12*D40/$C$5,'NG Inputs'!$B$9)*($B$5-'NG Inputs'!$B$5-'NG Inputs'!$B$6-2*'NG Inputs'!$B$7*SQRT(MIN('NG Inputs'!$B$12*D40/$C$5,'NG Inputs'!$B$9)/'NG Inputs'!$B$8))+MAX(D40-MIN('NG Inputs'!$B$12*D40/$C$5,'NG Inputs'!$B$9)*$C$5,0)*'NG Inputs'!$B$10/$D$5)*(1-'NG Inputs'!$B$4)+IF($D$5=1,(1-IF(OR($D$5=2,MOD(A41,2)=1),1,0))*D40*'NG Inputs'!$B$10*(1-'NG Inputs'!$B$4)/2,0)-IF(MOD(A41,2)=0,INDEX($B$11:$D$25,B41,2)*(1-'NG Inputs'!$B$4),0) | E41: =E40+IF(OR($D$5=2,MOD(A41,2)=1),1,0)*(MIN('NG Inputs'!$B$12*E40/$C$5,'NG Inputs'!$B$9)*($B$5-'NG Inputs'!$B$5-'NG Inputs'!$B$6-2*'NG Inputs'!$B$7*SQRT(MIN('NG Inputs'!$B$12*E40/$C$5,'NG Inputs'!$B$9)/'NG Inputs'!$B$8))+MAX(E40-MIN('NG Inputs'!$B$12*E40/$C$5,'NG Inputs'!$B$9)*$C$5,0)*'NG Inputs'!$B$10/$D$5)*(1-'NG Inputs'!$B$4)+IF($D$5=1,(1-IF(OR($D$5=2,MOD(A41,2)=1),1,0))*E40*'NG Inputs'!$B$10*(1-'NG Inputs'!$B$4)/2,0)-IF(MOD(A41,2)=0,INDEX($B$11:$D$25,B41,3)*(1-'NG Inputs'!$B$4),0) | F41: =F40+IF(OR($D$6=2,MOD(A41,2)=1),1,0)*(MIN('NG Inputs'!$B$12*F40/$C$6,'NG Inputs'!$B$9)*($B$6-'NG Inputs'!$B$5-'NG Inputs'!$B$6-2*'NG Inputs'!$B$7*SQRT(MIN('NG Inputs'!$B$12*F40/$C$6,'NG Inputs'!$B$9)/'NG Inputs'!$B$8))+MAX(F40-MIN('NG Inputs'!$B$12*F40/$C$6,'NG Inputs'!$B$9)*$C$6,0)*'NG Inputs'!$B$10/$D$6)*(1-'NG Inputs'!$B$4)+IF($D$6=1,(1-IF(OR($D$6=2,MOD(A41,2)=1),1,0))*F40*'NG Inputs'!$B$10*(1-'NG Inputs'!$B$4)/2,0)-IF(MOD(A41,2)=0,INDEX($B$11:$D$25,B41,1)*(1-'NG Inputs'!$B$4),0) | G41: =G40+IF(OR($D$6=2,MOD(A41,2)=1),1,0)*(MIN('NG Inputs'!$B$12*G40/$C$6,'NG Inputs'!$B$9)*($B$6-'NG Inputs'!$B$5-'NG Inputs'!$B$6-2*'NG Inputs'!$B$7*SQRT(MIN('NG Inputs'!$B$12*G40/$C$6,'NG Inputs'!$B$9)/'NG Inputs'!$B$8))+MAX(G40-MIN('NG Inputs'!$B$12*G40/$C$6,'NG Inputs'!$B$9)*$C$6,0)*'NG Inputs'!$B$10/$D$6)*(1-'NG Inputs'!$B$4)+IF($D$6=1,(1-IF(OR($D$6=2,MOD(A41,2)=1),1,0))*G40*'NG Inputs'!$B$10*(1-'NG Inputs'!$B$4)/2,0)-IF(MOD(A41,2)=0,INDEX($B$11:$D$25,B41,2)*(1-'NG Inputs'!$B$4),0) | H41: =H40+IF(OR($D$6=2,MOD(A41,2)=1),1,0)*(MIN('NG Inputs'!$B$12*H40/$C$6,'NG Inputs'!$B$9)*($B$6-'NG Inputs'!$B$5-'NG Inputs'!$B$6-2*'NG Inputs'!$B$7*SQRT(MIN('NG Inputs'!$B$12*H40/$C$6,'NG Inputs'!$B$9)/'NG Inputs'!$B$8))+MAX(H40-MIN('NG Inputs'!$B$12*H40/$C$6,'NG Inputs'!$B$9)*$C$6,0)*'NG Inputs'!$B$10/$D$6)*(1-'NG Inputs'!$B$4)+IF($D$6=1,(1-IF(OR($D$6=2,MOD(A41,2)=1),1,0))*H40*'NG Inputs'!$B$10*(1-'NG Inputs'!$B$4)/2,0)-IF(MOD(A41,2)=0,INDEX($B$11:$D$25,B41,3)*(1-'NG Inputs'!$B$4),0) | I41: =I40+IF(OR($D$7=2,MOD(A41,2)=1),1,0)*(MIN('NG Inputs'!$B$12*I40/$C$7,'NG Inputs'!$B$9)*($B$7-'NG Inputs'!$B$5-'NG Inputs'!$B$6-2*'NG Inputs'!$B$7*SQRT(MIN('NG Inputs'!$B$12*I40/$C$7,'NG Inputs'!$B$9)/'NG Inputs'!$B$8))+MAX(I40-MIN('NG Inputs'!$B$12*I40/$C$7,'NG Inputs'!$B$9)*$C$7,0)*'NG Inputs'!$B$10/$D$7)*(1-'NG Inputs'!$B$4)+IF($D$7=1,(1-IF(OR($D$7=2,MOD(A41,2)=1),1,0))*I40*'NG Inputs'!$B$10*(1-'NG Inputs'!$B$4)/2,0)-IF(MOD(A41,2)=0,INDEX($B$11:$D$25,B41,1)*(1-'NG Inputs'!$B$4),0) | J41: =J40+IF(OR($D$7=2,MOD(A41,2)=1),1,0)*(MIN('NG Inputs'!$B$12*J40/$C$7,'NG Inputs'!$B$9)*($B$7-'NG Inputs'!$B$5-'NG Inputs'!$B$6-2*'NG Inputs'!$B$7*SQRT(MIN('NG Inputs'!$B$12*J40/$C$7,'NG Inputs'!$B$9)/'NG Inputs'!$B$8))+MAX(J40-MIN('NG Inputs'!$B$12*J40/$C$7,'NG Inputs'!$B$9)*$C$7,0)*'NG Inputs'!$B$10/$D$7)*(1-'NG Inputs'!$B$4)+IF($D$7=1,(1-IF(OR($D$7=2,MOD(A41,2)=1),1,0))*J40*'NG Inputs'!$B$10*(1-'NG Inputs'!$B$4)/2,0)-IF(MOD(A41,2)=0,INDEX($B$11:$D$25,B41,2)*(1-'NG Inputs'!$B$4),0) | K41: =K40+IF(OR($D$7=2,MOD(A41,2)=1),1,0)*(MIN('NG Inputs'!$B$12*K40/$C$7,'NG Inputs'!$B$9)*($B$7-'NG Inputs'!$B$5-'NG Inputs'!$B$6-2*'NG Inputs'!$B$7*SQRT(MIN('NG Inputs'!$B$12*K40/$C$7,'NG Inputs'!$B$9)/'NG Inputs'!$B$8))+MAX(K40-MIN('NG Inputs'!$B$12*K40/$C$7,'NG Inputs'!$B$9)*$C$7,0)*'NG Inputs'!$B$10/$D$7)*(1-'NG Inputs'!$B$4)+IF($D$7=1,(1-IF(OR($D$7=2,MOD(A41,2)=1),1,0))*K40*'NG Inputs'!$B$10*(1-'NG Inputs'!$B$4)/2,0)-IF(MOD(A41,2)=0,INDEX($B$11:$D$25,B41,3)*(1-'NG Inputs'!$B$4),0)
... A58: 30 | B58: =ROUNDUP(A58/2,0) | C58: =C57+IF(OR($D$5=2,MOD(A58,2)=1),1,0)*(MIN('NG Inputs'!$B$12*C57/$C$5,'NG Inputs'!$B$9)*($B$5-'NG Inputs'!$B$5-'NG Inputs'!$B$6-2*'NG Inputs'!$B$7*SQRT(MIN('NG Inputs'!$B$12*C57/$C$5,'NG Inputs'!$B$9)/'NG Inputs'!$B$8))+MAX(C57-MIN('NG Inputs'!$B$12*C57/$C$5,'NG Inputs'!$B$9)*$C$5,0)*'NG Inputs'!$B$10/$D$5)*(1-'NG Inputs'!$B$4)+IF($D$5=1,(1-IF(OR($D$5=2,MOD(A58,2)=1),1,0))*C57*'NG Inputs'!$B$10*(1-'NG Inputs'!$B$4)/2,0)-IF(MOD(A58,2)=0,INDEX($B$11:$D$25,B58,1)*(1-'NG Inputs'!$B$4),0) | D58: =D57+IF(OR($D$5=2,MOD(A58,2)=1),1,0)*(MIN('NG Inputs'!$B$12*D57/$C$5,'NG Inputs'!$B$9)*($B$5-'NG Inputs'!$B$5-'NG Inputs'!$B$6-2*'NG Inputs'!$B$7*SQRT(MIN('NG Inputs'!$B$12*D57/$C$5,'NG Inputs'!$B$9)/'NG Inputs'!$B$8))+MAX(D57-MIN('NG Inputs'!$B$12*D57/$C$5,'NG Inputs'!$B$9)*$C$5,0)*'NG Inputs'!$B$10/$D$5)*(1-'NG Inputs'!$B$4)+IF($D$5=1,(1-IF(OR($D$5=2,MOD(A58,2)=1),1,0))*D57*'NG Inputs'!$B$10*(1-'NG Inputs'!$B$4)/2,0)-IF(MOD(A58,2)=0,INDEX($B$11:$D$25,B58,2)*(1-'NG Inputs'!$B$4),0) | E58: =E57+IF(OR($D$5=2,MOD(A58,2)=1),1,0)*(MIN('NG Inputs'!$B$12*E57/$C$5,'NG Inputs'!$B$9)*($B$5-'NG Inputs'!$B$5-'NG Inputs'!$B$6-2*'NG Inputs'!$B$7*SQRT(MIN('NG Inputs'!$B$12*E57/$C$5,'NG Inputs'!$B$9)/'NG Inputs'!$B$8))+MAX(E57-MIN('NG Inputs'!$B$12*E57/$C$5,'NG Inputs'!$B$9)*$C$5,0)*'NG Inputs'!$B$10/$D$5)*(1-'NG Inputs'!$B$4)+IF($D$5=1,(1-IF(OR($D$5=2,MOD(A58,2)=1),1,0))*E57*'NG Inputs'!$B$10*(1-'NG Inputs'!$B$4)/2,0)-IF(MOD(A58,2)=0,INDEX($B$11:$D$25,B58,3)*(1-'NG Inputs'!$B$4),0) | F58: =F57+IF(OR($D$6=2,MOD(A58,2)=1),1,0)*(MIN('NG Inputs'!$B$12*F57/$C$6,'NG Inputs'!$B$9)*($B$6-'NG Inputs'!$B$5-'NG Inputs'!$B$6-2*'NG Inputs'!$B$7*SQRT(MIN('NG Inputs'!$B$12*F57/$C$6,'NG Inputs'!$B$9)/'NG Inputs'!$B$8))+MAX(F57-MIN('NG Inputs'!$B$12*F57/$C$6,'NG Inputs'!$B$9)*$C$6,0)*'NG Inputs'!$B$10/$D$6)*(1-'NG Inputs'!$B$4)+IF($D$6=1,(1-IF(OR($D$6=2,MOD(A58,2)=1),1,0))*F57*'NG Inputs'!$B$10*(1-'NG Inputs'!$B$4)/2,0)-IF(MOD(A58,2)=0,INDEX($B$11:$D$25,B58,1)*(1-'NG Inputs'!$B$4),0) | G58: =G57+IF(OR($D$6=2,MOD(A58,2)=1),1,0)*(MIN('NG Inputs'!$B$12*G57/$C$6,'NG Inputs'!$B$9)*($B$6-'NG Inputs'!$B$5-'NG Inputs'!$B$6-2*'NG Inputs'!$B$7*SQRT(MIN('NG Inputs'!$B$12*G57/$C$6,'NG Inputs'!$B$9)/'NG Inputs'!$B$8))+MAX(G57-MIN('NG Inputs'!$B$12*G57/$C$6,'NG Inputs'!$B$9)*$C$6,0)*'NG Inputs'!$B$10/$D$6)*(1-'NG Inputs'!$B$4)+IF($D$6=1,(1-IF(OR($D$6=2,MOD(A58,2)=1),1,0))*G57*'NG Inputs'!$B$10*(1-'NG Inputs'!$B$4)/2,0)-IF(MOD(A58,2)=0,INDEX($B$11:$D$25,B58,2)*(1-'NG Inputs'!$B$4),0) | H58: =H57+IF(OR($D$6=2,MOD(A58,2)=1),1,0)*(MIN('NG Inputs'!$B$12*H57/$C$6,'NG Inputs'!$B$9)*($B$6-'NG Inputs'!$B$5-'NG Inputs'!$B$6-2*'NG Inputs'!$B$7*SQRT(MIN('NG Inputs'!$B$12*H57/$C$6,'NG Inputs'!$B$9)/'NG Inputs'!$B$8))+MAX(H57-MIN('NG Inputs'!$B$12*H57/$C$6,'NG Inputs'!$B$9)*$C$6,0)*'NG Inputs'!$B$10/$D$6)*(1-'NG Inputs'!$B$4)+IF($D$6=1,(1-IF(OR($D$6=2,MOD(A58,2)=1),1,0))*H57*'NG Inputs'!$B$10*(1-'NG Inputs'!$B$4)/2,0)-IF(MOD(A58,2)=0,INDEX($B$11:$D$25,B58,3)*(1-'NG Inputs'!$B$4),0) | I58: =I57+IF(OR($D$7=2,MOD(A58,2)=1),1,0)*(MIN('NG Inputs'!$B$12*I57/$C$7,'NG Inputs'!$B$9)*($B$7-'NG Inputs'!$B$5-'NG Inputs'!$B$6-2*'NG Inputs'!$B$7*SQRT(MIN('NG Inputs'!$B$12*I57/$C$7,'NG Inputs'!$B$9)/'NG Inputs'!$B$8))+MAX(I57-MIN('NG Inputs'!$B$12*I57/$C$7,'NG Inputs'!$B$9)*$C$7,0)*'NG Inputs'!$B$10/$D$7)*(1-'NG Inputs'!$B$4)+IF($D$7=1,(1-IF(OR($D$7=2,MOD(A58,2)=1),1,0))*I57*'NG Inputs'!$B$10*(1-'NG Inputs'!$B$4)/2,0)-IF(MOD(A58,2)=0,INDEX($B$11:$D$25,B58,1)*(1-'NG Inputs'!$B$4),0) | J58: =J57+IF(OR($D$7=2,MOD(A58,2)=1),1,0)*(MIN('NG Inputs'!$B$12*J57/$C$7,'NG Inputs'!$B$9)*($B$7-'NG Inputs'!$B$5-'NG Inputs'!$B$6-2*'NG Inputs'!$B$7*SQRT(MIN('NG Inputs'!$B$12*J57/$C$7,'NG Inputs'!$B$9)/'NG Inputs'!$B$8))+MAX(J57-MIN('NG Inputs'!$B$12*J57/$C$7,'NG Inputs'!$B$9)*$C$7,0)*'NG Inputs'!$B$10/$D$7)*(1-'NG Inputs'!$B$4)+IF($D$7=1,(1-IF(OR($D$7=2,MOD(A58,2)=1),1,0))*J57*'NG Inputs'!$B$10*(1-'NG Inputs'!$B$4)/2,0)-IF(MOD(A58,2)=0,INDEX($B$11:$D$25,B58,2)*(1-'NG Inputs'!$B$4),0) | K58: =K57+IF(OR($D$7=2,MOD(A58,2)=1),1,0)*(MIN('NG Inputs'!$B$12*K57/$C$7,'NG Inputs'!$B$9)*($B$7-'NG Inputs'!$B$5-'NG Inputs'!$B$6-2*'NG Inputs'!$B$7*SQRT(MIN('NG Inputs'!$B$12*K57/$C$7,'NG Inputs'!$B$9)/'NG Inputs'!$B$8))+MAX(K57-MIN('NG Inputs'!$B$12*K57/$C$7,'NG Inputs'!$B$9)*$C$7,0)*'NG Inputs'!$B$10/$D$7)*(1-'NG Inputs'!$B$4)+IF($D$7=1,(1-IF(OR($D$7=2,MOD(A58,2)=1),1,0))*K57*'NG Inputs'!$B$10*(1-'NG Inputs'!$B$4)/2,0)-IF(MOD(A58,2)=0,INDEX($B$11:$D$25,B58,3)*(1-'NG Inputs'!$B$4),0)
A60: YEAR-END SUMMARY (₹ Cr)
A61: Year | B61: ="BULL "&IF($C$3>=10000000,"₹"&TEXT($C$3/10000000,"0.##")&"Cr","₹"&TEXT($C$3/100000,"0.##")&"L") | C61: ="BULL "&IF($D$3>=10000000,"₹"&TEXT($D$3/10000000,"0.##")&"Cr","₹"&TEXT($D$3/100000,"0.##")&"L") | D61: ="BULL "&IF($E$3>=10000000,"₹"&TEXT($E$3/10000000,"0.##")&"Cr","₹"&TEXT($E$3/100000,"0.##")&"L") | E61: ="BASE "&IF($C$3>=10000000,"₹"&TEXT($C$3/10000000,"0.##")&"Cr","₹"&TEXT($C$3/100000,"0.##")&"L") | F61: ="BASE "&IF($D$3>=10000000,"₹"&TEXT($D$3/10000000,"0.##")&"Cr","₹"&TEXT($D$3/100000,"0.##")&"L") | G61: ="BASE "&IF($E$3>=10000000,"₹"&TEXT($E$3/10000000,"0.##")&"Cr","₹"&TEXT($E$3/100000,"0.##")&"L") | H61: ="BEAR "&IF($C$3>=10000000,"₹"&TEXT($C$3/10000000,"0.##")&"Cr","₹"&TEXT($C$3/100000,"0.##")&"L") | I61: ="BEAR "&IF($D$3>=10000000,"₹"&TEXT($D$3/10000000,"0.##")&"Cr","₹"&TEXT($D$3/100000,"0.##")&"L") | J61: ="BEAR "&IF($E$3>=10000000,"₹"&TEXT($E$3/10000000,"0.##")&"Cr","₹"&TEXT($E$3/100000,"0.##")&"L")
A62: 1 | B62: =C30/10000000 | C62: =D30/10000000 | D62: =E30/10000000 | E62: =F30/10000000 | F62: =G30/10000000 | G62: =H30/10000000 | H62: =I30/10000000 | I62: =J30/10000000 | J62: =K30/10000000
A63: 2 | B63: =C32/10000000 | C63: =D32/10000000 | D63: =E32/10000000 | E63: =F32/10000000 | F63: =G32/10000000 | G63: =H32/10000000 | H63: =I32/10000000 | I63: =J32/10000000 | J63: =K32/10000000
A64: 3 | B64: =C34/10000000 | C64: =D34/10000000 | D64: =E34/10000000 | E64: =F34/10000000 | F64: =G34/10000000 | G64: =H34/10000000 | H64: =I34/10000000 | I64: =J34/10000000 | J64: =K34/10000000
A65: 4 | B65: =C36/10000000 | C65: =D36/10000000 | D65: =E36/10000000 | E65: =F36/10000000 | F65: =G36/10000000 | G65: =H36/10000000 | H65: =I36/10000000 | I65: =J36/10000000 | J65: =K36/10000000
A66: 5 | B66: =C38/10000000 | C66: =D38/10000000 | D66: =E38/10000000 | E66: =F38/10000000 | F66: =G38/10000000 | G66: =H38/10000000 | H66: =I38/10000000 | I66: =J38/10000000 | J66: =K38/10000000
A67: 6 | B67: =C40/10000000 | C67: =D40/10000000 | D67: =E40/10000000 | E67: =F40/10000000 | F67: =G40/10000000 | G67: =H40/10000000 | H67: =I40/10000000 | I67: =J40/10000000 | J67: =K40/10000000
A68: 7 | B68: =C42/10000000 | C68: =D42/10000000 | D68: =E42/10000000 | E68: =F42/10000000 | F68: =G42/10000000 | G68: =H42/10000000 | H68: =I42/10000000 | I68: =J42/10000000 | J68: =K42/10000000
A69: 8 | B69: =C44/10000000 | C69: =D44/10000000 | D69: =E44/10000000 | E69: =F44/10000000 | F69: =G44/10000000 | G69: =H44/10000000 | H69: =I44/10000000 | I69: =J44/10000000 | J69: =K44/10000000
A70: 9 | B70: =C46/10000000 | C70: =D46/10000000 | D70: =E46/10000000 | E70: =F46/10000000 | F70: =G46/10000000 | G70: =H46/10000000 | H70: =I46/10000000 | I70: =J46/10000000 | J70: =K46/10000000
A71: 10 | B71: =C48/10000000 | C71: =D48/10000000 | D71: =E48/10000000 | E71: =F48/10000000 | F71: =G48/10000000 | G71: =H48/10000000 | H71: =I48/10000000 | I71: =J48/10000000 | J71: =K48/10000000
A72: 11 | B72: =C50/10000000 | C72: =D50/10000000 | D72: =E50/10000000 | E72: =F50/10000000 | F72: =G50/10000000 | G72: =H50/10000000 | H72: =I50/10000000 | I72: =J50/10000000 | J72: =K50/10000000
A73: 12 | B73: =C52/10000000 | C73: =D52/10000000 | D73: =E52/10000000 | E73: =F52/10000000 | F73: =G52/10000000 | G73: =H52/10000000 | H73: =I52/10000000 | I73: =J52/10000000 | J73: =K52/10000000
A74: 13 | B74: =C54/10000000 | C74: =D54/10000000 | D74: =E54/10000000 | E74: =F54/10000000 | F74: =G54/10000000 | G74: =H54/10000000 | H74: =I54/10000000 | I74: =J54/10000000 | J74: =K54/10000000
A75: 14 | B75: =C56/10000000 | C75: =D56/10000000 | D75: =E56/10000000 | E75: =F56/10000000 | F75: =G56/10000000 | G75: =H56/10000000 | H75: =I56/10000000 | I75: =J56/10000000 | J75: =K56/10000000
A76: 15 | B76: =C58/10000000 | C76: =D58/10000000 | D76: =E58/10000000 | E76: =F58/10000000 | F76: =G58/10000000 | G76: =H58/10000000 | H76: =I58/10000000 | I76: =J58/10000000 | J76: =K58/10000000
A78: GIFT gateway crossed (capital ≥ ₹20 Cr) in year: | B78: =IFERROR(INDEX($A$62:$A$76,MATCH(TRUE,INDEX(B62:B76>='NG Inputs'!$B$11/10000000,0),0)),"not reached") | C78: =IFERROR(INDEX($A$62:$A$76,MATCH(TRUE,INDEX(C62:C76>='NG Inputs'!$B$11/10000000,0),0)),"not reached") | D78: =IFERROR(INDEX($A$62:$A$76,MATCH(TRUE,INDEX(D62:D76>='NG Inputs'!$B$11/10000000,0),0)),"not reached") | E78: =IFERROR(INDEX($A$62:$A$76,MATCH(TRUE,INDEX(E62:E76>='NG Inputs'!$B$11/10000000,0),0)),"not reached") | F78: =IFERROR(INDEX($A$62:$A$76,MATCH(TRUE,INDEX(F62:F76>='NG Inputs'!$B$11/10000000,0),0)),"not reached") | G78: =IFERROR(INDEX($A$62:$A$76,MATCH(TRUE,INDEX(G62:G76>='NG Inputs'!$B$11/10000000,0),0)),"not reached") | H78: =IFERROR(INDEX($A$62:$A$76,MATCH(TRUE,INDEX(H62:H76>='NG Inputs'!$B$11/10000000,0),0)),"not reached") | I78: =IFERROR(INDEX($A$62:$A$76,MATCH(TRUE,INDEX(I62:I76>='NG Inputs'!$B$11/10000000,0),0)),"not reached") | J78: =IFERROR(INDEX($A$62:$A$76,MATCH(TRUE,INDEX(J62:J76>='NG Inputs'!$B$11/10000000,0),0)),"not reached")

Sheet NG GIFT Bridge
A1: PHASE-2 BRIDGE · STAY vs SWITCH vs HYBRID
A2: Cap the MCX sleeve, sweep overflow to GIFT — the hybrid dominates both pure strategies.
A4: Inputs
A5: MCX sleeve cap (₹) | B5: 1000000000
A6: GIFT gross return / 18-mo cycle | B6: 0.75
A7: GIFT expense per cycle (₹) | B7: 5000000
A8: Tax (115BAA corp) | B8: ='NG Inputs'!B4
A9: Move % | B9: ='NG Scenarios'!B6
A10: Margin % | B10: ='NG Data'!D134
A11: Start capital (₹) | B11: 7500000
A14: Year | B14: STAY: MCX only (₹) | C14: SWITCH: all→GIFT at ₹20Cr (₹) | D14: HYBRID MCX sleeve (₹) | E14: HYBRID GIFT sleeve (₹) | F14: HYBRID total (₹)
A15: 1 | B15: =($B$11+(MIN($B$11/$B$10,'NG Inputs'!$B$9)*($B$9-'NG Inputs'!$B$5-'NG Inputs'!$B$6-2*'NG Inputs'!$B$7*SQRT(MIN($B$11/$B$10,'NG Inputs'!$B$9)/'NG Inputs'!$B$8))+MAX($B$11-MIN($B$11/$B$10,'NG Inputs'!$B$9)*$B$10,0)*'NG Inputs'!$B$10/2)*(1-$B$8))+(MIN(($B$11+(MIN($B$11/$B$10,'NG Inputs'!$B$9)*($B$9-'NG Inputs'!$B$5-'NG Inputs'!$B$6-2*'NG Inputs'!$B$7*SQRT(MIN($B$11/$B$10,'NG Inputs'!$B$9)/'NG Inputs'!$B$8))+MAX($B$11-MIN($B$11/$B$10,'NG Inputs'!$B$9)*$B$10,0)*'NG Inputs'!$B$10/2)*(1-$B$8))/$B$10,'NG Inputs'!$B$9)*($B$9-'NG Inputs'!$B$5-'NG Inputs'!$B$6-2*'NG Inputs'!$B$7*SQRT(MIN(($B$11+(MIN($B$11/$B$10,'NG Inputs'!$B$9)*($B$9-'NG Inputs'!$B$5-'NG Inputs'!$B$6-2*'NG Inputs'!$B$7*SQRT(MIN($B$11/$B$10,'NG Inputs'!$B$9)/'NG Inputs'!$B$8))+MAX($B$11-MIN($B$11/$B$10,'NG Inputs'!$B$9)*$B$10,0)*'NG Inputs'!$B$10/2)*(1-$B$8))/$B$10,'NG Inputs'!$B$9)/'NG Inputs'!$B$8))+MAX(($B$11+(MIN($B$11/$B$10,'NG Inputs'!$B$9)*($B$9-'NG Inputs'!$B$5-'NG Inputs'!$B$6-2*'NG Inputs'!$B$7*SQRT(MIN($B$11/$B$10,'NG Inputs'!$B$9)/'NG Inputs'!$B$8))+MAX($B$11-MIN($B$11/$B$10,'NG Inputs'!$B$9)*$B$10,0)*'NG Inputs'!$B$10/2)*(1-$B$8))-MIN(($B$11+(MIN($B$11/$B$10,'NG Inputs'!$B$9)*($B$9-'NG Inputs'!$B$5-'NG Inputs'!$B$6-2*'NG Inputs'!$B$7*SQRT(MIN($B$11/$B$10,'NG Inputs'!$B$9)/'NG Inputs'!$B$8))+MAX($B$11-MIN($B$11/$B$10,'NG Inputs'!$B$9)*$B$10,0)*'NG Inputs'!$B$10/2)*(1-$B$8))/$B$10,'NG Inputs'!$B$9)*$B$10,0)*'NG Inputs'!$B$10/2)*(1-$B$8)-INDEX('NG Scenarios'!$C$11:$C$25,A15)*(1-$B$8) | C15: =IF($B$11<'NG Inputs'!$B$11,($B$11+(MIN($B$11/$B$10,'NG Inputs'!$B$9)*($B$9-'NG Inputs'!$B$5-'NG Inputs'!$B$6-2*'NG Inputs'!$B$7*SQRT(MIN($B$11/$B$10,'NG Inputs'!$B$9)/'NG Inputs'!$B$8))+MAX($B$11-MIN($B$11/$B$10,'NG Inputs'!$B$9)*$B$10,0)*'NG Inputs'!$B$10/2)*(1-$B$8))+(MIN(($B$11+(MIN($B$11/$B$10,'NG Inputs'!$B$9)*($B$9-'NG Inputs'!$B$5-'NG Inputs'!$B$6-2*'NG Inputs'!$B$7*SQRT(MIN($B$11/$B$10,'NG Inputs'!$B$9)/'NG Inputs'!$B$8))+MAX($B$11-MIN($B$11/$B$10,'NG Inputs'!$B$9)*$B$10,0)*'NG Inputs'!$B$10/2)*(1-$B$8))/$B$10,'NG Inputs'!$B$9)*($B$9-'NG Inputs'!$B$5-'NG Inputs'!$B$6-2*'NG Inputs'!$B$7*SQRT(MIN(($B$11+(MIN($B$11/$B$10,'NG Inputs'!$B$9)*($B$9-'NG Inputs'!$B$5-'NG Inputs'!$B$6-2*'NG Inputs'!$B$7*SQRT(MIN($B$11/$B$10,'NG Inputs'!$B$9)/'NG Inputs'!$B$8))+MAX($B$11-MIN($B$11/$B$10,'NG Inputs'!$B$9)*$B$10,0)*'NG Inputs'!$B$10/2)*(1-$B$8))/$B$10,'NG Inputs'!$B$9)/'NG Inputs'!$B$8))+MAX(($B$11+(MIN($B$11/$B$10,'NG Inputs'!$B$9)*($B$9-'NG Inputs'!$B$5-'NG Inputs'!$B$6-2*'NG Inputs'!$B$7*SQRT(MIN($B$11/$B$10,'NG Inputs'!$B$9)/'NG Inputs'!$B$8))+MAX($B$11-MIN($B$11/$B$10,'NG Inputs'!$B$9)*$B$10,0)*'NG Inputs'!$B$10/2)*(1-$B$8))-MIN(($B$11+(MIN($B$11/$B$10,'NG Inputs'!$B$9)*($B$9-'NG Inputs'!$B$5-'NG Inputs'!$B$6-2*'NG Inputs'!$B$7*SQRT(MIN($B$11/$B$10,'NG Inputs'!$B$9)/'NG Inputs'!$B$8))+MAX($B$11-MIN($B$11/$B$10,'NG Inputs'!$B$9)*$B$10,0)*'NG Inputs'!$B$10/2)*(1-$B$8))/$B$10,'NG Inputs'!$B$9)*$B$10,0)*'NG Inputs'!$B$10/2)*(1-$B$8)-INDEX('NG Scenarios'!$C$11:$C$25,A15)*(1-$B$8),$B$11+(($B$6*$B$11-$B$7)*(12/18))*(1-$B$8)) | D15: =MIN(($B$11+(MIN($B$11/$B$10,'NG Inputs'!$B$9)*($B$9-'NG Inputs'!$B$5-'NG Inputs'!$B$6-2*'NG Inputs'!$B$7*SQRT(MIN($B$11/$B$10,'NG Inputs'!$B$9)/'NG Inputs'!$B$8))+MAX($B$11-MIN($B$11/$B$10,'NG Inputs'!$B$9)*$B$10,0)*'NG Inputs'!$B$10/2)*(1-$B$8))+(MIN(($B$11+(MIN($B$11/$B$10,'NG Inputs'!$B$9)*($B$9-'NG Inputs'!$B$5-'NG Inputs'!$B$6-2*'NG Inputs'!$B$7*SQRT(MIN($B$11/$B$10,'NG Inputs'!$B$9)/'NG Inputs'!$B$8))+MAX($B$11-MIN($B$11/$B$10,'NG Inputs'!$B$9)*$B$10,0)*'NG Inputs'!$B$10/2)*(1-$B$8))/$B$10,'NG Inputs'!$B$9)*($B$9-'NG Inputs'!$B$5-'NG Inputs'!$B$6-2*'NG Inputs'!$B$7*SQRT(MIN(($B$11+(MIN($B$11/$B$10,'NG Inputs'!$B$9)*($B$9-'NG Inputs'!$B$5-'NG Inputs'!$B$6-2*'NG Inputs'!$B$7*SQRT(MIN($B$11/$B$10,'NG Inputs'!$B$9)/'NG Inputs'!$B$8))+MAX($B$11-MIN($B$11/$B$10,'NG Inputs'!$B$9)*$B$10,0)*'NG Inputs'!$B$10/2)*(1-$B$8))/$B$10,'NG Inputs'!$B$9)/'NG Inputs'!$B$8))+MAX(($B$11+(MIN($B$11/$B$10,'NG Inputs'!$B$9)*($B$9-'NG Inputs'!$B$5-'NG Inputs'!$B$6-2*'NG Inputs'!$B$7*SQRT(MIN($B$11/$B$10,'NG Inputs'!$B$9)/'NG Inputs'!$B$8))+MAX($B$11-MIN($B$11/$B$10,'NG Inputs'!$B$9)*$B$10,0)*'NG Inputs'!$B$10/2)*(1-$B$8))-MIN(($B$11+(MIN($B$11/$B$10,'NG Inputs'!$B$9)*($B$9-'NG Inputs'!$B$5-'NG Inputs'!$B$6-2*'NG Inputs'!$B$7*SQRT(MIN($B$11/$B$10,'NG Inputs'!$B$9)/'NG Inputs'!$B$8))+MAX($B$11-MIN($B$11/$B$10,'NG Inputs'!$B$9)*$B$10,0)*'NG Inputs'!$B$10/2)*(1-$B$8))/$B$10,'NG Inputs'!$B$9)*$B$10,0)*'NG Inputs'!$B$10/2)*(1-$B$8)-INDEX('NG Scenarios'!$C$11:$C$25,A15)*(1-$B$8),$B$5) | E15: =IF(0>0,0+(($B$6*0-$B$7)*(12/18))*(1-$B$8),0)+MAX(($B$11+(MIN($B$11/$B$10,'NG Inputs'!$B$9)*($B$9-'NG Inputs'!$B$5-'NG Inputs'!$B$6-2*'NG Inputs'!$B$7*SQRT(MIN($B$11/$B$10,'NG Inputs'!$B$9)/'NG Inputs'!$B$8))+MAX($B$11-MIN($B$11/$B$10,'NG Inputs'!$B$9)*$B$10,0)*'NG Inputs'!$B$10/2)*(1-$B$8))+(MIN(($B$11+(MIN($B$11/$B$10,'NG Inputs'!$B$9)*($B$9-'NG Inputs'!$B$5-'NG Inputs'!$B$6-2*'NG Inputs'!$B$7*SQRT(MIN($B$11/$B$10,'NG Inputs'!$B$9)/'NG Inputs'!$B$8))+MAX($B$11-MIN($B$11/$B$10,'NG Inputs'!$B$9)*$B$10,0)*'NG Inputs'!$B$10/2)*(1-$B$8))/$B$10,'NG Inputs'!$B$9)*($B$9-'NG Inputs'!$B$5-'NG Inputs'!$B$6-2*'NG Inputs'!$B$7*SQRT(MIN(($B$11+(MIN($B$11/$B$10,'NG Inputs'!$B$9)*($B$9-'NG Inputs'!$B$5-'NG Inputs'!$B$6-2*'NG Inputs'!$B$7*SQRT(MIN($B$11/$B$10,'NG Inputs'!$B$9)/'NG Inputs'!$B$8))+MAX($B$11-MIN($B$11/$B$10,'NG Inputs'!$B$9)*$B$10,0)*'NG Inputs'!$B$10/2)*(1-$B$8))/$B$10,'NG Inputs'!$B$9)/'NG Inputs'!$B$8))+MAX(($B$11+(MIN($B$11/$B$10,'NG Inputs'!$B$9)*($B$9-'NG Inputs'!$B$5-'NG Inputs'!$B$6-2*'NG Inputs'!$B$7*SQRT(MIN($B$11/$B$10,'NG Inputs'!$B$9)/'NG Inputs'!$B$8))+MAX($B$11-MIN($B$11/$B$10,'NG Inputs'!$B$9)*$B$10,0)*'NG Inputs'!$B$10/2)*(1-$B$8))-MIN(($B$11+(MIN($B$11/$B$10,'NG Inputs'!$B$9)*($B$9-'NG Inputs'!$B$5-'NG Inputs'!$B$6-2*'NG Inputs'!$B$7*SQRT(MIN($B$11/$B$10,'NG Inputs'!$B$9)/'NG Inputs'!$B$8))+MAX($B$11-MIN($B$11/$B$10,'NG Inputs'!$B$9)*$B$10,0)*'NG Inputs'!$B$10/2)*(1-$B$8))/$B$10,'NG Inputs'!$B$9)*$B$10,0)*'NG Inputs'!$B$10/2)*(1-$B$8)-INDEX('NG Scenarios'!$C$11:$C$25,A15)*(1-$B$8)-$B$5,0) | F15: =D15+E15
A16: 2 | B16: =(B15+(MIN(B15/$B$10,'NG Inputs'!$B$9)*($B$9-'NG Inputs'!$B$5-'NG Inputs'!$B$6-2*'NG Inputs'!$B$7*SQRT(MIN(B15/$B$10,'NG Inputs'!$B$9)/'NG Inputs'!$B$8))+MAX(B15-MIN(B15/$B$10,'NG Inputs'!$B$9)*$B$10,0)*'NG Inputs'!$B$10/2)*(1-$B$8))+(MIN((B15+(MIN(B15/$B$10,'NG Inputs'!$B$9)*($B$9-'NG Inputs'!$B$5-'NG Inputs'!$B$6-2*'NG Inputs'!$B$7*SQRT(MIN(B15/$B$10,'NG Inputs'!$B$9)/'NG Inputs'!$B$8))+MAX(B15-MIN(B15/$B$10,'NG Inputs'!$B$9)*$B$10,0)*'NG Inputs'!$B$10/2)*(1-$B$8))/$B$10,'NG Inputs'!$B$9)*($B$9-'NG Inputs'!$B$5-'NG Inputs'!$B$6-2*'NG Inputs'!$B$7*SQRT(MIN((B15+(MIN(B15/$B$10,'NG Inputs'!$B$9)*($B$9-'NG Inputs'!$B$5-'NG Inputs'!$B$6-2*'NG Inputs'!$B$7*SQRT(MIN(B15/$B$10,'NG Inputs'!$B$9)/'NG Inputs'!$B$8))+MAX(B15-MIN(B15/$B$10,'NG Inputs'!$B$9)*$B$10,0)*'NG Inputs'!$B$10/2)*(1-$B$8))/$B$10,'NG Inputs'!$B$9)/'NG Inputs'!$B$8))+MAX((B15+(MIN(B15/$B$10,'NG Inputs'!$B$9)*($B$9-'NG Inputs'!$B$5-'NG Inputs'!$B$6-2*'NG Inputs'!$B$7*SQRT(MIN(B15/$B$10,'NG Inputs'!$B$9)/'NG Inputs'!$B$8))+MAX(B15-MIN(B15/$B$10,'NG Inputs'!$B$9)*$B$10,0)*'NG Inputs'!$B$10/2)*(1-$B$8))-MIN((B15+(MIN(B15/$B$10,'NG Inputs'!$B$9)*($B$9-'NG Inputs'!$B$5-'NG Inputs'!$B$6-2*'NG Inputs'!$B$7*SQRT(MIN(B15/$B$10,'NG Inputs'!$B$9)/'NG Inputs'!$B$8))+MAX(B15-MIN(B15/$B$10,'NG Inputs'!$B$9)*$B$10,0)*'NG Inputs'!$B$10/2)*(1-$B$8))/$B$10,'NG Inputs'!$B$9)*$B$10,0)*'NG Inputs'!$B$10/2)*(1-$B$8)-INDEX('NG Scenarios'!$C$11:$C$25,A16)*(1-$B$8) | C16: =IF(C15<'NG Inputs'!$B$11,(C15+(MIN(C15/$B$10,'NG Inputs'!$B$9)*($B$9-'NG Inputs'!$B$5-'NG Inputs'!$B$6-2*'NG Inputs'!$B$7*SQRT(MIN(C15/$B$10,'NG Inputs'!$B$9)/'NG Inputs'!$B$8))+MAX(C15-MIN(C15/$B$10,'NG Inputs'!$B$9)*$B$10,0)*'NG Inputs'!$B$10/2)*(1-$B$8))+(MIN((C15+(MIN(C15/$B$10,'NG Inputs'!$B$9)*($B$9-'NG Inputs'!$B$5-'NG Inputs'!$B$6-2*'NG Inputs'!$B$7*SQRT(MIN(C15/$B$10,'NG Inputs'!$B$9)/'NG Inputs'!$B$8))+MAX(C15-MIN(C15/$B$10,'NG Inputs'!$B$9)*$B$10,0)*'NG Inputs'!$B$10/2)*(1-$B$8))/$B$10,'NG Inputs'!$B$9)*($B$9-'NG Inputs'!$B$5-'NG Inputs'!$B$6-2*'NG Inputs'!$B$7*SQRT(MIN((C15+(MIN(C15/$B$10,'NG Inputs'!$B$9)*($B$9-'NG Inputs'!$B$5-'NG Inputs'!$B$6-2*'NG Inputs'!$B$7*SQRT(MIN(C15/$B$10,'NG Inputs'!$B$9)/'NG Inputs'!$B$8))+MAX(C15-MIN(C15/$B$10,'NG Inputs'!$B$9)*$B$10,0)*'NG Inputs'!$B$10/2)*(1-$B$8))/$B$10,'NG Inputs'!$B$9)/'NG Inputs'!$B$8))+MAX((C15+(MIN(C15/$B$10,'NG Inputs'!$B$9)*($B$9-'NG Inputs'!$B$5-'NG Inputs'!$B$6-2*'NG Inputs'!$B$7*SQRT(MIN(C15/$B$10,'NG Inputs'!$B$9)/'NG Inputs'!$B$8))+MAX(C15-MIN(C15/$B$10,'NG Inputs'!$B$9)*$B$10,0)*'NG Inputs'!$B$10/2)*(1-$B$8))-MIN((C15+(MIN(C15/$B$10,'NG Inputs'!$B$9)*($B$9-'NG Inputs'!$B$5-'NG Inputs'!$B$6-2*'NG Inputs'!$B$7*SQRT(MIN(C15/$B$10,'NG Inputs'!$B$9)/'NG Inputs'!$B$8))+MAX(C15-MIN(C15/$B$10,'NG Inputs'!$B$9)*$B$10,0)*'NG Inputs'!$B$10/2)*(1-$B$8))/$B$10,'NG Inputs'!$B$9)*$B$10,0)*'NG Inputs'!$B$10/2)*(1-$B$8)-INDEX('NG Scenarios'!$C$11:$C$25,A16)*(1-$B$8),C15+(($B$6*C15-$B$7)*(12/18))*(1-$B$8)) | D16: =MIN((D15+(MIN(D15/$B$10,'NG Inputs'!$B$9)*($B$9-'NG Inputs'!$B$5-'NG Inputs'!$B$6-2*'NG Inputs'!$B$7*SQRT(MIN(D15/$B$10,'NG Inputs'!$B$9)/'NG Inputs'!$B$8))+MAX(D15-MIN(D15/$B$10,'NG Inputs'!$B$9)*$B$10,0)*'NG Inputs'!$B$10/2)*(1-$B$8))+(MIN((D15+(MIN(D15/$B$10,'NG Inputs'!$B$9)*($B$9-'NG Inputs'!$B$5-'NG Inputs'!$B$6-2*'NG Inputs'!$B$7*SQRT(MIN(D15/$B$10,'NG Inputs'!$B$9)/'NG Inputs'!$B$8))+MAX(D15-MIN(D15/$B$10,'NG Inputs'!$B$9)*$B$10,0)*'NG Inputs'!$B$10/2)*(1-$B$8))/$B$10,'NG Inputs'!$B$9)*($B$9-'NG Inputs'!$B$5-'NG Inputs'!$B$6-2*'NG Inputs'!$B$7*SQRT(MIN((D15+(MIN(D15/$B$10,'NG Inputs'!$B$9)*($B$9-'NG Inputs'!$B$5-'NG Inputs'!$B$6-2*'NG Inputs'!$B$7*SQRT(MIN(D15/$B$10,'NG Inputs'!$B$9)/'NG Inputs'!$B$8))+MAX(D15-MIN(D15/$B$10,'NG Inputs'!$B$9)*$B$10,0)*'NG Inputs'!$B$10/2)*(1-$B$8))/$B$10,'NG Inputs'!$B$9)/'NG Inputs'!$B$8))+MAX((D15+(MIN(D15/$B$10,'NG Inputs'!$B$9)*($B$9-'NG Inputs'!$B$5-'NG Inputs'!$B$6-2*'NG Inputs'!$B$7*SQRT(MIN(D15/$B$10,'NG Inputs'!$B$9)/'NG Inputs'!$B$8))+MAX(D15-MIN(D15/$B$10,'NG Inputs'!$B$9)*$B$10,0)*'NG Inputs'!$B$10/2)*(1-$B$8))-MIN((D15+(MIN(D15/$B$10,'NG Inputs'!$B$9)*($B$9-'NG Inputs'!$B$5-'NG Inputs'!$B$6-2*'NG Inputs'!$B$7*SQRT(MIN(D15/$B$10,'NG Inputs'!$B$9)/'NG Inputs'!$B$8))+MAX(D15-MIN(D15/$B$10,'NG Inputs'!$B$9)*$B$10,0)*'NG Inputs'!$B$10/2)*(1-$B$8))/$B$10,'NG Inputs'!$B$9)*$B$10,0)*'NG Inputs'!$B$10/2)*(1-$B$8)-INDEX('NG Scenarios'!$C$11:$C$25,A16)*(1-$B$8),$B$5) | E16: =IF(E15>0,E15+(($B$6*E15-$B$7)*(12/18))*(1-$B$8),0)+MAX((D15+(MIN(D15/$B$10,'NG Inputs'!$B$9)*($B$9-'NG Inputs'!$B$5-'NG Inputs'!$B$6-2*'NG Inputs'!$B$7*SQRT(MIN(D15/$B$10,'NG Inputs'!$B$9)/'NG Inputs'!$B$8))+MAX(D15-MIN(D15/$B$10,'NG Inputs'!$B$9)*$B$10,0)*'NG Inputs'!$B$10/2)*(1-$B$8))+(MIN((D15+(MIN(D15/$B$10,'NG Inputs'!$B$9)*($B$9-'NG Inputs'!$B$5-'NG Inputs'!$B$6-2*'NG Inputs'!$B$7*SQRT(MIN(D15/$B$10,'NG Inputs'!$B$9)/'NG Inputs'!$B$8))+MAX(D15-MIN(D15/$B$10,'NG Inputs'!$B$9)*$B$10,0)*'NG Inputs'!$B$10/2)*(1-$B$8))/$B$10,'NG Inputs'!$B$9)*($B$9-'NG Inputs'!$B$5-'NG Inputs'!$B$6-2*'NG Inputs'!$B$7*SQRT(MIN((D15+(MIN(D15/$B$10,'NG Inputs'!$B$9)*($B$9-'NG Inputs'!$B$5-'NG Inputs'!$B$6-2*'NG Inputs'!$B$7*SQRT(MIN(D15/$B$10,'NG Inputs'!$B$9)/'NG Inputs'!$B$8))+MAX(D15-MIN(D15/$B$10,'NG Inputs'!$B$9)*$B$10,0)*'NG Inputs'!$B$10/2)*(1-$B$8))/$B$10,'NG Inputs'!$B$9)/'NG Inputs'!$B$8))+MAX((D15+(MIN(D15/$B$10,'NG Inputs'!$B$9)*($B$9-'NG Inputs'!$B$5-'NG Inputs'!$B$6-2*'NG Inputs'!$B$7*SQRT(MIN(D15/$B$10,'NG Inputs'!$B$9)/'NG Inputs'!$B$8))+MAX(D15-MIN(D15/$B$10,'NG Inputs'!$B$9)*$B$10,0)*'NG Inputs'!$B$10/2)*(1-$B$8))-MIN((D15+(MIN(D15/$B$10,'NG Inputs'!$B$9)*($B$9-'NG Inputs'!$B$5-'NG Inputs'!$B$6-2*'NG Inputs'!$B$7*SQRT(MIN(D15/$B$10,'NG Inputs'!$B$9)/'NG Inputs'!$B$8))+MAX(D15-MIN(D15/$B$10,'NG Inputs'!$B$9)*$B$10,0)*'NG Inputs'!$B$10/2)*(1-$B$8))/$B$10,'NG Inputs'!$B$9)*$B$10,0)*'NG Inputs'!$B$10/2)*(1-$B$8)-INDEX('NG Scenarios'!$C$11:$C$25,A16)*(1-$B$8)-$B$5,0) | F16: =D16+E16
A17: 3 | B17: =(B16+(MIN(B16/$B$10,'NG Inputs'!$B$9)*($B$9-'NG Inputs'!$B$5-'NG Inputs'!$B$6-2*'NG Inputs'!$B$7*SQRT(MIN(B16/$B$10,'NG Inputs'!$B$9)/'NG Inputs'!$B$8))+MAX(B16-MIN(B16/$B$10,'NG Inputs'!$B$9)*$B$10,0)*'NG Inputs'!$B$10/2)*(1-$B$8))+(MIN((B16+(MIN(B16/$B$10,'NG Inputs'!$B$9)*($B$9-'NG Inputs'!$B$5-'NG Inputs'!$B$6-2*'NG Inputs'!$B$7*SQRT(MIN(B16/$B$10,'NG Inputs'!$B$9)/'NG Inputs'!$B$8))+MAX(B16-MIN(B16/$B$10,'NG Inputs'!$B$9)*$B$10,0)*'NG Inputs'!$B$10/2)*(1-$B$8))/$B$10,'NG Inputs'!$B$9)*($B$9-'NG Inputs'!$B$5-'NG Inputs'!$B$6-2*'NG Inputs'!$B$7*SQRT(MIN((B16+(MIN(B16/$B$10,'NG Inputs'!$B$9)*($B$9-'NG Inputs'!$B$5-'NG Inputs'!$B$6-2*'NG Inputs'!$B$7*SQRT(MIN(B16/$B$10,'NG Inputs'!$B$9)/'NG Inputs'!$B$8))+MAX(B16-MIN(B16/$B$10,'NG Inputs'!$B$9)*$B$10,0)*'NG Inputs'!$B$10/2)*(1-$B$8))/$B$10,'NG Inputs'!$B$9)/'NG Inputs'!$B$8))+MAX((B16+(MIN(B16/$B$10,'NG Inputs'!$B$9)*($B$9-'NG Inputs'!$B$5-'NG Inputs'!$B$6-2*'NG Inputs'!$B$7*SQRT(MIN(B16/$B$10,'NG Inputs'!$B$9)/'NG Inputs'!$B$8))+MAX(B16-MIN(B16/$B$10,'NG Inputs'!$B$9)*$B$10,0)*'NG Inputs'!$B$10/2)*(1-$B$8))-MIN((B16+(MIN(B16/$B$10,'NG Inputs'!$B$9)*($B$9-'NG Inputs'!$B$5-'NG Inputs'!$B$6-2*'NG Inputs'!$B$7*SQRT(MIN(B16/$B$10,'NG Inputs'!$B$9)/'NG Inputs'!$B$8))+MAX(B16-MIN(B16/$B$10,'NG Inputs'!$B$9)*$B$10,0)*'NG Inputs'!$B$10/2)*(1-$B$8))/$B$10,'NG Inputs'!$B$9)*$B$10,0)*'NG Inputs'!$B$10/2)*(1-$B$8)-INDEX('NG Scenarios'!$C$11:$C$25,A17)*(1-$B$8) | C17: =IF(C16<'NG Inputs'!$B$11,(C16+(MIN(C16/$B$10,'NG Inputs'!$B$9)*($B$9-'NG Inputs'!$B$5-'NG Inputs'!$B$6-2*'NG Inputs'!$B$7*SQRT(MIN(C16/$B$10,'NG Inputs'!$B$9)/'NG Inputs'!$B$8))+MAX(C16-MIN(C16/$B$10,'NG Inputs'!$B$9)*$B$10,0)*'NG Inputs'!$B$10/2)*(1-$B$8))+(MIN((C16+(MIN(C16/$B$10,'NG Inputs'!$B$9)*($B$9-'NG Inputs'!$B$5-'NG Inputs'!$B$6-2*'NG Inputs'!$B$7*SQRT(MIN(C16/$B$10,'NG Inputs'!$B$9)/'NG Inputs'!$B$8))+MAX(C16-MIN(C16/$B$10,'NG Inputs'!$B$9)*$B$10,0)*'NG Inputs'!$B$10/2)*(1-$B$8))/$B$10,'NG Inputs'!$B$9)*($B$9-'NG Inputs'!$B$5-'NG Inputs'!$B$6-2*'NG Inputs'!$B$7*SQRT(MIN((C16+(MIN(C16/$B$10,'NG Inputs'!$B$9)*($B$9-'NG Inputs'!$B$5-'NG Inputs'!$B$6-2*'NG Inputs'!$B$7*SQRT(MIN(C16/$B$10,'NG Inputs'!$B$9)/'NG Inputs'!$B$8))+MAX(C16-MIN(C16/$B$10,'NG Inputs'!$B$9)*$B$10,0)*'NG Inputs'!$B$10/2)*(1-$B$8))/$B$10,'NG Inputs'!$B$9)/'NG Inputs'!$B$8))+MAX((C16+(MIN(C16/$B$10,'NG Inputs'!$B$9)*($B$9-'NG Inputs'!$B$5-'NG Inputs'!$B$6-2*'NG Inputs'!$B$7*SQRT(MIN(C16/$B$10,'NG Inputs'!$B$9)/'NG Inputs'!$B$8))+MAX(C16-MIN(C16/$B$10,'NG Inputs'!$B$9)*$B$10,0)*'NG Inputs'!$B$10/2)*(1-$B$8))-MIN((C16+(MIN(C16/$B$10,'NG Inputs'!$B$9)*($B$9-'NG Inputs'!$B$5-'NG Inputs'!$B$6-2*'NG Inputs'!$B$7*SQRT(MIN(C16/$B$10,'NG Inputs'!$B$9)/'NG Inputs'!$B$8))+MAX(C16-MIN(C16/$B$10,'NG Inputs'!$B$9)*$B$10,0)*'NG Inputs'!$B$10/2)*(1-$B$8))/$B$10,'NG Inputs'!$B$9)*$B$10,0)*'NG Inputs'!$B$10/2)*(1-$B$8)-INDEX('NG Scenarios'!$C$11:$C$25,A17)*(1-$B$8),C16+(($B$6*C16-$B$7)*(12/18))*(1-$B$8)) | D17: =MIN((D16+(MIN(D16/$B$10,'NG Inputs'!$B$9)*($B$9-'NG Inputs'!$B$5-'NG Inputs'!$B$6-2*'NG Inputs'!$B$7*SQRT(MIN(D16/$B$10,'NG Inputs'!$B$9)/'NG Inputs'!$B$8))+MAX(D16-MIN(D16/$B$10,'NG Inputs'!$B$9)*$B$10,0)*'NG Inputs'!$B$10/2)*(1-$B$8))+(MIN((D16+(MIN(D16/$B$10,'NG Inputs'!$B$9)*($B$9-'NG Inputs'!$B$5-'NG Inputs'!$B$6-2*'NG Inputs'!$B$7*SQRT(MIN(D16/$B$10,'NG Inputs'!$B$9)/'NG Inputs'!$B$8))+MAX(D16-MIN(D16/$B$10,'NG Inputs'!$B$9)*$B$10,0)*'NG Inputs'!$B$10/2)*(1-$B$8))/$B$10,'NG Inputs'!$B$9)*($B$9-'NG Inputs'!$B$5-'NG Inputs'!$B$6-2*'NG Inputs'!$B$7*SQRT(MIN((D16+(MIN(D16/$B$10,'NG Inputs'!$B$9)*($B$9-'NG Inputs'!$B$5-'NG Inputs'!$B$6-2*'NG Inputs'!$B$7*SQRT(MIN(D16/$B$10,'NG Inputs'!$B$9)/'NG Inputs'!$B$8))+MAX(D16-MIN(D16/$B$10,'NG Inputs'!$B$9)*$B$10,0)*'NG Inputs'!$B$10/2)*(1-$B$8))/$B$10,'NG Inputs'!$B$9)/'NG Inputs'!$B$8))+MAX((D16+(MIN(D16/$B$10,'NG Inputs'!$B$9)*($B$9-'NG Inputs'!$B$5-'NG Inputs'!$B$6-2*'NG Inputs'!$B$7*SQRT(MIN(D16/$B$10,'NG Inputs'!$B$9)/'NG Inputs'!$B$8))+MAX(D16-MIN(D16/$B$10,'NG Inputs'!$B$9)*$B$10,0)*'NG Inputs'!$B$10/2)*(1-$B$8))-MIN((D16+(MIN(D16/$B$10,'NG Inputs'!$B$9)*($B$9-'NG Inputs'!$B$5-'NG Inputs'!$B$6-2*'NG Inputs'!$B$7*SQRT(MIN(D16/$B$10,'NG Inputs'!$B$9)/'NG Inputs'!$B$8))+MAX(D16-MIN(D16/$B$10,'NG Inputs'!$B$9)*$B$10,0)*'NG Inputs'!$B$10/2)*(1-$B$8))/$B$10,'NG Inputs'!$B$9)*$B$10,0)*'NG Inputs'!$B$10/2)*(1-$B$8)-INDEX('NG Scenarios'!$C$11:$C$25,A17)*(1-$B$8),$B$5) | E17: =IF(E16>0,E16+(($B$6*E16-$B$7)*(12/18))*(1-$B$8),0)+MAX((D16+(MIN(D16/$B$10,'NG Inputs'!$B$9)*($B$9-'NG Inputs'!$B$5-'NG Inputs'!$B$6-2*'NG Inputs'!$B$7*SQRT(MIN(D16/$B$10,'NG Inputs'!$B$9)/'NG Inputs'!$B$8))+MAX(D16-MIN(D16/$B$10,'NG Inputs'!$B$9)*$B$10,0)*'NG Inputs'!$B$10/2)*(1-$B$8))+(MIN((D16+(MIN(D16/$B$10,'NG Inputs'!$B$9)*($B$9-'NG Inputs'!$B$5-'NG Inputs'!$B$6-2*'NG Inputs'!$B$7*SQRT(MIN(D16/$B$10,'NG Inputs'!$B$9)/'NG Inputs'!$B$8))+MAX(D16-MIN(D16/$B$10,'NG Inputs'!$B$9)*$B$10,0)*'NG Inputs'!$B$10/2)*(1-$B$8))/$B$10,'NG Inputs'!$B$9)*($B$9-'NG Inputs'!$B$5-'NG Inputs'!$B$6-2*'NG Inputs'!$B$7*SQRT(MIN((D16+(MIN(D16/$B$10,'NG Inputs'!$B$9)*($B$9-'NG Inputs'!$B$5-'NG Inputs'!$B$6-2*'NG Inputs'!$B$7*SQRT(MIN(D16/$B$10,'NG Inputs'!$B$9)/'NG Inputs'!$B$8))+MAX(D16-MIN(D16/$B$10,'NG Inputs'!$B$9)*$B$10,0)*'NG Inputs'!$B$10/2)*(1-$B$8))/$B$10,'NG Inputs'!$B$9)/'NG Inputs'!$B$8))+MAX((D16+(MIN(D16/$B$10,'NG Inputs'!$B$9)*($B$9-'NG Inputs'!$B$5-'NG Inputs'!$B$6-2*'NG Inputs'!$B$7*SQRT(MIN(D16/$B$10,'NG Inputs'!$B$9)/'NG Inputs'!$B$8))+MAX(D16-MIN(D16/$B$10,'NG Inputs'!$B$9)*$B$10,0)*'NG Inputs'!$B$10/2)*(1-$B$8))-MIN((D16+(MIN(D16/$B$10,'NG Inputs'!$B$9)*($B$9-'NG Inputs'!$B$5-'NG Inputs'!$B$6-2*'NG Inputs'!$B$7*SQRT(MIN(D16/$B$10,'NG Inputs'!$B$9)/'NG Inputs'!$B$8))+MAX(D16-MIN(D16/$B$10,'NG Inputs'!$B$9)*$B$10,0)*'NG Inputs'!$B$10/2)*(1-$B$8))/$B$10,'NG Inputs'!$B$9)*$B$10,0)*'NG Inputs'!$B$10/2)*(1-$B$8)-INDEX('NG Scenarios'!$C$11:$C$25,A17)*(1-$B$8)-$B$5,0) | F17: =D17+E17
A18: 4 | B18: =(B17+(MIN(B17/$B$10,'NG Inputs'!$B$9)*($B$9-'NG Inputs'!$B$5-'NG Inputs'!$B$6-2*'NG Inputs'!$B$7*SQRT(MIN(B17/$B$10,'NG Inputs'!$B$9)/'NG Inputs'!$B$8))+MAX(B17-MIN(B17/$B$10,'NG Inputs'!$B$9)*$B$10,0)*'NG Inputs'!$B$10/2)*(1-$B$8))+(MIN((B17+(MIN(B17/$B$10,'NG Inputs'!$B$9)*($B$9-'NG Inputs'!$B$5-'NG Inputs'!$B$6-2*'NG Inputs'!$B$7*SQRT(MIN(B17/$B$10,'NG Inputs'!$B$9)/'NG Inputs'!$B$8))+MAX(B17-MIN(B17/$B$10,'NG Inputs'!$B$9)*$B$10,0)*'NG Inputs'!$B$10/2)*(1-$B$8))/$B$10,'NG Inputs'!$B$9)*($B$9-'NG Inputs'!$B$5-'NG Inputs'!$B$6-2*'NG Inputs'!$B$7*SQRT(MIN((B17+(MIN(B17/$B$10,'NG Inputs'!$B$9)*($B$9-'NG Inputs'!$B$5-'NG Inputs'!$B$6-2*'NG Inputs'!$B$7*SQRT(MIN(B17/$B$10,'NG Inputs'!$B$9)/'NG Inputs'!$B$8))+MAX(B17-MIN(B17/$B$10,'NG Inputs'!$B$9)*$B$10,0)*'NG Inputs'!$B$10/2)*(1-$B$8))/$B$10,'NG Inputs'!$B$9)/'NG Inputs'!$B$8))+MAX((B17+(MIN(B17/$B$10,'NG Inputs'!$B$9)*($B$9-'NG Inputs'!$B$5-'NG Inputs'!$B$6-2*'NG Inputs'!$B$7*SQRT(MIN(B17/$B$10,'NG Inputs'!$B$9)/'NG Inputs'!$B$8))+MAX(B17-MIN(B17/$B$10,'NG Inputs'!$B$9)*$B$10,0)*'NG Inputs'!$B$10/2)*(1-$B$8))-MIN((B17+(MIN(B17/$B$10,'NG Inputs'!$B$9)*($B$9-'NG Inputs'!$B$5-'NG Inputs'!$B$6-2*'NG Inputs'!$B$7*SQRT(MIN(B17/$B$10,'NG Inputs'!$B$9)/'NG Inputs'!$B$8))+MAX(B17-MIN(B17/$B$10,'NG Inputs'!$B$9)*$B$10,0)*'NG Inputs'!$B$10/2)*(1-$B$8))/$B$10,'NG Inputs'!$B$9)*$B$10,0)*'NG Inputs'!$B$10/2)*(1-$B$8)-INDEX('NG Scenarios'!$C$11:$C$25,A18)*(1-$B$8) | C18: =IF(C17<'NG Inputs'!$B$11,(C17+(MIN(C17/$B$10,'NG Inputs'!$B$9)*($B$9-'NG Inputs'!$B$5-'NG Inputs'!$B$6-2*'NG Inputs'!$B$7*SQRT(MIN(C17/$B$10,'NG Inputs'!$B$9)/'NG Inputs'!$B$8))+MAX(C17-MIN(C17/$B$10,'NG Inputs'!$B$9)*$B$10,0)*'NG Inputs'!$B$10/2)*(1-$B$8))+(MIN((C17+(MIN(C17/$B$10,'NG Inputs'!$B$9)*($B$9-'NG Inputs'!$B$5-'NG Inputs'!$B$6-2*'NG Inputs'!$B$7*SQRT(MIN(C17/$B$10,'NG Inputs'!$B$9)/'NG Inputs'!$B$8))+MAX(C17-MIN(C17/$B$10,'NG Inputs'!$B$9)*$B$10,0)*'NG Inputs'!$B$10/2)*(1-$B$8))/$B$10,'NG Inputs'!$B$9)*($B$9-'NG Inputs'!$B$5-'NG Inputs'!$B$6-2*'NG Inputs'!$B$7*SQRT(MIN((C17+(MIN(C17/$B$10,'NG Inputs'!$B$9)*($B$9-'NG Inputs'!$B$5-'NG Inputs'!$B$6-2*'NG Inputs'!$B$7*SQRT(MIN(C17/$B$10,'NG Inputs'!$B$9)/'NG Inputs'!$B$8))+MAX(C17-MIN(C17/$B$10,'NG Inputs'!$B$9)*$B$10,0)*'NG Inputs'!$B$10/2)*(1-$B$8))/$B$10,'NG Inputs'!$B$9)/'NG Inputs'!$B$8))+MAX((C17+(MIN(C17/$B$10,'NG Inputs'!$B$9)*($B$9-'NG Inputs'!$B$5-'NG Inputs'!$B$6-2*'NG Inputs'!$B$7*SQRT(MIN(C17/$B$10,'NG Inputs'!$B$9)/'NG Inputs'!$B$8))+MAX(C17-MIN(C17/$B$10,'NG Inputs'!$B$9)*$B$10,0)*'NG Inputs'!$B$10/2)*(1-$B$8))-MIN((C17+(MIN(C17/$B$10,'NG Inputs'!$B$9)*($B$9-'NG Inputs'!$B$5-'NG Inputs'!$B$6-2*'NG Inputs'!$B$7*SQRT(MIN(C17/$B$10,'NG Inputs'!$B$9)/'NG Inputs'!$B$8))+MAX(C17-MIN(C17/$B$10,'NG Inputs'!$B$9)*$B$10,0)*'NG Inputs'!$B$10/2)*(1-$B$8))/$B$10,'NG Inputs'!$B$9)*$B$10,0)*'NG Inputs'!$B$10/2)*(1-$B$8)-INDEX('NG Scenarios'!$C$11:$C$25,A18)*(1-$B$8),C17+(($B$6*C17-$B$7)*(12/18))*(1-$B$8)) | D18: =MIN((D17+(MIN(D17/$B$10,'NG Inputs'!$B$9)*($B$9-'NG Inputs'!$B$5-'NG Inputs'!$B$6-2*'NG Inputs'!$B$7*SQRT(MIN(D17/$B$10,'NG Inputs'!$B$9)/'NG Inputs'!$B$8))+MAX(D17-MIN(D17/$B$10,'NG Inputs'!$B$9)*$B$10,0)*'NG Inputs'!$B$10/2)*(1-$B$8))+(MIN((D17+(MIN(D17/$B$10,'NG Inputs'!$B$9)*($B$9-'NG Inputs'!$B$5-'NG Inputs'!$B$6-2*'NG Inputs'!$B$7*SQRT(MIN(D17/$B$10,'NG Inputs'!$B$9)/'NG Inputs'!$B$8))+MAX(D17-MIN(D17/$B$10,'NG Inputs'!$B$9)*$B$10,0)*'NG Inputs'!$B$10/2)*(1-$B$8))/$B$10,'NG Inputs'!$B$9)*($B$9-'NG Inputs'!$B$5-'NG Inputs'!$B$6-2*'NG Inputs'!$B$7*SQRT(MIN((D17+(MIN(D17/$B$10,'NG Inputs'!$B$9)*($B$9-'NG Inputs'!$B$5-'NG Inputs'!$B$6-2*'NG Inputs'!$B$7*SQRT(MIN(D17/$B$10,'NG Inputs'!$B$9)/'NG Inputs'!$B$8))+MAX(D17-MIN(D17/$B$10,'NG Inputs'!$B$9)*$B$10,0)*'NG Inputs'!$B$10/2)*(1-$B$8))/$B$10,'NG Inputs'!$B$9)/'NG Inputs'!$B$8))+MAX((D17+(MIN(D17/$B$10,'NG Inputs'!$B$9)*($B$9-'NG Inputs'!$B$5-'NG Inputs'!$B$6-2*'NG Inputs'!$B$7*SQRT(MIN(D17/$B$10,'NG Inputs'!$B$9)/'NG Inputs'!$B$8))+MAX(D17-MIN(D17/$B$10,'NG Inputs'!$B$9)*$B$10,0)*'NG Inputs'!$B$10/2)*(1-$B$8))-MIN((D17+(MIN(D17/$B$10,'NG Inputs'!$B$9)*($B$9-'NG Inputs'!$B$5-'NG Inputs'!$B$6-2*'NG Inputs'!$B$7*SQRT(MIN(D17/$B$10,'NG Inputs'!$B$9)/'NG Inputs'!$B$8))+MAX(D17-MIN(D17/$B$10,'NG Inputs'!$B$9)*$B$10,0)*'NG Inputs'!$B$10/2)*(1-$B$8))/$B$10,'NG Inputs'!$B$9)*$B$10,0)*'NG Inputs'!$B$10/2)*(1-$B$8)-INDEX('NG Scenarios'!$C$11:$C$25,A18)*(1-$B$8),$B$5) | E18: =IF(E17>0,E17+(($B$6*E17-$B$7)*(12/18))*(1-$B$8),0)+MAX((D17+(MIN(D17/$B$10,'NG Inputs'!$B$9)*($B$9-'NG Inputs'!$B$5-'NG Inputs'!$B$6-2*'NG Inputs'!$B$7*SQRT(MIN(D17/$B$10,'NG Inputs'!$B$9)/'NG Inputs'!$B$8))+MAX(D17-MIN(D17/$B$10,'NG Inputs'!$B$9)*$B$10,0)*'NG Inputs'!$B$10/2)*(1-$B$8))+(MIN((D17+(MIN(D17/$B$10,'NG Inputs'!$B$9)*($B$9-'NG Inputs'!$B$5-'NG Inputs'!$B$6-2*'NG Inputs'!$B$7*SQRT(MIN(D17/$B$10,'NG Inputs'!$B$9)/'NG Inputs'!$B$8))+MAX(D17-MIN(D17/$B$10,'NG Inputs'!$B$9)*$B$10,0)*'NG Inputs'!$B$10/2)*(1-$B$8))/$B$10,'NG Inputs'!$B$9)*($B$9-'NG Inputs'!$B$5-'NG Inputs'!$B$6-2*'NG Inputs'!$B$7*SQRT(MIN((D17+(MIN(D17/$B$10,'NG Inputs'!$B$9)*($B$9-'NG Inputs'!$B$5-'NG Inputs'!$B$6-2*'NG Inputs'!$B$7*SQRT(MIN(D17/$B$10,'NG Inputs'!$B$9)/'NG Inputs'!$B$8))+MAX(D17-MIN(D17/$B$10,'NG Inputs'!$B$9)*$B$10,0)*'NG Inputs'!$B$10/2)*(1-$B$8))/$B$10,'NG Inputs'!$B$9)/'NG Inputs'!$B$8))+MAX((D17+(MIN(D17/$B$10,'NG Inputs'!$B$9)*($B$9-'NG Inputs'!$B$5-'NG Inputs'!$B$6-2*'NG Inputs'!$B$7*SQRT(MIN(D17/$B$10,'NG Inputs'!$B$9)/'NG Inputs'!$B$8))+MAX(D17-MIN(D17/$B$10,'NG Inputs'!$B$9)*$B$10,0)*'NG Inputs'!$B$10/2)*(1-$B$8))-MIN((D17+(MIN(D17/$B$10,'NG Inputs'!$B$9)*($B$9-'NG Inputs'!$B$5-'NG Inputs'!$B$6-2*'NG Inputs'!$B$7*SQRT(MIN(D17/$B$10,'NG Inputs'!$B$9)/'NG Inputs'!$B$8))+MAX(D17-MIN(D17/$B$10,'NG Inputs'!$B$9)*$B$10,0)*'NG Inputs'!$B$10/2)*(1-$B$8))/$B$10,'NG Inputs'!$B$9)*$B$10,0)*'NG Inputs'!$B$10/2)*(1-$B$8)-INDEX('NG Scenarios'!$C$11:$C$25,A18)*(1-$B$8)-$B$5,0) | F18: =D18+E18
A19: 5 | B19: =(B18+(MIN(B18/$B$10,'NG Inputs'!$B$9)*($B$9-'NG Inputs'!$B$5-'NG Inputs'!$B$6-2*'NG Inputs'!$B$7*SQRT(MIN(B18/$B$10,'NG Inputs'!$B$9)/'NG Inputs'!$B$8))+MAX(B18-MIN(B18/$B$10,'NG Inputs'!$B$9)*$B$10,0)*'NG Inputs'!$B$10/2)*(1-$B$8))+(MIN((B18+(MIN(B18/$B$10,'NG Inputs'!$B$9)*($B$9-'NG Inputs'!$B$5-'NG Inputs'!$B$6-2*'NG Inputs'!$B$7*SQRT(MIN(B18/$B$10,'NG Inputs'!$B$9)/'NG Inputs'!$B$8))+MAX(B18-MIN(B18/$B$10,'NG Inputs'!$B$9)*$B$10,0)*'NG Inputs'!$B$10/2)*(1-$B$8))/$B$10,'NG Inputs'!$B$9)*($B$9-'NG Inputs'!$B$5-'NG Inputs'!$B$6-2*'NG Inputs'!$B$7*SQRT(MIN((B18+(MIN(B18/$B$10,'NG Inputs'!$B$9)*($B$9-'NG Inputs'!$B$5-'NG Inputs'!$B$6-2*'NG Inputs'!$B$7*SQRT(MIN(B18/$B$10,'NG Inputs'!$B$9)/'NG Inputs'!$B$8))+MAX(B18-MIN(B18/$B$10,'NG Inputs'!$B$9)*$B$10,0)*'NG Inputs'!$B$10/2)*(1-$B$8))/$B$10,'NG Inputs'!$B$9)/'NG Inputs'!$B$8))+MAX((B18+(MIN(B18/$B$10,'NG Inputs'!$B$9)*($B$9-'NG Inputs'!$B$5-'NG Inputs'!$B$6-2*'NG Inputs'!$B$7*SQRT(MIN(B18/$B$10,'NG Inputs'!$B$9)/'NG Inputs'!$B$8))+MAX(B18-MIN(B18/$B$10,'NG Inputs'!$B$9)*$B$10,0)*'NG Inputs'!$B$10/2)*(1-$B$8))-MIN((B18+(MIN(B18/$B$10,'NG Inputs'!$B$9)*($B$9-'NG Inputs'!$B$5-'NG Inputs'!$B$6-2*'NG Inputs'!$B$7*SQRT(MIN(B18/$B$10,'NG Inputs'!$B$9)/'NG Inputs'!$B$8))+MAX(B18-MIN(B18/$B$10,'NG Inputs'!$B$9)*$B$10,0)*'NG Inputs'!$B$10/2)*(1-$B$8))/$B$10,'NG Inputs'!$B$9)*$B$10,0)*'NG Inputs'!$B$10/2)*(1-$B$8)-INDEX('NG Scenarios'!$C$11:$C$25,A19)*(1-$B$8) | C19: =IF(C18<'NG Inputs'!$B$11,(C18+(MIN(C18/$B$10,'NG Inputs'!$B$9)*($B$9-'NG Inputs'!$B$5-'NG Inputs'!$B$6-2*'NG Inputs'!$B$7*SQRT(MIN(C18/$B$10,'NG Inputs'!$B$9)/'NG Inputs'!$B$8))+MAX(C18-MIN(C18/$B$10,'NG Inputs'!$B$9)*$B$10,0)*'NG Inputs'!$B$10/2)*(1-$B$8))+(MIN((C18+(MIN(C18/$B$10,'NG Inputs'!$B$9)*($B$9-'NG Inputs'!$B$5-'NG Inputs'!$B$6-2*'NG Inputs'!$B$7*SQRT(MIN(C18/$B$10,'NG Inputs'!$B$9)/'NG Inputs'!$B$8))+MAX(C18-MIN(C18/$B$10,'NG Inputs'!$B$9)*$B$10,0)*'NG Inputs'!$B$10/2)*(1-$B$8))/$B$10,'NG Inputs'!$B$9)*($B$9-'NG Inputs'!$B$5-'NG Inputs'!$B$6-2*'NG Inputs'!$B$7*SQRT(MIN((C18+(MIN(C18/$B$10,'NG Inputs'!$B$9)*($B$9-'NG Inputs'!$B$5-'NG Inputs'!$B$6-2*'NG Inputs'!$B$7*SQRT(MIN(C18/$B$10,'NG Inputs'!$B$9)/'NG Inputs'!$B$8))+MAX(C18-MIN(C18/$B$10,'NG Inputs'!$B$9)*$B$10,0)*'NG Inputs'!$B$10/2)*(1-$B$8))/$B$10,'NG Inputs'!$B$9)/'NG Inputs'!$B$8))+MAX((C18+(MIN(C18/$B$10,'NG Inputs'!$B$9)*($B$9-'NG Inputs'!$B$5-'NG Inputs'!$B$6-2*'NG Inputs'!$B$7*SQRT(MIN(C18/$B$10,'NG Inputs'!$B$9)/'NG Inputs'!$B$8))+MAX(C18-MIN(C18/$B$10,'NG Inputs'!$B$9)*$B$10,0)*'NG Inputs'!$B$10/2)*(1-$B$8))-MIN((C18+(MIN(C18/$B$10,'NG Inputs'!$B$9)*($B$9-'NG Inputs'!$B$5-'NG Inputs'!$B$6-2*'NG Inputs'!$B$7*SQRT(MIN(C18/$B$10,'NG Inputs'!$B$9)/'NG Inputs'!$B$8))+MAX(C18-MIN(C18/$B$10,'NG Inputs'!$B$9)*$B$10,0)*'NG Inputs'!$B$10/2)*(1-$B$8))/$B$10,'NG Inputs'!$B$9)*$B$10,0)*'NG Inputs'!$B$10/2)*(1-$B$8)-INDEX('NG Scenarios'!$C$11:$C$25,A19)*(1-$B$8),C18+(($B$6*C18-$B$7)*(12/18))*(1-$B$8)) | D19: =MIN((D18+(MIN(D18/$B$10,'NG Inputs'!$B$9)*($B$9-'NG Inputs'!$B$5-'NG Inputs'!$B$6-2*'NG Inputs'!$B$7*SQRT(MIN(D18/$B$10,'NG Inputs'!$B$9)/'NG Inputs'!$B$8))+MAX(D18-MIN(D18/$B$10,'NG Inputs'!$B$9)*$B$10,0)*'NG Inputs'!$B$10/2)*(1-$B$8))+(MIN((D18+(MIN(D18/$B$10,'NG Inputs'!$B$9)*($B$9-'NG Inputs'!$B$5-'NG Inputs'!$B$6-2*'NG Inputs'!$B$7*SQRT(MIN(D18/$B$10,'NG Inputs'!$B$9)/'NG Inputs'!$B$8))+MAX(D18-MIN(D18/$B$10,'NG Inputs'!$B$9)*$B$10,0)*'NG Inputs'!$B$10/2)*(1-$B$8))/$B$10,'NG Inputs'!$B$9)*($B$9-'NG Inputs'!$B$5-'NG Inputs'!$B$6-2*'NG Inputs'!$B$7*SQRT(MIN((D18+(MIN(D18/$B$10,'NG Inputs'!$B$9)*($B$9-'NG Inputs'!$B$5-'NG Inputs'!$B$6-2*'NG Inputs'!$B$7*SQRT(MIN(D18/$B$10,'NG Inputs'!$B$9)/'NG Inputs'!$B$8))+MAX(D18-MIN(D18/$B$10,'NG Inputs'!$B$9)*$B$10,0)*'NG Inputs'!$B$10/2)*(1-$B$8))/$B$10,'NG Inputs'!$B$9)/'NG Inputs'!$B$8))+MAX((D18+(MIN(D18/$B$10,'NG Inputs'!$B$9)*($B$9-'NG Inputs'!$B$5-'NG Inputs'!$B$6-2*'NG Inputs'!$B$7*SQRT(MIN(D18/$B$10,'NG Inputs'!$B$9)/'NG Inputs'!$B$8))+MAX(D18-MIN(D18/$B$10,'NG Inputs'!$B$9)*$B$10,0)*'NG Inputs'!$B$10/2)*(1-$B$8))-MIN((D18+(MIN(D18/$B$10,'NG Inputs'!$B$9)*($B$9-'NG Inputs'!$B$5-'NG Inputs'!$B$6-2*'NG Inputs'!$B$7*SQRT(MIN(D18/$B$10,'NG Inputs'!$B$9)/'NG Inputs'!$B$8))+MAX(D18-MIN(D18/$B$10,'NG Inputs'!$B$9)*$B$10,0)*'NG Inputs'!$B$10/2)*(1-$B$8))/$B$10,'NG Inputs'!$B$9)*$B$10,0)*'NG Inputs'!$B$10/2)*(1-$B$8)-INDEX('NG Scenarios'!$C$11:$C$25,A19)*(1-$B$8),$B$5) | E19: =IF(E18>0,E18+(($B$6*E18-$B$7)*(12/18))*(1-$B$8),0)+MAX((D18+(MIN(D18/$B$10,'NG Inputs'!$B$9)*($B$9-'NG Inputs'!$B$5-'NG Inputs'!$B$6-2*'NG Inputs'!$B$7*SQRT(MIN(D18/$B$10,'NG Inputs'!$B$9)/'NG Inputs'!$B$8))+MAX(D18-MIN(D18/$B$10,'NG Inputs'!$B$9)*$B$10,0)*'NG Inputs'!$B$10/2)*(1-$B$8))+(MIN((D18+(MIN(D18/$B$10,'NG Inputs'!$B$9)*($B$9-'NG Inputs'!$B$5-'NG Inputs'!$B$6-2*'NG Inputs'!$B$7*SQRT(MIN(D18/$B$10,'NG Inputs'!$B$9)/'NG Inputs'!$B$8))+MAX(D18-MIN(D18/$B$10,'NG Inputs'!$B$9)*$B$10,0)*'NG Inputs'!$B$10/2)*(1-$B$8))/$B$10,'NG Inputs'!$B$9)*($B$9-'NG Inputs'!$B$5-'NG Inputs'!$B$6-2*'NG Inputs'!$B$7*SQRT(MIN((D18+(MIN(D18/$B$10,'NG Inputs'!$B$9)*($B$9-'NG Inputs'!$B$5-'NG Inputs'!$B$6-2*'NG Inputs'!$B$7*SQRT(MIN(D18/$B$10,'NG Inputs'!$B$9)/'NG Inputs'!$B$8))+MAX(D18-MIN(D18/$B$10,'NG Inputs'!$B$9)*$B$10,0)*'NG Inputs'!$B$10/2)*(1-$B$8))/$B$10,'NG Inputs'!$B$9)/'NG Inputs'!$B$8))+MAX((D18+(MIN(D18/$B$10,'NG Inputs'!$B$9)*($B$9-'NG Inputs'!$B$5-'NG Inputs'!$B$6-2*'NG Inputs'!$B$7*SQRT(MIN(D18/$B$10,'NG Inputs'!$B$9)/'NG Inputs'!$B$8))+MAX(D18-MIN(D18/$B$10,'NG Inputs'!$B$9)*$B$10,0)*'NG Inputs'!$B$10/2)*(1-$B$8))-MIN((D18+(MIN(D18/$B$10,'NG Inputs'!$B$9)*($B$9-'NG Inputs'!$B$5-'NG Inputs'!$B$6-2*'NG Inputs'!$B$7*SQRT(MIN(D18/$B$10,'NG Inputs'!$B$9)/'NG Inputs'!$B$8))+MAX(D18-MIN(D18/$B$10,'NG Inputs'!$B$9)*$B$10,0)*'NG Inputs'!$B$10/2)*(1-$B$8))/$B$10,'NG Inputs'!$B$9)*$B$10,0)*'NG Inputs'!$B$10/2)*(1-$B$8)-INDEX('NG Scenarios'!$C$11:$C$25,A19)*(1-$B$8)-$B$5,0) | F19: =D19+E19
A20: 6 | B20: =(B19+(MIN(B19/$B$10,'NG Inputs'!$B$9)*($B$9-'NG Inputs'!$B$5-'NG Inputs'!$B$6-2*'NG Inputs'!$B$7*SQRT(MIN(B19/$B$10,'NG Inputs'!$B$9)/'NG Inputs'!$B$8))+MAX(B19-MIN(B19/$B$10,'NG Inputs'!$B$9)*$B$10,0)*'NG Inputs'!$B$10/2)*(1-$B$8))+(MIN((B19+(MIN(B19/$B$10,'NG Inputs'!$B$9)*($B$9-'NG Inputs'!$B$5-'NG Inputs'!$B$6-2*'NG Inputs'!$B$7*SQRT(MIN(B19/$B$10,'NG Inputs'!$B$9)/'NG Inputs'!$B$8))+MAX(B19-MIN(B19/$B$10,'NG Inputs'!$B$9)*$B$10,0)*'NG Inputs'!$B$10/2)*(1-$B$8))/$B$10,'NG Inputs'!$B$9)*($B$9-'NG Inputs'!$B$5-'NG Inputs'!$B$6-2*'NG Inputs'!$B$7*SQRT(MIN((B19+(MIN(B19/$B$10,'NG Inputs'!$B$9)*($B$9-'NG Inputs'!$B$5-'NG Inputs'!$B$6-2*'NG Inputs'!$B$7*SQRT(MIN(B19/$B$10,'NG Inputs'!$B$9)/'NG Inputs'!$B$8))+MAX(B19-MIN(B19/$B$10,'NG Inputs'!$B$9)*$B$10,0)*'NG Inputs'!$B$10/2)*(1-$B$8))/$B$10,'NG Inputs'!$B$9)/'NG Inputs'!$B$8))+MAX((B19+(MIN(B19/$B$10,'NG Inputs'!$B$9)*($B$9-'NG Inputs'!$B$5-'NG Inputs'!$B$6-2*'NG Inputs'!$B$7*SQRT(MIN(B19/$B$10,'NG Inputs'!$B$9)/'NG Inputs'!$B$8))+MAX(B19-MIN(B19/$B$10,'NG Inputs'!$B$9)*$B$10,0)*'NG Inputs'!$B$10/2)*(1-$B$8))-MIN((B19+(MIN(B19/$B$10,'NG Inputs'!$B$9)*($B$9-'NG Inputs'!$B$5-'NG Inputs'!$B$6-2*'NG Inputs'!$B$7*SQRT(MIN(B19/$B$10,'NG Inputs'!$B$9)/'NG Inputs'!$B$8))+MAX(B19-MIN(B19/$B$10,'NG Inputs'!$B$9)*$B$10,0)*'NG Inputs'!$B$10/2)*(1-$B$8))/$B$10,'NG Inputs'!$B$9)*$B$10,0)*'NG Inputs'!$B$10/2)*(1-$B$8)-INDEX('NG Scenarios'!$C$11:$C$25,A20)*(1-$B$8) | C20: =IF(C19<'NG Inputs'!$B$11,(C19+(MIN(C19/$B$10,'NG Inputs'!$B$9)*($B$9-'NG Inputs'!$B$5-'NG Inputs'!$B$6-2*'NG Inputs'!$B$7*SQRT(MIN(C19/$B$10,'NG Inputs'!$B$9)/'NG Inputs'!$B$8))+MAX(C19-MIN(C19/$B$10,'NG Inputs'!$B$9)*$B$10,0)*'NG Inputs'!$B$10/2)*(1-$B$8))+(MIN((C19+(MIN(C19/$B$10,'NG Inputs'!$B$9)*($B$9-'NG Inputs'!$B$5-'NG Inputs'!$B$6-2*'NG Inputs'!$B$7*SQRT(MIN(C19/$B$10,'NG Inputs'!$B$9)/'NG Inputs'!$B$8))+MAX(C19-MIN(C19/$B$10,'NG Inputs'!$B$9)*$B$10,0)*'NG Inputs'!$B$10/2)*(1-$B$8))/$B$10,'NG Inputs'!$B$9)*($B$9-'NG Inputs'!$B$5-'NG Inputs'!$B$6-2*'NG Inputs'!$B$7*SQRT(MIN((C19+(MIN(C19/$B$10,'NG Inputs'!$B$9)*($B$9-'NG Inputs'!$B$5-'NG Inputs'!$B$6-2*'NG Inputs'!$B$7*SQRT(MIN(C19/$B$10,'NG Inputs'!$B$9)/'NG Inputs'!$B$8))+MAX(C19-MIN(C19/$B$10,'NG Inputs'!$B$9)*$B$10,0)*'NG Inputs'!$B$10/2)*(1-$B$8))/$B$10,'NG Inputs'!$B$9)/'NG Inputs'!$B$8))+MAX((C19+(MIN(C19/$B$10,'NG Inputs'!$B$9)*($B$9-'NG Inputs'!$B$5-'NG Inputs'!$B$6-2*'NG Inputs'!$B$7*SQRT(MIN(C19/$B$10,'NG Inputs'!$B$9)/'NG Inputs'!$B$8))+MAX(C19-MIN(C19/$B$10,'NG Inputs'!$B$9)*$B$10,0)*'NG Inputs'!$B$10/2)*(1-$B$8))-MIN((C19+(MIN(C19/$B$10,'NG Inputs'!$B$9)*($B$9-'NG Inputs'!$B$5-'NG Inputs'!$B$6-2*'NG Inputs'!$B$7*SQRT(MIN(C19/$B$10,'NG Inputs'!$B$9)/'NG Inputs'!$B$8))+MAX(C19-MIN(C19/$B$10,'NG Inputs'!$B$9)*$B$10,0)*'NG Inputs'!$B$10/2)*(1-$B$8))/$B$10,'NG Inputs'!$B$9)*$B$10,0)*'NG Inputs'!$B$10/2)*(1-$B$8)-INDEX('NG Scenarios'!$C$11:$C$25,A20)*(1-$B$8),C19+(($B$6*C19-$B$7)*(12/18))*(1-$B$8)) | D20: =MIN((D19+(MIN(D19/$B$10,'NG Inputs'!$B$9)*($B$9-'NG Inputs'!$B$5-'NG Inputs'!$B$6-2*'NG Inputs'!$B$7*SQRT(MIN(D19/$B$10,'NG Inputs'!$B$9)/'NG Inputs'!$B$8))+MAX(D19-MIN(D19/$B$10,'NG Inputs'!$B$9)*$B$10,0)*'NG Inputs'!$B$10/2)*(1-$B$8))+(MIN((D19+(MIN(D19/$B$10,'NG Inputs'!$B$9)*($B$9-'NG Inputs'!$B$5-'NG Inputs'!$B$6-2*'NG Inputs'!$B$7*SQRT(MIN(D19/$B$10,'NG Inputs'!$B$9)/'NG Inputs'!$B$8))+MAX(D19-MIN(D19/$B$10,'NG Inputs'!$B$9)*$B$10,0)*'NG Inputs'!$B$10/2)*(1-$B$8))/$B$10,'NG Inputs'!$B$9)*($B$9-'NG Inputs'!$B$5-'NG Inputs'!$B$6-2*'NG Inputs'!$B$7*SQRT(MIN((D19+(MIN(D19/$B$10,'NG Inputs'!$B$9)*($B$9-'NG Inputs'!$B$5-'NG Inputs'!$B$6-2*'NG Inputs'!$B$7*SQRT(MIN(D19/$B$10,'NG Inputs'!$B$9)/'NG Inputs'!$B$8))+MAX(D19-MIN(D19/$B$10,'NG Inputs'!$B$9)*$B$10,0)*'NG Inputs'!$B$10/2)*(1-$B$8))/$B$10,'NG Inputs'!$B$9)/'NG Inputs'!$B$8))+MAX((D19+(MIN(D19/$B$10,'NG Inputs'!$B$9)*($B$9-'NG Inputs'!$B$5-'NG Inputs'!$B$6-2*'NG Inputs'!$B$7*SQRT(MIN(D19/$B$10,'NG Inputs'!$B$9)/'NG Inputs'!$B$8))+MAX(D19-MIN(D19/$B$10,'NG Inputs'!$B$9)*$B$10,0)*'NG Inputs'!$B$10/2)*(1-$B$8))-MIN((D19+(MIN(D19/$B$10,'NG Inputs'!$B$9)*($B$9-'NG Inputs'!$B$5-'NG Inputs'!$B$6-2*'NG Inputs'!$B$7*SQRT(MIN(D19/$B$10,'NG Inputs'!$B$9)/'NG Inputs'!$B$8))+MAX(D19-MIN(D19/$B$10,'NG Inputs'!$B$9)*$B$10,0)*'NG Inputs'!$B$10/2)*(1-$B$8))/$B$10,'NG Inputs'!$B$9)*$B$10,0)*'NG Inputs'!$B$10/2)*(1-$B$8)-INDEX('NG Scenarios'!$C$11:$C$25,A20)*(1-$B$8),$B$5) | E20: =IF(E19>0,E19+(($B$6*E19-$B$7)*(12/18))*(1-$B$8),0)+MAX((D19+(MIN(D19/$B$10,'NG Inputs'!$B$9)*($B$9-'NG Inputs'!$B$5-'NG Inputs'!$B$6-2*'NG Inputs'!$B$7*SQRT(MIN(D19/$B$10,'NG Inputs'!$B$9)/'NG Inputs'!$B$8))+MAX(D19-MIN(D19/$B$10,'NG Inputs'!$B$9)*$B$10,0)*'NG Inputs'!$B$10/2)*(1-$B$8))+(MIN((D19+(MIN(D19/$B$10,'NG Inputs'!$B$9)*($B$9-'NG Inputs'!$B$5-'NG Inputs'!$B$6-2*'NG Inputs'!$B$7*SQRT(MIN(D19/$B$10,'NG Inputs'!$B$9)/'NG Inputs'!$B$8))+MAX(D19-MIN(D19/$B$10,'NG Inputs'!$B$9)*$B$10,0)*'NG Inputs'!$B$10/2)*(1-$B$8))/$B$10,'NG Inputs'!$B$9)*($B$9-'NG Inputs'!$B$5-'NG Inputs'!$B$6-2*'NG Inputs'!$B$7*SQRT(MIN((D19+(MIN(D19/$B$10,'NG Inputs'!$B$9)*($B$9-'NG Inputs'!$B$5-'NG Inputs'!$B$6-2*'NG Inputs'!$B$7*SQRT(MIN(D19/$B$10,'NG Inputs'!$B$9)/'NG Inputs'!$B$8))+MAX(D19-MIN(D19/$B$10,'NG Inputs'!$B$9)*$B$10,0)*'NG Inputs'!$B$10/2)*(1-$B$8))/$B$10,'NG Inputs'!$B$9)/'NG Inputs'!$B$8))+MAX((D19+(MIN(D19/$B$10,'NG Inputs'!$B$9)*($B$9-'NG Inputs'!$B$5-'NG Inputs'!$B$6-2*'NG Inputs'!$B$7*SQRT(MIN(D19/$B$10,'NG Inputs'!$B$9)/'NG Inputs'!$B$8))+MAX(D19-MIN(D19/$B$10,'NG Inputs'!$B$9)*$B$10,0)*'NG Inputs'!$B$10/2)*(1-$B$8))-MIN((D19+(MIN(D19/$B$10,'NG Inputs'!$B$9)*($B$9-'NG Inputs'!$B$5-'NG Inputs'!$B$6-2*'NG Inputs'!$B$7*SQRT(MIN(D19/$B$10,'NG Inputs'!$B$9)/'NG Inputs'!$B$8))+MAX(D19-MIN(D19/$B$10,'NG Inputs'!$B$9)*$B$10,0)*'NG Inputs'!$B$10/2)*(1-$B$8))/$B$10,'NG Inputs'!$B$9)*$B$10,0)*'NG Inputs'!$B$10/2)*(1-$B$8)-INDEX('NG Scenarios'!$C$11:$C$25,A20)*(1-$B$8)-$B$5,0) | F20: =D20+E20
A21: 7 | B21: =(B20+(MIN(B20/$B$10,'NG Inputs'!$B$9)*($B$9-'NG Inputs'!$B$5-'NG Inputs'!$B$6-2*'NG Inputs'!$B$7*SQRT(MIN(B20/$B$10,'NG Inputs'!$B$9)/'NG Inputs'!$B$8))+MAX(B20-MIN(B20/$B$10,'NG Inputs'!$B$9)*$B$10,0)*'NG Inputs'!$B$10/2)*(1-$B$8))+(MIN((B20+(MIN(B20/$B$10,'NG Inputs'!$B$9)*($B$9-'NG Inputs'!$B$5-'NG Inputs'!$B$6-2*'NG Inputs'!$B$7*SQRT(MIN(B20/$B$10,'NG Inputs'!$B$9)/'NG Inputs'!$B$8))+MAX(B20-MIN(B20/$B$10,'NG Inputs'!$B$9)*$B$10,0)*'NG Inputs'!$B$10/2)*(1-$B$8))/$B$10,'NG Inputs'!$B$9)*($B$9-'NG Inputs'!$B$5-'NG Inputs'!$B$6-2*'NG Inputs'!$B$7*SQRT(MIN((B20+(MIN(B20/$B$10,'NG Inputs'!$B$9)*($B$9-'NG Inputs'!$B$5-'NG Inputs'!$B$6-2*'NG Inputs'!$B$7*SQRT(MIN(B20/$B$10,'NG Inputs'!$B$9)/'NG Inputs'!$B$8))+MAX(B20-MIN(B20/$B$10,'NG Inputs'!$B$9)*$B$10,0)*'NG Inputs'!$B$10/2)*(1-$B$8))/$B$10,'NG Inputs'!$B$9)/'NG Inputs'!$B$8))+MAX((B20+(MIN(B20/$B$10,'NG Inputs'!$B$9)*($B$9-'NG Inputs'!$B$5-'NG Inputs'!$B$6-2*'NG Inputs'!$B$7*SQRT(MIN(B20/$B$10,'NG Inputs'!$B$9)/'NG Inputs'!$B$8))+MAX(B20-MIN(B20/$B$10,'NG Inputs'!$B$9)*$B$10,0)*'NG Inputs'!$B$10/2)*(1-$B$8))-MIN((B20+(MIN(B20/$B$10,'NG Inputs'!$B$9)*($B$9-'NG Inputs'!$B$5-'NG Inputs'!$B$6-2*'NG Inputs'!$B$7*SQRT(MIN(B20/$B$10,'NG Inputs'!$B$9)/'NG Inputs'!$B$8))+MAX(B20-MIN(B20/$B$10,'NG Inputs'!$B$9)*$B$10,0)*'NG Inputs'!$B$10/2)*(1-$B$8))/$B$10,'NG Inputs'!$B$9)*$B$10,0)*'NG Inputs'!$B$10/2)*(1-$B$8)-INDEX('NG Scenarios'!$C$11:$C$25,A21)*(1-$B$8) | C21: =IF(C20<'NG Inputs'!$B$11,(C20+(MIN(C20/$B$10,'NG Inputs'!$B$9)*($B$9-'NG Inputs'!$B$5-'NG Inputs'!$B$6-2*'NG Inputs'!$B$7*SQRT(MIN(C20/$B$10,'NG Inputs'!$B$9)/'NG Inputs'!$B$8))+MAX(C20-MIN(C20/$B$10,'NG Inputs'!$B$9)*$B$10,0)*'NG Inputs'!$B$10/2)*(1-$B$8))+(MIN((C20+(MIN(C20/$B$10,'NG Inputs'!$B$9)*($B$9-'NG Inputs'!$B$5-'NG Inputs'!$B$6-2*'NG Inputs'!$B$7*SQRT(MIN(C20/$B$10,'NG Inputs'!$B$9)/'NG Inputs'!$B$8))+MAX(C20-MIN(C20/$B$10,'NG Inputs'!$B$9)*$B$10,0)*'NG Inputs'!$B$10/2)*(1-$B$8))/$B$10,'NG Inputs'!$B$9)*($B$9-'NG Inputs'!$B$5-'NG Inputs'!$B$6-2*'NG Inputs'!$B$7*SQRT(MIN((C20+(MIN(C20/$B$10,'NG Inputs'!$B$9)*($B$9-'NG Inputs'!$B$5-'NG Inputs'!$B$6-2*'NG Inputs'!$B$7*SQRT(MIN(C20/$B$10,'NG Inputs'!$B$9)/'NG Inputs'!$B$8))+MAX(C20-MIN(C20/$B$10,'NG Inputs'!$B$9)*$B$10,0)*'NG Inputs'!$B$10/2)*(1-$B$8))/$B$10,'NG Inputs'!$B$9)/'NG Inputs'!$B$8))+MAX((C20+(MIN(C20/$B$10,'NG Inputs'!$B$9)*($B$9-'NG Inputs'!$B$5-'NG Inputs'!$B$6-2*'NG Inputs'!$B$7*SQRT(MIN(C20/$B$10,'NG Inputs'!$B$9)/'NG Inputs'!$B$8))+MAX(C20-MIN(C20/$B$10,'NG Inputs'!$B$9)*$B$10,0)*'NG Inputs'!$B$10/2)*(1-$B$8))-MIN((C20+(MIN(C20/$B$10,'NG Inputs'!$B$9)*($B$9-'NG Inputs'!$B$5-'NG Inputs'!$B$6-2*'NG Inputs'!$B$7*SQRT(MIN(C20/$B$10,'NG Inputs'!$B$9)/'NG Inputs'!$B$8))+MAX(C20-MIN(C20/$B$10,'NG Inputs'!$B$9)*$B$10,0)*'NG Inputs'!$B$10/2)*(1-$B$8))/$B$10,'NG Inputs'!$B$9)*$B$10,0)*'NG Inputs'!$B$10/2)*(1-$B$8)-INDEX('NG Scenarios'!$C$11:$C$25,A21)*(1-$B$8),C20+(($B$6*C20-$B$7)*(12/18))*(1-$B$8)) | D21: =MIN((D20+(MIN(D20/$B$10,'NG Inputs'!$B$9)*($B$9-'NG Inputs'!$B$5-'NG Inputs'!$B$6-2*'NG Inputs'!$B$7*SQRT(MIN(D20/$B$10,'NG Inputs'!$B$9)/'NG Inputs'!$B$8))+MAX(D20-MIN(D20/$B$10,'NG Inputs'!$B$9)*$B$10,0)*'NG Inputs'!$B$10/2)*(1-$B$8))+(MIN((D20+(MIN(D20/$B$10,'NG Inputs'!$B$9)*($B$9-'NG Inputs'!$B$5-'NG Inputs'!$B$6-2*'NG Inputs'!$B$7*SQRT(MIN(D20/$B$10,'NG Inputs'!$B$9)/'NG Inputs'!$B$8))+MAX(D20-MIN(D20/$B$10,'NG Inputs'!$B$9)*$B$10,0)*'NG Inputs'!$B$10/2)*(1-$B$8))/$B$10,'NG Inputs'!$B$9)*($B$9-'NG Inputs'!$B$5-'NG Inputs'!$B$6-2*'NG Inputs'!$B$7*SQRT(MIN((D20+(MIN(D20/$B$10,'NG Inputs'!$B$9)*($B$9-'NG Inputs'!$B$5-'NG Inputs'!$B$6-2*'NG Inputs'!$B$7*SQRT(MIN(D20/$B$10,'NG Inputs'!$B$9)/'NG Inputs'!$B$8))+MAX(D20-MIN(D20/$B$10,'NG Inputs'!$B$9)*$B$10,0)*'NG Inputs'!$B$10/2)*(1-$B$8))/$B$10,'NG Inputs'!$B$9)/'NG Inputs'!$B$8))+MAX((D20+(MIN(D20/$B$10,'NG Inputs'!$B$9)*($B$9-'NG Inputs'!$B$5-'NG Inputs'!$B$6-2*'NG Inputs'!$B$7*SQRT(MIN(D20/$B$10,'NG Inputs'!$B$9)/'NG Inputs'!$B$8))+MAX(D20-MIN(D20/$B$10,'NG Inputs'!$B$9)*$B$10,0)*'NG Inputs'!$B$10/2)*(1-$B$8))-MIN((D20+(MIN(D20/$B$10,'NG Inputs'!$B$9)*($B$9-'NG Inputs'!$B$5-'NG Inputs'!$B$6-2*'NG Inputs'!$B$7*SQRT(MIN(D20/$B$10,'NG Inputs'!$B$9)/'NG Inputs'!$B$8))+MAX(D20-MIN(D20/$B$10,'NG Inputs'!$B$9)*$B$10,0)*'NG Inputs'!$B$10/2)*(1-$B$8))/$B$10,'NG Inputs'!$B$9)*$B$10,0)*'NG Inputs'!$B$10/2)*(1-$B$8)-INDEX('NG Scenarios'!$C$11:$C$25,A21)*(1-$B$8),$B$5) | E21: =IF(E20>0,E20+(($B$6*E20-$B$7)*(12/18))*(1-$B$8),0)+MAX((D20+(MIN(D20/$B$10,'NG Inputs'!$B$9)*($B$9-'NG Inputs'!$B$5-'NG Inputs'!$B$6-2*'NG Inputs'!$B$7*SQRT(MIN(D20/$B$10,'NG Inputs'!$B$9)/'NG Inputs'!$B$8))+MAX(D20-MIN(D20/$B$10,'NG Inputs'!$B$9)*$B$10,0)*'NG Inputs'!$B$10/2)*(1-$B$8))+(MIN((D20+(MIN(D20/$B$10,'NG Inputs'!$B$9)*($B$9-'NG Inputs'!$B$5-'NG Inputs'!$B$6-2*'NG Inputs'!$B$7*SQRT(MIN(D20/$B$10,'NG Inputs'!$B$9)/'NG Inputs'!$B$8))+MAX(D20-MIN(D20/$B$10,'NG Inputs'!$B$9)*$B$10,0)*'NG Inputs'!$B$10/2)*(1-$B$8))/$B$10,'NG Inputs'!$B$9)*($B$9-'NG Inputs'!$B$5-'NG Inputs'!$B$6-2*'NG Inputs'!$B$7*SQRT(MIN((D20+(MIN(D20/$B$10,'NG Inputs'!$B$9)*($B$9-'NG Inputs'!$B$5-'NG Inputs'!$B$6-2*'NG Inputs'!$B$7*SQRT(MIN(D20/$B$10,'NG Inputs'!$B$9)/'NG Inputs'!$B$8))+MAX(D20-MIN(D20/$B$10,'NG Inputs'!$B$9)*$B$10,0)*'NG Inputs'!$B$10/2)*(1-$B$8))/$B$10,'NG Inputs'!$B$9)/'NG Inputs'!$B$8))+MAX((D20+(MIN(D20/$B$10,'NG Inputs'!$B$9)*($B$9-'NG Inputs'!$B$5-'NG Inputs'!$B$6-2*'NG Inputs'!$B$7*SQRT(MIN(D20/$B$10,'NG Inputs'!$B$9)/'NG Inputs'!$B$8))+MAX(D20-MIN(D20/$B$10,'NG Inputs'!$B$9)*$B$10,0)*'NG Inputs'!$B$10/2)*(1-$B$8))-MIN((D20+(MIN(D20/$B$10,'NG Inputs'!$B$9)*($B$9-'NG Inputs'!$B$5-'NG Inputs'!$B$6-2*'NG Inputs'!$B$7*SQRT(MIN(D20/$B$10,'NG Inputs'!$B$9)/'NG Inputs'!$B$8))+MAX(D20-MIN(D20/$B$10,'NG Inputs'!$B$9)*$B$10,0)*'NG Inputs'!$B$10/2)*(1-$B$8))/$B$10,'NG Inputs'!$B$9)*$B$10,0)*'NG Inputs'!$B$10/2)*(1-$B$8)-INDEX('NG Scenarios'!$C$11:$C$25,A21)*(1-$B$8)-$B$5,0) | F21: =D21+E21
A22: 8 | B22: =(B21+(MIN(B21/$B$10,'NG Inputs'!$B$9)*($B$9-'NG Inputs'!$B$5-'NG Inputs'!$B$6-2*'NG Inputs'!$B$7*SQRT(MIN(B21/$B$10,'NG Inputs'!$B$9)/'NG Inputs'!$B$8))+MAX(B21-MIN(B21/$B$10,'NG Inputs'!$B$9)*$B$10,0)*'NG Inputs'!$B$10/2)*(1-$B$8))+(MIN((B21+(MIN(B21/$B$10,'NG Inputs'!$B$9)*($B$9-'NG Inputs'!$B$5-'NG Inputs'!$B$6-2*'NG Inputs'!$B$7*SQRT(MIN(B21/$B$10,'NG Inputs'!$B$9)/'NG Inputs'!$B$8))+MAX(B21-MIN(B21/$B$10,'NG Inputs'!$B$9)*$B$10,0)*'NG Inputs'!$B$10/2)*(1-$B$8))/$B$10,'NG Inputs'!$B$9)*($B$9-'NG Inputs'!$B$5-'NG Inputs'!$B$6-2*'NG Inputs'!$B$7*SQRT(MIN((B21+(MIN(B21/$B$10,'NG Inputs'!$B$9)*($B$9-'NG Inputs'!$B$5-'NG Inputs'!$B$6-2*'NG Inputs'!$B$7*SQRT(MIN(B21/$B$10,'NG Inputs'!$B$9)/'NG Inputs'!$B$8))+MAX(B21-MIN(B21/$B$10,'NG Inputs'!$B$9)*$B$10,0)*'NG Inputs'!$B$10/2)*(1-$B$8))/$B$10,'NG Inputs'!$B$9)/'NG Inputs'!$B$8))+MAX((B21+(MIN(B21/$B$10,'NG Inputs'!$B$9)*($B$9-'NG Inputs'!$B$5-'NG Inputs'!$B$6-2*'NG Inputs'!$B$7*SQRT(MIN(B21/$B$10,'NG Inputs'!$B$9)/'NG Inputs'!$B$8))+MAX(B21-MIN(B21/$B$10,'NG Inputs'!$B$9)*$B$10,0)*'NG Inputs'!$B$10/2)*(1-$B$8))-MIN((B21+(MIN(B21/$B$10,'NG Inputs'!$B$9)*($B$9-'NG Inputs'!$B$5-'NG Inputs'!$B$6-2*'NG Inputs'!$B$7*SQRT(MIN(B21/$B$10,'NG Inputs'!$B$9)/'NG Inputs'!$B$8))+MAX(B21-MIN(B21/$B$10,'NG Inputs'!$B$9)*$B$10,0)*'NG Inputs'!$B$10/2)*(1-$B$8))/$B$10,'NG Inputs'!$B$9)*$B$10,0)*'NG Inputs'!$B$10/2)*(1-$B$8)-INDEX('NG Scenarios'!$C$11:$C$25,A22)*(1-$B$8) | C22: =IF(C21<'NG Inputs'!$B$11,(C21+(MIN(C21/$B$10,'NG Inputs'!$B$9)*($B$9-'NG Inputs'!$B$5-'NG Inputs'!$B$6-2*'NG Inputs'!$B$7*SQRT(MIN(C21/$B$10,'NG Inputs'!$B$9)/'NG Inputs'!$B$8))+MAX(C21-MIN(C21/$B$10,'NG Inputs'!$B$9)*$B$10,0)*'NG Inputs'!$B$10/2)*(1-$B$8))+(MIN((C21+(MIN(C21/$B$10,'NG Inputs'!$B$9)*($B$9-'NG Inputs'!$B$5-'NG Inputs'!$B$6-2*'NG Inputs'!$B$7*SQRT(MIN(C21/$B$10,'NG Inputs'!$B$9)/'NG Inputs'!$B$8))+MAX(C21-MIN(C21/$B$10,'NG Inputs'!$B$9)*$B$10,0)*'NG Inputs'!$B$10/2)*(1-$B$8))/$B$10,'NG Inputs'!$B$9)*($B$9-'NG Inputs'!$B$5-'NG Inputs'!$B$6-2*'NG Inputs'!$B$7*SQRT(MIN((C21+(MIN(C21/$B$10,'NG Inputs'!$B$9)*($B$9-'NG Inputs'!$B$5-'NG Inputs'!$B$6-2*'NG Inputs'!$B$7*SQRT(MIN(C21/$B$10,'NG Inputs'!$B$9)/'NG Inputs'!$B$8))+MAX(C21-MIN(C21/$B$10,'NG Inputs'!$B$9)*$B$10,0)*'NG Inputs'!$B$10/2)*(1-$B$8))/$B$10,'NG Inputs'!$B$9)/'NG Inputs'!$B$8))+MAX((C21+(MIN(C21/$B$10,'NG Inputs'!$B$9)*($B$9-'NG Inputs'!$B$5-'NG Inputs'!$B$6-2*'NG Inputs'!$B$7*SQRT(MIN(C21/$B$10,'NG Inputs'!$B$9)/'NG Inputs'!$B$8))+MAX(C21-MIN(C21/$B$10,'NG Inputs'!$B$9)*$B$10,0)*'NG Inputs'!$B$10/2)*(1-$B$8))-MIN((C21+(MIN(C21/$B$10,'NG Inputs'!$B$9)*($B$9-'NG Inputs'!$B$5-'NG Inputs'!$B$6-2*'NG Inputs'!$B$7*SQRT(MIN(C21/$B$10,'NG Inputs'!$B$9)/'NG Inputs'!$B$8))+MAX(C21-MIN(C21/$B$10,'NG Inputs'!$B$9)*$B$10,0)*'NG Inputs'!$B$10/2)*(1-$B$8))/$B$10,'NG Inputs'!$B$9)*$B$10,0)*'NG Inputs'!$B$10/2)*(1-$B$8)-INDEX('NG Scenarios'!$C$11:$C$25,A22)*(1-$B$8),C21+(($B$6*C21-$B$7)*(12/18))*(1-$B$8)) | D22: =MIN((D21+(MIN(D21/$B$10,'NG Inputs'!$B$9)*($B$9-'NG Inputs'!$B$5-'NG Inputs'!$B$6-2*'NG Inputs'!$B$7*SQRT(MIN(D21/$B$10,'NG Inputs'!$B$9)/'NG Inputs'!$B$8))+MAX(D21-MIN(D21/$B$10,'NG Inputs'!$B$9)*$B$10,0)*'NG Inputs'!$B$10/2)*(1-$B$8))+(MIN((D21+(MIN(D21/$B$10,'NG Inputs'!$B$9)*($B$9-'NG Inputs'!$B$5-'NG Inputs'!$B$6-2*'NG Inputs'!$B$7*SQRT(MIN(D21/$B$10,'NG Inputs'!$B$9)/'NG Inputs'!$B$8))+MAX(D21-MIN(D21/$B$10,'NG Inputs'!$B$9)*$B$10,0)*'NG Inputs'!$B$10/2)*(1-$B$8))/$B$10,'NG Inputs'!$B$9)*($B$9-'NG Inputs'!$B$5-'NG Inputs'!$B$6-2*'NG Inputs'!$B$7*SQRT(MIN((D21+(MIN(D21/$B$10,'NG Inputs'!$B$9)*($B$9-'NG Inputs'!$B$5-'NG Inputs'!$B$6-2*'NG Inputs'!$B$7*SQRT(MIN(D21/$B$10,'NG Inputs'!$B$9)/'NG Inputs'!$B$8))+MAX(D21-MIN(D21/$B$10,'NG Inputs'!$B$9)*$B$10,0)*'NG Inputs'!$B$10/2)*(1-$B$8))/$B$10,'NG Inputs'!$B$9)/'NG Inputs'!$B$8))+MAX((D21+(MIN(D21/$B$10,'NG Inputs'!$B$9)*($B$9-'NG Inputs'!$B$5-'NG Inputs'!$B$6-2*'NG Inputs'!$B$7*SQRT(MIN(D21/$B$10,'NG Inputs'!$B$9)/'NG Inputs'!$B$8))+MAX(D21-MIN(D21/$B$10,'NG Inputs'!$B$9)*$B$10,0)*'NG Inputs'!$B$10/2)*(1-$B$8))-MIN((D21+(MIN(D21/$B$10,'NG Inputs'!$B$9)*($B$9-'NG Inputs'!$B$5-'NG Inputs'!$B$6-2*'NG Inputs'!$B$7*SQRT(MIN(D21/$B$10,'NG Inputs'!$B$9)/'NG Inputs'!$B$8))+MAX(D21-MIN(D21/$B$10,'NG Inputs'!$B$9)*$B$10,0)*'NG Inputs'!$B$10/2)*(1-$B$8))/$B$10,'NG Inputs'!$B$9)*$B$10,0)*'NG Inputs'!$B$10/2)*(1-$B$8)-INDEX('NG Scenarios'!$C$11:$C$25,A22)*(1-$B$8),$B$5) | E22: =IF(E21>0,E21+(($B$6*E21-$B$7)*(12/18))*(1-$B$8),0)+MAX((D21+(MIN(D21/$B$10,'NG Inputs'!$B$9)*($B$9-'NG Inputs'!$B$5-'NG Inputs'!$B$6-2*'NG Inputs'!$B$7*SQRT(MIN(D21/$B$10,'NG Inputs'!$B$9)/'NG Inputs'!$B$8))+MAX(D21-MIN(D21/$B$10,'NG Inputs'!$B$9)*$B$10,0)*'NG Inputs'!$B$10/2)*(1-$B$8))+(MIN((D21+(MIN(D21/$B$10,'NG Inputs'!$B$9)*($B$9-'NG Inputs'!$B$5-'NG Inputs'!$B$6-2*'NG Inputs'!$B$7*SQRT(MIN(D21/$B$10,'NG Inputs'!$B$9)/'NG Inputs'!$B$8))+MAX(D21-MIN(D21/$B$10,'NG Inputs'!$B$9)*$B$10,0)*'NG Inputs'!$B$10/2)*(1-$B$8))/$B$10,'NG Inputs'!$B$9)*($B$9-'NG Inputs'!$B$5-'NG Inputs'!$B$6-2*'NG Inputs'!$B$7*SQRT(MIN((D21+(MIN(D21/$B$10,'NG Inputs'!$B$9)*($B$9-'NG Inputs'!$B$5-'NG Inputs'!$B$6-2*'NG Inputs'!$B$7*SQRT(MIN(D21/$B$10,'NG Inputs'!$B$9)/'NG Inputs'!$B$8))+MAX(D21-MIN(D21/$B$10,'NG Inputs'!$B$9)*$B$10,0)*'NG Inputs'!$B$10/2)*(1-$B$8))/$B$10,'NG Inputs'!$B$9)/'NG Inputs'!$B$8))+MAX((D21+(MIN(D21/$B$10,'NG Inputs'!$B$9)*($B$9-'NG Inputs'!$B$5-'NG Inputs'!$B$6-2*'NG Inputs'!$B$7*SQRT(MIN(D21/$B$10,'NG Inputs'!$B$9)/'NG Inputs'!$B$8))+MAX(D21-MIN(D21/$B$10,'NG Inputs'!$B$9)*$B$10,0)*'NG Inputs'!$B$10/2)*(1-$B$8))-MIN((D21+(MIN(D21/$B$10,'NG Inputs'!$B$9)*($B$9-'NG Inputs'!$B$5-'NG Inputs'!$B$6-2*'NG Inputs'!$B$7*SQRT(MIN(D21/$B$10,'NG Inputs'!$B$9)/'NG Inputs'!$B$8))+MAX(D21-MIN(D21/$B$10,'NG Inputs'!$B$9)*$B$10,0)*'NG Inputs'!$B$10/2)*(1-$B$8))/$B$10,'NG Inputs'!$B$9)*$B$10,0)*'NG Inputs'!$B$10/2)*(1-$B$8)-INDEX('NG Scenarios'!$C$11:$C$25,A22)*(1-$B$8)-$B$5,0) | F22: =D22+E22
A23: 9 | B23: =(B22+(MIN(B22/$B$10,'NG Inputs'!$B$9)*($B$9-'NG Inputs'!$B$5-'NG Inputs'!$B$6-2*'NG Inputs'!$B$7*SQRT(MIN(B22/$B$10,'NG Inputs'!$B$9)/'NG Inputs'!$B$8))+MAX(B22-MIN(B22/$B$10,'NG Inputs'!$B$9)*$B$10,0)*'NG Inputs'!$B$10/2)*(1-$B$8))+(MIN((B22+(MIN(B22/$B$10,'NG Inputs'!$B$9)*($B$9-'NG Inputs'!$B$5-'NG Inputs'!$B$6-2*'NG Inputs'!$B$7*SQRT(MIN(B22/$B$10,'NG Inputs'!$B$9)/'NG Inputs'!$B$8))+MAX(B22-MIN(B22/$B$10,'NG Inputs'!$B$9)*$B$10,0)*'NG Inputs'!$B$10/2)*(1-$B$8))/$B$10,'NG Inputs'!$B$9)*($B$9-'NG Inputs'!$B$5-'NG Inputs'!$B$6-2*'NG Inputs'!$B$7*SQRT(MIN((B22+(MIN(B22/$B$10,'NG Inputs'!$B$9)*($B$9-'NG Inputs'!$B$5-'NG Inputs'!$B$6-2*'NG Inputs'!$B$7*SQRT(MIN(B22/$B$10,'NG Inputs'!$B$9)/'NG Inputs'!$B$8))+MAX(B22-MIN(B22/$B$10,'NG Inputs'!$B$9)*$B$10,0)*'NG Inputs'!$B$10/2)*(1-$B$8))/$B$10,'NG Inputs'!$B$9)/'NG Inputs'!$B$8))+MAX((B22+(MIN(B22/$B$10,'NG Inputs'!$B$9)*($B$9-'NG Inputs'!$B$5-'NG Inputs'!$B$6-2*'NG Inputs'!$B$7*SQRT(MIN(B22/$B$10,'NG Inputs'!$B$9)/'NG Inputs'!$B$8))+MAX(B22-MIN(B22/$B$10,'NG Inputs'!$B$9)*$B$10,0)*'NG Inputs'!$B$10/2)*(1-$B$8))-MIN((B22+(MIN(B22/$B$10,'NG Inputs'!$B$9)*($B$9-'NG Inputs'!$B$5-'NG Inputs'!$B$6-2*'NG Inputs'!$B$7*SQRT(MIN(B22/$B$10,'NG Inputs'!$B$9)/'NG Inputs'!$B$8))+MAX(B22-MIN(B22/$B$10,'NG Inputs'!$B$9)*$B$10,0)*'NG Inputs'!$B$10/2)*(1-$B$8))/$B$10,'NG Inputs'!$B$9)*$B$10,0)*'NG Inputs'!$B$10/2)*(1-$B$8)-INDEX('NG Scenarios'!$C$11:$C$25,A23)*(1-$B$8) | C23: =IF(C22<'NG Inputs'!$B$11,(C22+(MIN(C22/$B$10,'NG Inputs'!$B$9)*($B$9-'NG Inputs'!$B$5-'NG Inputs'!$B$6-2*'NG Inputs'!$B$7*SQRT(MIN(C22/$B$10,'NG Inputs'!$B$9)/'NG Inputs'!$B$8))+MAX(C22-MIN(C22/$B$10,'NG Inputs'!$B$9)*$B$10,0)*'NG Inputs'!$B$10/2)*(1-$B$8))+(MIN((C22+(MIN(C22/$B$10,'NG Inputs'!$B$9)*($B$9-'NG Inputs'!$B$5-'NG Inputs'!$B$6-2*'NG Inputs'!$B$7*SQRT(MIN(C22/$B$10,'NG Inputs'!$B$9)/'NG Inputs'!$B$8))+MAX(C22-MIN(C22/$B$10,'NG Inputs'!$B$9)*$B$10,0)*'NG Inputs'!$B$10/2)*(1-$B$8))/$B$10,'NG Inputs'!$B$9)*($B$9-'NG Inputs'!$B$5-'NG Inputs'!$B$6-2*'NG Inputs'!$B$7*SQRT(MIN((C22+(MIN(C22/$B$10,'NG Inputs'!$B$9)*($B$9-'NG Inputs'!$B$5-'NG Inputs'!$B$6-2*'NG Inputs'!$B$7*SQRT(MIN(C22/$B$10,'NG Inputs'!$B$9)/'NG Inputs'!$B$8))+MAX(C22-MIN(C22/$B$10,'NG Inputs'!$B$9)*$B$10,0)*'NG Inputs'!$B$10/2)*(1-$B$8))/$B$10,'NG Inputs'!$B$9)/'NG Inputs'!$B$8))+MAX((C22+(MIN(C22/$B$10,'NG Inputs'!$B$9)*($B$9-'NG Inputs'!$B$5-'NG Inputs'!$B$6-2*'NG Inputs'!$B$7*SQRT(MIN(C22/$B$10,'NG Inputs'!$B$9)/'NG Inputs'!$B$8))+MAX(C22-MIN(C22/$B$10,'NG Inputs'!$B$9)*$B$10,0)*'NG Inputs'!$B$10/2)*(1-$B$8))-MIN((C22+(MIN(C22/$B$10,'NG Inputs'!$B$9)*($B$9-'NG Inputs'!$B$5-'NG Inputs'!$B$6-2*'NG Inputs'!$B$7*SQRT(MIN(C22/$B$10,'NG Inputs'!$B$9)/'NG Inputs'!$B$8))+MAX(C22-MIN(C22/$B$10,'NG Inputs'!$B$9)*$B$10,0)*'NG Inputs'!$B$10/2)*(1-$B$8))/$B$10,'NG Inputs'!$B$9)*$B$10,0)*'NG Inputs'!$B$10/2)*(1-$B$8)-INDEX('NG Scenarios'!$C$11:$C$25,A23)*(1-$B$8),C22+(($B$6*C22-$B$7)*(12/18))*(1-$B$8)) | D23: =MIN((D22+(MIN(D22/$B$10,'NG Inputs'!$B$9)*($B$9-'NG Inputs'!$B$5-'NG Inputs'!$B$6-2*'NG Inputs'!$B$7*SQRT(MIN(D22/$B$10,'NG Inputs'!$B$9)/'NG Inputs'!$B$8))+MAX(D22-MIN(D22/$B$10,'NG Inputs'!$B$9)*$B$10,0)*'NG Inputs'!$B$10/2)*(1-$B$8))+(MIN((D22+(MIN(D22/$B$10,'NG Inputs'!$B$9)*($B$9-'NG Inputs'!$B$5-'NG Inputs'!$B$6-2*'NG Inputs'!$B$7*SQRT(MIN(D22/$B$10,'NG Inputs'!$B$9)/'NG Inputs'!$B$8))+MAX(D22-MIN(D22/$B$10,'NG Inputs'!$B$9)*$B$10,0)*'NG Inputs'!$B$10/2)*(1-$B$8))/$B$10,'NG Inputs'!$B$9)*($B$9-'NG Inputs'!$B$5-'NG Inputs'!$B$6-2*'NG Inputs'!$B$7*SQRT(MIN((D22+(MIN(D22/$B$10,'NG Inputs'!$B$9)*($B$9-'NG Inputs'!$B$5-'NG Inputs'!$B$6-2*'NG Inputs'!$B$7*SQRT(MIN(D22/$B$10,'NG Inputs'!$B$9)/'NG Inputs'!$B$8))+MAX(D22-MIN(D22/$B$10,'NG Inputs'!$B$9)*$B$10,0)*'NG Inputs'!$B$10/2)*(1-$B$8))/$B$10,'NG Inputs'!$B$9)/'NG Inputs'!$B$8))+MAX((D22+(MIN(D22/$B$10,'NG Inputs'!$B$9)*($B$9-'NG Inputs'!$B$5-'NG Inputs'!$B$6-2*'NG Inputs'!$B$7*SQRT(MIN(D22/$B$10,'NG Inputs'!$B$9)/'NG Inputs'!$B$8))+MAX(D22-MIN(D22/$B$10,'NG Inputs'!$B$9)*$B$10,0)*'NG Inputs'!$B$10/2)*(1-$B$8))-MIN((D22+(MIN(D22/$B$10,'NG Inputs'!$B$9)*($B$9-'NG Inputs'!$B$5-'NG Inputs'!$B$6-2*'NG Inputs'!$B$7*SQRT(MIN(D22/$B$10,'NG Inputs'!$B$9)/'NG Inputs'!$B$8))+MAX(D22-MIN(D22/$B$10,'NG Inputs'!$B$9)*$B$10,0)*'NG Inputs'!$B$10/2)*(1-$B$8))/$B$10,'NG Inputs'!$B$9)*$B$10,0)*'NG Inputs'!$B$10/2)*(1-$B$8)-INDEX('NG Scenarios'!$C$11:$C$25,A23)*(1-$B$8),$B$5) | E23: =IF(E22>0,E22+(($B$6*E22-$B$7)*(12/18))*(1-$B$8),0)+MAX((D22+(MIN(D22/$B$10,'NG Inputs'!$B$9)*($B$9-'NG Inputs'!$B$5-'NG Inputs'!$B$6-2*'NG Inputs'!$B$7*SQRT(MIN(D22/$B$10,'NG Inputs'!$B$9)/'NG Inputs'!$B$8))+MAX(D22-MIN(D22/$B$10,'NG Inputs'!$B$9)*$B$10,0)*'NG Inputs'!$B$10/2)*(1-$B$8))+(MIN((D22+(MIN(D22/$B$10,'NG Inputs'!$B$9)*($B$9-'NG Inputs'!$B$5-'NG Inputs'!$B$6-2*'NG Inputs'!$B$7*SQRT(MIN(D22/$B$10,'NG Inputs'!$B$9)/'NG Inputs'!$B$8))+MAX(D22-MIN(D22/$B$10,'NG Inputs'!$B$9)*$B$10,0)*'NG Inputs'!$B$10/2)*(1-$B$8))/$B$10,'NG Inputs'!$B$9)*($B$9-'NG Inputs'!$B$5-'NG Inputs'!$B$6-2*'NG Inputs'!$B$7*SQRT(MIN((D22+(MIN(D22/$B$10,'NG Inputs'!$B$9)*($B$9-'NG Inputs'!$B$5-'NG Inputs'!$B$6-2*'NG Inputs'!$B$7*SQRT(MIN(D22/$B$10,'NG Inputs'!$B$9)/'NG Inputs'!$B$8))+MAX(D22-MIN(D22/$B$10,'NG Inputs'!$B$9)*$B$10,0)*'NG Inputs'!$B$10/2)*(1-$B$8))/$B$10,'NG Inputs'!$B$9)/'NG Inputs'!$B$8))+MAX((D22+(MIN(D22/$B$10,'NG Inputs'!$B$9)*($B$9-'NG Inputs'!$B$5-'NG Inputs'!$B$6-2*'NG Inputs'!$B$7*SQRT(MIN(D22/$B$10,'NG Inputs'!$B$9)/'NG Inputs'!$B$8))+MAX(D22-MIN(D22/$B$10,'NG Inputs'!$B$9)*$B$10,0)*'NG Inputs'!$B$10/2)*(1-$B$8))-MIN((D22+(MIN(D22/$B$10,'NG Inputs'!$B$9)*($B$9-'NG Inputs'!$B$5-'NG Inputs'!$B$6-2*'NG Inputs'!$B$7*SQRT(MIN(D22/$B$10,'NG Inputs'!$B$9)/'NG Inputs'!$B$8))+MAX(D22-MIN(D22/$B$10,'NG Inputs'!$B$9)*$B$10,0)*'NG Inputs'!$B$10/2)*(1-$B$8))/$B$10,'NG Inputs'!$B$9)*$B$10,0)*'NG Inputs'!$B$10/2)*(1-$B$8)-INDEX('NG Scenarios'!$C$11:$C$25,A23)*(1-$B$8)-$B$5,0) | F23: =D23+E23
A24: 10 | B24: =(B23+(MIN(B23/$B$10,'NG Inputs'!$B$9)*($B$9-'NG Inputs'!$B$5-'NG Inputs'!$B$6-2*'NG Inputs'!$B$7*SQRT(MIN(B23/$B$10,'NG Inputs'!$B$9)/'NG Inputs'!$B$8))+MAX(B23-MIN(B23/$B$10,'NG Inputs'!$B$9)*$B$10,0)*'NG Inputs'!$B$10/2)*(1-$B$8))+(MIN((B23+(MIN(B23/$B$10,'NG Inputs'!$B$9)*($B$9-'NG Inputs'!$B$5-'NG Inputs'!$B$6-2*'NG Inputs'!$B$7*SQRT(MIN(B23/$B$10,'NG Inputs'!$B$9)/'NG Inputs'!$B$8))+MAX(B23-MIN(B23/$B$10,'NG Inputs'!$B$9)*$B$10,0)*'NG Inputs'!$B$10/2)*(1-$B$8))/$B$10,'NG Inputs'!$B$9)*($B$9-'NG Inputs'!$B$5-'NG Inputs'!$B$6-2*'NG Inputs'!$B$7*SQRT(MIN((B23+(MIN(B23/$B$10,'NG Inputs'!$B$9)*($B$9-'NG Inputs'!$B$5-'NG Inputs'!$B$6-2*'NG Inputs'!$B$7*SQRT(MIN(B23/$B$10,'NG Inputs'!$B$9)/'NG Inputs'!$B$8))+MAX(B23-MIN(B23/$B$10,'NG Inputs'!$B$9)*$B$10,0)*'NG Inputs'!$B$10/2)*(1-$B$8))/$B$10,'NG Inputs'!$B$9)/'NG Inputs'!$B$8))+MAX((B23+(MIN(B23/$B$10,'NG Inputs'!$B$9)*($B$9-'NG Inputs'!$B$5-'NG Inputs'!$B$6-2*'NG Inputs'!$B$7*SQRT(MIN(B23/$B$10,'NG Inputs'!$B$9)/'NG Inputs'!$B$8))+MAX(B23-MIN(B23/$B$10,'NG Inputs'!$B$9)*$B$10,0)*'NG Inputs'!$B$10/2)*(1-$B$8))-MIN((B23+(MIN(B23/$B$10,'NG Inputs'!$B$9)*($B$9-'NG Inputs'!$B$5-'NG Inputs'!$B$6-2*'NG Inputs'!$B$7*SQRT(MIN(B23/$B$10,'NG Inputs'!$B$9)/'NG Inputs'!$B$8))+MAX(B23-MIN(B23/$B$10,'NG Inputs'!$B$9)*$B$10,0)*'NG Inputs'!$B$10/2)*(1-$B$8))/$B$10,'NG Inputs'!$B$9)*$B$10,0)*'NG Inputs'!$B$10/2)*(1-$B$8)-INDEX('NG Scenarios'!$C$11:$C$25,A24)*(1-$B$8) | C24: =IF(C23<'NG Inputs'!$B$11,(C23+(MIN(C23/$B$10,'NG Inputs'!$B$9)*($B$9-'NG Inputs'!$B$5-'NG Inputs'!$B$6-2*'NG Inputs'!$B$7*SQRT(MIN(C23/$B$10,'NG Inputs'!$B$9)/'NG Inputs'!$B$8))+MAX(C23-MIN(C23/$B$10,'NG Inputs'!$B$9)*$B$10,0)*'NG Inputs'!$B$10/2)*(1-$B$8))+(MIN((C23+(MIN(C23/$B$10,'NG Inputs'!$B$9)*($B$9-'NG Inputs'!$B$5-'NG Inputs'!$B$6-2*'NG Inputs'!$B$7*SQRT(MIN(C23/$B$10,'NG Inputs'!$B$9)/'NG Inputs'!$B$8))+MAX(C23-MIN(C23/$B$10,'NG Inputs'!$B$9)*$B$10,0)*'NG Inputs'!$B$10/2)*(1-$B$8))/$B$10,'NG Inputs'!$B$9)*($B$9-'NG Inputs'!$B$5-'NG Inputs'!$B$6-2*'NG Inputs'!$B$7*SQRT(MIN((C23+(MIN(C23/$B$10,'NG Inputs'!$B$9)*($B$9-'NG Inputs'!$B$5-'NG Inputs'!$B$6-2*'NG Inputs'!$B$7*SQRT(MIN(C23/$B$10,'NG Inputs'!$B$9)/'NG Inputs'!$B$8))+MAX(C23-MIN(C23/$B$10,'NG Inputs'!$B$9)*$B$10,0)*'NG Inputs'!$B$10/2)*(1-$B$8))/$B$10,'NG Inputs'!$B$9)/'NG Inputs'!$B$8))+MAX((C23+(MIN(C23/$B$10,'NG Inputs'!$B$9)*($B$9-'NG Inputs'!$B$5-'NG Inputs'!$B$6-2*'NG Inputs'!$B$7*SQRT(MIN(C23/$B$10,'NG Inputs'!$B$9)/'NG Inputs'!$B$8))+MAX(C23-MIN(C23/$B$10,'NG Inputs'!$B$9)*$B$10,0)*'NG Inputs'!$B$10/2)*(1-$B$8))-MIN((C23+(MIN(C23/$B$10,'NG Inputs'!$B$9)*($B$9-'NG Inputs'!$B$5-'NG Inputs'!$B$6-2*'NG Inputs'!$B$7*SQRT(MIN(C23/$B$10,'NG Inputs'!$B$9)/'NG Inputs'!$B$8))+MAX(C23-MIN(C23/$B$10,'NG Inputs'!$B$9)*$B$10,0)*'NG Inputs'!$B$10/2)*(1-$B$8))/$B$10,'NG Inputs'!$B$9)*$B$10,0)*'NG Inputs'!$B$10/2)*(1-$B$8)-INDEX('NG Scenarios'!$C$11:$C$25,A24)*(1-$B$8),C23+(($B$6*C23-$B$7)*(12/18))*(1-$B$8)) | D24: =MIN((D23+(MIN(D23/$B$10,'NG Inputs'!$B$9)*($B$9-'NG Inputs'!$B$5-'NG Inputs'!$B$6-2*'NG Inputs'!$B$7*SQRT(MIN(D23/$B$10,'NG Inputs'!$B$9)/'NG Inputs'!$B$8))+MAX(D23-MIN(D23/$B$10,'NG Inputs'!$B$9)*$B$10,0)*'NG Inputs'!$B$10/2)*(1-$B$8))+(MIN((D23+(MIN(D23/$B$10,'NG Inputs'!$B$9)*($B$9-'NG Inputs'!$B$5-'NG Inputs'!$B$6-2*'NG Inputs'!$B$7*SQRT(MIN(D23/$B$10,'NG Inputs'!$B$9)/'NG Inputs'!$B$8))+MAX(D23-MIN(D23/$B$10,'NG Inputs'!$B$9)*$B$10,0)*'NG Inputs'!$B$10/2)*(1-$B$8))/$B$10,'NG Inputs'!$B$9)*($B$9-'NG Inputs'!$B$5-'NG Inputs'!$B$6-2*'NG Inputs'!$B$7*SQRT(MIN((D23+(MIN(D23/$B$10,'NG Inputs'!$B$9)*($B$9-'NG Inputs'!$B$5-'NG Inputs'!$B$6-2*'NG Inputs'!$B$7*SQRT(MIN(D23/$B$10,'NG Inputs'!$B$9)/'NG Inputs'!$B$8))+MAX(D23-MIN(D23/$B$10,'NG Inputs'!$B$9)*$B$10,0)*'NG Inputs'!$B$10/2)*(1-$B$8))/$B$10,'NG Inputs'!$B$9)/'NG Inputs'!$B$8))+MAX((D23+(MIN(D23/$B$10,'NG Inputs'!$B$9)*($B$9-'NG Inputs'!$B$5-'NG Inputs'!$B$6-2*'NG Inputs'!$B$7*SQRT(MIN(D23/$B$10,'NG Inputs'!$B$9)/'NG Inputs'!$B$8))+MAX(D23-MIN(D23/$B$10,'NG Inputs'!$B$9)*$B$10,0)*'NG Inputs'!$B$10/2)*(1-$B$8))-MIN((D23+(MIN(D23/$B$10,'NG Inputs'!$B$9)*($B$9-'NG Inputs'!$B$5-'NG Inputs'!$B$6-2*'NG Inputs'!$B$7*SQRT(MIN(D23/$B$10,'NG Inputs'!$B$9)/'NG Inputs'!$B$8))+MAX(D23-MIN(D23/$B$10,'NG Inputs'!$B$9)*$B$10,0)*'NG Inputs'!$B$10/2)*(1-$B$8))/$B$10,'NG Inputs'!$B$9)*$B$10,0)*'NG Inputs'!$B$10/2)*(1-$B$8)-INDEX('NG Scenarios'!$C$11:$C$25,A24)*(1-$B$8),$B$5) | E24: =IF(E23>0,E23+(($B$6*E23-$B$7)*(12/18))*(1-$B$8),0)+MAX((D23+(MIN(D23/$B$10,'NG Inputs'!$B$9)*($B$9-'NG Inputs'!$B$5-'NG Inputs'!$B$6-2*'NG Inputs'!$B$7*SQRT(MIN(D23/$B$10,'NG Inputs'!$B$9)/'NG Inputs'!$B$8))+MAX(D23-MIN(D23/$B$10,'NG Inputs'!$B$9)*$B$10,0)*'NG Inputs'!$B$10/2)*(1-$B$8))+(MIN((D23+(MIN(D23/$B$10,'NG Inputs'!$B$9)*($B$9-'NG Inputs'!$B$5-'NG Inputs'!$B$6-2*'NG Inputs'!$B$7*SQRT(MIN(D23/$B$10,'NG Inputs'!$B$9)/'NG Inputs'!$B$8))+MAX(D23-MIN(D23/$B$10,'NG Inputs'!$B$9)*$B$10,0)*'NG Inputs'!$B$10/2)*(1-$B$8))/$B$10,'NG Inputs'!$B$9)*($B$9-'NG Inputs'!$B$5-'NG Inputs'!$B$6-2*'NG Inputs'!$B$7*SQRT(MIN((D23+(MIN(D23/$B$10,'NG Inputs'!$B$9)*($B$9-'NG Inputs'!$B$5-'NG Inputs'!$B$6-2*'NG Inputs'!$B$7*SQRT(MIN(D23/$B$10,'NG Inputs'!$B$9)/'NG Inputs'!$B$8))+MAX(D23-MIN(D23/$B$10,'NG Inputs'!$B$9)*$B$10,0)*'NG Inputs'!$B$10/2)*(1-$B$8))/$B$10,'NG Inputs'!$B$9)/'NG Inputs'!$B$8))+MAX((D23+(MIN(D23/$B$10,'NG Inputs'!$B$9)*($B$9-'NG Inputs'!$B$5-'NG Inputs'!$B$6-2*'NG Inputs'!$B$7*SQRT(MIN(D23/$B$10,'NG Inputs'!$B$9)/'NG Inputs'!$B$8))+MAX(D23-MIN(D23/$B$10,'NG Inputs'!$B$9)*$B$10,0)*'NG Inputs'!$B$10/2)*(1-$B$8))-MIN((D23+(MIN(D23/$B$10,'NG Inputs'!$B$9)*($B$9-'NG Inputs'!$B$5-'NG Inputs'!$B$6-2*'NG Inputs'!$B$7*SQRT(MIN(D23/$B$10,'NG Inputs'!$B$9)/'NG Inputs'!$B$8))+MAX(D23-MIN(D23/$B$10,'NG Inputs'!$B$9)*$B$10,0)*'NG Inputs'!$B$10/2)*(1-$B$8))/$B$10,'NG Inputs'!$B$9)*$B$10,0)*'NG Inputs'!$B$10/2)*(1-$B$8)-INDEX('NG Scenarios'!$C$11:$C$25,A24)*(1-$B$8)-$B$5,0) | F24: =D24+E24
A25: 11 | B25: =(B24+(MIN(B24/$B$10,'NG Inputs'!$B$9)*($B$9-'NG Inputs'!$B$5-'NG Inputs'!$B$6-2*'NG Inputs'!$B$7*SQRT(MIN(B24/$B$10,'NG Inputs'!$B$9)/'NG Inputs'!$B$8))+MAX(B24-MIN(B24/$B$10,'NG Inputs'!$B$9)*$B$10,0)*'NG Inputs'!$B$10/2)*(1-$B$8))+(MIN((B24+(MIN(B24/$B$10,'NG Inputs'!$B$9)*($B$9-'NG Inputs'!$B$5-'NG Inputs'!$B$6-2*'NG Inputs'!$B$7*SQRT(MIN(B24/$B$10,'NG Inputs'!$B$9)/'NG Inputs'!$B$8))+MAX(B24-MIN(B24/$B$10,'NG Inputs'!$B$9)*$B$10,0)*'NG Inputs'!$B$10/2)*(1-$B$8))/$B$10,'NG Inputs'!$B$9)*($B$9-'NG Inputs'!$B$5-'NG Inputs'!$B$6-2*'NG Inputs'!$B$7*SQRT(MIN((B24+(MIN(B24/$B$10,'NG Inputs'!$B$9)*($B$9-'NG Inputs'!$B$5-'NG Inputs'!$B$6-2*'NG Inputs'!$B$7*SQRT(MIN(B24/$B$10,'NG Inputs'!$B$9)/'NG Inputs'!$B$8))+MAX(B24-MIN(B24/$B$10,'NG Inputs'!$B$9)*$B$10,0)*'NG Inputs'!$B$10/2)*(1-$B$8))/$B$10,'NG Inputs'!$B$9)/'NG Inputs'!$B$8))+MAX((B24+(MIN(B24/$B$10,'NG Inputs'!$B$9)*($B$9-'NG Inputs'!$B$5-'NG Inputs'!$B$6-2*'NG Inputs'!$B$7*SQRT(MIN(B24/$B$10,'NG Inputs'!$B$9)/'NG Inputs'!$B$8))+MAX(B24-MIN(B24/$B$10,'NG Inputs'!$B$9)*$B$10,0)*'NG Inputs'!$B$10/2)*(1-$B$8))-MIN((B24+(MIN(B24/$B$10,'NG Inputs'!$B$9)*($B$9-'NG Inputs'!$B$5-'NG Inputs'!$B$6-2*'NG Inputs'!$B$7*SQRT(MIN(B24/$B$10,'NG Inputs'!$B$9)/'NG Inputs'!$B$8))+MAX(B24-MIN(B24/$B$10,'NG Inputs'!$B$9)*$B$10,0)*'NG Inputs'!$B$10/2)*(1-$B$8))/$B$10,'NG Inputs'!$B$9)*$B$10,0)*'NG Inputs'!$B$10/2)*(1-$B$8)-INDEX('NG Scenarios'!$C$11:$C$25,A25)*(1-$B$8) | C25: =IF(C24<'NG Inputs'!$B$11,(C24+(MIN(C24/$B$10,'NG Inputs'!$B$9)*($B$9-'NG Inputs'!$B$5-'NG Inputs'!$B$6-2*'NG Inputs'!$B$7*SQRT(MIN(C24/$B$10,'NG Inputs'!$B$9)/'NG Inputs'!$B$8))+MAX(C24-MIN(C24/$B$10,'NG Inputs'!$B$9)*$B$10,0)*'NG Inputs'!$B$10/2)*(1-$B$8))+(MIN((C24+(MIN(C24/$B$10,'NG Inputs'!$B$9)*($B$9-'NG Inputs'!$B$5-'NG Inputs'!$B$6-2*'NG Inputs'!$B$7*SQRT(MIN(C24/$B$10,'NG Inputs'!$B$9)/'NG Inputs'!$B$8))+MAX(C24-MIN(C24/$B$10,'NG Inputs'!$B$9)*$B$10,0)*'NG Inputs'!$B$10/2)*(1-$B$8))/$B$10,'NG Inputs'!$B$9)*($B$9-'NG Inputs'!$B$5-'NG Inputs'!$B$6-2*'NG Inputs'!$B$7*SQRT(MIN((C24+(MIN(C24/$B$10,'NG Inputs'!$B$9)*($B$9-'NG Inputs'!$B$5-'NG Inputs'!$B$6-2*'NG Inputs'!$B$7*SQRT(MIN(C24/$B$10,'NG Inputs'!$B$9)/'NG Inputs'!$B$8))+MAX(C24-MIN(C24/$B$10,'NG Inputs'!$B$9)*$B$10,0)*'NG Inputs'!$B$10/2)*(1-$B$8))/$B$10,'NG Inputs'!$B$9)/'NG Inputs'!$B$8))+MAX((C24+(MIN(C24/$B$10,'NG Inputs'!$B$9)*($B$9-'NG Inputs'!$B$5-'NG Inputs'!$B$6-2*'NG Inputs'!$B$7*SQRT(MIN(C24/$B$10,'NG Inputs'!$B$9)/'NG Inputs'!$B$8))+MAX(C24-MIN(C24/$B$10,'NG Inputs'!$B$9)*$B$10,0)*'NG Inputs'!$B$10/2)*(1-$B$8))-MIN((C24+(MIN(C24/$B$10,'NG Inputs'!$B$9)*($B$9-'NG Inputs'!$B$5-'NG Inputs'!$B$6-2*'NG Inputs'!$B$7*SQRT(MIN(C24/$B$10,'NG Inputs'!$B$9)/'NG Inputs'!$B$8))+MAX(C24-MIN(C24/$B$10,'NG Inputs'!$B$9)*$B$10,0)*'NG Inputs'!$B$10/2)*(1-$B$8))/$B$10,'NG Inputs'!$B$9)*$B$10,0)*'NG Inputs'!$B$10/2)*(1-$B$8)-INDEX('NG Scenarios'!$C$11:$C$25,A25)*(1-$B$8),C24+(($B$6*C24-$B$7)*(12/18))*(1-$B$8)) | D25: =MIN((D24+(MIN(D24/$B$10,'NG Inputs'!$B$9)*($B$9-'NG Inputs'!$B$5-'NG Inputs'!$B$6-2*'NG Inputs'!$B$7*SQRT(MIN(D24/$B$10,'NG Inputs'!$B$9)/'NG Inputs'!$B$8))+MAX(D24-MIN(D24/$B$10,'NG Inputs'!$B$9)*$B$10,0)*'NG Inputs'!$B$10/2)*(1-$B$8))+(MIN((D24+(MIN(D24/$B$10,'NG Inputs'!$B$9)*($B$9-'NG Inputs'!$B$5-'NG Inputs'!$B$6-2*'NG Inputs'!$B$7*SQRT(MIN(D24/$B$10,'NG Inputs'!$B$9)/'NG Inputs'!$B$8))+MAX(D24-MIN(D24/$B$10,'NG Inputs'!$B$9)*$B$10,0)*'NG Inputs'!$B$10/2)*(1-$B$8))/$B$10,'NG Inputs'!$B$9)*($B$9-'NG Inputs'!$B$5-'NG Inputs'!$B$6-2*'NG Inputs'!$B$7*SQRT(MIN((D24+(MIN(D24/$B$10,'NG Inputs'!$B$9)*($B$9-'NG Inputs'!$B$5-'NG Inputs'!$B$6-2*'NG Inputs'!$B$7*SQRT(MIN(D24/$B$10,'NG Inputs'!$B$9)/'NG Inputs'!$B$8))+MAX(D24-MIN(D24/$B$10,'NG Inputs'!$B$9)*$B$10,0)*'NG Inputs'!$B$10/2)*(1-$B$8))/$B$10,'NG Inputs'!$B$9)/'NG Inputs'!$B$8))+MAX((D24+(MIN(D24/$B$10,'NG Inputs'!$B$9)*($B$9-'NG Inputs'!$B$5-'NG Inputs'!$B$6-2*'NG Inputs'!$B$7*SQRT(MIN(D24/$B$10,'NG Inputs'!$B$9)/'NG Inputs'!$B$8))+MAX(D24-MIN(D24/$B$10,'NG Inputs'!$B$9)*$B$10,0)*'NG Inputs'!$B$10/2)*(1-$B$8))-MIN((D24+(MIN(D24/$B$10,'NG Inputs'!$B$9)*($B$9-'NG Inputs'!$B$5-'NG Inputs'!$B$6-2*'NG Inputs'!$B$7*SQRT(MIN(D24/$B$10,'NG Inputs'!$B$9)/'NG Inputs'!$B$8))+MAX(D24-MIN(D24/$B$10,'NG Inputs'!$B$9)*$B$10,0)*'NG Inputs'!$B$10/2)*(1-$B$8))/$B$10,'NG Inputs'!$B$9)*$B$10,0)*'NG Inputs'!$B$10/2)*(1-$B$8)-INDEX('NG Scenarios'!$C$11:$C$25,A25)*(1-$B$8),$B$5) | E25: =IF(E24>0,E24+(($B$6*E24-$B$7)*(12/18))*(1-$B$8),0)+MAX((D24+(MIN(D24/$B$10,'NG Inputs'!$B$9)*($B$9-'NG Inputs'!$B$5-'NG Inputs'!$B$6-2*'NG Inputs'!$B$7*SQRT(MIN(D24/$B$10,'NG Inputs'!$B$9)/'NG Inputs'!$B$8))+MAX(D24-MIN(D24/$B$10,'NG Inputs'!$B$9)*$B$10,0)*'NG Inputs'!$B$10/2)*(1-$B$8))+(MIN((D24+(MIN(D24/$B$10,'NG Inputs'!$B$9)*($B$9-'NG Inputs'!$B$5-'NG Inputs'!$B$6-2*'NG Inputs'!$B$7*SQRT(MIN(D24/$B$10,'NG Inputs'!$B$9)/'NG Inputs'!$B$8))+MAX(D24-MIN(D24/$B$10,'NG Inputs'!$B$9)*$B$10,0)*'NG Inputs'!$B$10/2)*(1-$B$8))/$B$10,'NG Inputs'!$B$9)*($B$9-'NG Inputs'!$B$5-'NG Inputs'!$B$6-2*'NG Inputs'!$B$7*SQRT(MIN((D24+(MIN(D24/$B$10,'NG Inputs'!$B$9)*($B$9-'NG Inputs'!$B$5-'NG Inputs'!$B$6-2*'NG Inputs'!$B$7*SQRT(MIN(D24/$B$10,'NG Inputs'!$B$9)/'NG Inputs'!$B$8))+MAX(D24-MIN(D24/$B$10,'NG Inputs'!$B$9)*$B$10,0)*'NG Inputs'!$B$10/2)*(1-$B$8))/$B$10,'NG Inputs'!$B$9)/'NG Inputs'!$B$8))+MAX((D24+(MIN(D24/$B$10,'NG Inputs'!$B$9)*($B$9-'NG Inputs'!$B$5-'NG Inputs'!$B$6-2*'NG Inputs'!$B$7*SQRT(MIN(D24/$B$10,'NG Inputs'!$B$9)/'NG Inputs'!$B$8))+MAX(D24-MIN(D24/$B$10,'NG Inputs'!$B$9)*$B$10,0)*'NG Inputs'!$B$10/2)*(1-$B$8))-MIN((D24+(MIN(D24/$B$10,'NG Inputs'!$B$9)*($B$9-'NG Inputs'!$B$5-'NG Inputs'!$B$6-2*'NG Inputs'!$B$7*SQRT(MIN(D24/$B$10,'NG Inputs'!$B$9)/'NG Inputs'!$B$8))+MAX(D24-MIN(D24/$B$10,'NG Inputs'!$B$9)*$B$10,0)*'NG Inputs'!$B$10/2)*(1-$B$8))/$B$10,'NG Inputs'!$B$9)*$B$10,0)*'NG Inputs'!$B$10/2)*(1-$B$8)-INDEX('NG Scenarios'!$C$11:$C$25,A25)*(1-$B$8)-$B$5,0) | F25: =D25+E25
