Workbook

Sheet Engine Inputs
A1: REBUILT ENGINE · SHARED INPUTS
A2: Blue cells drive every NG scenario tab. Edit here; the whole model reprices.
A3: Parameter | B3: Value | C3: Basis
A4: Tax rate (115BAA per-trade) | B4: 0.25168 | C4: Flat 22%+10% surch+4% cess; applied per trade (conservative vs annual assessment)
A5: Roll + carry cost (% notional / trade) | B5: 0.005 | C5: PDF gives MARGIN term structure only, not price contango; 0.50% is a placeholder INPUT — replace with measured roll gaps
A6: Txn + brokerage RT (% notional) | B6: 0.0006 | C6: CTT 0.01% sell side + brokerage + stamp; round trip
A7: Daily realized vol (for impact) | B7: 0.028 | C7: ≈45% ann. vol (PDF leg avg) / √252
A8: ADV notional (₹) | B8: 37800000000 | C8: ≈100,000 lots/day (PDF 2025-26 legs) × 1,250 mmBtu × ₹302.4 ≈ ₹3,780 Cr
A9: Max notional per position (₹) | B9: 3780000000 | C9: 10% of ADV: ≤2%/day participation × ~5-day entry+exit. HARD liquidity ceiling
A10: Idle-capital yield (liquid fund) | B10: 0.065 | C10: Undeployable capital above ceiling parked in liquid funds
A11: GIFT gateway capital (₹) | B11: 200000000 | C11: ₹20 Cr — corporate wrapper inflection from US ETF tab
A12: Deployment fraction of corpus | B12: 1 | C12: Set <1 to apply Kelly sizing from Kelly tab

Sheet Margin-Move Link
A1: DYNAMIC MARGIN ↔ MOVE LINK
A2: 123 contract legs (2020-2026) from the PDF Leg Dynamics table — kills the Static Margin Fallacy.
A4: Year | B4: Move % | C4: Avg Margin % during leg | D4: |Move| % | E4: Lev. Eff. (|move|/margin)
A5: 2020 | B5: -0.2431 | C5: 0.1412 | D5: =ABS(B5) -> 0.2431 | E5: =D5/C5 -> 1.7216714
A6: 2020 | B6: -0.1927 | C6: 0.1153 | D6: =ABS(B6) -> 0.1927 | E6: =D6/C6 -> 1.6712923
A7: 2020 | B7: 0.1746 | C7: 0.1417 | D7: =ABS(B7) -> 0.1746 | E7: =D7/C7 -> 1.2321807
A8: 2020 | B8: 0.1665 | C8: 0.1297 | D8: =ABS(B8) -> 0.1665 | E8: =D8/C8 -> 1.2837317
A9: 2020 | B9: -0.1842 | C9: 0.1728 | D9: =ABS(B9) -> 0.1842 | E9: =D9/C9 -> 1.0659722
A10: 2020 | B10: -0.1901 | C10: 0.1709 | D10: =ABS(B10) -> 0.1901 | E10: =D10/C10 -> 1.1123464
A11: 2020 | B11: 0.2155 | C11: 0.2316 | D11: =ABS(B11) -> 0.2155 | E11: =D11/C11 -> 0.93048359
A12: 2020 | B12: 0.2158 | C12: 0.2428 | D12: =ABS(B12) -> 0.2158 | E12: =D12/C12 -> 0.88879736
A13: 2020 | B13: -0.2978 | C13: 0.2164 | D13: =ABS(B13) -> 0.2978 | E13: =D13/C13 -> 1.3761553
A14: 2020 | B14: -0.2316 | C14: 0.2691 | D14: =ABS(B14) -> 0.2316 | E14: =D14/C14 -> 0.8606466
A15: 2020 | B15: -0.1927 | C15: 0.1675 | D15: =ABS(B15) -> 0.1927 | E15: =D15/C15 -> 1.1504478
A16: 2020 | B16: 0.209 | C16: 0.2228 | D16: =ABS(B16) -> 0.209 | E16: =D16/C16 -> 0.93806104
... A127: 2026 | B127: 0.1876 | C127: 0.1644 | D127: =ABS(B127) -> 0.1876 | E127: =D127/C127 -> 1.1411192
A130: BUCKET STATISTICS (live formulas)
A131: Bucket |move| | B131: n legs | C131: Avg |move| | D131: Avg margin during leg | E131: Avg Lev. Eff. | F131: Implied gross ROC (avg|move|/avg margin)
A132: 15–20% | B132: =COUNTIFS(D5:D127,">="&0.15,D5:D127,"<"&0.2) -> 42 | C132: =AVERAGEIFS(D5:D127,D5:D127,">="&0.15,D5:D127,"<"&0.2) -> 0.17562619 | D132: =AVERAGEIFS(C5:C127,D5:D127,">="&0.15,D5:D127,"<"&0.2) -> 0.21009048 | E132: =AVERAGEIFS(E5:E127,D5:D127,">="&0.15,D5:D127,"<"&0.2) -> 0.91175104 | F132: =C132/D132 -> 0.83595503
A133: 20–25% | B133: =COUNTIFS(D5:D127,">="&0.2,D5:D127,"<"&0.25) -> 26 | C133: =AVERAGEIFS(D5:D127,D5:D127,">="&0.2,D5:D127,"<"&0.25) -> 0.22343462 | D133: =AVERAGEIFS(C5:C127,D5:D127,">="&0.2,D5:D127,"<"&0.25) -> 0.21355 | E133: =AVERAGEIFS(E5:E127,D5:D127,">="&0.2,D5:D127,"<"&0.25) -> 1.1036244 | F133: =C133/D133 -> 1.0462871
A134: 25–30% | B134: =COUNTIFS(D5:D127,">="&0.25,D5:D127,"<"&0.3) -> 17 | C134: =AVERAGEIFS(D5:D127,D5:D127,">="&0.25,D5:D127,"<"&0.3) -> 0.27347059 | D134: =AVERAGEIFS(C5:C127,D5:D127,">="&0.25,D5:D127,"<"&0.3) -> 0.27272941 | E134: =AVERAGEIFS(E5:E127,D5:D127,">="&0.25,D5:D127,"<"&0.3) -> 1.0640057 | F134: =C134/D134 -> 1.0027176
A135: ≥30% | B135: =COUNTIFS(D5:D127,">="&0.3,D5:D127,"<"&10) -> 38 | C135: =AVERAGEIFS(D5:D127,D5:D127,">="&0.3,D5:D127,"<"&10) -> 0.43265263 | D135: =AVERAGEIFS(C5:C127,D5:D127,">="&0.3,D5:D127,"<"&10) -> 0.25867632 | E135: =AVERAGEIFS(E5:E127,D5:D127,">="&0.3,D5:D127,"<"&10) -> 1.7892979 | F135: =C135/D135 -> 1.6725638
A137: Correlation |move| vs margin | B137: =CORREL(D5:D127,C5:C127) -> 0.29945113
A138: Linear fit: margin = a + b·|move| | B138: =INTERCEPT(C5:C127,D5:D127) -> 0.18662725 | C138: =SLOPE(C5:C127,D5:D127) -> 0.17175723

Sheet Rebuilt Scenarios
A1: REBUILT SCENARIOS · BULL / BASE / BEAR
A2: Per-trade tax, dynamic PDF-bucket margins, costs, slippage, ₹378 Cr ceiling. K'=K+min(dep·K/m,Nmax)·(move−roll−txn−slip)·(1−tax)+idle·yield·(1−tax).
A3: Starting capital bases → | C3: 2000000 | D3: 7500000 | E3: 20000000 | F3: ◄ Edit these to rescale every scenario & the expense schedule. Cells: C3=Base1, D3=Base2, E3=Base3
A4: Scenario | B4: Move % | C4: Margin % | D4: Calls/yr | E4: Gross ROC/call | F4: Rationale
A5: BULL | B5: 0.3 | C5: ='Margin-Move Link'!D135 -> 0.25867632 | D5: 2 | E5: =B5/C5 -> 1.1597506 | F5: Catch 2 legs/yr, capture first 30% of a ≥30% swing; margin = PDF ≥30%-bucket avg (25.9%)
A6: BASE | B6: 0.18 | C6: ='Margin-Move Link'!D134 -> 0.27272941 | D6: 2 | E6: =B6/C6 -> 0.65999482 | F6: TRUE BASE: 25% move (7-11×/yr, 2020-26) at the 25-30% bucket avg margin 27.3% — NOT 22%
A7: BEAR | B7: 0.15 | C7: 0.28 | D7: 1 | E7: =B7/C7 -> 0.53571429 | F7: 1 catch/yr of a 15% move in an elevated-margin regime (2022-style / Nov-26 fwd 29.7%)
A9: Expense schedule (₹) — blue, scales with each starting-capital base above (C3/D3/E3)
A10: Year | B10: =IF($C$3>=10000000,"₹"&TEXT($C$3/10000000,"0.##")&"Cr","₹"&TEXT($C$3/100000,"0.##")&"L")&" start" -> ₹20.L start | C10: =IF($D$3>=10000000,"₹"&TEXT($D$3/10000000,"0.##")&"Cr","₹"&TEXT($D$3/100000,"0.##")&"L")&" start" -> ₹75.L start | D10: =IF($E$3>=10000000,"₹"&TEXT($E$3/10000000,"0.##")&"Cr","₹"&TEXT($E$3/100000,"0.##")&"L")&" start" -> ₹2.Cr start
A11: 1 | B11: =ROUND(0.01*$C$3,0) -> 20000 | C11: =ROUND(0.01*$D$3,0) -> 75000 | D11: =ROUND(0.01*$E$3,0) -> 200000
A12: 2 | B12: =ROUND(0.01*$C$3,0) -> 20000 | C12: =ROUND(0.01*$D$3,0) -> 75000 | D12: =ROUND(0.01*$E$3,0) -> 200000
A13: 3 | B13: =ROUND(0.025*$C$3,0) -> 50000 | C13: =ROUND(0.025*$D$3,0) -> 187500 | D13: =ROUND(0.025*$E$3,0) -> 500000
A14: 4 | B14: =ROUND(0.025*$C$3,0) -> 50000 | C14: =ROUND(0.025*$D$3,0) -> 187500 | D14: =ROUND(0.025*$E$3,0) -> 500000
A15: 5 | B15: =ROUND(0.05*$C$3,0) -> 100000 | C15: =ROUND(0.05*$D$3,0) -> 375000 | D15: =ROUND(0.05*$E$3,0) -> 1000000
A16: 6 | B16: =ROUND(0.05*$C$3,0) -> 100000 | C16: =ROUND(0.05*$D$3,0) -> 375000 | D16: =ROUND(0.05*$E$3,0) -> 1000000
A17: 7 | B17: =ROUND(0.05*$C$3,0) -> 100000 | C17: =ROUND(0.05*$D$3,0) -> 375000 | D17: =ROUND(0.05*$E$3,0) -> 1000000
A18: 8 | B18: =ROUND(0.1*$C$3,0) -> 200000 | C18: =ROUND(0.1*$D$3,0) -> 750000 | D18: =ROUND(0.1*$E$3,0) -> 2000000
A19: 9 | B19: =ROUND(0.1*$C$3,0) -> 200000 | C19: =ROUND(0.1*$D$3,0) -> 750000 | D19: =ROUND(0.1*$E$3,0) -> 2000000
A20: 10 | B20: =ROUND(0.1*$C$3,0) -> 200000 | C20: =ROUND(0.1*$D$3,0) -> 750000 | D20: =ROUND(0.1*$E$3,0) -> 2000000
A21: 11 | B21: =ROUND(0.1*$C$3,0) -> 200000 | C21: =ROUND(0.1*$D$3,0) -> 750000 | D21: =ROUND(0.1*$E$3,0) -> 2000000
A22: 12 | B22: =ROUND(0.1*$C$3,0) -> 200000 | C22: =ROUND(0.1*$D$3,0) -> 750000 | D22: =ROUND(0.1*$E$3,0) -> 2000000
A23: 13 | B23: =ROUND(0.1*$C$3,0) -> 200000 | C23: =ROUND(0.1*$D$3,0) -> 750000 | D23: =ROUND(0.1*$E$3,0) -> 2000000
A24: 14 | B24: =ROUND(0.1*$C$3,0) -> 200000 | C24: =ROUND(0.1*$D$3,0) -> 750000 | D24: =ROUND(0.1*$E$3,0) -> 2000000
A25: 15 | B25: =ROUND(0.1*$C$3,0) -> 200000 | C25: =ROUND(0.1*$D$3,0) -> 750000 | D25: =ROUND(0.1*$E$3,0) -> 2000000
A27: TRADE-BY-TRADE LEDGER — 15 years × calls; even call # = year end (expense applied)
A28: Call # | B28: Year | C28: ="BULL "&IF($C$3>=10000000,"₹"&TEXT($C$3/10000000,"0.##")&"Cr","₹"&TEXT($C$3/100000,"0.##")&"L") -> BULL ₹20.L | D28: ="BULL "&IF($D$3>=10000000,"₹"&TEXT($D$3/10000000,"0.##")&"Cr","₹"&TEXT($D$3/100000,"0.##")&"L") -> BULL ₹75.L | E28: ="BULL "&IF($E$3>=10000000,"₹"&TEXT($E$3/10000000,"0.##")&"Cr","₹"&TEXT($E$3/100000,"0.##")&"L") -> BULL ₹2.Cr | F28: ="BASE "&IF($C$3>=10000000,"₹"&TEXT($C$3/10000000,"0.##")&"Cr","₹"&TEXT($C$3/100000,"0.##")&"L") -> BASE ₹20.L | G28: ="BASE "&IF($D$3>=10000000,"₹"&TEXT($D$3/10000000,"0.##")&"Cr","₹"&TEXT($D$3/100000,"0.##")&"L") -> BASE ₹75.L | H28: ="BASE "&IF($E$3>=10000000,"₹"&TEXT($E$3/10000000,"0.##")&"Cr","₹"&TEXT($E$3/100000,"0.##")&"L") -> BASE ₹2.Cr | I28: ="BEAR "&IF($C$3>=10000000,"₹"&TEXT($C$3/10000000,"0.##")&"Cr","₹"&TEXT($C$3/100000,"0.##")&"L") -> BEAR ₹20.L | J28: ="BEAR "&IF($D$3>=10000000,"₹"&TEXT($D$3/10000000,"0.##")&"Cr","₹"&TEXT($D$3/100000,"0.##")&"L") -> BEAR ₹75.L | K28: ="BEAR "&IF($E$3>=10000000,"₹"&TEXT($E$3/10000000,"0.##")&"Cr","₹"&TEXT($E$3/100000,"0.##")&"L") -> BEAR ₹2.Cr
A29: 1 | B29: =ROUNDUP(A29/2,0) -> 1 | C29: =$C$3+IF(OR($D$5=2,MOD(A29,2)=1),1,0)*(MIN('Engine Inputs'!$B$12*$C$3/$C$5,'Engine Inputs'!$B$9)*($B$5-'Engine Inputs'!$B$5-'Engine Inputs'!$B$6-2*'Engine Inputs'!$B$7*SQRT(MIN('Engine Inputs'!$B$12*$C$3/$C$5,'Engine Inputs'!$B$9)/'Engine Inputs'!$B$8))+MAX($C$3-MIN('Engine Inputs'!$B$12*$C$3/$C$5,'Engine Inputs'!$B$9)*$C$5,0)*'Engine Inputs'!$B$10/$D$5)*(1-'Engine Inputs'!$B$4)+IF($D$5=1,(1-IF(OR($D$5=2,MOD(A29,2)=1),1,0))*$C$3*'Engine Inputs'!$B$10*(1-'Engine Inputs'!$B$4)/2,0)-IF(MOD(A29,2)=0,INDEX($B$11:$D$25,B29,1)*(1-'Engine Inputs'!$B$4),0) -> 3698695 | D29: =$D$3+IF(OR($D$5=2,MOD(A29,2)=1),1,0)*(MIN('Engine Inputs'!$B$12*$D$3/$C$5,'Engine Inputs'!$B$9)*($B$5-'Engine Inputs'!$B$5-'Engine Inputs'!$B$6-2*'Engine Inputs'!$B$7*SQRT(MIN('Engine Inputs'!$B$12*$D$3/$C$5,'Engine Inputs'!$B$9)/'Engine Inputs'!$B$8))+MAX($D$3-MIN('Engine Inputs'!$B$12*$D$3/$C$5,'Engine Inputs'!$B$9)*$C$5,0)*'Engine Inputs'!$B$10/$D$5)*(1-'Engine Inputs'!$B$4)+IF($D$5=1,(1-IF(OR($D$5=2,MOD(A29,2)=1),1,0))*$D$3*'Engine Inputs'!$B$10*(1-'Engine Inputs'!$B$4)/2,0)-IF(MOD(A29,2)=0,INDEX($B$11:$D$25,B29,2)*(1-'Engine Inputs'!$B$4),0) -> 13853833 | E29: =$E$3+IF(OR($D$5=2,MOD(A29,2)=1),1,0)*(MIN('Engine Inputs'!$B$12*$E$3/$C$5,'Engine Inputs'!$B$9)*($B$5-'Engine Inputs'!$B$5-'Engine Inputs'!$B$6-2*'Engine Inputs'!$B$7*SQRT(MIN('Engine Inputs'!$B$12*$E$3/$C$5,'Engine Inputs'!$B$9)/'Engine Inputs'!$B$8))+MAX($E$3-MIN('Engine Inputs'!$B$12*$E$3/$C$5,'Engine Inputs'!$B$9)*$C$5,0)*'Engine Inputs'!$B$10/$D$5)*(1-'Engine Inputs'!$B$4)+IF($D$5=1,(1-IF(OR($D$5=2,MOD(A29,2)=1),1,0))*$E$3*'Engine Inputs'!$B$10*(1-'Engine Inputs'!$B$4)/2,0)-IF(MOD(A29,2)=0,INDEX($B$11:$D$25,B29,3)*(1-'Engine Inputs'!$B$4),0) -> 36886754 | F29: =$C$3+IF(OR($D$6=2,MOD(A29,2)=1),1,0)*(MIN('Engine Inputs'!$B$12*$C$3/$C$6,'Engine Inputs'!$B$9)*($B$6-'Engine Inputs'!$B$5-'Engine Inputs'!$B$6-2*'Engine Inputs'!$B$7*SQRT(MIN('Engine Inputs'!$B$12*$C$3/$C$6,'Engine Inputs'!$B$9)/'Engine Inputs'!$B$8))+MAX($C$3-MIN('Engine Inputs'!$B$12*$C$3/$C$6,'Engine Inputs'!$B$9)*$C$6,0)*'Engine Inputs'!$B$10/$D$6)*(1-'Engine Inputs'!$B$4)+IF($D$6=1,(1-IF(OR($D$6=2,MOD(A29,2)=1),1,0))*$C$3*'Engine Inputs'!$B$10*(1-'Engine Inputs'!$B$4)/2,0)-IF(MOD(A29,2)=0,INDEX($B$11:$D$25,B29,1)*(1-'Engine Inputs'!$B$4),0) -> 2952763.6 | G29: =$D$3+IF(OR($D$6=2,MOD(A29,2)=1),1,0)*(MIN('Engine Inputs'!$B$12*$D$3/$C$6,'Engine Inputs'!$B$9)*($B$6-'Engine Inputs'!$B$5-'Engine Inputs'!$B$6-2*'Engine Inputs'!$B$7*SQRT(MIN('Engine Inputs'!$B$12*$D$3/$C$6,'Engine Inputs'!$B$9)/'Engine Inputs'!$B$8))+MAX($D$3-MIN('Engine Inputs'!$B$12*$D$3/$C$6,'Engine Inputs'!$B$9)*$C$6,0)*'Engine Inputs'!$B$10/$D$6)*(1-'Engine Inputs'!$B$4)+IF($D$6=1,(1-IF(OR($D$6=2,MOD(A29,2)=1),1,0))*$D$3*'Engine Inputs'!$B$10*(1-'Engine Inputs'!$B$4)/2,0)-IF(MOD(A29,2)=0,INDEX($B$11:$D$25,B29,2)*(1-'Engine Inputs'!$B$4),0) -> 11057832 | H29: =$E$3+IF(OR($D$6=2,MOD(A29,2)=1),1,0)*(MIN('Engine Inputs'!$B$12*$E$3/$C$6,'Engine Inputs'!$B$9)*($B$6-'Engine Inputs'!$B$5-'Engine Inputs'!$B$6-2*'Engine Inputs'!$B$7*SQRT(MIN('Engine Inputs'!$B$12*$E$3/$C$6,'Engine Inputs'!$B$9)/'Engine Inputs'!$B$8))+MAX($E$3-MIN('Engine Inputs'!$B$12*$E$3/$C$6,'Engine Inputs'!$B$9)*$C$6,0)*'Engine Inputs'!$B$10/$D$6)*(1-'Engine Inputs'!$B$4)+IF($D$6=1,(1-IF(OR($D$6=2,MOD(A29,2)=1),1,0))*$E$3*'Engine Inputs'!$B$10*(1-'Engine Inputs'!$B$4)/2,0)-IF(MOD(A29,2)=0,INDEX($B$11:$D$25,B29,3)*(1-'Engine Inputs'!$B$4),0) -> 29435083 | I29: =$C$3+IF(OR($D$7=2,MOD(A29,2)=1),1,0)*(MIN('Engine Inputs'!$B$12*$C$3/$C$7,'Engine Inputs'!$B$9)*($B$7-'Engine Inputs'!$B$5-'Engine Inputs'!$B$6-2*'Engine Inputs'!$B$7*SQRT(MIN('Engine Inputs'!$B$12*$C$3/$C$7,'Engine Inputs'!$B$9)/'Engine Inputs'!$B$8))+MAX($C$3-MIN('Engine Inputs'!$B$12*$C$3/$C$7,'Engine Inputs'!$B$9)*$C$7,0)*'Engine Inputs'!$B$10/$D$7)*(1-'Engine Inputs'!$B$4)+IF($D$7=1,(1-IF(OR($D$7=2,MOD(A29,2)=1),1,0))*$C$3*'Engine Inputs'!$B$10*(1-'Engine Inputs'!$B$4)/2,0)-IF(MOD(A29,2)=0,INDEX($B$11:$D$25,B29,1)*(1-'Engine Inputs'!$B$4),0) -> 2767723.9 | J29: =$D$3+IF(OR($D$7=2,MOD(A29,2)=1),1,0)*(MIN('Engine Inputs'!$B$12*$D$3/$C$7,'Engine Inputs'!$B$9)*($B$7-'Engine Inputs'!$B$5-'Engine Inputs'!$B$6-2*'Engine Inputs'!$B$7*SQRT(MIN('Engine Inputs'!$B$12*$D$3/$C$7,'Engine Inputs'!$B$9)/'Engine Inputs'!$B$8))+MAX($D$3-MIN('Engine Inputs'!$B$12*$D$3/$C$7,'Engine Inputs'!$B$9)*$C$7,0)*'Engine Inputs'!$B$10/$D$7)*(1-'Engine Inputs'!$B$4)+IF($D$7=1,(1-IF(OR($D$7=2,MOD(A29,2)=1),1,0))*$D$3*'Engine Inputs'!$B$10*(1-'Engine Inputs'!$B$4)/2,0)-IF(MOD(A29,2)=0,INDEX($B$11:$D$25,B29,2)*(1-'Engine Inputs'!$B$4),0) -> 10364515 | K29: =$E$3+IF(OR($D$7=2,MOD(A29,2)=1),1,0)*(MIN('Engine Inputs'!$B$12*$E$3/$C$7,'Engine Inputs'!$B$9)*($B$7-'Engine Inputs'!$B$5-'Engine Inputs'!$B$6-2*'Engine Inputs'!$B$7*SQRT(MIN('Engine Inputs'!$B$12*$E$3/$C$7,'Engine Inputs'!$B$9)/'Engine Inputs'!$B$8))+MAX($E$3-MIN('Engine Inputs'!$B$12*$E$3/$C$7,'Engine Inputs'!$B$9)*$C$7,0)*'Engine Inputs'!$B$10/$D$7)*(1-'Engine Inputs'!$B$4)+IF($D$7=1,(1-IF(OR($D$7=2,MOD(A29,2)=1),1,0))*$E$3*'Engine Inputs'!$B$10*(1-'Engine Inputs'!$B$4)/2,0)-IF(MOD(A29,2)=0,INDEX($B$11:$D$25,B29,3)*(1-'Engine Inputs'!$B$4),0) -> 27588268
A30: 2 | B30: =ROUNDUP(A30/2,0) -> 1 | C30: =C29+IF(OR($D$5=2,MOD(A30,2)=1),1,0)*(MIN('Engine Inputs'!$B$12*C29/$C$5,'Engine Inputs'!$B$9)*($B$5-'Engine Inputs'!$B$5-'Engine Inputs'!$B$6-2*'Engine Inputs'!$B$7*SQRT(MIN('Engine Inputs'!$B$12*C29/$C$5,'Engine Inputs'!$B$9)/'Engine Inputs'!$B$8))+MAX(C29-MIN('Engine Inputs'!$B$12*C29/$C$5,'Engine Inputs'!$B$9)*$C$5,0)*'Engine Inputs'!$B$10/$D$5)*(1-'Engine Inputs'!$B$4)+IF($D$5=1,(1-IF(OR($D$5=2,MOD(A30,2)=1),1,0))*C29*'Engine Inputs'!$B$10*(1-'Engine Inputs'!$B$4)/2,0)-IF(MOD(A30,2)=0,INDEX($B$11:$D$25,B30,1)*(1-'Engine Inputs'!$B$4),0) -> 6822121.6 | D30: =D29+IF(OR($D$5=2,MOD(A30,2)=1),1,0)*(MIN('Engine Inputs'!$B$12*D29/$C$5,'Engine Inputs'!$B$9)*($B$5-'Engine Inputs'!$B$5-'Engine Inputs'!$B$6-2*'Engine Inputs'!$B$7*SQRT(MIN('Engine Inputs'!$B$12*D29/$C$5,'Engine Inputs'!$B$9)/'Engine Inputs'!$B$8))+MAX(D29-MIN('Engine Inputs'!$B$12*D29/$C$5,'Engine Inputs'!$B$9)*$C$5,0)*'Engine Inputs'!$B$10/$D$5)*(1-'Engine Inputs'!$B$4)+IF($D$5=1,(1-IF(OR($D$5=2,MOD(A30,2)=1),1,0))*D29*'Engine Inputs'!$B$10*(1-'Engine Inputs'!$B$4)/2,0)-IF(MOD(A30,2)=0,INDEX($B$11:$D$25,B30,2)*(1-'Engine Inputs'!$B$4),0) -> 25512046 | E30: =E29+IF(OR($D$5=2,MOD(A30,2)=1),1,0)*(MIN('Engine Inputs'!$B$12*E29/$C$5,'Engine Inputs'!$B$9)*($B$5-'Engine Inputs'!$B$5-'Engine Inputs'!$B$6-2*'Engine Inputs'!$B$7*SQRT(MIN('Engine Inputs'!$B$12*E29/$C$5,'Engine Inputs'!$B$9)/'Engine Inputs'!$B$8))+MAX(E29-MIN('Engine Inputs'!$B$12*E29/$C$5,'Engine Inputs'!$B$9)*$C$5,0)*'Engine Inputs'!$B$10/$D$5)*(1-'Engine Inputs'!$B$4)+IF($D$5=1,(1-IF(OR($D$5=2,MOD(A30,2)=1),1,0))*E29*'Engine Inputs'!$B$10*(1-'Engine Inputs'!$B$4)/2,0)-IF(MOD(A30,2)=0,INDEX($B$11:$D$25,B30,3)*(1-'Engine Inputs'!$B$4),0) -> 67785195 | F30: =F29+IF(OR($D$6=2,MOD(A30,2)=1),1,0)*(MIN('Engine Inputs'!$B$12*F29/$C$6,'Engine Inputs'!$B$9)*($B$6-'Engine Inputs'!$B$5-'Engine Inputs'!$B$6-2*'Engine Inputs'!$B$7*SQRT(MIN('Engine Inputs'!$B$12*F29/$C$6,'Engine Inputs'!$B$9)/'Engine Inputs'!$B$8))+MAX(F29-MIN('Engine Inputs'!$B$12*F29/$C$6,'Engine Inputs'!$B$9)*$C$6,0)*'Engine Inputs'!$B$10/$D$6)*(1-'Engine Inputs'!$B$4)+IF($D$6=1,(1-IF(OR($D$6=2,MOD(A30,2)=1),1,0))*F29*'Engine Inputs'!$B$10*(1-'Engine Inputs'!$B$4)/2,0)-IF(MOD(A30,2)=0,INDEX($B$11:$D$25,B30,1)*(1-'Engine Inputs'!$B$4),0) -> 4343080.9 | G30: =G29+IF(OR($D$6=2,MOD(A30,2)=1),1,0)*(MIN('Engine Inputs'!$B$12*G29/$C$6,'Engine Inputs'!$B$9)*($B$6-'Engine Inputs'!$B$5-'Engine Inputs'!$B$6-2*'Engine Inputs'!$B$7*SQRT(MIN('Engine Inputs'!$B$12*G29/$C$6,'Engine Inputs'!$B$9)/'Engine Inputs'!$B$8))+MAX(G29-MIN('Engine Inputs'!$B$12*G29/$C$6,'Engine Inputs'!$B$9)*$C$6,0)*'Engine Inputs'!$B$10/$D$6)*(1-'Engine Inputs'!$B$4)+IF($D$6=1,(1-IF(OR($D$6=2,MOD(A30,2)=1),1,0))*G29*'Engine Inputs'!$B$10*(1-'Engine Inputs'!$B$4)/2,0)-IF(MOD(A30,2)=0,INDEX($B$11:$D$25,B30,2)*(1-'Engine Inputs'!$B$4),0) -> 16237476 | H30: =H29+IF(OR($D$6=2,MOD(A30,2)=1),1,0)*(MIN('Engine Inputs'!$B$12*H29/$C$6,'Engine Inputs'!$B$9)*($B$6-'Engine Inputs'!$B$5-'Engine Inputs'!$B$6-2*'Engine Inputs'!$B$7*SQRT(MIN('Engine Inputs'!$B$12*H29/$C$6,'Engine Inputs'!$B$9)/'Engine Inputs'!$B$8))+MAX(H29-MIN('Engine Inputs'!$B$12*H29/$C$6,'Engine Inputs'!$B$9)*$C$6,0)*'Engine Inputs'!$B$10/$D$6)*(1-'Engine Inputs'!$B$4)+IF($D$6=1,(1-IF(OR($D$6=2,MOD(A30,2)=1),1,0))*H29*'Engine Inputs'!$B$10*(1-'Engine Inputs'!$B$4)/2,0)-IF(MOD(A30,2)=0,INDEX($B$11:$D$25,B30,3)*(1-'Engine Inputs'!$B$4),0) -> 43129079 | I30: =I29+IF(OR($D$7=2,MOD(A30,2)=1),1,0)*(MIN('Engine Inputs'!$B$12*I29/$C$7,'Engine Inputs'!$B$9)*($B$7-'Engine Inputs'!$B$5-'Engine Inputs'!$B$6-2*'Engine Inputs'!$B$7*SQRT(MIN('Engine Inputs'!$B$12*I29/$C$7,'Engine Inputs'!$B$9)/'Engine Inputs'!$B$8))+MAX(I29-MIN('Engine Inputs'!$B$12*I29/$C$7,'Engine Inputs'!$B$9)*$C$7,0)*'Engine Inputs'!$B$10/$D$7)*(1-'Engine Inputs'!$B$4)+IF($D$7=1,(1-IF(OR($D$7=2,MOD(A30,2)=1),1,0))*I29*'Engine Inputs'!$B$10*(1-'Engine Inputs'!$B$4)/2,0)-IF(MOD(A30,2)=0,INDEX($B$11:$D$25,B30,1)*(1-'Engine Inputs'!$B$4),0) -> 2820069.7 | J30: =J29+IF(OR($D$7=2,MOD(A30,2)=1),1,0)*(MIN('Engine Inputs'!$B$12*J29/$C$7,'Engine Inputs'!$B$9)*($B$7-'Engine Inputs'!$B$5-'Engine Inputs'!$B$6-2*'Engine Inputs'!$B$7*SQRT(MIN('Engine Inputs'!$B$12*J29/$C$7,'Engine Inputs'!$B$9)/'Engine Inputs'!$B$8))+MAX(J29-MIN('Engine Inputs'!$B$12*J29/$C$7,'Engine Inputs'!$B$9)*$C$7,0)*'Engine Inputs'!$B$10/$D$7)*(1-'Engine Inputs'!$B$4)+IF($D$7=1,(1-IF(OR($D$7=2,MOD(A30,2)=1),1,0))*J29*'Engine Inputs'!$B$10*(1-'Engine Inputs'!$B$4)/2,0)-IF(MOD(A30,2)=0,INDEX($B$11:$D$25,B30,2)*(1-'Engine Inputs'!$B$4),0) -> 10560460 | K30: =K29+IF(OR($D$7=2,MOD(A30,2)=1),1,0)*(MIN('Engine Inputs'!$B$12*K29/$C$7,'Engine Inputs'!$B$9)*($B$7-'Engine Inputs'!$B$5-'Engine Inputs'!$B$6-2*'Engine Inputs'!$B$7*SQRT(MIN('Engine Inputs'!$B$12*K29/$C$7,'Engine Inputs'!$B$9)/'Engine Inputs'!$B$8))+MAX(K29-MIN('Engine Inputs'!$B$12*K29/$C$7,'Engine Inputs'!$B$9)*$C$7,0)*'Engine Inputs'!$B$10/$D$7)*(1-'Engine Inputs'!$B$4)+IF($D$7=1,(1-IF(OR($D$7=2,MOD(A30,2)=1),1,0))*K29*'Engine Inputs'!$B$10*(1-'Engine Inputs'!$B$4)/2,0)-IF(MOD(A30,2)=0,INDEX($B$11:$D$25,B30,3)*(1-'Engine Inputs'!$B$4),0) -> 28109562
A31: 3 | B31: =ROUNDUP(A31/2,0) -> 2 | C31: =C30+IF(OR($D$5=2,MOD(A31,2)=1),1,0)*(MIN('Engine Inputs'!$B$12*C30/$C$5,'Engine Inputs'!$B$9)*($B$5-'Engine Inputs'!$B$5-'Engine Inputs'!$B$6-2*'Engine Inputs'!$B$7*SQRT(MIN('Engine Inputs'!$B$12*C30/$C$5,'Engine Inputs'!$B$9)/'Engine Inputs'!$B$8))+MAX(C30-MIN('Engine Inputs'!$B$12*C30/$C$5,'Engine Inputs'!$B$9)*$C$5,0)*'Engine Inputs'!$B$10/$D$5)*(1-'Engine Inputs'!$B$4)+IF($D$5=1,(1-IF(OR($D$5=2,MOD(A31,2)=1),1,0))*C30*'Engine Inputs'!$B$10*(1-'Engine Inputs'!$B$4)/2,0)-IF(MOD(A31,2)=0,INDEX($B$11:$D$25,B31,1)*(1-'Engine Inputs'!$B$4),0) -> 12603087 | D31: =D30+IF(OR($D$5=2,MOD(A31,2)=1),1,0)*(MIN('Engine Inputs'!$B$12*D30/$C$5,'Engine Inputs'!$B$9)*($B$5-'Engine Inputs'!$B$5-'Engine Inputs'!$B$6-2*'Engine Inputs'!$B$7*SQRT(MIN('Engine Inputs'!$B$12*D30/$C$5,'Engine Inputs'!$B$9)/'Engine Inputs'!$B$8))+MAX(D30-MIN('Engine Inputs'!$B$12*D30/$C$5,'Engine Inputs'!$B$9)*$C$5,0)*'Engine Inputs'!$B$10/$D$5)*(1-'Engine Inputs'!$B$4)+IF($D$5=1,(1-IF(OR($D$5=2,MOD(A31,2)=1),1,0))*D30*'Engine Inputs'!$B$10*(1-'Engine Inputs'!$B$4)/2,0)-IF(MOD(A31,2)=0,INDEX($B$11:$D$25,B31,2)*(1-'Engine Inputs'!$B$4),0) -> 47028635 | E31: =E30+IF(OR($D$5=2,MOD(A31,2)=1),1,0)*(MIN('Engine Inputs'!$B$12*E30/$C$5,'Engine Inputs'!$B$9)*($B$5-'Engine Inputs'!$B$5-'Engine Inputs'!$B$6-2*'Engine Inputs'!$B$7*SQRT(MIN('Engine Inputs'!$B$12*E30/$C$5,'Engine Inputs'!$B$9)/'Engine Inputs'!$B$8))+MAX(E30-MIN('Engine Inputs'!$B$12*E30/$C$5,'Engine Inputs'!$B$9)*$C$5,0)*'Engine Inputs'!$B$10/$D$5)*(1-'Engine Inputs'!$B$4)+IF($D$5=1,(1-IF(OR($D$5=2,MOD(A31,2)=1),1,0))*E30*'Engine Inputs'!$B$10*(1-'Engine Inputs'!$B$4)/2,0)-IF(MOD(A31,2)=0,INDEX($B$11:$D$25,B31,3)*(1-'Engine Inputs'!$B$4),0) -> 1.2460112e+08 | F31: =F30+IF(OR($D$6=2,MOD(A31,2)=1),1,0)*(MIN('Engine Inputs'!$B$12*F30/$C$6,'Engine Inputs'!$B$9)*($B$6-'Engine Inputs'!$B$5-'Engine Inputs'!$B$6-2*'Engine Inputs'!$B$7*SQRT(MIN('Engine Inputs'!$B$12*F30/$C$6,'Engine Inputs'!$B$9)/'Engine Inputs'!$B$8))+MAX(F30-MIN('Engine Inputs'!$B$12*F30/$C$6,'Engine Inputs'!$B$9)*$C$6,0)*'Engine Inputs'!$B$10/$D$6)*(1-'Engine Inputs'!$B$4)+IF($D$6=1,(1-IF(OR($D$6=2,MOD(A31,2)=1),1,0))*F30*'Engine Inputs'!$B$10*(1-'Engine Inputs'!$B$4)/2,0)-IF(MOD(A31,2)=0,INDEX($B$11:$D$25,B31,1)*(1-'Engine Inputs'!$B$4),0) -> 6407643.2 | G31: =G30+IF(OR($D$6=2,MOD(A31,2)=1),1,0)*(MIN('Engine Inputs'!$B$12*G30/$C$6,'Engine Inputs'!$B$9)*($B$6-'Engine Inputs'!$B$5-'Engine Inputs'!$B$6-2*'Engine Inputs'!$B$7*SQRT(MIN('Engine Inputs'!$B$12*G30/$C$6,'Engine Inputs'!$B$9)/'Engine Inputs'!$B$8))+MAX(G30-MIN('Engine Inputs'!$B$12*G30/$C$6,'Engine Inputs'!$B$9)*$C$6,0)*'Engine Inputs'!$B$10/$D$6)*(1-'Engine Inputs'!$B$4)+IF($D$6=1,(1-IF(OR($D$6=2,MOD(A31,2)=1),1,0))*G30*'Engine Inputs'!$B$10*(1-'Engine Inputs'!$B$4)/2,0)-IF(MOD(A31,2)=0,INDEX($B$11:$D$25,B31,2)*(1-'Engine Inputs'!$B$4),0) -> 23908448 | H31: =H30+IF(OR($D$6=2,MOD(A31,2)=1),1,0)*(MIN('Engine Inputs'!$B$12*H30/$C$6,'Engine Inputs'!$B$9)*($B$6-'Engine Inputs'!$B$5-'Engine Inputs'!$B$6-2*'Engine Inputs'!$B$7*SQRT(MIN('Engine Inputs'!$B$12*H30/$C$6,'Engine Inputs'!$B$9)/'Engine Inputs'!$B$8))+MAX(H30-MIN('Engine Inputs'!$B$12*H30/$C$6,'Engine Inputs'!$B$9)*$C$6,0)*'Engine Inputs'!$B$10/$D$6)*(1-'Engine Inputs'!$B$4)+IF($D$6=1,(1-IF(OR($D$6=2,MOD(A31,2)=1),1,0))*H30*'Engine Inputs'!$B$10*(1-'Engine Inputs'!$B$4)/2,0)-IF(MOD(A31,2)=0,INDEX($B$11:$D$25,B31,3)*(1-'Engine Inputs'!$B$4),0) -> 63338655 | I31: =I30+IF(OR($D$7=2,MOD(A31,2)=1),1,0)*(MIN('Engine Inputs'!$B$12*I30/$C$7,'Engine Inputs'!$B$9)*($B$7-'Engine Inputs'!$B$5-'Engine Inputs'!$B$6-2*'Engine Inputs'!$B$7*SQRT(MIN('Engine Inputs'!$B$12*I30/$C$7,'Engine Inputs'!$B$9)/'Engine Inputs'!$B$8))+MAX(I30-MIN('Engine Inputs'!$B$12*I30/$C$7,'Engine Inputs'!$B$9)*$C$7,0)*'Engine Inputs'!$B$10/$D$7)*(1-'Engine Inputs'!$B$4)+IF($D$7=1,(1-IF(OR($D$7=2,MOD(A31,2)=1),1,0))*I30*'Engine Inputs'!$B$10*(1-'Engine Inputs'!$B$4)/2,0)-IF(MOD(A31,2)=0,INDEX($B$11:$D$25,B31,1)*(1-'Engine Inputs'!$B$4),0) -> 3901499.6 | J31: =J30+IF(OR($D$7=2,MOD(A31,2)=1),1,0)*(MIN('Engine Inputs'!$B$12*J30/$C$7,'Engine Inputs'!$B$9)*($B$7-'Engine Inputs'!$B$5-'Engine Inputs'!$B$6-2*'Engine Inputs'!$B$7*SQRT(MIN('Engine Inputs'!$B$12*J30/$C$7,'Engine Inputs'!$B$9)/'Engine Inputs'!$B$8))+MAX(J30-MIN('Engine Inputs'!$B$12*J30/$C$7,'Engine Inputs'!$B$9)*$C$7,0)*'Engine Inputs'!$B$10/$D$7)*(1-'Engine Inputs'!$B$4)+IF($D$7=1,(1-IF(OR($D$7=2,MOD(A31,2)=1),1,0))*J30*'Engine Inputs'!$B$10*(1-'Engine Inputs'!$B$4)/2,0)-IF(MOD(A31,2)=0,INDEX($B$11:$D$25,B31,2)*(1-'Engine Inputs'!$B$4),0) -> 14586020 | K31: =K30+IF(OR($D$7=2,MOD(A31,2)=1),1,0)*(MIN('Engine Inputs'!$B$12*K30/$C$7,'Engine Inputs'!$B$9)*($B$7-'Engine Inputs'!$B$5-'Engine Inputs'!$B$6-2*'Engine Inputs'!$B$7*SQRT(MIN('Engine Inputs'!$B$12*K30/$C$7,'Engine Inputs'!$B$9)/'Engine Inputs'!$B$8))+MAX(K30-MIN('Engine Inputs'!$B$12*K30/$C$7,'Engine Inputs'!$B$9)*$C$7,0)*'Engine Inputs'!$B$10/$D$7)*(1-'Engine Inputs'!$B$4)+IF($D$7=1,(1-IF(OR($D$7=2,MOD(A31,2)=1),1,0))*K30*'Engine Inputs'!$B$10*(1-'Engine Inputs'!$B$4)/2,0)-IF(MOD(A31,2)=0,INDEX($B$11:$D$25,B31,3)*(1-'Engine Inputs'!$B$4),0) -> 38740778
A32: 4 | B32: =ROUNDUP(A32/2,0) -> 2 | C32: =C31+IF(OR($D$5=2,MOD(A32,2)=1),1,0)*(MIN('Engine Inputs'!$B$12*C31/$C$5,'Engine Inputs'!$B$9)*($B$5-'Engine Inputs'!$B$5-'Engine Inputs'!$B$6-2*'Engine Inputs'!$B$7*SQRT(MIN('Engine Inputs'!$B$12*C31/$C$5,'Engine Inputs'!$B$9)/'Engine Inputs'!$B$8))+MAX(C31-MIN('Engine Inputs'!$B$12*C31/$C$5,'Engine Inputs'!$B$9)*$C$5,0)*'Engine Inputs'!$B$10/$D$5)*(1-'Engine Inputs'!$B$4)+IF($D$5=1,(1-IF(OR($D$5=2,MOD(A32,2)=1),1,0))*C31*'Engine Inputs'!$B$10*(1-'Engine Inputs'!$B$4)/2,0)-IF(MOD(A32,2)=0,INDEX($B$11:$D$25,B32,1)*(1-'Engine Inputs'!$B$4),0) -> 23248420 | D32: =D31+IF(OR($D$5=2,MOD(A32,2)=1),1,0)*(MIN('Engine Inputs'!$B$12*D31/$C$5,'Engine Inputs'!$B$9)*($B$5-'Engine Inputs'!$B$5-'Engine Inputs'!$B$6-2*'Engine Inputs'!$B$7*SQRT(MIN('Engine Inputs'!$B$12*D31/$C$5,'Engine Inputs'!$B$9)/'Engine Inputs'!$B$8))+MAX(D31-MIN('Engine Inputs'!$B$12*D31/$C$5,'Engine Inputs'!$B$9)*$C$5,0)*'Engine Inputs'!$B$10/$D$5)*(1-'Engine Inputs'!$B$4)+IF($D$5=1,(1-IF(OR($D$5=2,MOD(A32,2)=1),1,0))*D31*'Engine Inputs'!$B$10*(1-'Engine Inputs'!$B$4)/2,0)-IF(MOD(A32,2)=0,INDEX($B$11:$D$25,B32,2)*(1-'Engine Inputs'!$B$4),0) -> 86496756 | E32: =E31+IF(OR($D$5=2,MOD(A32,2)=1),1,0)*(MIN('Engine Inputs'!$B$12*E31/$C$5,'Engine Inputs'!$B$9)*($B$5-'Engine Inputs'!$B$5-'Engine Inputs'!$B$6-2*'Engine Inputs'!$B$7*SQRT(MIN('Engine Inputs'!$B$12*E31/$C$5,'Engine Inputs'!$B$9)/'Engine Inputs'!$B$8))+MAX(E31-MIN('Engine Inputs'!$B$12*E31/$C$5,'Engine Inputs'!$B$9)*$C$5,0)*'Engine Inputs'!$B$10/$D$5)*(1-'Engine Inputs'!$B$4)+IF($D$5=1,(1-IF(OR($D$5=2,MOD(A32,2)=1),1,0))*E31*'Engine Inputs'!$B$10*(1-'Engine Inputs'!$B$4)/2,0)-IF(MOD(A32,2)=0,INDEX($B$11:$D$25,B32,3)*(1-'Engine Inputs'!$B$4),0) -> 2.2829114e+08 | F32: =F31+IF(OR($D$6=2,MOD(A32,2)=1),1,0)*(MIN('Engine Inputs'!$B$12*F31/$C$6,'Engine Inputs'!$B$9)*($B$6-'Engine Inputs'!$B$5-'Engine Inputs'!$B$6-2*'Engine Inputs'!$B$7*SQRT(MIN('Engine Inputs'!$B$12*F31/$C$6,'Engine Inputs'!$B$9)/'Engine Inputs'!$B$8))+MAX(F31-MIN('Engine Inputs'!$B$12*F31/$C$6,'Engine Inputs'!$B$9)*$C$6,0)*'Engine Inputs'!$B$10/$D$6)*(1-'Engine Inputs'!$B$4)+IF($D$6=1,(1-IF(OR($D$6=2,MOD(A32,2)=1),1,0))*F31*'Engine Inputs'!$B$10*(1-'Engine Inputs'!$B$4)/2,0)-IF(MOD(A32,2)=0,INDEX($B$11:$D$25,B32,1)*(1-'Engine Inputs'!$B$4),0) -> 9434328.8 | G32: =G31+IF(OR($D$6=2,MOD(A32,2)=1),1,0)*(MIN('Engine Inputs'!$B$12*G31/$C$6,'Engine Inputs'!$B$9)*($B$6-'Engine Inputs'!$B$5-'Engine Inputs'!$B$6-2*'Engine Inputs'!$B$7*SQRT(MIN('Engine Inputs'!$B$12*G31/$C$6,'Engine Inputs'!$B$9)/'Engine Inputs'!$B$8))+MAX(G31-MIN('Engine Inputs'!$B$12*G31/$C$6,'Engine Inputs'!$B$9)*$C$6,0)*'Engine Inputs'!$B$10/$D$6)*(1-'Engine Inputs'!$B$4)+IF($D$6=1,(1-IF(OR($D$6=2,MOD(A32,2)=1),1,0))*G31*'Engine Inputs'!$B$10*(1-'Engine Inputs'!$B$4)/2,0)-IF(MOD(A32,2)=0,INDEX($B$11:$D$25,B32,2)*(1-'Engine Inputs'!$B$4),0) -> 35116129 | H32: =H31+IF(OR($D$6=2,MOD(A32,2)=1),1,0)*(MIN('Engine Inputs'!$B$12*H31/$C$6,'Engine Inputs'!$B$9)*($B$6-'Engine Inputs'!$B$5-'Engine Inputs'!$B$6-2*'Engine Inputs'!$B$7*SQRT(MIN('Engine Inputs'!$B$12*H31/$C$6,'Engine Inputs'!$B$9)/'Engine Inputs'!$B$8))+MAX(H31-MIN('Engine Inputs'!$B$12*H31/$C$6,'Engine Inputs'!$B$9)*$C$6,0)*'Engine Inputs'!$B$10/$D$6)*(1-'Engine Inputs'!$B$4)+IF($D$6=1,(1-IF(OR($D$6=2,MOD(A32,2)=1),1,0))*H31*'Engine Inputs'!$B$10*(1-'Engine Inputs'!$B$4)/2,0)-IF(MOD(A32,2)=0,INDEX($B$11:$D$25,B32,3)*(1-'Engine Inputs'!$B$4),0) -> 92735085 | I32: =I31+IF(OR($D$7=2,MOD(A32,2)=1),1,0)*(MIN('Engine Inputs'!$B$12*I31/$C$7,'Engine Inputs'!$B$9)*($B$7-'Engine Inputs'!$B$5-'Engine Inputs'!$B$6-2*'Engine Inputs'!$B$7*SQRT(MIN('Engine Inputs'!$B$12*I31/$C$7,'Engine Inputs'!$B$9)/'Engine Inputs'!$B$8))+MAX(I31-MIN('Engine Inputs'!$B$12*I31/$C$7,'Engine Inputs'!$B$9)*$C$7,0)*'Engine Inputs'!$B$10/$D$7)*(1-'Engine Inputs'!$B$4)+IF($D$7=1,(1-IF(OR($D$7=2,MOD(A32,2)=1),1,0))*I31*'Engine Inputs'!$B$10*(1-'Engine Inputs'!$B$4)/2,0)-IF(MOD(A32,2)=0,INDEX($B$11:$D$25,B32,1)*(1-'Engine Inputs'!$B$4),0) -> 3981419.3 | J32: =J31+IF(OR($D$7=2,MOD(A32,2)=1),1,0)*(MIN('Engine Inputs'!$B$12*J31/$C$7,'Engine Inputs'!$B$9)*($B$7-'Engine Inputs'!$B$5-'Engine Inputs'!$B$6-2*'Engine Inputs'!$B$7*SQRT(MIN('Engine Inputs'!$B$12*J31/$C$7,'Engine Inputs'!$B$9)/'Engine Inputs'!$B$8))+MAX(J31-MIN('Engine Inputs'!$B$12*J31/$C$7,'Engine Inputs'!$B$9)*$C$7,0)*'Engine Inputs'!$B$10/$D$7)*(1-'Engine Inputs'!$B$4)+IF($D$7=1,(1-IF(OR($D$7=2,MOD(A32,2)=1),1,0))*J31*'Engine Inputs'!$B$10*(1-'Engine Inputs'!$B$4)/2,0)-IF(MOD(A32,2)=0,INDEX($B$11:$D$25,B32,2)*(1-'Engine Inputs'!$B$4),0) -> 14884634 | K32: =K31+IF(OR($D$7=2,MOD(A32,2)=1),1,0)*(MIN('Engine Inputs'!$B$12*K31/$C$7,'Engine Inputs'!$B$9)*($B$7-'Engine Inputs'!$B$5-'Engine Inputs'!$B$6-2*'Engine Inputs'!$B$7*SQRT(MIN('Engine Inputs'!$B$12*K31/$C$7,'Engine Inputs'!$B$9)/'Engine Inputs'!$B$8))+MAX(K31-MIN('Engine Inputs'!$B$12*K31/$C$7,'Engine Inputs'!$B$9)*$C$7,0)*'Engine Inputs'!$B$10/$D$7)*(1-'Engine Inputs'!$B$4)+IF($D$7=1,(1-IF(OR($D$7=2,MOD(A32,2)=1),1,0))*K31*'Engine Inputs'!$B$10*(1-'Engine Inputs'!$B$4)/2,0)-IF(MOD(A32,2)=0,INDEX($B$11:$D$25,B32,3)*(1-'Engine Inputs'!$B$4),0) -> 39533305
A33: 5 | B33: =ROUNDUP(A33/2,0) -> 3 | C33: =C32+IF(OR($D$5=2,MOD(A33,2)=1),1,0)*(MIN('Engine Inputs'!$B$12*C32/$C$5,'Engine Inputs'!$B$9)*($B$5-'Engine Inputs'!$B$5-'Engine Inputs'!$B$6-2*'Engine Inputs'!$B$7*SQRT(MIN('Engine Inputs'!$B$12*C32/$C$5,'Engine Inputs'!$B$9)/'Engine Inputs'!$B$8))+MAX(C32-MIN('Engine Inputs'!$B$12*C32/$C$5,'Engine Inputs'!$B$9)*$C$5,0)*'Engine Inputs'!$B$10/$D$5)*(1-'Engine Inputs'!$B$4)+IF($D$5=1,(1-IF(OR($D$5=2,MOD(A33,2)=1),1,0))*C32*'Engine Inputs'!$B$10*(1-'Engine Inputs'!$B$4)/2,0)-IF(MOD(A33,2)=0,INDEX($B$11:$D$25,B33,1)*(1-'Engine Inputs'!$B$4),0) -> 42864624 | D33: =D32+IF(OR($D$5=2,MOD(A33,2)=1),1,0)*(MIN('Engine Inputs'!$B$12*D32/$C$5,'Engine Inputs'!$B$9)*($B$5-'Engine Inputs'!$B$5-'Engine Inputs'!$B$6-2*'Engine Inputs'!$B$7*SQRT(MIN('Engine Inputs'!$B$12*D32/$C$5,'Engine Inputs'!$B$9)/'Engine Inputs'!$B$8))+MAX(D32-MIN('Engine Inputs'!$B$12*D32/$C$5,'Engine Inputs'!$B$9)*$C$5,0)*'Engine Inputs'!$B$10/$D$5)*(1-'Engine Inputs'!$B$4)+IF($D$5=1,(1-IF(OR($D$5=2,MOD(A33,2)=1),1,0))*D32*'Engine Inputs'!$B$10*(1-'Engine Inputs'!$B$4)/2,0)-IF(MOD(A33,2)=0,INDEX($B$11:$D$25,B33,2)*(1-'Engine Inputs'!$B$4),0) -> 1.5884503e+08 | E33: =E32+IF(OR($D$5=2,MOD(A33,2)=1),1,0)*(MIN('Engine Inputs'!$B$12*E32/$C$5,'Engine Inputs'!$B$9)*($B$5-'Engine Inputs'!$B$5-'Engine Inputs'!$B$6-2*'Engine Inputs'!$B$7*SQRT(MIN('Engine Inputs'!$B$12*E32/$C$5,'Engine Inputs'!$B$9)/'Engine Inputs'!$B$8))+MAX(E32-MIN('Engine Inputs'!$B$12*E32/$C$5,'Engine Inputs'!$B$9)*$C$5,0)*'Engine Inputs'!$B$10/$D$5)*(1-'Engine Inputs'!$B$4)+IF($D$5=1,(1-IF(OR($D$5=2,MOD(A33,2)=1),1,0))*E32*'Engine Inputs'!$B$10*(1-'Engine Inputs'!$B$4)/2,0)-IF(MOD(A33,2)=0,INDEX($B$11:$D$25,B33,3)*(1-'Engine Inputs'!$B$4),0) -> 4.1706753e+08 | F33: =F32+IF(OR($D$6=2,MOD(A33,2)=1),1,0)*(MIN('Engine Inputs'!$B$12*F32/$C$6,'Engine Inputs'!$B$9)*($B$6-'Engine Inputs'!$B$5-'Engine Inputs'!$B$6-2*'Engine Inputs'!$B$7*SQRT(MIN('Engine Inputs'!$B$12*F32/$C$6,'Engine Inputs'!$B$9)/'Engine Inputs'!$B$8))+MAX(F32-MIN('Engine Inputs'!$B$12*F32/$C$6,'Engine Inputs'!$B$9)*$C$6,0)*'Engine Inputs'!$B$10/$D$6)*(1-'Engine Inputs'!$B$4)+IF($D$6=1,(1-IF(OR($D$6=2,MOD(A33,2)=1),1,0))*F32*'Engine Inputs'!$B$10*(1-'Engine Inputs'!$B$4)/2,0)-IF(MOD(A33,2)=0,INDEX($B$11:$D$25,B33,1)*(1-'Engine Inputs'!$B$4),0) -> 13905009 | G33: =G32+IF(OR($D$6=2,MOD(A33,2)=1),1,0)*(MIN('Engine Inputs'!$B$12*G32/$C$6,'Engine Inputs'!$B$9)*($B$6-'Engine Inputs'!$B$5-'Engine Inputs'!$B$6-2*'Engine Inputs'!$B$7*SQRT(MIN('Engine Inputs'!$B$12*G32/$C$6,'Engine Inputs'!$B$9)/'Engine Inputs'!$B$8))+MAX(G32-MIN('Engine Inputs'!$B$12*G32/$C$6,'Engine Inputs'!$B$9)*$C$6,0)*'Engine Inputs'!$B$10/$D$6)*(1-'Engine Inputs'!$B$4)+IF($D$6=1,(1-IF(OR($D$6=2,MOD(A33,2)=1),1,0))*G32*'Engine Inputs'!$B$10*(1-'Engine Inputs'!$B$4)/2,0)-IF(MOD(A33,2)=0,INDEX($B$11:$D$25,B33,2)*(1-'Engine Inputs'!$B$4),0) -> 51605053 | H33: =H32+IF(OR($D$6=2,MOD(A33,2)=1),1,0)*(MIN('Engine Inputs'!$B$12*H32/$C$6,'Engine Inputs'!$B$9)*($B$6-'Engine Inputs'!$B$5-'Engine Inputs'!$B$6-2*'Engine Inputs'!$B$7*SQRT(MIN('Engine Inputs'!$B$12*H32/$C$6,'Engine Inputs'!$B$9)/'Engine Inputs'!$B$8))+MAX(H32-MIN('Engine Inputs'!$B$12*H32/$C$6,'Engine Inputs'!$B$9)*$C$6,0)*'Engine Inputs'!$B$10/$D$6)*(1-'Engine Inputs'!$B$4)+IF($D$6=1,(1-IF(OR($D$6=2,MOD(A33,2)=1),1,0))*H32*'Engine Inputs'!$B$10*(1-'Engine Inputs'!$B$4)/2,0)-IF(MOD(A33,2)=0,INDEX($B$11:$D$25,B33,3)*(1-'Engine Inputs'!$B$4),0) -> 1.3575942e+08 | I33: =I32+IF(OR($D$7=2,MOD(A33,2)=1),1,0)*(MIN('Engine Inputs'!$B$12*I32/$C$7,'Engine Inputs'!$B$9)*($B$7-'Engine Inputs'!$B$5-'Engine Inputs'!$B$6-2*'Engine Inputs'!$B$7*SQRT(MIN('Engine Inputs'!$B$12*I32/$C$7,'Engine Inputs'!$B$9)/'Engine Inputs'!$B$8))+MAX(I32-MIN('Engine Inputs'!$B$12*I32/$C$7,'Engine Inputs'!$B$9)*$C$7,0)*'Engine Inputs'!$B$10/$D$7)*(1-'Engine Inputs'!$B$4)+IF($D$7=1,(1-IF(OR($D$7=2,MOD(A33,2)=1),1,0))*I32*'Engine Inputs'!$B$10*(1-'Engine Inputs'!$B$4)/2,0)-IF(MOD(A33,2)=0,INDEX($B$11:$D$25,B33,1)*(1-'Engine Inputs'!$B$4),0) -> 5506368.8 | J33: =J32+IF(OR($D$7=2,MOD(A33,2)=1),1,0)*(MIN('Engine Inputs'!$B$12*J32/$C$7,'Engine Inputs'!$B$9)*($B$7-'Engine Inputs'!$B$5-'Engine Inputs'!$B$6-2*'Engine Inputs'!$B$7*SQRT(MIN('Engine Inputs'!$B$12*J32/$C$7,'Engine Inputs'!$B$9)/'Engine Inputs'!$B$8))+MAX(J32-MIN('Engine Inputs'!$B$12*J32/$C$7,'Engine Inputs'!$B$9)*$C$7,0)*'Engine Inputs'!$B$10/$D$7)*(1-'Engine Inputs'!$B$4)+IF($D$7=1,(1-IF(OR($D$7=2,MOD(A33,2)=1),1,0))*J32*'Engine Inputs'!$B$10*(1-'Engine Inputs'!$B$4)/2,0)-IF(MOD(A33,2)=0,INDEX($B$11:$D$25,B33,2)*(1-'Engine Inputs'!$B$4),0) -> 20545361 | K33: =K32+IF(OR($D$7=2,MOD(A33,2)=1),1,0)*(MIN('Engine Inputs'!$B$12*K32/$C$7,'Engine Inputs'!$B$9)*($B$7-'Engine Inputs'!$B$5-'Engine Inputs'!$B$6-2*'Engine Inputs'!$B$7*SQRT(MIN('Engine Inputs'!$B$12*K32/$C$7,'Engine Inputs'!$B$9)/'Engine Inputs'!$B$8))+MAX(K32-MIN('Engine Inputs'!$B$12*K32/$C$7,'Engine Inputs'!$B$9)*$C$7,0)*'Engine Inputs'!$B$10/$D$7)*(1-'Engine Inputs'!$B$4)+IF($D$7=1,(1-IF(OR($D$7=2,MOD(A33,2)=1),1,0))*K32*'Engine Inputs'!$B$10*(1-'Engine Inputs'!$B$4)/2,0)-IF(MOD(A33,2)=0,INDEX($B$11:$D$25,B33,3)*(1-'Engine Inputs'!$B$4),0) -> 54428364
A34: 6 | B34: =ROUNDUP(A34/2,0) -> 3 | C34: =C33+IF(OR($D$5=2,MOD(A34,2)=1),1,0)*(MIN('Engine Inputs'!$B$12*C33/$C$5,'Engine Inputs'!$B$9)*($B$5-'Engine Inputs'!$B$5-'Engine Inputs'!$B$6-2*'Engine Inputs'!$B$7*SQRT(MIN('Engine Inputs'!$B$12*C33/$C$5,'Engine Inputs'!$B$9)/'Engine Inputs'!$B$8))+MAX(C33-MIN('Engine Inputs'!$B$12*C33/$C$5,'Engine Inputs'!$B$9)*$C$5,0)*'Engine Inputs'!$B$10/$D$5)*(1-'Engine Inputs'!$B$4)+IF($D$5=1,(1-IF(OR($D$5=2,MOD(A34,2)=1),1,0))*C33*'Engine Inputs'!$B$10*(1-'Engine Inputs'!$B$4)/2,0)-IF(MOD(A34,2)=0,INDEX($B$11:$D$25,B34,1)*(1-'Engine Inputs'!$B$4),0) -> 78873710 | D34: =D33+IF(OR($D$5=2,MOD(A34,2)=1),1,0)*(MIN('Engine Inputs'!$B$12*D33/$C$5,'Engine Inputs'!$B$9)*($B$5-'Engine Inputs'!$B$5-'Engine Inputs'!$B$6-2*'Engine Inputs'!$B$7*SQRT(MIN('Engine Inputs'!$B$12*D33/$C$5,'Engine Inputs'!$B$9)/'Engine Inputs'!$B$8))+MAX(D33-MIN('Engine Inputs'!$B$12*D33/$C$5,'Engine Inputs'!$B$9)*$C$5,0)*'Engine Inputs'!$B$10/$D$5)*(1-'Engine Inputs'!$B$4)+IF($D$5=1,(1-IF(OR($D$5=2,MOD(A34,2)=1),1,0))*D33*'Engine Inputs'!$B$10*(1-'Engine Inputs'!$B$4)/2,0)-IF(MOD(A34,2)=0,INDEX($B$11:$D$25,B34,2)*(1-'Engine Inputs'!$B$4),0) -> 2.9070751e+08 | E34: =E33+IF(OR($D$5=2,MOD(A34,2)=1),1,0)*(MIN('Engine Inputs'!$B$12*E33/$C$5,'Engine Inputs'!$B$9)*($B$5-'Engine Inputs'!$B$5-'Engine Inputs'!$B$6-2*'Engine Inputs'!$B$7*SQRT(MIN('Engine Inputs'!$B$12*E33/$C$5,'Engine Inputs'!$B$9)/'Engine Inputs'!$B$8))+MAX(E33-MIN('Engine Inputs'!$B$12*E33/$C$5,'Engine Inputs'!$B$9)*$C$5,0)*'Engine Inputs'!$B$10/$D$5)*(1-'Engine Inputs'!$B$4)+IF($D$5=1,(1-IF(OR($D$5=2,MOD(A34,2)=1),1,0))*E33*'Engine Inputs'!$B$10*(1-'Engine Inputs'!$B$4)/2,0)-IF(MOD(A34,2)=0,INDEX($B$11:$D$25,B34,3)*(1-'Engine Inputs'!$B$4),0) -> 7.5794077e+08 | F34: =F33+IF(OR($D$6=2,MOD(A34,2)=1),1,0)*(MIN('Engine Inputs'!$B$12*F33/$C$6,'Engine Inputs'!$B$9)*($B$6-'Engine Inputs'!$B$5-'Engine Inputs'!$B$6-2*'Engine Inputs'!$B$7*SQRT(MIN('Engine Inputs'!$B$12*F33/$C$6,'Engine Inputs'!$B$9)/'Engine Inputs'!$B$8))+MAX(F33-MIN('Engine Inputs'!$B$12*F33/$C$6,'Engine Inputs'!$B$9)*$C$6,0)*'Engine Inputs'!$B$10/$D$6)*(1-'Engine Inputs'!$B$4)+IF($D$6=1,(1-IF(OR($D$6=2,MOD(A34,2)=1),1,0))*F33*'Engine Inputs'!$B$10*(1-'Engine Inputs'!$B$4)/2,0)-IF(MOD(A34,2)=0,INDEX($B$11:$D$25,B34,1)*(1-'Engine Inputs'!$B$4),0) -> 20442978 | G34: =G33+IF(OR($D$6=2,MOD(A34,2)=1),1,0)*(MIN('Engine Inputs'!$B$12*G33/$C$6,'Engine Inputs'!$B$9)*($B$6-'Engine Inputs'!$B$5-'Engine Inputs'!$B$6-2*'Engine Inputs'!$B$7*SQRT(MIN('Engine Inputs'!$B$12*G33/$C$6,'Engine Inputs'!$B$9)/'Engine Inputs'!$B$8))+MAX(G33-MIN('Engine Inputs'!$B$12*G33/$C$6,'Engine Inputs'!$B$9)*$C$6,0)*'Engine Inputs'!$B$10/$D$6)*(1-'Engine Inputs'!$B$4)+IF($D$6=1,(1-IF(OR($D$6=2,MOD(A34,2)=1),1,0))*G33*'Engine Inputs'!$B$10*(1-'Engine Inputs'!$B$4)/2,0)-IF(MOD(A34,2)=0,INDEX($B$11:$D$25,B34,2)*(1-'Engine Inputs'!$B$4),0) -> 75597884 | H34: =H33+IF(OR($D$6=2,MOD(A34,2)=1),1,0)*(MIN('Engine Inputs'!$B$12*H33/$C$6,'Engine Inputs'!$B$9)*($B$6-'Engine Inputs'!$B$5-'Engine Inputs'!$B$6-2*'Engine Inputs'!$B$7*SQRT(MIN('Engine Inputs'!$B$12*H33/$C$6,'Engine Inputs'!$B$9)/'Engine Inputs'!$B$8))+MAX(H33-MIN('Engine Inputs'!$B$12*H33/$C$6,'Engine Inputs'!$B$9)*$C$6,0)*'Engine Inputs'!$B$10/$D$6)*(1-'Engine Inputs'!$B$4)+IF($D$6=1,(1-IF(OR($D$6=2,MOD(A34,2)=1),1,0))*H33*'Engine Inputs'!$B$10*(1-'Engine Inputs'!$B$4)/2,0)-IF(MOD(A34,2)=0,INDEX($B$11:$D$25,B34,3)*(1-'Engine Inputs'!$B$4),0) -> 1.9795532e+08 | I34: =I33+IF(OR($D$7=2,MOD(A34,2)=1),1,0)*(MIN('Engine Inputs'!$B$12*I33/$C$7,'Engine Inputs'!$B$9)*($B$7-'Engine Inputs'!$B$5-'Engine Inputs'!$B$6-2*'Engine Inputs'!$B$7*SQRT(MIN('Engine Inputs'!$B$12*I33/$C$7,'Engine Inputs'!$B$9)/'Engine Inputs'!$B$8))+MAX(I33-MIN('Engine Inputs'!$B$12*I33/$C$7,'Engine Inputs'!$B$9)*$C$7,0)*'Engine Inputs'!$B$10/$D$7)*(1-'Engine Inputs'!$B$4)+IF($D$7=1,(1-IF(OR($D$7=2,MOD(A34,2)=1),1,0))*I33*'Engine Inputs'!$B$10*(1-'Engine Inputs'!$B$4)/2,0)-IF(MOD(A34,2)=0,INDEX($B$11:$D$25,B34,1)*(1-'Engine Inputs'!$B$4),0) -> 5602869.8 | J34: =J33+IF(OR($D$7=2,MOD(A34,2)=1),1,0)*(MIN('Engine Inputs'!$B$12*J33/$C$7,'Engine Inputs'!$B$9)*($B$7-'Engine Inputs'!$B$5-'Engine Inputs'!$B$6-2*'Engine Inputs'!$B$7*SQRT(MIN('Engine Inputs'!$B$12*J33/$C$7,'Engine Inputs'!$B$9)/'Engine Inputs'!$B$8))+MAX(J33-MIN('Engine Inputs'!$B$12*J33/$C$7,'Engine Inputs'!$B$9)*$C$7,0)*'Engine Inputs'!$B$10/$D$7)*(1-'Engine Inputs'!$B$4)+IF($D$7=1,(1-IF(OR($D$7=2,MOD(A34,2)=1),1,0))*J33*'Engine Inputs'!$B$10*(1-'Engine Inputs'!$B$4)/2,0)-IF(MOD(A34,2)=0,INDEX($B$11:$D$25,B34,2)*(1-'Engine Inputs'!$B$4),0) -> 20904722 | K34: =K33+IF(OR($D$7=2,MOD(A34,2)=1),1,0)*(MIN('Engine Inputs'!$B$12*K33/$C$7,'Engine Inputs'!$B$9)*($B$7-'Engine Inputs'!$B$5-'Engine Inputs'!$B$6-2*'Engine Inputs'!$B$7*SQRT(MIN('Engine Inputs'!$B$12*K33/$C$7,'Engine Inputs'!$B$9)/'Engine Inputs'!$B$8))+MAX(K33-MIN('Engine Inputs'!$B$12*K33/$C$7,'Engine Inputs'!$B$9)*$C$7,0)*'Engine Inputs'!$B$10/$D$7)*(1-'Engine Inputs'!$B$4)+IF($D$7=1,(1-IF(OR($D$7=2,MOD(A34,2)=1),1,0))*K33*'Engine Inputs'!$B$10*(1-'Engine Inputs'!$B$4)/2,0)-IF(MOD(A34,2)=0,INDEX($B$11:$D$25,B34,3)*(1-'Engine Inputs'!$B$4),0) -> 55377923
A35: 7 | B35: =ROUNDUP(A35/2,0) -> 4 | C35: =C34+IF(OR($D$5=2,MOD(A35,2)=1),1,0)*(MIN('Engine Inputs'!$B$12*C34/$C$5,'Engine Inputs'!$B$9)*($B$5-'Engine Inputs'!$B$5-'Engine Inputs'!$B$6-2*'Engine Inputs'!$B$7*SQRT(MIN('Engine Inputs'!$B$12*C34/$C$5,'Engine Inputs'!$B$9)/'Engine Inputs'!$B$8))+MAX(C34-MIN('Engine Inputs'!$B$12*C34/$C$5,'Engine Inputs'!$B$9)*$C$5,0)*'Engine Inputs'!$B$10/$D$5)*(1-'Engine Inputs'!$B$4)+IF($D$5=1,(1-IF(OR($D$5=2,MOD(A35,2)=1),1,0))*C34*'Engine Inputs'!$B$10*(1-'Engine Inputs'!$B$4)/2,0)-IF(MOD(A35,2)=0,INDEX($B$11:$D$25,B35,1)*(1-'Engine Inputs'!$B$4),0) -> 1.4490003e+08 | D35: =D34+IF(OR($D$5=2,MOD(A35,2)=1),1,0)*(MIN('Engine Inputs'!$B$12*D34/$C$5,'Engine Inputs'!$B$9)*($B$5-'Engine Inputs'!$B$5-'Engine Inputs'!$B$6-2*'Engine Inputs'!$B$7*SQRT(MIN('Engine Inputs'!$B$12*D34/$C$5,'Engine Inputs'!$B$9)/'Engine Inputs'!$B$8))+MAX(D34-MIN('Engine Inputs'!$B$12*D34/$C$5,'Engine Inputs'!$B$9)*$C$5,0)*'Engine Inputs'!$B$10/$D$5)*(1-'Engine Inputs'!$B$4)+IF($D$5=1,(1-IF(OR($D$5=2,MOD(A35,2)=1),1,0))*D34*'Engine Inputs'!$B$10*(1-'Engine Inputs'!$B$4)/2,0)-IF(MOD(A35,2)=0,INDEX($B$11:$D$25,B35,2)*(1-'Engine Inputs'!$B$4),0) -> 5.3017233e+08 | E35: =E34+IF(OR($D$5=2,MOD(A35,2)=1),1,0)*(MIN('Engine Inputs'!$B$12*E34/$C$5,'Engine Inputs'!$B$9)*($B$5-'Engine Inputs'!$B$5-'Engine Inputs'!$B$6-2*'Engine Inputs'!$B$7*SQRT(MIN('Engine Inputs'!$B$12*E34/$C$5,'Engine Inputs'!$B$9)/'Engine Inputs'!$B$8))+MAX(E34-MIN('Engine Inputs'!$B$12*E34/$C$5,'Engine Inputs'!$B$9)*$C$5,0)*'Engine Inputs'!$B$10/$D$5)*(1-'Engine Inputs'!$B$4)+IF($D$5=1,(1-IF(OR($D$5=2,MOD(A35,2)=1),1,0))*E34*'Engine Inputs'!$B$10*(1-'Engine Inputs'!$B$4)/2,0)-IF(MOD(A35,2)=0,INDEX($B$11:$D$25,B35,3)*(1-'Engine Inputs'!$B$4),0) -> 1.369266e+09 | F35: =F34+IF(OR($D$6=2,MOD(A35,2)=1),1,0)*(MIN('Engine Inputs'!$B$12*F34/$C$6,'Engine Inputs'!$B$9)*($B$6-'Engine Inputs'!$B$5-'Engine Inputs'!$B$6-2*'Engine Inputs'!$B$7*SQRT(MIN('Engine Inputs'!$B$12*F34/$C$6,'Engine Inputs'!$B$9)/'Engine Inputs'!$B$8))+MAX(F34-MIN('Engine Inputs'!$B$12*F34/$C$6,'Engine Inputs'!$B$9)*$C$6,0)*'Engine Inputs'!$B$10/$D$6)*(1-'Engine Inputs'!$B$4)+IF($D$6=1,(1-IF(OR($D$6=2,MOD(A35,2)=1),1,0))*F34*'Engine Inputs'!$B$10*(1-'Engine Inputs'!$B$4)/2,0)-IF(MOD(A35,2)=0,INDEX($B$11:$D$25,B35,1)*(1-'Engine Inputs'!$B$4),0) -> 30085514 | G35: =G34+IF(OR($D$6=2,MOD(A35,2)=1),1,0)*(MIN('Engine Inputs'!$B$12*G34/$C$6,'Engine Inputs'!$B$9)*($B$6-'Engine Inputs'!$B$5-'Engine Inputs'!$B$6-2*'Engine Inputs'!$B$7*SQRT(MIN('Engine Inputs'!$B$12*G34/$C$6,'Engine Inputs'!$B$9)/'Engine Inputs'!$B$8))+MAX(G34-MIN('Engine Inputs'!$B$12*G34/$C$6,'Engine Inputs'!$B$9)*$C$6,0)*'Engine Inputs'!$B$10/$D$6)*(1-'Engine Inputs'!$B$4)+IF($D$6=1,(1-IF(OR($D$6=2,MOD(A35,2)=1),1,0))*G34*'Engine Inputs'!$B$10*(1-'Engine Inputs'!$B$4)/2,0)-IF(MOD(A35,2)=0,INDEX($B$11:$D$25,B35,2)*(1-'Engine Inputs'!$B$4),0) -> 1.1077842e+08 | H35: =H34+IF(OR($D$6=2,MOD(A35,2)=1),1,0)*(MIN('Engine Inputs'!$B$12*H34/$C$6,'Engine Inputs'!$B$9)*($B$6-'Engine Inputs'!$B$5-'Engine Inputs'!$B$6-2*'Engine Inputs'!$B$7*SQRT(MIN('Engine Inputs'!$B$12*H34/$C$6,'Engine Inputs'!$B$9)/'Engine Inputs'!$B$8))+MAX(H34-MIN('Engine Inputs'!$B$12*H34/$C$6,'Engine Inputs'!$B$9)*$C$6,0)*'Engine Inputs'!$B$10/$D$6)*(1-'Engine Inputs'!$B$4)+IF($D$6=1,(1-IF(OR($D$6=2,MOD(A35,2)=1),1,0))*H34*'Engine Inputs'!$B$10*(1-'Engine Inputs'!$B$4)/2,0)-IF(MOD(A35,2)=0,INDEX($B$11:$D$25,B35,3)*(1-'Engine Inputs'!$B$4),0) -> 2.8846644e+08 | I35: =I34+IF(OR($D$7=2,MOD(A35,2)=1),1,0)*(MIN('Engine Inputs'!$B$12*I34/$C$7,'Engine Inputs'!$B$9)*($B$7-'Engine Inputs'!$B$5-'Engine Inputs'!$B$6-2*'Engine Inputs'!$B$7*SQRT(MIN('Engine Inputs'!$B$12*I34/$C$7,'Engine Inputs'!$B$9)/'Engine Inputs'!$B$8))+MAX(I34-MIN('Engine Inputs'!$B$12*I34/$C$7,'Engine Inputs'!$B$9)*$C$7,0)*'Engine Inputs'!$B$10/$D$7)*(1-'Engine Inputs'!$B$4)+IF($D$7=1,(1-IF(OR($D$7=2,MOD(A35,2)=1),1,0))*I34*'Engine Inputs'!$B$10*(1-'Engine Inputs'!$B$4)/2,0)-IF(MOD(A35,2)=0,INDEX($B$11:$D$25,B35,1)*(1-'Engine Inputs'!$B$4),0) -> 7745832.2 | J35: =J34+IF(OR($D$7=2,MOD(A35,2)=1),1,0)*(MIN('Engine Inputs'!$B$12*J34/$C$7,'Engine Inputs'!$B$9)*($B$7-'Engine Inputs'!$B$5-'Engine Inputs'!$B$6-2*'Engine Inputs'!$B$7*SQRT(MIN('Engine Inputs'!$B$12*J34/$C$7,'Engine Inputs'!$B$9)/'Engine Inputs'!$B$8))+MAX(J34-MIN('Engine Inputs'!$B$12*J34/$C$7,'Engine Inputs'!$B$9)*$C$7,0)*'Engine Inputs'!$B$10/$D$7)*(1-'Engine Inputs'!$B$4)+IF($D$7=1,(1-IF(OR($D$7=2,MOD(A35,2)=1),1,0))*J34*'Engine Inputs'!$B$10*(1-'Engine Inputs'!$B$4)/2,0)-IF(MOD(A35,2)=0,INDEX($B$11:$D$25,B35,2)*(1-'Engine Inputs'!$B$4),0) -> 28833212 | K35: =K34+IF(OR($D$7=2,MOD(A35,2)=1),1,0)*(MIN('Engine Inputs'!$B$12*K34/$C$7,'Engine Inputs'!$B$9)*($B$7-'Engine Inputs'!$B$5-'Engine Inputs'!$B$6-2*'Engine Inputs'!$B$7*SQRT(MIN('Engine Inputs'!$B$12*K34/$C$7,'Engine Inputs'!$B$9)/'Engine Inputs'!$B$8))+MAX(K34-MIN('Engine Inputs'!$B$12*K34/$C$7,'Engine Inputs'!$B$9)*$C$7,0)*'Engine Inputs'!$B$10/$D$7)*(1-'Engine Inputs'!$B$4)+IF($D$7=1,(1-IF(OR($D$7=2,MOD(A35,2)=1),1,0))*K34*'Engine Inputs'!$B$10*(1-'Engine Inputs'!$B$4)/2,0)-IF(MOD(A35,2)=0,INDEX($B$11:$D$25,B35,3)*(1-'Engine Inputs'!$B$4),0) -> 76149822
A36: 8 | B36: =ROUNDUP(A36/2,0) -> 4 | C36: =C35+IF(OR($D$5=2,MOD(A36,2)=1),1,0)*(MIN('Engine Inputs'!$B$12*C35/$C$5,'Engine Inputs'!$B$9)*($B$5-'Engine Inputs'!$B$5-'Engine Inputs'!$B$6-2*'Engine Inputs'!$B$7*SQRT(MIN('Engine Inputs'!$B$12*C35/$C$5,'Engine Inputs'!$B$9)/'Engine Inputs'!$B$8))+MAX(C35-MIN('Engine Inputs'!$B$12*C35/$C$5,'Engine Inputs'!$B$9)*$C$5,0)*'Engine Inputs'!$B$10/$D$5)*(1-'Engine Inputs'!$B$4)+IF($D$5=1,(1-IF(OR($D$5=2,MOD(A36,2)=1),1,0))*C35*'Engine Inputs'!$B$10*(1-'Engine Inputs'!$B$4)/2,0)-IF(MOD(A36,2)=0,INDEX($B$11:$D$25,B36,1)*(1-'Engine Inputs'!$B$4),0) -> 2.6541125e+08 | D36: =D35+IF(OR($D$5=2,MOD(A36,2)=1),1,0)*(MIN('Engine Inputs'!$B$12*D35/$C$5,'Engine Inputs'!$B$9)*($B$5-'Engine Inputs'!$B$5-'Engine Inputs'!$B$6-2*'Engine Inputs'!$B$7*SQRT(MIN('Engine Inputs'!$B$12*D35/$C$5,'Engine Inputs'!$B$9)/'Engine Inputs'!$B$8))+MAX(D35-MIN('Engine Inputs'!$B$12*D35/$C$5,'Engine Inputs'!$B$9)*$C$5,0)*'Engine Inputs'!$B$10/$D$5)*(1-'Engine Inputs'!$B$4)+IF($D$5=1,(1-IF(OR($D$5=2,MOD(A36,2)=1),1,0))*D35*'Engine Inputs'!$B$10*(1-'Engine Inputs'!$B$4)/2,0)-IF(MOD(A36,2)=0,INDEX($B$11:$D$25,B36,2)*(1-'Engine Inputs'!$B$4),0) -> 9.6156137e+08 | E36: =E35+IF(OR($D$5=2,MOD(A36,2)=1),1,0)*(MIN('Engine Inputs'!$B$12*E35/$C$5,'Engine Inputs'!$B$9)*($B$5-'Engine Inputs'!$B$5-'Engine Inputs'!$B$6-2*'Engine Inputs'!$B$7*SQRT(MIN('Engine Inputs'!$B$12*E35/$C$5,'Engine Inputs'!$B$9)/'Engine Inputs'!$B$8))+MAX(E35-MIN('Engine Inputs'!$B$12*E35/$C$5,'Engine Inputs'!$B$9)*$C$5,0)*'Engine Inputs'!$B$10/$D$5)*(1-'Engine Inputs'!$B$4)+IF($D$5=1,(1-IF(OR($D$5=2,MOD(A36,2)=1),1,0))*E35*'Engine Inputs'!$B$10*(1-'Engine Inputs'!$B$4)/2,0)-IF(MOD(A36,2)=0,INDEX($B$11:$D$25,B36,3)*(1-'Engine Inputs'!$B$4),0) -> 2.1610751e+09 | F36: =F35+IF(OR($D$6=2,MOD(A36,2)=1),1,0)*(MIN('Engine Inputs'!$B$12*F35/$C$6,'Engine Inputs'!$B$9)*($B$6-'Engine Inputs'!$B$5-'Engine Inputs'!$B$6-2*'Engine Inputs'!$B$7*SQRT(MIN('Engine Inputs'!$B$12*F35/$C$6,'Engine Inputs'!$B$9)/'Engine Inputs'!$B$8))+MAX(F35-MIN('Engine Inputs'!$B$12*F35/$C$6,'Engine Inputs'!$B$9)*$C$6,0)*'Engine Inputs'!$B$10/$D$6)*(1-'Engine Inputs'!$B$4)+IF($D$6=1,(1-IF(OR($D$6=2,MOD(A36,2)=1),1,0))*F35*'Engine Inputs'!$B$10*(1-'Engine Inputs'!$B$4)/2,0)-IF(MOD(A36,2)=0,INDEX($B$11:$D$25,B36,1)*(1-'Engine Inputs'!$B$4),0) -> 44194949 | G36: =G35+IF(OR($D$6=2,MOD(A36,2)=1),1,0)*(MIN('Engine Inputs'!$B$12*G35/$C$6,'Engine Inputs'!$B$9)*($B$6-'Engine Inputs'!$B$5-'Engine Inputs'!$B$6-2*'Engine Inputs'!$B$7*SQRT(MIN('Engine Inputs'!$B$12*G35/$C$6,'Engine Inputs'!$B$9)/'Engine Inputs'!$B$8))+MAX(G35-MIN('Engine Inputs'!$B$12*G35/$C$6,'Engine Inputs'!$B$9)*$C$6,0)*'Engine Inputs'!$B$10/$D$6)*(1-'Engine Inputs'!$B$4)+IF($D$6=1,(1-IF(OR($D$6=2,MOD(A36,2)=1),1,0))*G35*'Engine Inputs'!$B$10*(1-'Engine Inputs'!$B$4)/2,0)-IF(MOD(A36,2)=0,INDEX($B$11:$D$25,B36,2)*(1-'Engine Inputs'!$B$4),0) -> 1.6188355e+08 | H36: =H35+IF(OR($D$6=2,MOD(A36,2)=1),1,0)*(MIN('Engine Inputs'!$B$12*H35/$C$6,'Engine Inputs'!$B$9)*($B$6-'Engine Inputs'!$B$5-'Engine Inputs'!$B$6-2*'Engine Inputs'!$B$7*SQRT(MIN('Engine Inputs'!$B$12*H35/$C$6,'Engine Inputs'!$B$9)/'Engine Inputs'!$B$8))+MAX(H35-MIN('Engine Inputs'!$B$12*H35/$C$6,'Engine Inputs'!$B$9)*$C$6,0)*'Engine Inputs'!$B$10/$D$6)*(1-'Engine Inputs'!$B$4)+IF($D$6=1,(1-IF(OR($D$6=2,MOD(A36,2)=1),1,0))*H35*'Engine Inputs'!$B$10*(1-'Engine Inputs'!$B$4)/2,0)-IF(MOD(A36,2)=0,INDEX($B$11:$D$25,B36,3)*(1-'Engine Inputs'!$B$4),0) -> 4.1871542e+08 | I36: =I35+IF(OR($D$7=2,MOD(A36,2)=1),1,0)*(MIN('Engine Inputs'!$B$12*I35/$C$7,'Engine Inputs'!$B$9)*($B$7-'Engine Inputs'!$B$5-'Engine Inputs'!$B$6-2*'Engine Inputs'!$B$7*SQRT(MIN('Engine Inputs'!$B$12*I35/$C$7,'Engine Inputs'!$B$9)/'Engine Inputs'!$B$8))+MAX(I35-MIN('Engine Inputs'!$B$12*I35/$C$7,'Engine Inputs'!$B$9)*$C$7,0)*'Engine Inputs'!$B$10/$D$7)*(1-'Engine Inputs'!$B$4)+IF($D$7=1,(1-IF(OR($D$7=2,MOD(A36,2)=1),1,0))*I35*'Engine Inputs'!$B$10*(1-'Engine Inputs'!$B$4)/2,0)-IF(MOD(A36,2)=0,INDEX($B$11:$D$25,B36,1)*(1-'Engine Inputs'!$B$4),0) -> 7896797.9 | J36: =J35+IF(OR($D$7=2,MOD(A36,2)=1),1,0)*(MIN('Engine Inputs'!$B$12*J35/$C$7,'Engine Inputs'!$B$9)*($B$7-'Engine Inputs'!$B$5-'Engine Inputs'!$B$6-2*'Engine Inputs'!$B$7*SQRT(MIN('Engine Inputs'!$B$12*J35/$C$7,'Engine Inputs'!$B$9)/'Engine Inputs'!$B$8))+MAX(J35-MIN('Engine Inputs'!$B$12*J35/$C$7,'Engine Inputs'!$B$9)*$C$7,0)*'Engine Inputs'!$B$10/$D$7)*(1-'Engine Inputs'!$B$4)+IF($D$7=1,(1-IF(OR($D$7=2,MOD(A36,2)=1),1,0))*J35*'Engine Inputs'!$B$10*(1-'Engine Inputs'!$B$4)/2,0)-IF(MOD(A36,2)=0,INDEX($B$11:$D$25,B36,2)*(1-'Engine Inputs'!$B$4),0) -> 29394138 | K36: =K35+IF(OR($D$7=2,MOD(A36,2)=1),1,0)*(MIN('Engine Inputs'!$B$12*K35/$C$7,'Engine Inputs'!$B$9)*($B$7-'Engine Inputs'!$B$5-'Engine Inputs'!$B$6-2*'Engine Inputs'!$B$7*SQRT(MIN('Engine Inputs'!$B$12*K35/$C$7,'Engine Inputs'!$B$9)/'Engine Inputs'!$B$8))+MAX(K35-MIN('Engine Inputs'!$B$12*K35/$C$7,'Engine Inputs'!$B$9)*$C$7,0)*'Engine Inputs'!$B$10/$D$7)*(1-'Engine Inputs'!$B$4)+IF($D$7=1,(1-IF(OR($D$7=2,MOD(A36,2)=1),1,0))*K35*'Engine Inputs'!$B$10*(1-'Engine Inputs'!$B$4)/2,0)-IF(MOD(A36,2)=0,INDEX($B$11:$D$25,B36,3)*(1-'Engine Inputs'!$B$4),0) -> 77627656
A37: 9 | B37: =ROUNDUP(A37/2,0) -> 5 | C37: =C36+IF(OR($D$5=2,MOD(A37,2)=1),1,0)*(MIN('Engine Inputs'!$B$12*C36/$C$5,'Engine Inputs'!$B$9)*($B$5-'Engine Inputs'!$B$5-'Engine Inputs'!$B$6-2*'Engine Inputs'!$B$7*SQRT(MIN('Engine Inputs'!$B$12*C36/$C$5,'Engine Inputs'!$B$9)/'Engine Inputs'!$B$8))+MAX(C36-MIN('Engine Inputs'!$B$12*C36/$C$5,'Engine Inputs'!$B$9)*$C$5,0)*'Engine Inputs'!$B$10/$D$5)*(1-'Engine Inputs'!$B$4)+IF($D$5=1,(1-IF(OR($D$5=2,MOD(A37,2)=1),1,0))*C36*'Engine Inputs'!$B$10*(1-'Engine Inputs'!$B$4)/2,0)-IF(MOD(A37,2)=0,INDEX($B$11:$D$25,B37,1)*(1-'Engine Inputs'!$B$4),0) -> 4.8436864e+08 | D37: =D36+IF(OR($D$5=2,MOD(A37,2)=1),1,0)*(MIN('Engine Inputs'!$B$12*D36/$C$5,'Engine Inputs'!$B$9)*($B$5-'Engine Inputs'!$B$5-'Engine Inputs'!$B$6-2*'Engine Inputs'!$B$7*SQRT(MIN('Engine Inputs'!$B$12*D36/$C$5,'Engine Inputs'!$B$9)/'Engine Inputs'!$B$8))+MAX(D36-MIN('Engine Inputs'!$B$12*D36/$C$5,'Engine Inputs'!$B$9)*$C$5,0)*'Engine Inputs'!$B$10/$D$5)*(1-'Engine Inputs'!$B$4)+IF($D$5=1,(1-IF(OR($D$5=2,MOD(A37,2)=1),1,0))*D36*'Engine Inputs'!$B$10*(1-'Engine Inputs'!$B$4)/2,0)-IF(MOD(A37,2)=0,INDEX($B$11:$D$25,B37,2)*(1-'Engine Inputs'!$B$4),0) -> 1.7316395e+09 | E37: =E36+IF(OR($D$5=2,MOD(A37,2)=1),1,0)*(MIN('Engine Inputs'!$B$12*E36/$C$5,'Engine Inputs'!$B$9)*($B$5-'Engine Inputs'!$B$5-'Engine Inputs'!$B$6-2*'Engine Inputs'!$B$7*SQRT(MIN('Engine Inputs'!$B$12*E36/$C$5,'Engine Inputs'!$B$9)/'Engine Inputs'!$B$8))+MAX(E36-MIN('Engine Inputs'!$B$12*E36/$C$5,'Engine Inputs'!$B$9)*$C$5,0)*'Engine Inputs'!$B$10/$D$5)*(1-'Engine Inputs'!$B$4)+IF($D$5=1,(1-IF(OR($D$5=2,MOD(A37,2)=1),1,0))*E36*'Engine Inputs'!$B$10*(1-'Engine Inputs'!$B$4)/2,0)-IF(MOD(A37,2)=0,INDEX($B$11:$D$25,B37,3)*(1-'Engine Inputs'!$B$4),0) -> 2.9725155e+09 | F37: =F36+IF(OR($D$6=2,MOD(A37,2)=1),1,0)*(MIN('Engine Inputs'!$B$12*F36/$C$6,'Engine Inputs'!$B$9)*($B$6-'Engine Inputs'!$B$5-'Engine Inputs'!$B$6-2*'Engine Inputs'!$B$7*SQRT(MIN('Engine Inputs'!$B$12*F36/$C$6,'Engine Inputs'!$B$9)/'Engine Inputs'!$B$8))+MAX(F36-MIN('Engine Inputs'!$B$12*F36/$C$6,'Engine Inputs'!$B$9)*$C$6,0)*'Engine Inputs'!$B$10/$D$6)*(1-'Engine Inputs'!$B$4)+IF($D$6=1,(1-IF(OR($D$6=2,MOD(A37,2)=1),1,0))*F36*'Engine Inputs'!$B$10*(1-'Engine Inputs'!$B$4)/2,0)-IF(MOD(A37,2)=0,INDEX($B$11:$D$25,B37,1)*(1-'Engine Inputs'!$B$4),0) -> 64898580 | G37: =G36+IF(OR($D$6=2,MOD(A37,2)=1),1,0)*(MIN('Engine Inputs'!$B$12*G36/$C$6,'Engine Inputs'!$B$9)*($B$6-'Engine Inputs'!$B$5-'Engine Inputs'!$B$6-2*'Engine Inputs'!$B$7*SQRT(MIN('Engine Inputs'!$B$12*G36/$C$6,'Engine Inputs'!$B$9)/'Engine Inputs'!$B$8))+MAX(G36-MIN('Engine Inputs'!$B$12*G36/$C$6,'Engine Inputs'!$B$9)*$C$6,0)*'Engine Inputs'!$B$10/$D$6)*(1-'Engine Inputs'!$B$4)+IF($D$6=1,(1-IF(OR($D$6=2,MOD(A37,2)=1),1,0))*G36*'Engine Inputs'!$B$10*(1-'Engine Inputs'!$B$4)/2,0)-IF(MOD(A37,2)=0,INDEX($B$11:$D$25,B37,2)*(1-'Engine Inputs'!$B$4),0) -> 2.3623139e+08 | H37: =H36+IF(OR($D$6=2,MOD(A37,2)=1),1,0)*(MIN('Engine Inputs'!$B$12*H36/$C$6,'Engine Inputs'!$B$9)*($B$6-'Engine Inputs'!$B$5-'Engine Inputs'!$B$6-2*'Engine Inputs'!$B$7*SQRT(MIN('Engine Inputs'!$B$12*H36/$C$6,'Engine Inputs'!$B$9)/'Engine Inputs'!$B$8))+MAX(H36-MIN('Engine Inputs'!$B$12*H36/$C$6,'Engine Inputs'!$B$9)*$C$6,0)*'Engine Inputs'!$B$10/$D$6)*(1-'Engine Inputs'!$B$4)+IF($D$6=1,(1-IF(OR($D$6=2,MOD(A37,2)=1),1,0))*H36*'Engine Inputs'!$B$10*(1-'Engine Inputs'!$B$4)/2,0)-IF(MOD(A37,2)=0,INDEX($B$11:$D$25,B37,3)*(1-'Engine Inputs'!$B$4),0) -> 6.0611382e+08 | I37: =I36+IF(OR($D$7=2,MOD(A37,2)=1),1,0)*(MIN('Engine Inputs'!$B$12*I36/$C$7,'Engine Inputs'!$B$9)*($B$7-'Engine Inputs'!$B$5-'Engine Inputs'!$B$6-2*'Engine Inputs'!$B$7*SQRT(MIN('Engine Inputs'!$B$12*I36/$C$7,'Engine Inputs'!$B$9)/'Engine Inputs'!$B$8))+MAX(I36-MIN('Engine Inputs'!$B$12*I36/$C$7,'Engine Inputs'!$B$9)*$C$7,0)*'Engine Inputs'!$B$10/$D$7)*(1-'Engine Inputs'!$B$4)+IF($D$7=1,(1-IF(OR($D$7=2,MOD(A37,2)=1),1,0))*I36*'Engine Inputs'!$B$10*(1-'Engine Inputs'!$B$4)/2,0)-IF(MOD(A37,2)=0,INDEX($B$11:$D$25,B37,1)*(1-'Engine Inputs'!$B$4),0) -> 10912042 | J37: =J36+IF(OR($D$7=2,MOD(A37,2)=1),1,0)*(MIN('Engine Inputs'!$B$12*J36/$C$7,'Engine Inputs'!$B$9)*($B$7-'Engine Inputs'!$B$5-'Engine Inputs'!$B$6-2*'Engine Inputs'!$B$7*SQRT(MIN('Engine Inputs'!$B$12*J36/$C$7,'Engine Inputs'!$B$9)/'Engine Inputs'!$B$8))+MAX(J36-MIN('Engine Inputs'!$B$12*J36/$C$7,'Engine Inputs'!$B$9)*$C$7,0)*'Engine Inputs'!$B$10/$D$7)*(1-'Engine Inputs'!$B$4)+IF($D$7=1,(1-IF(OR($D$7=2,MOD(A37,2)=1),1,0))*J36*'Engine Inputs'!$B$10*(1-'Engine Inputs'!$B$4)/2,0)-IF(MOD(A37,2)=0,INDEX($B$11:$D$25,B37,2)*(1-'Engine Inputs'!$B$4),0) -> 40506065 | K37: =K36+IF(OR($D$7=2,MOD(A37,2)=1),1,0)*(MIN('Engine Inputs'!$B$12*K36/$C$7,'Engine Inputs'!$B$9)*($B$7-'Engine Inputs'!$B$5-'Engine Inputs'!$B$6-2*'Engine Inputs'!$B$7*SQRT(MIN('Engine Inputs'!$B$12*K36/$C$7,'Engine Inputs'!$B$9)/'Engine Inputs'!$B$8))+MAX(K36-MIN('Engine Inputs'!$B$12*K36/$C$7,'Engine Inputs'!$B$9)*$C$7,0)*'Engine Inputs'!$B$10/$D$7)*(1-'Engine Inputs'!$B$4)+IF($D$7=1,(1-IF(OR($D$7=2,MOD(A37,2)=1),1,0))*K36*'Engine Inputs'!$B$10*(1-'Engine Inputs'!$B$4)/2,0)-IF(MOD(A37,2)=0,INDEX($B$11:$D$25,B37,3)*(1-'Engine Inputs'!$B$4),0) -> 1.0659068e+08
A38: 10 | B38: =ROUNDUP(A38/2,0) -> 5 | C38: =C37+IF(OR($D$5=2,MOD(A38,2)=1),1,0)*(MIN('Engine Inputs'!$B$12*C37/$C$5,'Engine Inputs'!$B$9)*($B$5-'Engine Inputs'!$B$5-'Engine Inputs'!$B$6-2*'Engine Inputs'!$B$7*SQRT(MIN('Engine Inputs'!$B$12*C37/$C$5,'Engine Inputs'!$B$9)/'Engine Inputs'!$B$8))+MAX(C37-MIN('Engine Inputs'!$B$12*C37/$C$5,'Engine Inputs'!$B$9)*$C$5,0)*'Engine Inputs'!$B$10/$D$5)*(1-'Engine Inputs'!$B$4)+IF($D$5=1,(1-IF(OR($D$5=2,MOD(A38,2)=1),1,0))*C37*'Engine Inputs'!$B$10*(1-'Engine Inputs'!$B$4)/2,0)-IF(MOD(A38,2)=0,INDEX($B$11:$D$25,B38,1)*(1-'Engine Inputs'!$B$4),0) -> 8.7934873e+08 | D38: =D37+IF(OR($D$5=2,MOD(A38,2)=1),1,0)*(MIN('Engine Inputs'!$B$12*D37/$C$5,'Engine Inputs'!$B$9)*($B$5-'Engine Inputs'!$B$5-'Engine Inputs'!$B$6-2*'Engine Inputs'!$B$7*SQRT(MIN('Engine Inputs'!$B$12*D37/$C$5,'Engine Inputs'!$B$9)/'Engine Inputs'!$B$8))+MAX(D37-MIN('Engine Inputs'!$B$12*D37/$C$5,'Engine Inputs'!$B$9)*$C$5,0)*'Engine Inputs'!$B$10/$D$5)*(1-'Engine Inputs'!$B$4)+IF($D$5=1,(1-IF(OR($D$5=2,MOD(A38,2)=1),1,0))*D37*'Engine Inputs'!$B$10*(1-'Engine Inputs'!$B$4)/2,0)-IF(MOD(A38,2)=0,INDEX($B$11:$D$25,B38,2)*(1-'Engine Inputs'!$B$4),0) -> 2.5323552e+09 | E38: =E37+IF(OR($D$5=2,MOD(A38,2)=1),1,0)*(MIN('Engine Inputs'!$B$12*E37/$C$5,'Engine Inputs'!$B$9)*($B$5-'Engine Inputs'!$B$5-'Engine Inputs'!$B$6-2*'Engine Inputs'!$B$7*SQRT(MIN('Engine Inputs'!$B$12*E37/$C$5,'Engine Inputs'!$B$9)/'Engine Inputs'!$B$8))+MAX(E37-MIN('Engine Inputs'!$B$12*E37/$C$5,'Engine Inputs'!$B$9)*$C$5,0)*'Engine Inputs'!$B$10/$D$5)*(1-'Engine Inputs'!$B$4)+IF($D$5=1,(1-IF(OR($D$5=2,MOD(A38,2)=1),1,0))*E37*'Engine Inputs'!$B$10*(1-'Engine Inputs'!$B$4)/2,0)-IF(MOD(A38,2)=0,INDEX($B$11:$D$25,B38,3)*(1-'Engine Inputs'!$B$4),0) -> 3.8029421e+09 | F38: =F37+IF(OR($D$6=2,MOD(A38,2)=1),1,0)*(MIN('Engine Inputs'!$B$12*F37/$C$6,'Engine Inputs'!$B$9)*($B$6-'Engine Inputs'!$B$5-'Engine Inputs'!$B$6-2*'Engine Inputs'!$B$7*SQRT(MIN('Engine Inputs'!$B$12*F37/$C$6,'Engine Inputs'!$B$9)/'Engine Inputs'!$B$8))+MAX(F37-MIN('Engine Inputs'!$B$12*F37/$C$6,'Engine Inputs'!$B$9)*$C$6,0)*'Engine Inputs'!$B$10/$D$6)*(1-'Engine Inputs'!$B$4)+IF($D$6=1,(1-IF(OR($D$6=2,MOD(A38,2)=1),1,0))*F37*'Engine Inputs'!$B$10*(1-'Engine Inputs'!$B$4)/2,0)-IF(MOD(A38,2)=0,INDEX($B$11:$D$25,B38,1)*(1-'Engine Inputs'!$B$4),0) -> 95087946 | G38: =G37+IF(OR($D$6=2,MOD(A38,2)=1),1,0)*(MIN('Engine Inputs'!$B$12*G37/$C$6,'Engine Inputs'!$B$9)*($B$6-'Engine Inputs'!$B$5-'Engine Inputs'!$B$6-2*'Engine Inputs'!$B$7*SQRT(MIN('Engine Inputs'!$B$12*G37/$C$6,'Engine Inputs'!$B$9)/'Engine Inputs'!$B$8))+MAX(G37-MIN('Engine Inputs'!$B$12*G37/$C$6,'Engine Inputs'!$B$9)*$C$6,0)*'Engine Inputs'!$B$10/$D$6)*(1-'Engine Inputs'!$B$4)+IF($D$6=1,(1-IF(OR($D$6=2,MOD(A38,2)=1),1,0))*G37*'Engine Inputs'!$B$10*(1-'Engine Inputs'!$B$4)/2,0)-IF(MOD(A38,2)=0,INDEX($B$11:$D$25,B38,2)*(1-'Engine Inputs'!$B$4),0) -> 3.4349804e+08 | H38: =H37+IF(OR($D$6=2,MOD(A38,2)=1),1,0)*(MIN('Engine Inputs'!$B$12*H37/$C$6,'Engine Inputs'!$B$9)*($B$6-'Engine Inputs'!$B$5-'Engine Inputs'!$B$6-2*'Engine Inputs'!$B$7*SQRT(MIN('Engine Inputs'!$B$12*H37/$C$6,'Engine Inputs'!$B$9)/'Engine Inputs'!$B$8))+MAX(H37-MIN('Engine Inputs'!$B$12*H37/$C$6,'Engine Inputs'!$B$9)*$C$6,0)*'Engine Inputs'!$B$10/$D$6)*(1-'Engine Inputs'!$B$4)+IF($D$6=1,(1-IF(OR($D$6=2,MOD(A38,2)=1),1,0))*H37*'Engine Inputs'!$B$10*(1-'Engine Inputs'!$B$4)/2,0)-IF(MOD(A38,2)=0,INDEX($B$11:$D$25,B38,3)*(1-'Engine Inputs'!$B$4),0) -> 8.7282224e+08 | I38: =I37+IF(OR($D$7=2,MOD(A38,2)=1),1,0)*(MIN('Engine Inputs'!$B$12*I37/$C$7,'Engine Inputs'!$B$9)*($B$7-'Engine Inputs'!$B$5-'Engine Inputs'!$B$6-2*'Engine Inputs'!$B$7*SQRT(MIN('Engine Inputs'!$B$12*I37/$C$7,'Engine Inputs'!$B$9)/'Engine Inputs'!$B$8))+MAX(I37-MIN('Engine Inputs'!$B$12*I37/$C$7,'Engine Inputs'!$B$9)*$C$7,0)*'Engine Inputs'!$B$10/$D$7)*(1-'Engine Inputs'!$B$4)+IF($D$7=1,(1-IF(OR($D$7=2,MOD(A38,2)=1),1,0))*I37*'Engine Inputs'!$B$10*(1-'Engine Inputs'!$B$4)/2,0)-IF(MOD(A38,2)=0,INDEX($B$11:$D$25,B38,1)*(1-'Engine Inputs'!$B$4),0) -> 11102595 | J38: =J37+IF(OR($D$7=2,MOD(A38,2)=1),1,0)*(MIN('Engine Inputs'!$B$12*J37/$C$7,'Engine Inputs'!$B$9)*($B$7-'Engine Inputs'!$B$5-'Engine Inputs'!$B$6-2*'Engine Inputs'!$B$7*SQRT(MIN('Engine Inputs'!$B$12*J37/$C$7,'Engine Inputs'!$B$9)/'Engine Inputs'!$B$8))+MAX(J37-MIN('Engine Inputs'!$B$12*J37/$C$7,'Engine Inputs'!$B$9)*$C$7,0)*'Engine Inputs'!$B$10/$D$7)*(1-'Engine Inputs'!$B$4)+IF($D$7=1,(1-IF(OR($D$7=2,MOD(A38,2)=1),1,0))*J37*'Engine Inputs'!$B$10*(1-'Engine Inputs'!$B$4)/2,0)-IF(MOD(A38,2)=0,INDEX($B$11:$D$25,B38,2)*(1-'Engine Inputs'!$B$4),0) -> 41210569 | K38: =K37+IF(OR($D$7=2,MOD(A38,2)=1),1,0)*(MIN('Engine Inputs'!$B$12*K37/$C$7,'Engine Inputs'!$B$9)*($B$7-'Engine Inputs'!$B$5-'Engine Inputs'!$B$6-2*'Engine Inputs'!$B$7*SQRT(MIN('Engine Inputs'!$B$12*K37/$C$7,'Engine Inputs'!$B$9)/'Engine Inputs'!$B$8))+MAX(K37-MIN('Engine Inputs'!$B$12*K37/$C$7,'Engine Inputs'!$B$9)*$C$7,0)*'Engine Inputs'!$B$10/$D$7)*(1-'Engine Inputs'!$B$4)+IF($D$7=1,(1-IF(OR($D$7=2,MOD(A38,2)=1),1,0))*K37*'Engine Inputs'!$B$10*(1-'Engine Inputs'!$B$4)/2,0)-IF(MOD(A38,2)=0,INDEX($B$11:$D$25,B38,3)*(1-'Engine Inputs'!$B$4),0) -> 1.0843469e+08
A39: 11 | B39: =ROUNDUP(A39/2,0) -> 6 | C39: =C38+IF(OR($D$5=2,MOD(A39,2)=1),1,0)*(MIN('Engine Inputs'!$B$12*C38/$C$5,'Engine Inputs'!$B$9)*($B$5-'Engine Inputs'!$B$5-'Engine Inputs'!$B$6-2*'Engine Inputs'!$B$7*SQRT(MIN('Engine Inputs'!$B$12*C38/$C$5,'Engine Inputs'!$B$9)/'Engine Inputs'!$B$8))+MAX(C38-MIN('Engine Inputs'!$B$12*C38/$C$5,'Engine Inputs'!$B$9)*$C$5,0)*'Engine Inputs'!$B$10/$D$5)*(1-'Engine Inputs'!$B$4)+IF($D$5=1,(1-IF(OR($D$5=2,MOD(A39,2)=1),1,0))*C38*'Engine Inputs'!$B$10*(1-'Engine Inputs'!$B$4)/2,0)-IF(MOD(A39,2)=0,INDEX($B$11:$D$25,B39,1)*(1-'Engine Inputs'!$B$4),0) -> 1.5855383e+09 | D39: =D38+IF(OR($D$5=2,MOD(A39,2)=1),1,0)*(MIN('Engine Inputs'!$B$12*D38/$C$5,'Engine Inputs'!$B$9)*($B$5-'Engine Inputs'!$B$5-'Engine Inputs'!$B$6-2*'Engine Inputs'!$B$7*SQRT(MIN('Engine Inputs'!$B$12*D38/$C$5,'Engine Inputs'!$B$9)/'Engine Inputs'!$B$8))+MAX(D38-MIN('Engine Inputs'!$B$12*D38/$C$5,'Engine Inputs'!$B$9)*$C$5,0)*'Engine Inputs'!$B$10/$D$5)*(1-'Engine Inputs'!$B$4)+IF($D$5=1,(1-IF(OR($D$5=2,MOD(A39,2)=1),1,0))*D38*'Engine Inputs'!$B$10*(1-'Engine Inputs'!$B$4)/2,0)-IF(MOD(A39,2)=0,INDEX($B$11:$D$25,B39,2)*(1-'Engine Inputs'!$B$4),0) -> 3.3528253e+09 | E39: =E38+IF(OR($D$5=2,MOD(A39,2)=1),1,0)*(MIN('Engine Inputs'!$B$12*E38/$C$5,'Engine Inputs'!$B$9)*($B$5-'Engine Inputs'!$B$5-'Engine Inputs'!$B$6-2*'Engine Inputs'!$B$7*SQRT(MIN('Engine Inputs'!$B$12*E38/$C$5,'Engine Inputs'!$B$9)/'Engine Inputs'!$B$8))+MAX(E38-MIN('Engine Inputs'!$B$12*E38/$C$5,'Engine Inputs'!$B$9)*$C$5,0)*'Engine Inputs'!$B$10/$D$5)*(1-'Engine Inputs'!$B$4)+IF($D$5=1,(1-IF(OR($D$5=2,MOD(A39,2)=1),1,0))*E38*'Engine Inputs'!$B$10*(1-'Engine Inputs'!$B$4)/2,0)-IF(MOD(A39,2)=0,INDEX($B$11:$D$25,B39,3)*(1-'Engine Inputs'!$B$4),0) -> 4.6543134e+09 | F39: =F38+IF(OR($D$6=2,MOD(A39,2)=1),1,0)*(MIN('Engine Inputs'!$B$12*F38/$C$6,'Engine Inputs'!$B$9)*($B$6-'Engine Inputs'!$B$5-'Engine Inputs'!$B$6-2*'Engine Inputs'!$B$7*SQRT(MIN('Engine Inputs'!$B$12*F38/$C$6,'Engine Inputs'!$B$9)/'Engine Inputs'!$B$8))+MAX(F38-MIN('Engine Inputs'!$B$12*F38/$C$6,'Engine Inputs'!$B$9)*$C$6,0)*'Engine Inputs'!$B$10/$D$6)*(1-'Engine Inputs'!$B$4)+IF($D$6=1,(1-IF(OR($D$6=2,MOD(A39,2)=1),1,0))*F38*'Engine Inputs'!$B$10*(1-'Engine Inputs'!$B$4)/2,0)-IF(MOD(A39,2)=0,INDEX($B$11:$D$25,B39,1)*(1-'Engine Inputs'!$B$4),0) -> 1.3918641e+08 | G39: =G38+IF(OR($D$6=2,MOD(A39,2)=1),1,0)*(MIN('Engine Inputs'!$B$12*G38/$C$6,'Engine Inputs'!$B$9)*($B$6-'Engine Inputs'!$B$5-'Engine Inputs'!$B$6-2*'Engine Inputs'!$B$7*SQRT(MIN('Engine Inputs'!$B$12*G38/$C$6,'Engine Inputs'!$B$9)/'Engine Inputs'!$B$8))+MAX(G38-MIN('Engine Inputs'!$B$12*G38/$C$6,'Engine Inputs'!$B$9)*$C$6,0)*'Engine Inputs'!$B$10/$D$6)*(1-'Engine Inputs'!$B$4)+IF($D$6=1,(1-IF(OR($D$6=2,MOD(A39,2)=1),1,0))*G38*'Engine Inputs'!$B$10*(1-'Engine Inputs'!$B$4)/2,0)-IF(MOD(A39,2)=0,INDEX($B$11:$D$25,B39,2)*(1-'Engine Inputs'!$B$4),0) -> 4.9823514e+08 | H39: =H38+IF(OR($D$6=2,MOD(A39,2)=1),1,0)*(MIN('Engine Inputs'!$B$12*H38/$C$6,'Engine Inputs'!$B$9)*($B$6-'Engine Inputs'!$B$5-'Engine Inputs'!$B$6-2*'Engine Inputs'!$B$7*SQRT(MIN('Engine Inputs'!$B$12*H38/$C$6,'Engine Inputs'!$B$9)/'Engine Inputs'!$B$8))+MAX(H38-MIN('Engine Inputs'!$B$12*H38/$C$6,'Engine Inputs'!$B$9)*$C$6,0)*'Engine Inputs'!$B$10/$D$6)*(1-'Engine Inputs'!$B$4)+IF($D$6=1,(1-IF(OR($D$6=2,MOD(A39,2)=1),1,0))*H38*'Engine Inputs'!$B$10*(1-'Engine Inputs'!$B$4)/2,0)-IF(MOD(A39,2)=0,INDEX($B$11:$D$25,B39,3)*(1-'Engine Inputs'!$B$4),0) -> 1.2514639e+09 | I39: =I38+IF(OR($D$7=2,MOD(A39,2)=1),1,0)*(MIN('Engine Inputs'!$B$12*I38/$C$7,'Engine Inputs'!$B$9)*($B$7-'Engine Inputs'!$B$5-'Engine Inputs'!$B$6-2*'Engine Inputs'!$B$7*SQRT(MIN('Engine Inputs'!$B$12*I38/$C$7,'Engine Inputs'!$B$9)/'Engine Inputs'!$B$8))+MAX(I38-MIN('Engine Inputs'!$B$12*I38/$C$7,'Engine Inputs'!$B$9)*$C$7,0)*'Engine Inputs'!$B$10/$D$7)*(1-'Engine Inputs'!$B$4)+IF($D$7=1,(1-IF(OR($D$7=2,MOD(A39,2)=1),1,0))*I38*'Engine Inputs'!$B$10*(1-'Engine Inputs'!$B$4)/2,0)-IF(MOD(A39,2)=0,INDEX($B$11:$D$25,B39,1)*(1-'Engine Inputs'!$B$4),0) -> 15333483 | J39: =J38+IF(OR($D$7=2,MOD(A39,2)=1),1,0)*(MIN('Engine Inputs'!$B$12*J38/$C$7,'Engine Inputs'!$B$9)*($B$7-'Engine Inputs'!$B$5-'Engine Inputs'!$B$6-2*'Engine Inputs'!$B$7*SQRT(MIN('Engine Inputs'!$B$12*J38/$C$7,'Engine Inputs'!$B$9)/'Engine Inputs'!$B$8))+MAX(J38-MIN('Engine Inputs'!$B$12*J38/$C$7,'Engine Inputs'!$B$9)*$C$7,0)*'Engine Inputs'!$B$10/$D$7)*(1-'Engine Inputs'!$B$4)+IF($D$7=1,(1-IF(OR($D$7=2,MOD(A39,2)=1),1,0))*J38*'Engine Inputs'!$B$10*(1-'Engine Inputs'!$B$4)/2,0)-IF(MOD(A39,2)=0,INDEX($B$11:$D$25,B39,2)*(1-'Engine Inputs'!$B$4),0) -> 56729662 | K39: =K38+IF(OR($D$7=2,MOD(A39,2)=1),1,0)*(MIN('Engine Inputs'!$B$12*K38/$C$7,'Engine Inputs'!$B$9)*($B$7-'Engine Inputs'!$B$5-'Engine Inputs'!$B$6-2*'Engine Inputs'!$B$7*SQRT(MIN('Engine Inputs'!$B$12*K38/$C$7,'Engine Inputs'!$B$9)/'Engine Inputs'!$B$8))+MAX(K38-MIN('Engine Inputs'!$B$12*K38/$C$7,'Engine Inputs'!$B$9)*$C$7,0)*'Engine Inputs'!$B$10/$D$7)*(1-'Engine Inputs'!$B$4)+IF($D$7=1,(1-IF(OR($D$7=2,MOD(A39,2)=1),1,0))*K38*'Engine Inputs'!$B$10*(1-'Engine Inputs'!$B$4)/2,0)-IF(MOD(A39,2)=0,INDEX($B$11:$D$25,B39,3)*(1-'Engine Inputs'!$B$4),0) -> 1.4863908e+08
A40: 12 | B40: =ROUNDUP(A40/2,0) -> 6 | C40: =C39+IF(OR($D$5=2,MOD(A40,2)=1),1,0)*(MIN('Engine Inputs'!$B$12*C39/$C$5,'Engine Inputs'!$B$9)*($B$5-'Engine Inputs'!$B$5-'Engine Inputs'!$B$6-2*'Engine Inputs'!$B$7*SQRT(MIN('Engine Inputs'!$B$12*C39/$C$5,'Engine Inputs'!$B$9)/'Engine Inputs'!$B$8))+MAX(C39-MIN('Engine Inputs'!$B$12*C39/$C$5,'Engine Inputs'!$B$9)*$C$5,0)*'Engine Inputs'!$B$10/$D$5)*(1-'Engine Inputs'!$B$4)+IF($D$5=1,(1-IF(OR($D$5=2,MOD(A40,2)=1),1,0))*C39*'Engine Inputs'!$B$10*(1-'Engine Inputs'!$B$4)/2,0)-IF(MOD(A40,2)=0,INDEX($B$11:$D$25,B40,1)*(1-'Engine Inputs'!$B$4),0) -> 2.3829065e+09 | D40: =D39+IF(OR($D$5=2,MOD(A40,2)=1),1,0)*(MIN('Engine Inputs'!$B$12*D39/$C$5,'Engine Inputs'!$B$9)*($B$5-'Engine Inputs'!$B$5-'Engine Inputs'!$B$6-2*'Engine Inputs'!$B$7*SQRT(MIN('Engine Inputs'!$B$12*D39/$C$5,'Engine Inputs'!$B$9)/'Engine Inputs'!$B$8))+MAX(D39-MIN('Engine Inputs'!$B$12*D39/$C$5,'Engine Inputs'!$B$9)*$C$5,0)*'Engine Inputs'!$B$10/$D$5)*(1-'Engine Inputs'!$B$4)+IF($D$5=1,(1-IF(OR($D$5=2,MOD(A40,2)=1),1,0))*D39*'Engine Inputs'!$B$10*(1-'Engine Inputs'!$B$4)/2,0)-IF(MOD(A40,2)=0,INDEX($B$11:$D$25,B40,2)*(1-'Engine Inputs'!$B$4),0) -> 4.1929689e+09 | E40: =E39+IF(OR($D$5=2,MOD(A40,2)=1),1,0)*(MIN('Engine Inputs'!$B$12*E39/$C$5,'Engine Inputs'!$B$9)*($B$5-'Engine Inputs'!$B$5-'Engine Inputs'!$B$6-2*'Engine Inputs'!$B$7*SQRT(MIN('Engine Inputs'!$B$12*E39/$C$5,'Engine Inputs'!$B$9)/'Engine Inputs'!$B$8))+MAX(E39-MIN('Engine Inputs'!$B$12*E39/$C$5,'Engine Inputs'!$B$9)*$C$5,0)*'Engine Inputs'!$B$10/$D$5)*(1-'Engine Inputs'!$B$4)+IF($D$5=1,(1-IF(OR($D$5=2,MOD(A40,2)=1),1,0))*E39*'Engine Inputs'!$B$10*(1-'Engine Inputs'!$B$4)/2,0)-IF(MOD(A40,2)=0,INDEX($B$11:$D$25,B40,3)*(1-'Engine Inputs'!$B$4),0) -> 5.525642e+09 | F40: =F39+IF(OR($D$6=2,MOD(A40,2)=1),1,0)*(MIN('Engine Inputs'!$B$12*F39/$C$6,'Engine Inputs'!$B$9)*($B$6-'Engine Inputs'!$B$5-'Engine Inputs'!$B$6-2*'Engine Inputs'!$B$7*SQRT(MIN('Engine Inputs'!$B$12*F39/$C$6,'Engine Inputs'!$B$9)/'Engine Inputs'!$B$8))+MAX(F39-MIN('Engine Inputs'!$B$12*F39/$C$6,'Engine Inputs'!$B$9)*$C$6,0)*'Engine Inputs'!$B$10/$D$6)*(1-'Engine Inputs'!$B$4)+IF($D$6=1,(1-IF(OR($D$6=2,MOD(A40,2)=1),1,0))*F39*'Engine Inputs'!$B$10*(1-'Engine Inputs'!$B$4)/2,0)-IF(MOD(A40,2)=0,INDEX($B$11:$D$25,B40,1)*(1-'Engine Inputs'!$B$4),0) -> 2.0323033e+08 | G40: =G39+IF(OR($D$6=2,MOD(A40,2)=1),1,0)*(MIN('Engine Inputs'!$B$12*G39/$C$6,'Engine Inputs'!$B$9)*($B$6-'Engine Inputs'!$B$5-'Engine Inputs'!$B$6-2*'Engine Inputs'!$B$7*SQRT(MIN('Engine Inputs'!$B$12*G39/$C$6,'Engine Inputs'!$B$9)/'Engine Inputs'!$B$8))+MAX(G39-MIN('Engine Inputs'!$B$12*G39/$C$6,'Engine Inputs'!$B$9)*$C$6,0)*'Engine Inputs'!$B$10/$D$6)*(1-'Engine Inputs'!$B$4)+IF($D$6=1,(1-IF(OR($D$6=2,MOD(A40,2)=1),1,0))*G39*'Engine Inputs'!$B$10*(1-'Engine Inputs'!$B$4)/2,0)-IF(MOD(A40,2)=0,INDEX($B$11:$D$25,B40,2)*(1-'Engine Inputs'!$B$4),0) -> 7.1954102e+08 | H40: =H39+IF(OR($D$6=2,MOD(A40,2)=1),1,0)*(MIN('Engine Inputs'!$B$12*H39/$C$6,'Engine Inputs'!$B$9)*($B$6-'Engine Inputs'!$B$5-'Engine Inputs'!$B$6-2*'Engine Inputs'!$B$7*SQRT(MIN('Engine Inputs'!$B$12*H39/$C$6,'Engine Inputs'!$B$9)/'Engine Inputs'!$B$8))+MAX(H39-MIN('Engine Inputs'!$B$12*H39/$C$6,'Engine Inputs'!$B$9)*$C$6,0)*'Engine Inputs'!$B$10/$D$6)*(1-'Engine Inputs'!$B$4)+IF($D$6=1,(1-IF(OR($D$6=2,MOD(A40,2)=1),1,0))*H39*'Engine Inputs'!$B$10*(1-'Engine Inputs'!$B$4)/2,0)-IF(MOD(A40,2)=0,INDEX($B$11:$D$25,B40,3)*(1-'Engine Inputs'!$B$4),0) -> 1.699304e+09 | I40: =I39+IF(OR($D$7=2,MOD(A40,2)=1),1,0)*(MIN('Engine Inputs'!$B$12*I39/$C$7,'Engine Inputs'!$B$9)*($B$7-'Engine Inputs'!$B$5-'Engine Inputs'!$B$6-2*'Engine Inputs'!$B$7*SQRT(MIN('Engine Inputs'!$B$12*I39/$C$7,'Engine Inputs'!$B$9)/'Engine Inputs'!$B$8))+MAX(I39-MIN('Engine Inputs'!$B$12*I39/$C$7,'Engine Inputs'!$B$9)*$C$7,0)*'Engine Inputs'!$B$10/$D$7)*(1-'Engine Inputs'!$B$4)+IF($D$7=1,(1-IF(OR($D$7=2,MOD(A40,2)=1),1,0))*I39*'Engine Inputs'!$B$10*(1-'Engine Inputs'!$B$4)/2,0)-IF(MOD(A40,2)=0,INDEX($B$11:$D$25,B40,1)*(1-'Engine Inputs'!$B$4),0) -> 15631568 | J40: =J39+IF(OR($D$7=2,MOD(A40,2)=1),1,0)*(MIN('Engine Inputs'!$B$12*J39/$C$7,'Engine Inputs'!$B$9)*($B$7-'Engine Inputs'!$B$5-'Engine Inputs'!$B$6-2*'Engine Inputs'!$B$7*SQRT(MIN('Engine Inputs'!$B$12*J39/$C$7,'Engine Inputs'!$B$9)/'Engine Inputs'!$B$8))+MAX(J39-MIN('Engine Inputs'!$B$12*J39/$C$7,'Engine Inputs'!$B$9)*$C$7,0)*'Engine Inputs'!$B$10/$D$7)*(1-'Engine Inputs'!$B$4)+IF($D$7=1,(1-IF(OR($D$7=2,MOD(A40,2)=1),1,0))*J39*'Engine Inputs'!$B$10*(1-'Engine Inputs'!$B$4)/2,0)-IF(MOD(A40,2)=0,INDEX($B$11:$D$25,B40,2)*(1-'Engine Inputs'!$B$4),0) -> 57828730 | K40: =K39+IF(OR($D$7=2,MOD(A40,2)=1),1,0)*(MIN('Engine Inputs'!$B$12*K39/$C$7,'Engine Inputs'!$B$9)*($B$7-'Engine Inputs'!$B$5-'Engine Inputs'!$B$6-2*'Engine Inputs'!$B$7*SQRT(MIN('Engine Inputs'!$B$12*K39/$C$7,'Engine Inputs'!$B$9)/'Engine Inputs'!$B$8))+MAX(K39-MIN('Engine Inputs'!$B$12*K39/$C$7,'Engine Inputs'!$B$9)*$C$7,0)*'Engine Inputs'!$B$10/$D$7)*(1-'Engine Inputs'!$B$4)+IF($D$7=1,(1-IF(OR($D$7=2,MOD(A40,2)=1),1,0))*K39*'Engine Inputs'!$B$10*(1-'Engine Inputs'!$B$4)/2,0)-IF(MOD(A40,2)=0,INDEX($B$11:$D$25,B40,3)*(1-'Engine Inputs'!$B$4),0) -> 1.5150572e+08
A41: 13 | B41: =ROUNDUP(A41/2,0) -> 7 | C41: =C40+IF(OR($D$5=2,MOD(A41,2)=1),1,0)*(MIN('Engine Inputs'!$B$12*C40/$C$5,'Engine Inputs'!$B$9)*($B$5-'Engine Inputs'!$B$5-'Engine Inputs'!$B$6-2*'Engine Inputs'!$B$7*SQRT(MIN('Engine Inputs'!$B$12*C40/$C$5,'Engine Inputs'!$B$9)/'Engine Inputs'!$B$8))+MAX(C40-MIN('Engine Inputs'!$B$12*C40/$C$5,'Engine Inputs'!$B$9)*$C$5,0)*'Engine Inputs'!$B$10/$D$5)*(1-'Engine Inputs'!$B$4)+IF($D$5=1,(1-IF(OR($D$5=2,MOD(A41,2)=1),1,0))*C40*'Engine Inputs'!$B$10*(1-'Engine Inputs'!$B$4)/2,0)-IF(MOD(A41,2)=0,INDEX($B$11:$D$25,B41,1)*(1-'Engine Inputs'!$B$4),0) -> 3.1997419e+09 | D41: =D40+IF(OR($D$5=2,MOD(A41,2)=1),1,0)*(MIN('Engine Inputs'!$B$12*D40/$C$5,'Engine Inputs'!$B$9)*($B$5-'Engine Inputs'!$B$5-'Engine Inputs'!$B$6-2*'Engine Inputs'!$B$7*SQRT(MIN('Engine Inputs'!$B$12*D40/$C$5,'Engine Inputs'!$B$9)/'Engine Inputs'!$B$8))+MAX(D40-MIN('Engine Inputs'!$B$12*D40/$C$5,'Engine Inputs'!$B$9)*$C$5,0)*'Engine Inputs'!$B$10/$D$5)*(1-'Engine Inputs'!$B$4)+IF($D$5=1,(1-IF(OR($D$5=2,MOD(A41,2)=1),1,0))*D40*'Engine Inputs'!$B$10*(1-'Engine Inputs'!$B$4)/2,0)-IF(MOD(A41,2)=0,INDEX($B$11:$D$25,B41,2)*(1-'Engine Inputs'!$B$4),0) -> 5.0538257e+09 | E41: =E40+IF(OR($D$5=2,MOD(A41,2)=1),1,0)*(MIN('Engine Inputs'!$B$12*E40/$C$5,'Engine Inputs'!$B$9)*($B$5-'Engine Inputs'!$B$5-'Engine Inputs'!$B$6-2*'Engine Inputs'!$B$7*SQRT(MIN('Engine Inputs'!$B$12*E40/$C$5,'Engine Inputs'!$B$9)/'Engine Inputs'!$B$8))+MAX(E40-MIN('Engine Inputs'!$B$12*E40/$C$5,'Engine Inputs'!$B$9)*$C$5,0)*'Engine Inputs'!$B$10/$D$5)*(1-'Engine Inputs'!$B$4)+IF($D$5=1,(1-IF(OR($D$5=2,MOD(A41,2)=1),1,0))*E40*'Engine Inputs'!$B$10*(1-'Engine Inputs'!$B$4)/2,0)-IF(MOD(A41,2)=0,INDEX($B$11:$D$25,B41,3)*(1-'Engine Inputs'!$B$4),0) -> 6.41891e+09 | F41: =F40+IF(OR($D$6=2,MOD(A41,2)=1),1,0)*(MIN('Engine Inputs'!$B$12*F40/$C$6,'Engine Inputs'!$B$9)*($B$6-'Engine Inputs'!$B$5-'Engine Inputs'!$B$6-2*'Engine Inputs'!$B$7*SQRT(MIN('Engine Inputs'!$B$12*F40/$C$6,'Engine Inputs'!$B$9)/'Engine Inputs'!$B$8))+MAX(F40-MIN('Engine Inputs'!$B$12*F40/$C$6,'Engine Inputs'!$B$9)*$C$6,0)*'Engine Inputs'!$B$10/$D$6)*(1-'Engine Inputs'!$B$4)+IF($D$6=1,(1-IF(OR($D$6=2,MOD(A41,2)=1),1,0))*F40*'Engine Inputs'!$B$10*(1-'Engine Inputs'!$B$4)/2,0)-IF(MOD(A41,2)=0,INDEX($B$11:$D$25,B41,1)*(1-'Engine Inputs'!$B$4),0) -> 2.9609607e+08 | G41: =G40+IF(OR($D$6=2,MOD(A41,2)=1),1,0)*(MIN('Engine Inputs'!$B$12*G40/$C$6,'Engine Inputs'!$B$9)*($B$6-'Engine Inputs'!$B$5-'Engine Inputs'!$B$6-2*'Engine Inputs'!$B$7*SQRT(MIN('Engine Inputs'!$B$12*G40/$C$6,'Engine Inputs'!$B$9)/'Engine Inputs'!$B$8))+MAX(G40-MIN('Engine Inputs'!$B$12*G40/$C$6,'Engine Inputs'!$B$9)*$C$6,0)*'Engine Inputs'!$B$10/$D$6)*(1-'Engine Inputs'!$B$4)+IF($D$6=1,(1-IF(OR($D$6=2,MOD(A41,2)=1),1,0))*G40*'Engine Inputs'!$B$10*(1-'Engine Inputs'!$B$4)/2,0)-IF(MOD(A41,2)=0,INDEX($B$11:$D$25,B41,2)*(1-'Engine Inputs'!$B$4),0) -> 1.0346483e+09 | H41: =H40+IF(OR($D$6=2,MOD(A41,2)=1),1,0)*(MIN('Engine Inputs'!$B$12*H40/$C$6,'Engine Inputs'!$B$9)*($B$6-'Engine Inputs'!$B$5-'Engine Inputs'!$B$6-2*'Engine Inputs'!$B$7*SQRT(MIN('Engine Inputs'!$B$12*H40/$C$6,'Engine Inputs'!$B$9)/'Engine Inputs'!$B$8))+MAX(H40-MIN('Engine Inputs'!$B$12*H40/$C$6,'Engine Inputs'!$B$9)*$C$6,0)*'Engine Inputs'!$B$10/$D$6)*(1-'Engine Inputs'!$B$4)+IF($D$6=1,(1-IF(OR($D$6=2,MOD(A41,2)=1),1,0))*H40*'Engine Inputs'!$B$10*(1-'Engine Inputs'!$B$4)/2,0)-IF(MOD(A41,2)=0,INDEX($B$11:$D$25,B41,3)*(1-'Engine Inputs'!$B$4),0) -> 2.158784e+09 | I41: =I40+IF(OR($D$7=2,MOD(A41,2)=1),1,0)*(MIN('Engine Inputs'!$B$12*I40/$C$7,'Engine Inputs'!$B$9)*($B$7-'Engine Inputs'!$B$5-'Engine Inputs'!$B$6-2*'Engine Inputs'!$B$7*SQRT(MIN('Engine Inputs'!$B$12*I40/$C$7,'Engine Inputs'!$B$9)/'Engine Inputs'!$B$8))+MAX(I40-MIN('Engine Inputs'!$B$12*I40/$C$7,'Engine Inputs'!$B$9)*$C$7,0)*'Engine Inputs'!$B$10/$D$7)*(1-'Engine Inputs'!$B$4)+IF($D$7=1,(1-IF(OR($D$7=2,MOD(A41,2)=1),1,0))*I40*'Engine Inputs'!$B$10*(1-'Engine Inputs'!$B$4)/2,0)-IF(MOD(A41,2)=0,INDEX($B$11:$D$25,B41,1)*(1-'Engine Inputs'!$B$4),0) -> 21574184 | J41: =J40+IF(OR($D$7=2,MOD(A41,2)=1),1,0)*(MIN('Engine Inputs'!$B$12*J40/$C$7,'Engine Inputs'!$B$9)*($B$7-'Engine Inputs'!$B$5-'Engine Inputs'!$B$6-2*'Engine Inputs'!$B$7*SQRT(MIN('Engine Inputs'!$B$12*J40/$C$7,'Engine Inputs'!$B$9)/'Engine Inputs'!$B$8))+MAX(J40-MIN('Engine Inputs'!$B$12*J40/$C$7,'Engine Inputs'!$B$9)*$C$7,0)*'Engine Inputs'!$B$10/$D$7)*(1-'Engine Inputs'!$B$4)+IF($D$7=1,(1-IF(OR($D$7=2,MOD(A41,2)=1),1,0))*J40*'Engine Inputs'!$B$10*(1-'Engine Inputs'!$B$4)/2,0)-IF(MOD(A41,2)=0,INDEX($B$11:$D$25,B41,2)*(1-'Engine Inputs'!$B$4),0) -> 79506207 | K41: =K40+IF(OR($D$7=2,MOD(A41,2)=1),1,0)*(MIN('Engine Inputs'!$B$12*K40/$C$7,'Engine Inputs'!$B$9)*($B$7-'Engine Inputs'!$B$5-'Engine Inputs'!$B$6-2*'Engine Inputs'!$B$7*SQRT(MIN('Engine Inputs'!$B$12*K40/$C$7,'Engine Inputs'!$B$9)/'Engine Inputs'!$B$8))+MAX(K40-MIN('Engine Inputs'!$B$12*K40/$C$7,'Engine Inputs'!$B$9)*$C$7,0)*'Engine Inputs'!$B$10/$D$7)*(1-'Engine Inputs'!$B$4)+IF($D$7=1,(1-IF(OR($D$7=2,MOD(A41,2)=1),1,0))*K40*'Engine Inputs'!$B$10*(1-'Engine Inputs'!$B$4)/2,0)-IF(MOD(A41,2)=0,INDEX($B$11:$D$25,B41,3)*(1-'Engine Inputs'!$B$4),0) -> 2.0726179e+08
... A58: 30 | B58: =ROUNDUP(A58/2,0) -> 15 | C58: =C57+IF(OR($D$5=2,MOD(A58,2)=1),1,0)*(MIN('Engine Inputs'!$B$12*C57/$C$5,'Engine Inputs'!$B$9)*($B$5-'Engine Inputs'!$B$5-'Engine Inputs'!$B$6-2*'Engine Inputs'!$B$7*SQRT(MIN('Engine Inputs'!$B$12*C57/$C$5,'Engine Inputs'!$B$9)/'Engine Inputs'!$B$8))+MAX(C57-MIN('Engine Inputs'!$B$12*C57/$C$5,'Engine Inputs'!$B$9)*$C$5,0)*'Engine Inputs'!$B$10/$D$5)*(1-'Engine Inputs'!$B$4)+IF($D$5=1,(1-IF(OR($D$5=2,MOD(A58,2)=1),1,0))*C57*'Engine Inputs'!$B$10*(1-'Engine Inputs'!$B$4)/2,0)-IF(MOD(A58,2)=0,INDEX($B$11:$D$25,B58,1)*(1-'Engine Inputs'!$B$4),0) -> 2.0556655e+10 | D58: =D57+IF(OR($D$5=2,MOD(A58,2)=1),1,0)*(MIN('Engine Inputs'!$B$12*D57/$C$5,'Engine Inputs'!$B$9)*($B$5-'Engine Inputs'!$B$5-'Engine Inputs'!$B$6-2*'Engine Inputs'!$B$7*SQRT(MIN('Engine Inputs'!$B$12*D57/$C$5,'Engine Inputs'!$B$9)/'Engine Inputs'!$B$8))+MAX(D57-MIN('Engine Inputs'!$B$12*D57/$C$5,'Engine Inputs'!$B$9)*$C$5,0)*'Engine Inputs'!$B$10/$D$5)*(1-'Engine Inputs'!$B$4)+IF($D$5=1,(1-IF(OR($D$5=2,MOD(A58,2)=1),1,0))*D57*'Engine Inputs'!$B$10*(1-'Engine Inputs'!$B$4)/2,0)-IF(MOD(A58,2)=0,INDEX($B$11:$D$25,B58,2)*(1-'Engine Inputs'!$B$4),0) -> 2.334201e+10 | E58: =E57+IF(OR($D$5=2,MOD(A58,2)=1),1,0)*(MIN('Engine Inputs'!$B$12*E57/$C$5,'Engine Inputs'!$B$9)*($B$5-'Engine Inputs'!$B$5-'Engine Inputs'!$B$6-2*'Engine Inputs'!$B$7*SQRT(MIN('Engine Inputs'!$B$12*E57/$C$5,'Engine Inputs'!$B$9)/'Engine Inputs'!$B$8))+MAX(E57-MIN('Engine Inputs'!$B$12*E57/$C$5,'Engine Inputs'!$B$9)*$C$5,0)*'Engine Inputs'!$B$10/$D$5)*(1-'Engine Inputs'!$B$4)+IF($D$5=1,(1-IF(OR($D$5=2,MOD(A58,2)=1),1,0))*E57*'Engine Inputs'!$B$10*(1-'Engine Inputs'!$B$4)/2,0)-IF(MOD(A58,2)=0,INDEX($B$11:$D$25,B58,3)*(1-'Engine Inputs'!$B$4),0) -> 2.5386264e+10 | F58: =F57+IF(OR($D$6=2,MOD(A58,2)=1),1,0)*(MIN('Engine Inputs'!$B$12*F57/$C$6,'Engine Inputs'!$B$9)*($B$6-'Engine Inputs'!$B$5-'Engine Inputs'!$B$6-2*'Engine Inputs'!$B$7*SQRT(MIN('Engine Inputs'!$B$12*F57/$C$6,'Engine Inputs'!$B$9)/'Engine Inputs'!$B$8))+MAX(F57-MIN('Engine Inputs'!$B$12*F57/$C$6,'Engine Inputs'!$B$9)*$C$6,0)*'Engine Inputs'!$B$10/$D$6)*(1-'Engine Inputs'!$B$4)+IF($D$6=1,(1-IF(OR($D$6=2,MOD(A58,2)=1),1,0))*F57*'Engine Inputs'!$B$10*(1-'Engine Inputs'!$B$4)/2,0)-IF(MOD(A58,2)=0,INDEX($B$11:$D$25,B58,1)*(1-'Engine Inputs'!$B$4),0) -> 8.0590378e+09 | G58: =G57+IF(OR($D$6=2,MOD(A58,2)=1),1,0)*(MIN('Engine Inputs'!$B$12*G57/$C$6,'Engine Inputs'!$B$9)*($B$6-'Engine Inputs'!$B$5-'Engine Inputs'!$B$6-2*'Engine Inputs'!$B$7*SQRT(MIN('Engine Inputs'!$B$12*G57/$C$6,'Engine Inputs'!$B$9)/'Engine Inputs'!$B$8))+MAX(G57-MIN('Engine Inputs'!$B$12*G57/$C$6,'Engine Inputs'!$B$9)*$C$6,0)*'Engine Inputs'!$B$10/$D$6)*(1-'Engine Inputs'!$B$4)+IF($D$6=1,(1-IF(OR($D$6=2,MOD(A58,2)=1),1,0))*G57*'Engine Inputs'!$B$10*(1-'Engine Inputs'!$B$4)/2,0)-IF(MOD(A58,2)=0,INDEX($B$11:$D$25,B58,2)*(1-'Engine Inputs'!$B$4),0) -> 1.0226042e+10 | H58: =H57+IF(OR($D$6=2,MOD(A58,2)=1),1,0)*(MIN('Engine Inputs'!$B$12*H57/$C$6,'Engine Inputs'!$B$9)*($B$6-'Engine Inputs'!$B$5-'Engine Inputs'!$B$6-2*'Engine Inputs'!$B$7*SQRT(MIN('Engine Inputs'!$B$12*H57/$C$6,'Engine Inputs'!$B$9)/'Engine Inputs'!$B$8))+MAX(H57-MIN('Engine Inputs'!$B$12*H57/$C$6,'Engine Inputs'!$B$9)*$C$6,0)*'Engine Inputs'!$B$10/$D$6)*(1-'Engine Inputs'!$B$4)+IF($D$6=1,(1-IF(OR($D$6=2,MOD(A58,2)=1),1,0))*H57*'Engine Inputs'!$B$10*(1-'Engine Inputs'!$B$4)/2,0)-IF(MOD(A58,2)=0,INDEX($B$11:$D$25,B58,3)*(1-'Engine Inputs'!$B$4),0) -> 1.1907775e+10 | I58: =I57+IF(OR($D$7=2,MOD(A58,2)=1),1,0)*(MIN('Engine Inputs'!$B$12*I57/$C$7,'Engine Inputs'!$B$9)*($B$7-'Engine Inputs'!$B$5-'Engine Inputs'!$B$6-2*'Engine Inputs'!$B$7*SQRT(MIN('Engine Inputs'!$B$12*I57/$C$7,'Engine Inputs'!$B$9)/'Engine Inputs'!$B$8))+MAX(I57-MIN('Engine Inputs'!$B$12*I57/$C$7,'Engine Inputs'!$B$9)*$C$7,0)*'Engine Inputs'!$B$10/$D$7)*(1-'Engine Inputs'!$B$4)+IF($D$7=1,(1-IF(OR($D$7=2,MOD(A58,2)=1),1,0))*I57*'Engine Inputs'!$B$10*(1-'Engine Inputs'!$B$4)/2,0)-IF(MOD(A58,2)=0,INDEX($B$11:$D$25,B58,1)*(1-'Engine Inputs'!$B$4),0) -> 3.310277e+08 | J58: =J57+IF(OR($D$7=2,MOD(A58,2)=1),1,0)*(MIN('Engine Inputs'!$B$12*J57/$C$7,'Engine Inputs'!$B$9)*($B$7-'Engine Inputs'!$B$5-'Engine Inputs'!$B$6-2*'Engine Inputs'!$B$7*SQRT(MIN('Engine Inputs'!$B$12*J57/$C$7,'Engine Inputs'!$B$9)/'Engine Inputs'!$B$8))+MAX(J57-MIN('Engine Inputs'!$B$12*J57/$C$7,'Engine Inputs'!$B$9)*$C$7,0)*'Engine Inputs'!$B$10/$D$7)*(1-'Engine Inputs'!$B$4)+IF($D$7=1,(1-IF(OR($D$7=2,MOD(A58,2)=1),1,0))*J57*'Engine Inputs'!$B$10*(1-'Engine Inputs'!$B$4)/2,0)-IF(MOD(A58,2)=0,INDEX($B$11:$D$25,B58,2)*(1-'Engine Inputs'!$B$4),0) -> 1.1370715e+09 | K58: =K57+IF(OR($D$7=2,MOD(A58,2)=1),1,0)*(MIN('Engine Inputs'!$B$12*K57/$C$7,'Engine Inputs'!$B$9)*($B$7-'Engine Inputs'!$B$5-'Engine Inputs'!$B$6-2*'Engine Inputs'!$B$7*SQRT(MIN('Engine Inputs'!$B$12*K57/$C$7,'Engine Inputs'!$B$9)/'Engine Inputs'!$B$8))+MAX(K57-MIN('Engine Inputs'!$B$12*K57/$C$7,'Engine Inputs'!$B$9)*$C$7,0)*'Engine Inputs'!$B$10/$D$7)*(1-'Engine Inputs'!$B$4)+IF($D$7=1,(1-IF(OR($D$7=2,MOD(A58,2)=1),1,0))*K57*'Engine Inputs'!$B$10*(1-'Engine Inputs'!$B$4)/2,0)-IF(MOD(A58,2)=0,INDEX($B$11:$D$25,B58,3)*(1-'Engine Inputs'!$B$4),0) -> 2.344273e+09
A60: YEAR-END SUMMARY (₹ Cr)
A61: Year | B61: ="BULL "&IF($C$3>=10000000,"₹"&TEXT($C$3/10000000,"0.##")&"Cr","₹"&TEXT($C$3/100000,"0.##")&"L") -> BULL ₹20.L | C61: ="BULL "&IF($D$3>=10000000,"₹"&TEXT($D$3/10000000,"0.##")&"Cr","₹"&TEXT($D$3/100000,"0.##")&"L") -> BULL ₹75.L | D61: ="BULL "&IF($E$3>=10000000,"₹"&TEXT($E$3/10000000,"0.##")&"Cr","₹"&TEXT($E$3/100000,"0.##")&"L") -> BULL ₹2.Cr | E61: ="BASE "&IF($C$3>=10000000,"₹"&TEXT($C$3/10000000,"0.##")&"Cr","₹"&TEXT($C$3/100000,"0.##")&"L") -> BASE ₹20.L | F61: ="BASE "&IF($D$3>=10000000,"₹"&TEXT($D$3/10000000,"0.##")&"Cr","₹"&TEXT($D$3/100000,"0.##")&"L") -> BASE ₹75.L | G61: ="BASE "&IF($E$3>=10000000,"₹"&TEXT($E$3/10000000,"0.##")&"Cr","₹"&TEXT($E$3/100000,"0.##")&"L") -> BASE ₹2.Cr | H61: ="BEAR "&IF($C$3>=10000000,"₹"&TEXT($C$3/10000000,"0.##")&"Cr","₹"&TEXT($C$3/100000,"0.##")&"L") -> BEAR ₹20.L | I61: ="BEAR "&IF($D$3>=10000000,"₹"&TEXT($D$3/10000000,"0.##")&"Cr","₹"&TEXT($D$3/100000,"0.##")&"L") -> BEAR ₹75.L | J61: ="BEAR "&IF($E$3>=10000000,"₹"&TEXT($E$3/10000000,"0.##")&"Cr","₹"&TEXT($E$3/100000,"0.##")&"L") -> BEAR ₹2.Cr
A62: 1 | B62: =C30/10000000 -> 0.68221216 | C62: =D30/10000000 -> 2.5512046 | D62: =E30/10000000 -> 6.7785195 | E62: =F30/10000000 -> 0.43430809 | F62: =G30/10000000 -> 1.6237476 | G62: =H30/10000000 -> 4.3129079 | H62: =I30/10000000 -> 0.28200697 | I62: =J30/10000000 -> 1.056046 | J62: =K30/10000000 -> 2.8109562
A63: 2 | B63: =C32/10000000 -> 2.324842 | C63: =D32/10000000 -> 8.6496756 | D63: =E32/10000000 -> 22.829114 | E63: =F32/10000000 -> 0.94343288 | F63: =G32/10000000 -> 3.5116129 | G63: =H32/10000000 -> 9.2735085 | H63: =I32/10000000 -> 0.39814193 | I63: =J32/10000000 -> 1.4884634 | J63: =K32/10000000 -> 3.9533305
A64: 3 | B64: =C34/10000000 -> 7.887371 | C64: =D34/10000000 -> 29.070751 | D64: =E34/10000000 -> 75.794077 | E64: =F34/10000000 -> 2.0442978 | F64: =G34/10000000 -> 7.5597884 | G64: =H34/10000000 -> 19.795532 | H64: =I34/10000000 -> 0.56028698 | I64: =J34/10000000 -> 2.0904722 | J64: =K34/10000000 -> 5.5377923
A65: 4 | B65: =C36/10000000 -> 26.541125 | C65: =D36/10000000 -> 96.156137 | D65: =E36/10000000 -> 216.10751 | E65: =F36/10000000 -> 4.4194949 | F65: =G36/10000000 -> 16.188355 | G65: =H36/10000000 -> 41.871542 | H65: =I36/10000000 -> 0.78967979 | I65: =J36/10000000 -> 2.9394138 | J65: =K36/10000000 -> 7.7627656
A66: 5 | B66: =C38/10000000 -> 87.934873 | C66: =D38/10000000 -> 253.23552 | D66: =E38/10000000 -> 380.29421 | E66: =F38/10000000 -> 9.5087946 | F66: =G38/10000000 -> 34.349804 | G66: =H38/10000000 -> 87.282224 | H66: =I38/10000000 -> 1.1102595 | I66: =J38/10000000 -> 4.1210569 | J66: =K38/10000000 -> 10.843469
A67: 6 | B67: =C40/10000000 -> 238.29065 | C67: =D40/10000000 -> 419.29689 | D67: =E40/10000000 -> 552.5642 | E67: =F40/10000000 -> 20.323033 | F67: =G40/10000000 -> 71.954102 | G67: =H40/10000000 -> 169.9304 | H67: =I40/10000000 -> 1.5631568 | I67: =J40/10000000 -> 5.782873 | J67: =K40/10000000 -> 15.150572
A68: 7 | B68: =C42/10000000 -> 403.63683 | C68: =D42/10000000 -> 593.53383 | D68: =E42/10000000 -> 733.31543 | E68: =F42/10000000 -> 42.999924 | F68: =G42/10000000 -> 147.76831 | G68: =H42/10000000 -> 262.86905 | H68: =I42/10000000 -> 2.2024045 | I68: =J42/10000000 -> 8.115921 | J68: =K42/10000000 -> 21.155416
A69: 8 | B69: =C44/10000000 -> 577.11589 | C69: =D44/10000000 -> 776.3208 | D69: =E44/10000000 -> 922.89063 | E69: =F44/10000000 -> 89.639863 | F69: =G44/10000000 -> 239.63458 | G69: =H44/10000000 -> 360.30846 | H69: =I44/10000000 -> 3.0962211 | I69: =J44/10000000 -> 11.356492 | J69: =K44/10000000 -> 29.424581
A70: 9 | B70: =C46/10000000 -> 759.13573 | C70: =D46/10000000 -> 968.10679 | D70: =E46/10000000 -> 1121.799 | E70: =F46/10000000 -> 173.39781 | F70: =G46/10000000 -> 336.02364 | G70: =H46/10000000 -> 462.54502 | H70: =I46/10000000 -> 4.3548348 | I70: =J46/10000000 -> 15.885499 | J70: =K46/10000000 -> 40.870087
A71: 10 | B71: =C48/10000000 -> 950.11681 | C71: =D48/10000000 -> 1169.3348 | D71: =E48/10000000 -> 1330.5002 | E71: =F48/10000000 -> 266.56704 | F71: =G48/10000000 -> 437.15815 | G71: =H48/10000000 -> 569.81493 | H71: =I48/10000000 -> 6.1244439 | I71: =J48/10000000 -> 22.196983 | J71: =K48/10000000 -> 56.639329
A72: 11 | B72: =C50/10000000 -> 1150.5003 | C72: =D50/10000000 -> 1380.4698 | D72: =E50/10000000 -> 1549.4761 | E72: =F50/10000000 -> 364.32321 | F72: =G50/10000000 -> 543.27174 | G72: =H50/10000000 -> 682.36598 | H72: =I50/10000000 -> 8.6080286 | I72: =J50/10000000 -> 30.962479 | J72: =K50/10000000 -> 78.248312
A73: 12 | B73: =C52/10000000 -> 1360.7492 | C73: =D52/10000000 -> 1601.9994 | D73: =E52/10000000 -> 1779.2328 | E73: =F52/10000000 -> 466.89213 | F73: =G52/10000000 -> 654.60955 | G73: =H52/10000000 -> 800.45818 | H73: =I52/10000000 -> 12.0862 | I73: =J52/10000000 -> 43.087137 | J73: =K52/10000000 -> 107.67195
A74: 13 | B74: =C54/10000000 -> 1581.3491 | C74: =D54/10000000 -> 1834.4355 | D74: =E54/10000000 -> 2020.3009 | E74: =F54/10000000 -> 574.51075 | F74: =G54/10000000 -> 771.42877 | G74: =H54/10000000 -> 924.36432 | H74: =I54/10000000 -> 16.944911 | I74: =J54/10000000 -> 59.778718 | J74: =K54/10000000 -> 146.94026
A75: 14 | B75: =C56/10000000 -> 1812.8096 | C75: =D56/10000000 -> 2078.3148 | D75: =E56/10000000 -> 2273.2373 | E75: =F56/10000000 -> 687.42768 | F75: =G56/10000000 -> 893.99927 | G75: =H56/10000000 -> 1054.3706 | H75: =I56/10000000 -> 23.71177 | I75: =J56/10000000 -> 82.629312 | J75: =K56/10000000 -> 189.12009
A76: 15 | B76: =C58/10000000 -> 2055.6655 | C76: =D58/10000000 -> 2334.201 | D76: =E58/10000000 -> 2538.6264 | E76: =F58/10000000 -> 805.90378 | F76: =G58/10000000 -> 1022.6042 | G76: =H58/10000000 -> 1190.7775 | H76: =I58/10000000 -> 33.10277 | I76: =J58/10000000 -> 113.70715 | J76: =K58/10000000 -> 234.4273
A78: GIFT gateway crossed (capital ≥ ₹20 Cr) in year:

Sheet Roll & Cost Drag
A1: ROLL YIELD / COST DRAG
A2: Actual tradeable alpha after rolling contracts in the DTE 5-60 window.
A3: Roll gap % is therefore a blue INPUT to be measured from your prices.db (front vs next close on roll dates), not a PDF-derived constant.
A4: Mechanics: swings average 20-40 days (PDF Task 2) inside a ~55-day liquid window, so expected rolls per trade ≈ 0.5. Cost is paid on NOTIONAL, so it scales with leverage: ROC drag = cost% ÷ margin%.
A6: Inputs
A7: Roll gap per roll (% notional) | B7: 0.01 | C7: Measure from prices.db; contango months can exceed 2%
A8: Expected rolls per trade | B8: 0.5 | C8: Swing duration / contract window
A9: Txn RT (% notional) | B9: 0.0006
A10: Margin % (Base) | B10: 0.2727
A11: Gross move per trade | B11: 0.25
A13: Outputs (live)
A14: Cost per trade (% notional) | B14: =B7*B8+B9 -> 0.0056
A15: Gross ROC per trade | B15: =B11/B10 -> 0.91675834
A16: ROC drag from costs | B16: =(B7*B8+B9)/B10 -> 0.020535387
A17: NET tradeable ROC per trade | B17: =(B11-B7*B8-B9)/B10 -> 0.89622296
A18: Alpha lost per trade (pp of ROC) | B18: =B15-B17 -> 0.020535387
A19: 15-yr terminal impact, 2 trades/yr, post-tax (× factor) | B19: =((1+B17*(1-0.25168))/(1+B15*(1-0.25168)))^30 -> 0.75981223

Sheet Margin Trap Risk
A1: PREEMPTIVE MARGIN TRAP
A2: Probability of capital lock-up at elevated margin and the IRR drag it creates.
A3: PDF Task 3 timing: peak margin LEADS the swing 16.4% of the time and is SIMULTANEOUS 44.1% — i.e. 60% of the time the hike hits before your move completes.
A4: From the 123-leg 2020-26 dataset: 5 legs (4.1%) carried an AVERAGE margin ≥40% for the whole leg.
A6: Inputs
A7: Quiet-spike events (PDF) | B7: 23
A8: Observation years | B8: 16.4
A9: Trading days/yr | B9: 250
A10: Trade window (days) | B10: 30
A11: Margin pre-trap | B11: 0.2727
A12: Margin in trap | B12: 0.4
A13: Avg share of move remaining when hiked | B13: 0.5
A14: Base gross ROC/trade | B14: 0.917
A16: Outputs
A17: Daily quiet-spike probability | B17: =B7/(B8*B9) -> 0.0056097561
A18: P(trap within one trade window) | B18: =1-(1-B7/(B8*B9))^B10 -> 0.15529388
A19: Forced position cut if fully deployed (1 − m/m') | B19: =1-B11/B12 -> 0.31825
A20: Expected ROC haircut per trade | B20: =B18*B19*B13*B14 -> 0.022660114
A21: Annualized IRR drag (2 trades/yr, post-tax) | B21: =((1+(B14-B20)*(1-0.25168))^2)/((1+B14*(1-0.25168))^2)-1 -> -0.020011457
A23: Mitigation rule: never deploy ≥ margin-utilisation 1/(1+headroom). With m→m' risk of 27%→40%, keep ≥32% of corpus as free collateral; this is another argument for Kelly < 1.

Sheet Kelly Sizing
A1: KELLY CRITERION
A2: Optimal deployment fraction of corpus as margin — p is YOUR calibration, not from the PDF.
A4: Inputs
A5: Win probability p (YOUR stat — not in PDF) | B5: 0.55
A6: Win ROC b (Base: 25%/27.3%) | B6: 0.917
A7: Stop-loss adverse move | B7: 0.07
A8: Margin % | B8: 0.2727
A10: Outputs
A11: Loss per unit staked a = stop/margin | B11: =B7/B8 -> 0.25669234
A12: Full Kelly f* = p/a − (1−p)/b | B12: =B5/B11-(1-B5)/B6 -> 1.6519122
A13: Capped deployable (min(f*,1)) | B13: =MIN(B12,1) -> 1
A14: Half-Kelly (recommended) | B14: =MIN(B12,2)/2 -> 0.82595611
A15: Expected log-growth at half-Kelly per trade | B15: =B5*LN(1+B14*B6)+(1-B5)*LN(1-B14*B11) -> 0.20288483
A18: FULL-KELLY f* SENSITIVITY — p (rows) × stop-loss move (cols), Base margin
A19: p \ stop | B19: 0.05 | C19: 0.07 | D19: 0.1 | E19: 0.12 | F19: 0.15
A20: 0.45 | B20: =$A20/(B$19/$B$8)-(1-$A20)/$B$6 -> 1.8545181 | C20: =$A20/(C$19/$B$8)-(1-$A20)/$B$6 -> 1.1532895 | D20: =$A20/(D$19/$B$8)-(1-$A20)/$B$6 -> 0.6273681 | E20: =$A20/(E$19/$B$8)-(1-$A20)/$B$6 -> 0.4228431 | F20: =$A20/(F$19/$B$8)-(1-$A20)/$B$6 -> 0.2183181
A21: 0.5 | B21: =$A21/(B$19/$B$8)-(1-$A21)/$B$6 -> 2.1817437 | C21: =$A21/(C$19/$B$8)-(1-$A21)/$B$6 -> 1.4026009 | D21: =$A21/(D$19/$B$8)-(1-$A21)/$B$6 -> 0.81824373 | E21: =$A21/(E$19/$B$8)-(1-$A21)/$B$6 -> 0.59099373 | F21: =$A21/(F$19/$B$8)-(1-$A21)/$B$6 -> 0.36374373
A22: 0.55 | B22: =$A22/(B$19/$B$8)-(1-$A22)/$B$6 -> 2.5089694 | C22: =$A22/(C$19/$B$8)-(1-$A22)/$B$6 -> 1.6519122 | D22: =$A22/(D$19/$B$8)-(1-$A22)/$B$6 -> 1.0091194 | E22: =$A22/(E$19/$B$8)-(1-$A22)/$B$6 -> 0.75914436 | F22: =$A22/(F$19/$B$8)-(1-$A22)/$B$6 -> 0.50916936
A23: 0.6 | B23: =$A23/(B$19/$B$8)-(1-$A23)/$B$6 -> 2.836195 | C23: =$A23/(C$19/$B$8)-(1-$A23)/$B$6 -> 1.9012236 | D23: =$A23/(D$19/$B$8)-(1-$A23)/$B$6 -> 1.199995 | E23: =$A23/(E$19/$B$8)-(1-$A23)/$B$6 -> 0.92729498 | F23: =$A23/(F$19/$B$8)-(1-$A23)/$B$6 -> 0.65459498
A24: 0.65 | B24: =$A24/(B$19/$B$8)-(1-$A24)/$B$6 -> 3.1634206 | C24: =$A24/(C$19/$B$8)-(1-$A24)/$B$6 -> 2.1505349 | D24: =$A24/(D$19/$B$8)-(1-$A24)/$B$6 -> 1.3908706 | E24: =$A24/(E$19/$B$8)-(1-$A24)/$B$6 -> 1.0954456 | F24: =$A24/(F$19/$B$8)-(1-$A24)/$B$6 -> 0.80002061
A25: 0.7 | B25: =$A25/(B$19/$B$8)-(1-$A25)/$B$6 -> 3.4906462 | C25: =$A25/(C$19/$B$8)-(1-$A25)/$B$6 -> 2.3998462 | D25: =$A25/(D$19/$B$8)-(1-$A25)/$B$6 -> 1.5817462 | E25: =$A25/(E$19/$B$8)-(1-$A25)/$B$6 -> 1.2635962 | F25: =$A25/(F$19/$B$8)-(1-$A25)/$B$6 -> 0.94544624

Sheet GIFT Bridge
A1: PHASE-2 BRIDGE · STAY vs SWITCH vs HYBRID
A2: Cap the MCX sleeve, sweep overflow to GIFT — the hybrid dominates both pure strategies.
A4: Inputs
A5: MCX sleeve cap (₹) | B5: 1000000000
A6: GIFT gross return / 18-mo cycle | B6: 0.75
A7: GIFT expense per cycle (₹) | B7: 5000000
A8: Tax (115BAA corp) | B8: 0.25168
A9: Move % | B9: 0.25
A10: Margin % | B10: 0.2727
A11: Start capital (₹) | B11: 7500000
A14: Year | B14: STAY: MCX only (₹) | C14: SWITCH: all→GIFT at ₹20Cr (₹) | D14: HYBRID MCX sleeve (₹) | E14: HYBRID GIFT sleeve (₹) | F14: HYBRID total (₹)
A15: 1 | B15: =($B$11+(MIN($B$11/$B$10,'Engine Inputs'!$B$9)*($B$9-'Engine Inputs'!$B$5-'Engine Inputs'!$B$6-2*'Engine Inputs'!$B$7*SQRT(MIN($B$11/$B$10,'Engine Inputs'!$B$9)/'Engine Inputs'!$B$8))+MAX($B$11-MIN($B$11/$B$10,'Engine Inputs'!$B$9)*$B$10,0)*'Engine Inputs'!$B$10/2)*(1-$B$8))+(MIN(($B$11+(MIN($B$11/$B$10,'Engine Inputs'!$B$9)*($B$9-'Engine Inputs'!$B$5-'Engine Inputs'!$B$6-2*'Engine Inputs'!$B$7*SQRT(MIN($B$11/$B$10,'Engine Inputs'!$B$9)/'Engine Inputs'!$B$8))+MAX($B$11-MIN($B$11/$B$10,'Engine Inputs'!$B$9)*$B$10,0)*'Engine Inputs'!$B$10/2)*(1-$B$8))/$B$10,'Engine Inputs'!$B$9)*($B$9-'Engine Inputs'!$B$5-'Engine Inputs'!$B$6-2*'Engine Inputs'!$B$7*SQRT(MIN(($B$11+(MIN($B$11/$B$10,'Engine Inputs'!$B$9)*($B$9-'Engine Inputs'!$B$5-'Engine Inputs'!$B$6-2*'Engine Inputs'!$B$7*SQRT(MIN($B$11/$B$10,'Engine Inputs'!$B$9)/'Engine Inputs'!$B$8))+MAX($B$11-MIN($B$11/$B$10,'Engine Inputs'!$B$9)*$B$10,0)*'Engine Inputs'!$B$10/2)*(1-$B$8))/$B$10,'Engine Inputs'!$B$9)/'Engine Inputs'!$B$8))+MAX(($B$11+(MIN($B$11/$B$10,'Engine Inputs'!$B$9)*($B$9-'Engine Inputs'!$B$5-'Engine Inputs'!$B$6-2*'Engine Inputs'!$B$7*SQRT(MIN($B$11/$B$10,'Engine Inputs'!$B$9)/'Engine Inputs'!$B$8))+MAX($B$11-MIN($B$11/$B$10,'Engine Inputs'!$B$9)*$B$10,0)*'Engine Inputs'!$B$10/2)*(1-$B$8))-MIN(($B$11+(MIN($B$11/$B$10,'Engine Inputs'!$B$9)*($B$9-'Engine Inputs'!$B$5-'Engine Inputs'!$B$6-2*'Engine Inputs'!$B$7*SQRT(MIN($B$11/$B$10,'Engine Inputs'!$B$9)/'Engine Inputs'!$B$8))+MAX($B$11-MIN($B$11/$B$10,'Engine Inputs'!$B$9)*$B$10,0)*'Engine Inputs'!$B$10/2)*(1-$B$8))/$B$10,'Engine Inputs'!$B$9)*$B$10,0)*'Engine Inputs'!$B$10/2)*(1-$B$8)-INDEX('Rebuilt Scenarios'!$C$11:$C$25,A15)*(1-$B$8) -> 20758382 | C15: =IF($B$11<'Engine Inputs'!$B$11,($B$11+(MIN($B$11/$B$10,'Engine Inputs'!$B$9)*($B$9-'Engine Inputs'!$B$5-'Engine Inputs'!$B$6-2*'Engine Inputs'!$B$7*SQRT(MIN($B$11/$B$10,'Engine Inputs'!$B$9)/'Engine Inputs'!$B$8))+MAX($B$11-MIN($B$11/$B$10,'Engine Inputs'!$B$9)*$B$10,0)*'Engine Inputs'!$B$10/2)*(1-$B$8))+(MIN(($B$11+(MIN($B$11/$B$10,'Engine Inputs'!$B$9)*($B$9-'Engine Inputs'!$B$5-'Engine Inputs'!$B$6-2*'Engine Inputs'!$B$7*SQRT(MIN($B$11/$B$10,'Engine Inputs'!$B$9)/'Engine Inputs'!$B$8))+MAX($B$11-MIN($B$11/$B$10,'Engine Inputs'!$B$9)*$B$10,0)*'Engine Inputs'!$B$10/2)*(1-$B$8))/$B$10,'Engine Inputs'!$B$9)*($B$9-'Engine Inputs'!$B$5-'Engine Inputs'!$B$6-2*'Engine Inputs'!$B$7*SQRT(MIN(($B$11+(MIN($B$11/$B$10,'Engine Inputs'!$B$9)*($B$9-'Engine Inputs'!$B$5-'Engine Inputs'!$B$6-2*'Engine Inputs'!$B$7*SQRT(MIN($B$11/$B$10,'Engine Inputs'!$B$9)/'Engine Inputs'!$B$8))+MAX($B$11-MIN($B$11/$B$10,'Engine Inputs'!$B$9)*$B$10,0)*'Engine Inputs'!$B$10/2)*(1-$B$8))/$B$10,'Engine Inputs'!$B$9)/'Engine Inputs'!$B$8))+MAX(($B$11+(MIN($B$11/$B$10,'Engine Inputs'!$B$9)*($B$9-'Engine Inputs'!$B$5-'Engine Inputs'!$B$6-2*'Engine Inputs'!$B$7*SQRT(MIN($B$11/$B$10,'Engine Inputs'!$B$9)/'Engine Inputs'!$B$8))+MAX($B$11-MIN($B$11/$B$10,'Engine Inputs'!$B$9)*$B$10,0)*'Engine Inputs'!$B$10/2)*(1-$B$8))-MIN(($B$11+(MIN($B$11/$B$10,'Engine Inputs'!$B$9)*($B$9-'Engine Inputs'!$B$5-'Engine Inputs'!$B$6-2*'Engine Inputs'!$B$7*SQRT(MIN($B$11/$B$10,'Engine Inputs'!$B$9)/'Engine Inputs'!$B$8))+MAX($B$11-MIN($B$11/$B$10,'Engine Inputs'!$B$9)*$B$10,0)*'Engine Inputs'!$B$10/2)*(1-$B$8))/$B$10,'Engine Inputs'!$B$9)*$B$10,0)*'Engine Inputs'!$B$10/2)*(1-$B$8)-INDEX('Rebuilt Scenarios'!$C$11:$C$25,A15)*(1-$B$8),$B$11+(($B$6*$B$11-$B$7)*(12/18))*(1-$B$8)) -> 20758382 | D15: =MIN(($B$11+(MIN($B$11/$B$10,'Engine Inputs'!$B$9)*($B$9-'Engine Inputs'!$B$5-'Engine Inputs'!$B$6-2*'Engine Inputs'!$B$7*SQRT(MIN($B$11/$B$10,'Engine Inputs'!$B$9)/'Engine Inputs'!$B$8))+MAX($B$11-MIN($B$11/$B$10,'Engine Inputs'!$B$9)*$B$10,0)*'Engine Inputs'!$B$10/2)*(1-$B$8))+(MIN(($B$11+(MIN($B$11/$B$10,'Engine Inputs'!$B$9)*($B$9-'Engine Inputs'!$B$5-'Engine Inputs'!$B$6-2*'Engine Inputs'!$B$7*SQRT(MIN($B$11/$B$10,'Engine Inputs'!$B$9)/'Engine Inputs'!$B$8))+MAX($B$11-MIN($B$11/$B$10,'Engine Inputs'!$B$9)*$B$10,0)*'Engine Inputs'!$B$10/2)*(1-$B$8))/$B$10,'Engine Inputs'!$B$9)*($B$9-'Engine Inputs'!$B$5-'Engine Inputs'!$B$6-2*'Engine Inputs'!$B$7*SQRT(MIN(($B$11+(MIN($B$11/$B$10,'Engine Inputs'!$B$9)*($B$9-'Engine Inputs'!$B$5-'Engine Inputs'!$B$6-2*'Engine Inputs'!$B$7*SQRT(MIN($B$11/$B$10,'Engine Inputs'!$B$9)/'Engine Inputs'!$B$8))+MAX($B$11-MIN($B$11/$B$10,'Engine Inputs'!$B$9)*$B$10,0)*'Engine Inputs'!$B$10/2)*(1-$B$8))/$B$10,'Engine Inputs'!$B$9)/'Engine Inputs'!$B$8))+MAX(($B$11+(MIN($B$11/$B$10,'Engine Inputs'!$B$9)*($B$9-'Engine Inputs'!$B$5-'Engine Inputs'!$B$6-2*'Engine Inputs'!$B$7*SQRT(MIN($B$11/$B$10,'Engine Inputs'!$B$9)/'Engine Inputs'!$B$8))+MAX($B$11-MIN($B$11/$B$10,'Engine Inputs'!$B$9)*$B$10,0)*'Engine Inputs'!$B$10/2)*(1-$B$8))-MIN(($B$11+(MIN($B$11/$B$10,'Engine Inputs'!$B$9)*($B$9-'Engine Inputs'!$B$5-'Engine Inputs'!$B$6-2*'Engine Inputs'!$B$7*SQRT(MIN($B$11/$B$10,'Engine Inputs'!$B$9)/'Engine Inputs'!$B$8))+MAX($B$11-MIN($B$11/$B$10,'Engine Inputs'!$B$9)*$B$10,0)*'Engine Inputs'!$B$10/2)*(1-$B$8))/$B$10,'Engine Inputs'!$B$9)*$B$10,0)*'Engine Inputs'!$B$10/2)*(1-$B$8)-INDEX('Rebuilt Scenarios'!$C$11:$C$25,A15)*(1-$B$8),$B$5) -> 20758382 | E15: =IF(0>0,0+(($B$6*0-$B$7)*(12/18))*(1-$B$8),0)+MAX(($B$11+(MIN($B$11/$B$10,'Engine Inputs'!$B$9)*($B$9-'Engine Inputs'!$B$5-'Engine Inputs'!$B$6-2*'Engine Inputs'!$B$7*SQRT(MIN($B$11/$B$10,'Engine Inputs'!$B$9)/'Engine Inputs'!$B$8))+MAX($B$11-MIN($B$11/$B$10,'Engine Inputs'!$B$9)*$B$10,0)*'Engine Inputs'!$B$10/2)*(1-$B$8))+(MIN(($B$11+(MIN($B$11/$B$10,'Engine Inputs'!$B$9)*($B$9-'Engine Inputs'!$B$5-'Engine Inputs'!$B$6-2*'Engine Inputs'!$B$7*SQRT(MIN($B$11/$B$10,'Engine Inputs'!$B$9)/'Engine Inputs'!$B$8))+MAX($B$11-MIN($B$11/$B$10,'Engine Inputs'!$B$9)*$B$10,0)*'Engine Inputs'!$B$10/2)*(1-$B$8))/$B$10,'Engine Inputs'!$B$9)*($B$9-'Engine Inputs'!$B$5-'Engine Inputs'!$B$6-2*'Engine Inputs'!$B$7*SQRT(MIN(($B$11+(MIN($B$11/$B$10,'Engine Inputs'!$B$9)*($B$9-'Engine Inputs'!$B$5-'Engine Inputs'!$B$6-2*'Engine Inputs'!$B$7*SQRT(MIN($B$11/$B$10,'Engine Inputs'!$B$9)/'Engine Inputs'!$B$8))+MAX($B$11-MIN($B$11/$B$10,'Engine Inputs'!$B$9)*$B$10,0)*'Engine Inputs'!$B$10/2)*(1-$B$8))/$B$10,'Engine Inputs'!$B$9)/'Engine Inputs'!$B$8))+MAX(($B$11+(MIN($B$11/$B$10,'Engine Inputs'!$B$9)*($B$9-'Engine Inputs'!$B$5-'Engine Inputs'!$B$6-2*'Engine Inputs'!$B$7*SQRT(MIN($B$11/$B$10,'Engine Inputs'!$B$9)/'Engine Inputs'!$B$8))+MAX($B$11-MIN($B$11/$B$10,'Engine Inputs'!$B$9)*$B$10,0)*'Engine Inputs'!$B$10/2)*(1-$B$8))-MIN(($B$11+(MIN($B$11/$B$10,'Engine Inputs'!$B$9)*($B$9-'Engine Inputs'!$B$5-'Engine Inputs'!$B$6-2*'Engine Inputs'!$B$7*SQRT(MIN($B$11/$B$10,'Engine Inputs'!$B$9)/'Engine Inputs'!$B$8))+MAX($B$11-MIN($B$11/$B$10,'Engine Inputs'!$B$9)*$B$10,0)*'Engine Inputs'!$B$10/2)*(1-$B$8))/$B$10,'Engine Inputs'!$B$9)*$B$10,0)*'Engine Inputs'!$B$10/2)*(1-$B$8)-INDEX('Rebuilt Scenarios'!$C$11:$C$25,A15)*(1-$B$8)-$B$5,0) -> 0 | F15: =D15+E15 -> 20758382
A16: 2 | B16: =(B15+(MIN(B15/$B$10,'Engine Inputs'!$B$9)*($B$9-'Engine Inputs'!$B$5-'Engine Inputs'!$B$6-2*'Engine Inputs'!$B$7*SQRT(MIN(B15/$B$10,'Engine Inputs'!$B$9)/'Engine Inputs'!$B$8))+MAX(B15-MIN(B15/$B$10,'Engine Inputs'!$B$9)*$B$10,0)*'Engine Inputs'!$B$10/2)*(1-$B$8))+(MIN((B15+(MIN(B15/$B$10,'Engine Inputs'!$B$9)*($B$9-'Engine Inputs'!$B$5-'Engine Inputs'!$B$6-2*'Engine Inputs'!$B$7*SQRT(MIN(B15/$B$10,'Engine Inputs'!$B$9)/'Engine Inputs'!$B$8))+MAX(B15-MIN(B15/$B$10,'Engine Inputs'!$B$9)*$B$10,0)*'Engine Inputs'!$B$10/2)*(1-$B$8))/$B$10,'Engine Inputs'!$B$9)*($B$9-'Engine Inputs'!$B$5-'Engine Inputs'!$B$6-2*'Engine Inputs'!$B$7*SQRT(MIN((B15+(MIN(B15/$B$10,'Engine Inputs'!$B$9)*($B$9-'Engine Inputs'!$B$5-'Engine Inputs'!$B$6-2*'Engine Inputs'!$B$7*SQRT(MIN(B15/$B$10,'Engine Inputs'!$B$9)/'Engine Inputs'!$B$8))+MAX(B15-MIN(B15/$B$10,'Engine Inputs'!$B$9)*$B$10,0)*'Engine Inputs'!$B$10/2)*(1-$B$8))/$B$10,'Engine Inputs'!$B$9)/'Engine Inputs'!$B$8))+MAX((B15+(MIN(B15/$B$10,'Engine Inputs'!$B$9)*($B$9-'Engine Inputs'!$B$5-'Engine Inputs'!$B$6-2*'Engine Inputs'!$B$7*SQRT(MIN(B15/$B$10,'Engine Inputs'!$B$9)/'Engine Inputs'!$B$8))+MAX(B15-MIN(B15/$B$10,'Engine Inputs'!$B$9)*$B$10,0)*'Engine Inputs'!$B$10/2)*(1-$B$8))-MIN((B15+(MIN(B15/$B$10,'Engine Inputs'!$B$9)*($B$9-'Engine Inputs'!$B$5-'Engine Inputs'!$B$6-2*'Engine Inputs'!$B$7*SQRT(MIN(B15/$B$10,'Engine Inputs'!$B$9)/'Engine Inputs'!$B$8))+MAX(B15-MIN(B15/$B$10,'Engine Inputs'!$B$9)*$B$10,0)*'Engine Inputs'!$B$10/2)*(1-$B$8))/$B$10,'Engine Inputs'!$B$9)*$B$10,0)*'Engine Inputs'!$B$10/2)*(1-$B$8)-INDEX('Rebuilt Scenarios'!$C$11:$C$25,A16)*(1-$B$8) -> 57336443 | C16: =IF(C15<'Engine Inputs'!$B$11,(C15+(MIN(C15/$B$10,'Engine Inputs'!$B$9)*($B$9-'Engine Inputs'!$B$5-'Engine Inputs'!$B$6-2*'Engine Inputs'!$B$7*SQRT(MIN(C15/$B$10,'Engine Inputs'!$B$9)/'Engine Inputs'!$B$8))+MAX(C15-MIN(C15/$B$10,'Engine Inputs'!$B$9)*$B$10,0)*'Engine Inputs'!$B$10/2)*(1-$B$8))+(MIN((C15+(MIN(C15/$B$10,'Engine Inputs'!$B$9)*($B$9-'Engine Inputs'!$B$5-'Engine Inputs'!$B$6-2*'Engine Inputs'!$B$7*SQRT(MIN(C15/$B$10,'Engine Inputs'!$B$9)/'Engine Inputs'!$B$8))+MAX(C15-MIN(C15/$B$10,'Engine Inputs'!$B$9)*$B$10,0)*'Engine Inputs'!$B$10/2)*(1-$B$8))/$B$10,'Engine Inputs'!$B$9)*($B$9-'Engine Inputs'!$B$5-'Engine Inputs'!$B$6-2*'Engine Inputs'!$B$7*SQRT(MIN((C15+(MIN(C15/$B$10,'Engine Inputs'!$B$9)*($B$9-'Engine Inputs'!$B$5-'Engine Inputs'!$B$6-2*'Engine Inputs'!$B$7*SQRT(MIN(C15/$B$10,'Engine Inputs'!$B$9)/'Engine Inputs'!$B$8))+MAX(C15-MIN(C15/$B$10,'Engine Inputs'!$B$9)*$B$10,0)*'Engine Inputs'!$B$10/2)*(1-$B$8))/$B$10,'Engine Inputs'!$B$9)/'Engine Inputs'!$B$8))+MAX((C15+(MIN(C15/$B$10,'Engine Inputs'!$B$9)*($B$9-'Engine Inputs'!$B$5-'Engine Inputs'!$B$6-2*'Engine Inputs'!$B$7*SQRT(MIN(C15/$B$10,'Engine Inputs'!$B$9)/'Engine Inputs'!$B$8))+MAX(C15-MIN(C15/$B$10,'Engine Inputs'!$B$9)*$B$10,0)*'Engine Inputs'!$B$10/2)*(1-$B$8))-MIN((C15+(MIN(C15/$B$10,'Engine Inputs'!$B$9)*($B$9-'Engine Inputs'!$B$5-'Engine Inputs'!$B$6-2*'Engine Inputs'!$B$7*SQRT(MIN(C15/$B$10,'Engine Inputs'!$B$9)/'Engine Inputs'!$B$8))+MAX(C15-MIN(C15/$B$10,'Engine Inputs'!$B$9)*$B$10,0)*'Engine Inputs'!$B$10/2)*(1-$B$8))/$B$10,'Engine Inputs'!$B$9)*$B$10,0)*'Engine Inputs'!$B$10/2)*(1-$B$8)-INDEX('Rebuilt Scenarios'!$C$11:$C$25,A16)*(1-$B$8),C15+(($B$6*C15-$B$7)*(12/18))*(1-$B$8)) -> 57336443 | D16: =MIN((D15+(MIN(D15/$B$10,'Engine Inputs'!$B$9)*($B$9-'Engine Inputs'!$B$5-'Engine Inputs'!$B$6-2*'Engine Inputs'!$B$7*SQRT(MIN(D15/$B$10,'Engine Inputs'!$B$9)/'Engine Inputs'!$B$8))+MAX(D15-MIN(D15/$B$10,'Engine Inputs'!$B$9)*$B$10,0)*'Engine Inputs'!$B$10/2)*(1-$B$8))+(MIN((D15+(MIN(D15/$B$10,'Engine Inputs'!$B$9)*($B$9-'Engine Inputs'!$B$5-'Engine Inputs'!$B$6-2*'Engine Inputs'!$B$7*SQRT(MIN(D15/$B$10,'Engine Inputs'!$B$9)/'Engine Inputs'!$B$8))+MAX(D15-MIN(D15/$B$10,'Engine Inputs'!$B$9)*$B$10,0)*'Engine Inputs'!$B$10/2)*(1-$B$8))/$B$10,'Engine Inputs'!$B$9)*($B$9-'Engine Inputs'!$B$5-'Engine Inputs'!$B$6-2*'Engine Inputs'!$B$7*SQRT(MIN((D15+(MIN(D15/$B$10,'Engine Inputs'!$B$9)*($B$9-'Engine Inputs'!$B$5-'Engine Inputs'!$B$6-2*'Engine Inputs'!$B$7*SQRT(MIN(D15/$B$10,'Engine Inputs'!$B$9)/'Engine Inputs'!$B$8))+MAX(D15-MIN(D15/$B$10,'Engine Inputs'!$B$9)*$B$10,0)*'Engine Inputs'!$B$10/2)*(1-$B$8))/$B$10,'Engine Inputs'!$B$9)/'Engine Inputs'!$B$8))+MAX((D15+(MIN(D15/$B$10,'Engine Inputs'!$B$9)*($B$9-'Engine Inputs'!$B$5-'Engine Inputs'!$B$6-2*'Engine Inputs'!$B$7*SQRT(MIN(D15/$B$10,'Engine Inputs'!$B$9)/'Engine Inputs'!$B$8))+MAX(D15-MIN(D15/$B$10,'Engine Inputs'!$B$9)*$B$10,0)*'Engine Inputs'!$B$10/2)*(1-$B$8))-MIN((D15+(MIN(D15/$B$10,'Engine Inputs'!$B$9)*($B$9-'Engine Inputs'!$B$5-'Engine Inputs'!$B$6-2*'Engine Inputs'!$B$7*SQRT(MIN(D15/$B$10,'Engine Inputs'!$B$9)/'Engine Inputs'!$B$8))+MAX(D15-MIN(D15/$B$10,'Engine Inputs'!$B$9)*$B$10,0)*'Engine Inputs'!$B$10/2)*(1-$B$8))/$B$10,'Engine Inputs'!$B$9)*$B$10,0)*'Engine Inputs'!$B$10/2)*(1-$B$8)-INDEX('Rebuilt Scenarios'!$C$11:$C$25,A16)*(1-$B$8),$B$5) -> 57336443 | E16: =IF(E15>0,E15+(($B$6*E15-$B$7)*(12/18))*(1-$B$8),0)+MAX((D15+(MIN(D15/$B$10,'Engine Inputs'!$B$9)*($B$9-'Engine Inputs'!$B$5-'Engine Inputs'!$B$6-2*'Engine Inputs'!$B$7*SQRT(MIN(D15/$B$10,'Engine Inputs'!$B$9)/'Engine Inputs'!$B$8))+MAX(D15-MIN(D15/$B$10,'Engine Inputs'!$B$9)*$B$10,0)*'Engine Inputs'!$B$10/2)*(1-$B$8))+(MIN((D15+(MIN(D15/$B$10,'Engine Inputs'!$B$9)*($B$9-'Engine Inputs'!$B$5-'Engine Inputs'!$B$6-2*'Engine Inputs'!$B$7*SQRT(MIN(D15/$B$10,'Engine Inputs'!$B$9)/'Engine Inputs'!$B$8))+MAX(D15-MIN(D15/$B$10,'Engine Inputs'!$B$9)*$B$10,0)*'Engine Inputs'!$B$10/2)*(1-$B$8))/$B$10,'Engine Inputs'!$B$9)*($B$9-'Engine Inputs'!$B$5-'Engine Inputs'!$B$6-2*'Engine Inputs'!$B$7*SQRT(MIN((D15+(MIN(D15/$B$10,'Engine Inputs'!$B$9)*($B$9-'Engine Inputs'!$B$5-'Engine Inputs'!$B$6-2*'Engine Inputs'!$B$7*SQRT(MIN(D15/$B$10,'Engine Inputs'!$B$9)/'Engine Inputs'!$B$8))+MAX(D15-MIN(D15/$B$10,'Engine Inputs'!$B$9)*$B$10,0)*'Engine Inputs'!$B$10/2)*(1-$B$8))/$B$10,'Engine Inputs'!$B$9)/'Engine Inputs'!$B$8))+MAX((D15+(MIN(D15/$B$10,'Engine Inputs'!$B$9)*($B$9-'Engine Inputs'!$B$5-'Engine Inputs'!$B$6-2*'Engine Inputs'!$B$7*SQRT(MIN(D15/$B$10,'Engine Inputs'!$B$9)/'Engine Inputs'!$B$8))+MAX(D15-MIN(D15/$B$10,'Engine Inputs'!$B$9)*$B$10,0)*'Engine Inputs'!$B$10/2)*(1-$B$8))-MIN((D15+(MIN(D15/$B$10,'Engine Inputs'!$B$9)*($B$9-'Engine Inputs'!$B$5-'Engine Inputs'!$B$6-2*'Engine Inputs'!$B$7*SQRT(MIN(D15/$B$10,'Engine Inputs'!$B$9)/'Engine Inputs'!$B$8))+MAX(D15-MIN(D15/$B$10,'Engine Inputs'!$B$9)*$B$10,0)*'Engine Inputs'!$B$10/2)*(1-$B$8))/$B$10,'Engine Inputs'!$B$9)*$B$10,0)*'Engine Inputs'!$B$10/2)*(1-$B$8)-INDEX('Rebuilt Scenarios'!$C$11:$C$25,A16)*(1-$B$8)-$B$5,0) -> 0 | F16: =D16+E16 -> 57336443
A17: 3 | B17: =(B16+(MIN(B16/$B$10,'Engine Inputs'!$B$9)*($B$9-'Engine Inputs'!$B$5-'Engine Inputs'!$B$6-2*'Engine Inputs'!$B$7*SQRT(MIN(B16/$B$10,'Engine Inputs'!$B$9)/'Engine Inputs'!$B$8))+MAX(B16-MIN(B16/$B$10,'Engine Inputs'!$B$9)*$B$10,0)*'Engine Inputs'!$B$10/2)*(1-$B$8))+(MIN((B16+(MIN(B16/$B$10,'Engine Inputs'!$B$9)*($B$9-'Engine Inputs'!$B$5-'Engine Inputs'!$B$6-2*'Engine Inputs'!$B$7*SQRT(MIN(B16/$B$10,'Engine Inputs'!$B$9)/'Engine Inputs'!$B$8))+MAX(B16-MIN(B16/$B$10,'Engine Inputs'!$B$9)*$B$10,0)*'Engine Inputs'!$B$10/2)*(1-$B$8))/$B$10,'Engine Inputs'!$B$9)*($B$9-'Engine Inputs'!$B$5-'Engine Inputs'!$B$6-2*'Engine Inputs'!$B$7*SQRT(MIN((B16+(MIN(B16/$B$10,'Engine Inputs'!$B$9)*($B$9-'Engine Inputs'!$B$5-'Engine Inputs'!$B$6-2*'Engine Inputs'!$B$7*SQRT(MIN(B16/$B$10,'Engine Inputs'!$B$9)/'Engine Inputs'!$B$8))+MAX(B16-MIN(B16/$B$10,'Engine Inputs'!$B$9)*$B$10,0)*'Engine Inputs'!$B$10/2)*(1-$B$8))/$B$10,'Engine Inputs'!$B$9)/'Engine Inputs'!$B$8))+MAX((B16+(MIN(B16/$B$10,'Engine Inputs'!$B$9)*($B$9-'Engine Inputs'!$B$5-'Engine Inputs'!$B$6-2*'Engine Inputs'!$B$7*SQRT(MIN(B16/$B$10,'Engine Inputs'!$B$9)/'Engine Inputs'!$B$8))+MAX(B16-MIN(B16/$B$10,'Engine Inputs'!$B$9)*$B$10,0)*'Engine Inputs'!$B$10/2)*(1-$B$8))-MIN((B16+(MIN(B16/$B$10,'Engine Inputs'!$B$9)*($B$9-'Engine Inputs'!$B$5-'Engine Inputs'!$B$6-2*'Engine Inputs'!$B$7*SQRT(MIN(B16/$B$10,'Engine Inputs'!$B$9)/'Engine Inputs'!$B$8))+MAX(B16-MIN(B16/$B$10,'Engine Inputs'!$B$9)*$B$10,0)*'Engine Inputs'!$B$10/2)*(1-$B$8))/$B$10,'Engine Inputs'!$B$9)*$B$10,0)*'Engine Inputs'!$B$10/2)*(1-$B$8)-INDEX('Rebuilt Scenarios'!$C$11:$C$25,A17)*(1-$B$8) -> 1.5738976e+08 | C17: =IF(C16<'Engine Inputs'!$B$11,(C16+(MIN(C16/$B$10,'Engine Inputs'!$B$9)*($B$9-'Engine Inputs'!$B$5-'Engine Inputs'!$B$6-2*'Engine Inputs'!$B$7*SQRT(MIN(C16/$B$10,'Engine Inputs'!$B$9)/'Engine Inputs'!$B$8))+MAX(C16-MIN(C16/$B$10,'Engine Inputs'!$B$9)*$B$10,0)*'Engine Inputs'!$B$10/2)*(1-$B$8))+(MIN((C16+(MIN(C16/$B$10,'Engine Inputs'!$B$9)*($B$9-'Engine Inputs'!$B$5-'Engine Inputs'!$B$6-2*'Engine Inputs'!$B$7*SQRT(MIN(C16/$B$10,'Engine Inputs'!$B$9)/'Engine Inputs'!$B$8))+MAX(C16-MIN(C16/$B$10,'Engine Inputs'!$B$9)*$B$10,0)*'Engine Inputs'!$B$10/2)*(1-$B$8))/$B$10,'Engine Inputs'!$B$9)*($B$9-'Engine Inputs'!$B$5-'Engine Inputs'!$B$6-2*'Engine Inputs'!$B$7*SQRT(MIN((C16+(MIN(C16/$B$10,'Engine Inputs'!$B$9)*($B$9-'Engine Inputs'!$B$5-'Engine Inputs'!$B$6-2*'Engine Inputs'!$B$7*SQRT(MIN(C16/$B$10,'Engine Inputs'!$B$9)/'Engine Inputs'!$B$8))+MAX(C16-MIN(C16/$B$10,'Engine Inputs'!$B$9)*$B$10,0)*'Engine Inputs'!$B$10/2)*(1-$B$8))/$B$10,'Engine Inputs'!$B$9)/'Engine Inputs'!$B$8))+MAX((C16+(MIN(C16/$B$10,'Engine Inputs'!$B$9)*($B$9-'Engine Inputs'!$B$5-'Engine Inputs'!$B$6-2*'Engine Inputs'!$B$7*SQRT(MIN(C16/$B$10,'Engine Inputs'!$B$9)/'Engine Inputs'!$B$8))+MAX(C16-MIN(C16/$B$10,'Engine Inputs'!$B$9)*$B$10,0)*'Engine Inputs'!$B$10/2)*(1-$B$8))-MIN((C16+(MIN(C16/$B$10,'Engine Inputs'!$B$9)*($B$9-'Engine Inputs'!$B$5-'Engine Inputs'!$B$6-2*'Engine Inputs'!$B$7*SQRT(MIN(C16/$B$10,'Engine Inputs'!$B$9)/'Engine Inputs'!$B$8))+MAX(C16-MIN(C16/$B$10,'Engine Inputs'!$B$9)*$B$10,0)*'Engine Inputs'!$B$10/2)*(1-$B$8))/$B$10,'Engine Inputs'!$B$9)*$B$10,0)*'Engine Inputs'!$B$10/2)*(1-$B$8)-INDEX('Rebuilt Scenarios'!$C$11:$C$25,A17)*(1-$B$8),C16+(($B$6*C16-$B$7)*(12/18))*(1-$B$8)) -> 1.5738976e+08 | D17: =MIN((D16+(MIN(D16/$B$10,'Engine Inputs'!$B$9)*($B$9-'Engine Inputs'!$B$5-'Engine Inputs'!$B$6-2*'Engine Inputs'!$B$7*SQRT(MIN(D16/$B$10,'Engine Inputs'!$B$9)/'Engine Inputs'!$B$8))+MAX(D16-MIN(D16/$B$10,'Engine Inputs'!$B$9)*$B$10,0)*'Engine Inputs'!$B$10/2)*(1-$B$8))+(MIN((D16+(MIN(D16/$B$10,'Engine Inputs'!$B$9)*($B$9-'Engine Inputs'!$B$5-'Engine Inputs'!$B$6-2*'Engine Inputs'!$B$7*SQRT(MIN(D16/$B$10,'Engine Inputs'!$B$9)/'Engine Inputs'!$B$8))+MAX(D16-MIN(D16/$B$10,'Engine Inputs'!$B$9)*$B$10,0)*'Engine Inputs'!$B$10/2)*(1-$B$8))/$B$10,'Engine Inputs'!$B$9)*($B$9-'Engine Inputs'!$B$5-'Engine Inputs'!$B$6-2*'Engine Inputs'!$B$7*SQRT(MIN((D16+(MIN(D16/$B$10,'Engine Inputs'!$B$9)*($B$9-'Engine Inputs'!$B$5-'Engine Inputs'!$B$6-2*'Engine Inputs'!$B$7*SQRT(MIN(D16/$B$10,'Engine Inputs'!$B$9)/'Engine Inputs'!$B$8))+MAX(D16-MIN(D16/$B$10,'Engine Inputs'!$B$9)*$B$10,0)*'Engine Inputs'!$B$10/2)*(1-$B$8))/$B$10,'Engine Inputs'!$B$9)/'Engine Inputs'!$B$8))+MAX((D16+(MIN(D16/$B$10,'Engine Inputs'!$B$9)*($B$9-'Engine Inputs'!$B$5-'Engine Inputs'!$B$6-2*'Engine Inputs'!$B$7*SQRT(MIN(D16/$B$10,'Engine Inputs'!$B$9)/'Engine Inputs'!$B$8))+MAX(D16-MIN(D16/$B$10,'Engine Inputs'!$B$9)*$B$10,0)*'Engine Inputs'!$B$10/2)*(1-$B$8))-MIN((D16+(MIN(D16/$B$10,'Engine Inputs'!$B$9)*($B$9-'Engine Inputs'!$B$5-'Engine Inputs'!$B$6-2*'Engine Inputs'!$B$7*SQRT(MIN(D16/$B$10,'Engine Inputs'!$B$9)/'Engine Inputs'!$B$8))+MAX(D16-MIN(D16/$B$10,'Engine Inputs'!$B$9)*$B$10,0)*'Engine Inputs'!$B$10/2)*(1-$B$8))/$B$10,'Engine Inputs'!$B$9)*$B$10,0)*'Engine Inputs'!$B$10/2)*(1-$B$8)-INDEX('Rebuilt Scenarios'!$C$11:$C$25,A17)*(1-$B$8),$B$5) -> 1.5738976e+08 | E17: =IF(E16>0,E16+(($B$6*E16-$B$7)*(12/18))*(1-$B$8),0)+MAX((D16+(MIN(D16/$B$10,'Engine Inputs'!$B$9)*($B$9-'Engine Inputs'!$B$5-'Engine Inputs'!$B$6-2*'Engine Inputs'!$B$7*SQRT(MIN(D16/$B$10,'Engine Inputs'!$B$9)/'Engine Inputs'!$B$8))+MAX(D16-MIN(D16/$B$10,'Engine Inputs'!$B$9)*$B$10,0)*'Engine Inputs'!$B$10/2)*(1-$B$8))+(MIN((D16+(MIN(D16/$B$10,'Engine Inputs'!$B$9)*($B$9-'Engine Inputs'!$B$5-'Engine Inputs'!$B$6-2*'Engine Inputs'!$B$7*SQRT(MIN(D16/$B$10,'Engine Inputs'!$B$9)/'Engine Inputs'!$B$8))+MAX(D16-MIN(D16/$B$10,'Engine Inputs'!$B$9)*$B$10,0)*'Engine Inputs'!$B$10/2)*(1-$B$8))/$B$10,'Engine Inputs'!$B$9)*($B$9-'Engine Inputs'!$B$5-'Engine Inputs'!$B$6-2*'Engine Inputs'!$B$7*SQRT(MIN((D16+(MIN(D16/$B$10,'Engine Inputs'!$B$9)*($B$9-'Engine Inputs'!$B$5-'Engine Inputs'!$B$6-2*'Engine Inputs'!$B$7*SQRT(MIN(D16/$B$10,'Engine Inputs'!$B$9)/'Engine Inputs'!$B$8))+MAX(D16-MIN(D16/$B$10,'Engine Inputs'!$B$9)*$B$10,0)*'Engine Inputs'!$B$10/2)*(1-$B$8))/$B$10,'Engine Inputs'!$B$9)/'Engine Inputs'!$B$8))+MAX((D16+(MIN(D16/$B$10,'Engine Inputs'!$B$9)*($B$9-'Engine Inputs'!$B$5-'Engine Inputs'!$B$6-2*'Engine Inputs'!$B$7*SQRT(MIN(D16/$B$10,'Engine Inputs'!$B$9)/'Engine Inputs'!$B$8))+MAX(D16-MIN(D16/$B$10,'Engine Inputs'!$B$9)*$B$10,0)*'Engine Inputs'!$B$10/2)*(1-$B$8))-MIN((D16+(MIN(D16/$B$10,'Engine Inputs'!$B$9)*($B$9-'Engine Inputs'!$B$5-'Engine Inputs'!$B$6-2*'Engine Inputs'!$B$7*SQRT(MIN(D16/$B$10,'Engine Inputs'!$B$9)/'Engine Inputs'!$B$8))+MAX(D16-MIN(D16/$B$10,'Engine Inputs'!$B$9)*$B$10,0)*'Engine Inputs'!$B$10/2)*(1-$B$8))/$B$10,'Engine Inputs'!$B$9)*$B$10,0)*'Engine Inputs'!$B$10/2)*(1-$B$8)-INDEX('Rebuilt Scenarios'!$C$11:$C$25,A17)*(1-$B$8)-$B$5,0) -> 0 | F17: =D17+E17 -> 1.5738976e+08
A18: 4 | B18: =(B17+(MIN(B17/$B$10,'Engine Inputs'!$B$9)*($B$9-'Engine Inputs'!$B$5-'Engine Inputs'!$B$6-2*'Engine Inputs'!$B$7*SQRT(MIN(B17/$B$10,'Engine Inputs'!$B$9)/'Engine Inputs'!$B$8))+MAX(B17-MIN(B17/$B$10,'Engine Inputs'!$B$9)*$B$10,0)*'Engine Inputs'!$B$10/2)*(1-$B$8))+(MIN((B17+(MIN(B17/$B$10,'Engine Inputs'!$B$9)*($B$9-'Engine Inputs'!$B$5-'Engine Inputs'!$B$6-2*'Engine Inputs'!$B$7*SQRT(MIN(B17/$B$10,'Engine Inputs'!$B$9)/'Engine Inputs'!$B$8))+MAX(B17-MIN(B17/$B$10,'Engine Inputs'!$B$9)*$B$10,0)*'Engine Inputs'!$B$10/2)*(1-$B$8))/$B$10,'Engine Inputs'!$B$9)*($B$9-'Engine Inputs'!$B$5-'Engine Inputs'!$B$6-2*'Engine Inputs'!$B$7*SQRT(MIN((B17+(MIN(B17/$B$10,'Engine Inputs'!$B$9)*($B$9-'Engine Inputs'!$B$5-'Engine Inputs'!$B$6-2*'Engine Inputs'!$B$7*SQRT(MIN(B17/$B$10,'Engine Inputs'!$B$9)/'Engine Inputs'!$B$8))+MAX(B17-MIN(B17/$B$10,'Engine Inputs'!$B$9)*$B$10,0)*'Engine Inputs'!$B$10/2)*(1-$B$8))/$B$10,'Engine Inputs'!$B$9)/'Engine Inputs'!$B$8))+MAX((B17+(MIN(B17/$B$10,'Engine Inputs'!$B$9)*($B$9-'Engine Inputs'!$B$5-'Engine Inputs'!$B$6-2*'Engine Inputs'!$B$7*SQRT(MIN(B17/$B$10,'Engine Inputs'!$B$9)/'Engine Inputs'!$B$8))+MAX(B17-MIN(B17/$B$10,'Engine Inputs'!$B$9)*$B$10,0)*'Engine Inputs'!$B$10/2)*(1-$B$8))-MIN((B17+(MIN(B17/$B$10,'Engine Inputs'!$B$9)*($B$9-'Engine Inputs'!$B$5-'Engine Inputs'!$B$6-2*'Engine Inputs'!$B$7*SQRT(MIN(B17/$B$10,'Engine Inputs'!$B$9)/'Engine Inputs'!$B$8))+MAX(B17-MIN(B17/$B$10,'Engine Inputs'!$B$9)*$B$10,0)*'Engine Inputs'!$B$10/2)*(1-$B$8))/$B$10,'Engine Inputs'!$B$9)*$B$10,0)*'Engine Inputs'!$B$10/2)*(1-$B$8)-INDEX('Rebuilt Scenarios'!$C$11:$C$25,A18)*(1-$B$8) -> 4.2781506e+08 | C18: =IF(C17<'Engine Inputs'!$B$11,(C17+(MIN(C17/$B$10,'Engine Inputs'!$B$9)*($B$9-'Engine Inputs'!$B$5-'Engine Inputs'!$B$6-2*'Engine Inputs'!$B$7*SQRT(MIN(C17/$B$10,'Engine Inputs'!$B$9)/'Engine Inputs'!$B$8))+MAX(C17-MIN(C17/$B$10,'Engine Inputs'!$B$9)*$B$10,0)*'Engine Inputs'!$B$10/2)*(1-$B$8))+(MIN((C17+(MIN(C17/$B$10,'Engine Inputs'!$B$9)*($B$9-'Engine Inputs'!$B$5-'Engine Inputs'!$B$6-2*'Engine Inputs'!$B$7*SQRT(MIN(C17/$B$10,'Engine Inputs'!$B$9)/'Engine Inputs'!$B$8))+MAX(C17-MIN(C17/$B$10,'Engine Inputs'!$B$9)*$B$10,0)*'Engine Inputs'!$B$10/2)*(1-$B$8))/$B$10,'Engine Inputs'!$B$9)*($B$9-'Engine Inputs'!$B$5-'Engine Inputs'!$B$6-2*'Engine Inputs'!$B$7*SQRT(MIN((C17+(MIN(C17/$B$10,'Engine Inputs'!$B$9)*($B$9-'Engine Inputs'!$B$5-'Engine Inputs'!$B$6-2*'Engine Inputs'!$B$7*SQRT(MIN(C17/$B$10,'Engine Inputs'!$B$9)/'Engine Inputs'!$B$8))+MAX(C17-MIN(C17/$B$10,'Engine Inputs'!$B$9)*$B$10,0)*'Engine Inputs'!$B$10/2)*(1-$B$8))/$B$10,'Engine Inputs'!$B$9)/'Engine Inputs'!$B$8))+MAX((C17+(MIN(C17/$B$10,'Engine Inputs'!$B$9)*($B$9-'Engine Inputs'!$B$5-'Engine Inputs'!$B$6-2*'Engine Inputs'!$B$7*SQRT(MIN(C17/$B$10,'Engine Inputs'!$B$9)/'Engine Inputs'!$B$8))+MAX(C17-MIN(C17/$B$10,'Engine Inputs'!$B$9)*$B$10,0)*'Engine Inputs'!$B$10/2)*(1-$B$8))-MIN((C17+(MIN(C17/$B$10,'Engine Inputs'!$B$9)*($B$9-'Engine Inputs'!$B$5-'Engine Inputs'!$B$6-2*'Engine Inputs'!$B$7*SQRT(MIN(C17/$B$10,'Engine Inputs'!$B$9)/'Engine Inputs'!$B$8))+MAX(C17-MIN(C17/$B$10,'Engine Inputs'!$B$9)*$B$10,0)*'Engine Inputs'!$B$10/2)*(1-$B$8))/$B$10,'Engine Inputs'!$B$9)*$B$10,0)*'Engine Inputs'!$B$10/2)*(1-$B$8)-INDEX('Rebuilt Scenarios'!$C$11:$C$25,A18)*(1-$B$8),C17+(($B$6*C17-$B$7)*(12/18))*(1-$B$8)) -> 4.2781506e+08 | D18: =MIN((D17+(MIN(D17/$B$10,'Engine Inputs'!$B$9)*($B$9-'Engine Inputs'!$B$5-'Engine Inputs'!$B$6-2*'Engine Inputs'!$B$7*SQRT(MIN(D17/$B$10,'Engine Inputs'!$B$9)/'Engine Inputs'!$B$8))+MAX(D17-MIN(D17/$B$10,'Engine Inputs'!$B$9)*$B$10,0)*'Engine Inputs'!$B$10/2)*(1-$B$8))+(MIN((D17+(MIN(D17/$B$10,'Engine Inputs'!$B$9)*($B$9-'Engine Inputs'!$B$5-'Engine Inputs'!$B$6-2*'Engine Inputs'!$B$7*SQRT(MIN(D17/$B$10,'Engine Inputs'!$B$9)/'Engine Inputs'!$B$8))+MAX(D17-MIN(D17/$B$10,'Engine Inputs'!$B$9)*$B$10,0)*'Engine Inputs'!$B$10/2)*(1-$B$8))/$B$10,'Engine Inputs'!$B$9)*($B$9-'Engine Inputs'!$B$5-'Engine Inputs'!$B$6-2*'Engine Inputs'!$B$7*SQRT(MIN((D17+(MIN(D17/$B$10,'Engine Inputs'!$B$9)*($B$9-'Engine Inputs'!$B$5-'Engine Inputs'!$B$6-2*'Engine Inputs'!$B$7*SQRT(MIN(D17/$B$10,'Engine Inputs'!$B$9)/'Engine Inputs'!$B$8))+MAX(D17-MIN(D17/$B$10,'Engine Inputs'!$B$9)*$B$10,0)*'Engine Inputs'!$B$10/2)*(1-$B$8))/$B$10,'Engine Inputs'!$B$9)/'Engine Inputs'!$B$8))+MAX((D17+(MIN(D17/$B$10,'Engine Inputs'!$B$9)*($B$9-'Engine Inputs'!$B$5-'Engine Inputs'!$B$6-2*'Engine Inputs'!$B$7*SQRT(MIN(D17/$B$10,'Engine Inputs'!$B$9)/'Engine Inputs'!$B$8))+MAX(D17-MIN(D17/$B$10,'Engine Inputs'!$B$9)*$B$10,0)*'Engine Inputs'!$B$10/2)*(1-$B$8))-MIN((D17+(MIN(D17/$B$10,'Engine Inputs'!$B$9)*($B$9-'Engine Inputs'!$B$5-'Engine Inputs'!$B$6-2*'Engine Inputs'!$B$7*SQRT(MIN(D17/$B$10,'Engine Inputs'!$B$9)/'Engine Inputs'!$B$8))+MAX(D17-MIN(D17/$B$10,'Engine Inputs'!$B$9)*$B$10,0)*'Engine Inputs'!$B$10/2)*(1-$B$8))/$B$10,'Engine Inputs'!$B$9)*$B$10,0)*'Engine Inputs'!$B$10/2)*(1-$B$8)-INDEX('Rebuilt Scenarios'!$C$11:$C$25,A18)*(1-$B$8),$B$5) -> 4.2781506e+08 | E18: =IF(E17>0,E17+(($B$6*E17-$B$7)*(12/18))*(1-$B$8),0)+MAX((D17+(MIN(D17/$B$10,'Engine Inputs'!$B$9)*($B$9-'Engine Inputs'!$B$5-'Engine Inputs'!$B$6-2*'Engine Inputs'!$B$7*SQRT(MIN(D17/$B$10,'Engine Inputs'!$B$9)/'Engine Inputs'!$B$8))+MAX(D17-MIN(D17/$B$10,'Engine Inputs'!$B$9)*$B$10,0)*'Engine Inputs'!$B$10/2)*(1-$B$8))+(MIN((D17+(MIN(D17/$B$10,'Engine Inputs'!$B$9)*($B$9-'Engine Inputs'!$B$5-'Engine Inputs'!$B$6-2*'Engine Inputs'!$B$7*SQRT(MIN(D17/$B$10,'Engine Inputs'!$B$9)/'Engine Inputs'!$B$8))+MAX(D17-MIN(D17/$B$10,'Engine Inputs'!$B$9)*$B$10,0)*'Engine Inputs'!$B$10/2)*(1-$B$8))/$B$10,'Engine Inputs'!$B$9)*($B$9-'Engine Inputs'!$B$5-'Engine Inputs'!$B$6-2*'Engine Inputs'!$B$7*SQRT(MIN((D17+(MIN(D17/$B$10,'Engine Inputs'!$B$9)*($B$9-'Engine Inputs'!$B$5-'Engine Inputs'!$B$6-2*'Engine Inputs'!$B$7*SQRT(MIN(D17/$B$10,'Engine Inputs'!$B$9)/'Engine Inputs'!$B$8))+MAX(D17-MIN(D17/$B$10,'Engine Inputs'!$B$9)*$B$10,0)*'Engine Inputs'!$B$10/2)*(1-$B$8))/$B$10,'Engine Inputs'!$B$9)/'Engine Inputs'!$B$8))+MAX((D17+(MIN(D17/$B$10,'Engine Inputs'!$B$9)*($B$9-'Engine Inputs'!$B$5-'Engine Inputs'!$B$6-2*'Engine Inputs'!$B$7*SQRT(MIN(D17/$B$10,'Engine Inputs'!$B$9)/'Engine Inputs'!$B$8))+MAX(D17-MIN(D17/$B$10,'Engine Inputs'!$B$9)*$B$10,0)*'Engine Inputs'!$B$10/2)*(1-$B$8))-MIN((D17+(MIN(D17/$B$10,'Engine Inputs'!$B$9)*($B$9-'Engine Inputs'!$B$5-'Engine Inputs'!$B$6-2*'Engine Inputs'!$B$7*SQRT(MIN(D17/$B$10,'Engine Inputs'!$B$9)/'Engine Inputs'!$B$8))+MAX(D17-MIN(D17/$B$10,'Engine Inputs'!$B$9)*$B$10,0)*'Engine Inputs'!$B$10/2)*(1-$B$8))/$B$10,'Engine Inputs'!$B$9)*$B$10,0)*'Engine Inputs'!$B$10/2)*(1-$B$8)-INDEX('Rebuilt Scenarios'!$C$11:$C$25,A18)*(1-$B$8)-$B$5,0) -> 0 | F18: =D18+E18 -> 4.2781506e+08
A19: 5 | B19: =(B18+(MIN(B18/$B$10,'Engine Inputs'!$B$9)*($B$9-'Engine Inputs'!$B$5-'Engine Inputs'!$B$6-2*'Engine Inputs'!$B$7*SQRT(MIN(B18/$B$10,'Engine Inputs'!$B$9)/'Engine Inputs'!$B$8))+MAX(B18-MIN(B18/$B$10,'Engine Inputs'!$B$9)*$B$10,0)*'Engine Inputs'!$B$10/2)*(1-$B$8))+(MIN((B18+(MIN(B18/$B$10,'Engine Inputs'!$B$9)*($B$9-'Engine Inputs'!$B$5-'Engine Inputs'!$B$6-2*'Engine Inputs'!$B$7*SQRT(MIN(B18/$B$10,'Engine Inputs'!$B$9)/'Engine Inputs'!$B$8))+MAX(B18-MIN(B18/$B$10,'Engine Inputs'!$B$9)*$B$10,0)*'Engine Inputs'!$B$10/2)*(1-$B$8))/$B$10,'Engine Inputs'!$B$9)*($B$9-'Engine Inputs'!$B$5-'Engine Inputs'!$B$6-2*'Engine Inputs'!$B$7*SQRT(MIN((B18+(MIN(B18/$B$10,'Engine Inputs'!$B$9)*($B$9-'Engine Inputs'!$B$5-'Engine Inputs'!$B$6-2*'Engine Inputs'!$B$7*SQRT(MIN(B18/$B$10,'Engine Inputs'!$B$9)/'Engine Inputs'!$B$8))+MAX(B18-MIN(B18/$B$10,'Engine Inputs'!$B$9)*$B$10,0)*'Engine Inputs'!$B$10/2)*(1-$B$8))/$B$10,'Engine Inputs'!$B$9)/'Engine Inputs'!$B$8))+MAX((B18+(MIN(B18/$B$10,'Engine Inputs'!$B$9)*($B$9-'Engine Inputs'!$B$5-'Engine Inputs'!$B$6-2*'Engine Inputs'!$B$7*SQRT(MIN(B18/$B$10,'Engine Inputs'!$B$9)/'Engine Inputs'!$B$8))+MAX(B18-MIN(B18/$B$10,'Engine Inputs'!$B$9)*$B$10,0)*'Engine Inputs'!$B$10/2)*(1-$B$8))-MIN((B18+(MIN(B18/$B$10,'Engine Inputs'!$B$9)*($B$9-'Engine Inputs'!$B$5-'Engine Inputs'!$B$6-2*'Engine Inputs'!$B$7*SQRT(MIN(B18/$B$10,'Engine Inputs'!$B$9)/'Engine Inputs'!$B$8))+MAX(B18-MIN(B18/$B$10,'Engine Inputs'!$B$9)*$B$10,0)*'Engine Inputs'!$B$10/2)*(1-$B$8))/$B$10,'Engine Inputs'!$B$9)*$B$10,0)*'Engine Inputs'!$B$10/2)*(1-$B$8)-INDEX('Rebuilt Scenarios'!$C$11:$C$25,A19)*(1-$B$8) -> 1.1433105e+09 | C19: =IF(C18<'Engine Inputs'!$B$11,(C18+(MIN(C18/$B$10,'Engine Inputs'!$B$9)*($B$9-'Engine Inputs'!$B$5-'Engine Inputs'!$B$6-2*'Engine Inputs'!$B$7*SQRT(MIN(C18/$B$10,'Engine Inputs'!$B$9)/'Engine Inputs'!$B$8))+MAX(C18-MIN(C18/$B$10,'Engine Inputs'!$B$9)*$B$10,0)*'Engine Inputs'!$B$10/2)*(1-$B$8))+(MIN((C18+(MIN(C18/$B$10,'Engine Inputs'!$B$9)*($B$9-'Engine Inputs'!$B$5-'Engine Inputs'!$B$6-2*'Engine Inputs'!$B$7*SQRT(MIN(C18/$B$10,'Engine Inputs'!$B$9)/'Engine Inputs'!$B$8))+MAX(C18-MIN(C18/$B$10,'Engine Inputs'!$B$9)*$B$10,0)*'Engine Inputs'!$B$10/2)*(1-$B$8))/$B$10,'Engine Inputs'!$B$9)*($B$9-'Engine Inputs'!$B$5-'Engine Inputs'!$B$6-2*'Engine Inputs'!$B$7*SQRT(MIN((C18+(MIN(C18/$B$10,'Engine Inputs'!$B$9)*($B$9-'Engine Inputs'!$B$5-'Engine Inputs'!$B$6-2*'Engine Inputs'!$B$7*SQRT(MIN(C18/$B$10,'Engine Inputs'!$B$9)/'Engine Inputs'!$B$8))+MAX(C18-MIN(C18/$B$10,'Engine Inputs'!$B$9)*$B$10,0)*'Engine Inputs'!$B$10/2)*(1-$B$8))/$B$10,'Engine Inputs'!$B$9)/'Engine Inputs'!$B$8))+MAX((C18+(MIN(C18/$B$10,'Engine Inputs'!$B$9)*($B$9-'Engine Inputs'!$B$5-'Engine Inputs'!$B$6-2*'Engine Inputs'!$B$7*SQRT(MIN(C18/$B$10,'Engine Inputs'!$B$9)/'Engine Inputs'!$B$8))+MAX(C18-MIN(C18/$B$10,'Engine Inputs'!$B$9)*$B$10,0)*'Engine Inputs'!$B$10/2)*(1-$B$8))-MIN((C18+(MIN(C18/$B$10,'Engine Inputs'!$B$9)*($B$9-'Engine Inputs'!$B$5-'Engine Inputs'!$B$6-2*'Engine Inputs'!$B$7*SQRT(MIN(C18/$B$10,'Engine Inputs'!$B$9)/'Engine Inputs'!$B$8))+MAX(C18-MIN(C18/$B$10,'Engine Inputs'!$B$9)*$B$10,0)*'Engine Inputs'!$B$10/2)*(1-$B$8))/$B$10,'Engine Inputs'!$B$9)*$B$10,0)*'Engine Inputs'!$B$10/2)*(1-$B$8)-INDEX('Rebuilt Scenarios'!$C$11:$C$25,A19)*(1-$B$8),C18+(($B$6*C18-$B$7)*(12/18))*(1-$B$8)) -> 5.8539195e+08 | D19: =MIN((D18+(MIN(D18/$B$10,'Engine Inputs'!$B$9)*($B$9-'Engine Inputs'!$B$5-'Engine Inputs'!$B$6-2*'Engine Inputs'!$B$7*SQRT(MIN(D18/$B$10,'Engine Inputs'!$B$9)/'Engine Inputs'!$B$8))+MAX(D18-MIN(D18/$B$10,'Engine Inputs'!$B$9)*$B$10,0)*'Engine Inputs'!$B$10/2)*(1-$B$8))+(MIN((D18+(MIN(D18/$B$10,'Engine Inputs'!$B$9)*($B$9-'Engine Inputs'!$B$5-'Engine Inputs'!$B$6-2*'Engine Inputs'!$B$7*SQRT(MIN(D18/$B$10,'Engine Inputs'!$B$9)/'Engine Inputs'!$B$8))+MAX(D18-MIN(D18/$B$10,'Engine Inputs'!$B$9)*$B$10,0)*'Engine Inputs'!$B$10/2)*(1-$B$8))/$B$10,'Engine Inputs'!$B$9)*($B$9-'Engine Inputs'!$B$5-'Engine Inputs'!$B$6-2*'Engine Inputs'!$B$7*SQRT(MIN((D18+(MIN(D18/$B$10,'Engine Inputs'!$B$9)*($B$9-'Engine Inputs'!$B$5-'Engine Inputs'!$B$6-2*'Engine Inputs'!$B$7*SQRT(MIN(D18/$B$10,'Engine Inputs'!$B$9)/'Engine Inputs'!$B$8))+MAX(D18-MIN(D18/$B$10,'Engine Inputs'!$B$9)*$B$10,0)*'Engine Inputs'!$B$10/2)*(1-$B$8))/$B$10,'Engine Inputs'!$B$9)/'Engine Inputs'!$B$8))+MAX((D18+(MIN(D18/$B$10,'Engine Inputs'!$B$9)*($B$9-'Engine Inputs'!$B$5-'Engine Inputs'!$B$6-2*'Engine Inputs'!$B$7*SQRT(MIN(D18/$B$10,'Engine Inputs'!$B$9)/'Engine Inputs'!$B$8))+MAX(D18-MIN(D18/$B$10,'Engine Inputs'!$B$9)*$B$10,0)*'Engine Inputs'!$B$10/2)*(1-$B$8))-MIN((D18+(MIN(D18/$B$10,'Engine Inputs'!$B$9)*($B$9-'Engine Inputs'!$B$5-'Engine Inputs'!$B$6-2*'Engine Inputs'!$B$7*SQRT(MIN(D18/$B$10,'Engine Inputs'!$B$9)/'Engine Inputs'!$B$8))+MAX(D18-MIN(D18/$B$10,'Engine Inputs'!$B$9)*$B$10,0)*'Engine Inputs'!$B$10/2)*(1-$B$8))/$B$10,'Engine Inputs'!$B$9)*$B$10,0)*'Engine Inputs'!$B$10/2)*(1-$B$8)-INDEX('Rebuilt Scenarios'!$C$11:$C$25,A19)*(1-$B$8),$B$5) -> 1000000000 | E19: =IF(E18>0,E18+(($B$6*E18-$B$7)*(12/18))*(1-$B$8),0)+MAX((D18+(MIN(D18/$B$10,'Engine Inputs'!$B$9)*($B$9-'Engine Inputs'!$B$5-'Engine Inputs'!$B$6-2*'Engine Inputs'!$B$7*SQRT(MIN(D18/$B$10,'Engine Inputs'!$B$9)/'Engine Inputs'!$B$8))+MAX(D18-MIN(D18/$B$10,'Engine Inputs'!$B$9)*$B$10,0)*'Engine Inputs'!$B$10/2)*(1-$B$8))+(MIN((D18+(MIN(D18/$B$10,'Engine Inputs'!$B$9)*($B$9-'Engine Inputs'!$B$5-'Engine Inputs'!$B$6-2*'Engine Inputs'!$B$7*SQRT(MIN(D18/$B$10,'Engine Inputs'!$B$9)/'Engine Inputs'!$B$8))+MAX(D18-MIN(D18/$B$10,'Engine Inputs'!$B$9)*$B$10,0)*'Engine Inputs'!$B$10/2)*(1-$B$8))/$B$10,'Engine Inputs'!$B$9)*($B$9-'Engine Inputs'!$B$5-'Engine Inputs'!$B$6-2*'Engine Inputs'!$B$7*SQRT(MIN((D18+(MIN(D18/$B$10,'Engine Inputs'!$B$9)*($B$9-'Engine Inputs'!$B$5-'Engine Inputs'!$B$6-2*'Engine Inputs'!$B$7*SQRT(MIN(D18/$B$10,'Engine Inputs'!$B$9)/'Engine Inputs'!$B$8))+MAX(D18-MIN(D18/$B$10,'Engine Inputs'!$B$9)*$B$10,0)*'Engine Inputs'!$B$10/2)*(1-$B$8))/$B$10,'Engine Inputs'!$B$9)/'Engine Inputs'!$B$8))+MAX((D18+(MIN(D18/$B$10,'Engine Inputs'!$B$9)*($B$9-'Engine Inputs'!$B$5-'Engine Inputs'!$B$6-2*'Engine Inputs'!$B$7*SQRT(MIN(D18/$B$10,'Engine Inputs'!$B$9)/'Engine Inputs'!$B$8))+MAX(D18-MIN(D18/$B$10,'Engine Inputs'!$B$9)*$B$10,0)*'Engine Inputs'!$B$10/2)*(1-$B$8))-MIN((D18+(MIN(D18/$B$10,'Engine Inputs'!$B$9)*($B$9-'Engine Inputs'!$B$5-'Engine Inputs'!$B$6-2*'Engine Inputs'!$B$7*SQRT(MIN(D18/$B$10,'Engine Inputs'!$B$9)/'Engine Inputs'!$B$8))+MAX(D18-MIN(D18/$B$10,'Engine Inputs'!$B$9)*$B$10,0)*'Engine Inputs'!$B$10/2)*(1-$B$8))/$B$10,'Engine Inputs'!$B$9)*$B$10,0)*'Engine Inputs'!$B$10/2)*(1-$B$8)-INDEX('Rebuilt Scenarios'!$C$11:$C$25,A19)*(1-$B$8)-$B$5,0) -> 1.4331048e+08 | F19: =D19+E19 -> 1.1433105e+09
A20: 6 | B20: =(B19+(MIN(B19/$B$10,'Engine Inputs'!$B$9)*($B$9-'Engine Inputs'!$B$5-'Engine Inputs'!$B$6-2*'Engine Inputs'!$B$7*SQRT(MIN(B19/$B$10,'Engine Inputs'!$B$9)/'Engine Inputs'!$B$8))+MAX(B19-MIN(B19/$B$10,'Engine Inputs'!$B$9)*$B$10,0)*'Engine Inputs'!$B$10/2)*(1-$B$8))+(MIN((B19+(MIN(B19/$B$10,'Engine Inputs'!$B$9)*($B$9-'Engine Inputs'!$B$5-'Engine Inputs'!$B$6-2*'Engine Inputs'!$B$7*SQRT(MIN(B19/$B$10,'Engine Inputs'!$B$9)/'Engine Inputs'!$B$8))+MAX(B19-MIN(B19/$B$10,'Engine Inputs'!$B$9)*$B$10,0)*'Engine Inputs'!$B$10/2)*(1-$B$8))/$B$10,'Engine Inputs'!$B$9)*($B$9-'Engine Inputs'!$B$5-'Engine Inputs'!$B$6-2*'Engine Inputs'!$B$7*SQRT(MIN((B19+(MIN(B19/$B$10,'Engine Inputs'!$B$9)*($B$9-'Engine Inputs'!$B$5-'Engine Inputs'!$B$6-2*'Engine Inputs'!$B$7*SQRT(MIN(B19/$B$10,'Engine Inputs'!$B$9)/'Engine Inputs'!$B$8))+MAX(B19-MIN(B19/$B$10,'Engine Inputs'!$B$9)*$B$10,0)*'Engine Inputs'!$B$10/2)*(1-$B$8))/$B$10,'Engine Inputs'!$B$9)/'Engine Inputs'!$B$8))+MAX((B19+(MIN(B19/$B$10,'Engine Inputs'!$B$9)*($B$9-'Engine Inputs'!$B$5-'Engine Inputs'!$B$6-2*'Engine Inputs'!$B$7*SQRT(MIN(B19/$B$10,'Engine Inputs'!$B$9)/'Engine Inputs'!$B$8))+MAX(B19-MIN(B19/$B$10,'Engine Inputs'!$B$9)*$B$10,0)*'Engine Inputs'!$B$10/2)*(1-$B$8))-MIN((B19+(MIN(B19/$B$10,'Engine Inputs'!$B$9)*($B$9-'Engine Inputs'!$B$5-'Engine Inputs'!$B$6-2*'Engine Inputs'!$B$7*SQRT(MIN(B19/$B$10,'Engine Inputs'!$B$9)/'Engine Inputs'!$B$8))+MAX(B19-MIN(B19/$B$10,'Engine Inputs'!$B$9)*$B$10,0)*'Engine Inputs'!$B$10/2)*(1-$B$8))/$B$10,'Engine Inputs'!$B$9)*$B$10,0)*'Engine Inputs'!$B$10/2)*(1-$B$8)-INDEX('Rebuilt Scenarios'!$C$11:$C$25,A20)*(1-$B$8) -> 2.4466239e+09 | C20: =IF(C19<'Engine Inputs'!$B$11,(C19+(MIN(C19/$B$10,'Engine Inputs'!$B$9)*($B$9-'Engine Inputs'!$B$5-'Engine Inputs'!$B$6-2*'Engine Inputs'!$B$7*SQRT(MIN(C19/$B$10,'Engine Inputs'!$B$9)/'Engine Inputs'!$B$8))+MAX(C19-MIN(C19/$B$10,'Engine Inputs'!$B$9)*$B$10,0)*'Engine Inputs'!$B$10/2)*(1-$B$8))+(MIN((C19+(MIN(C19/$B$10,'Engine Inputs'!$B$9)*($B$9-'Engine Inputs'!$B$5-'Engine Inputs'!$B$6-2*'Engine Inputs'!$B$7*SQRT(MIN(C19/$B$10,'Engine Inputs'!$B$9)/'Engine Inputs'!$B$8))+MAX(C19-MIN(C19/$B$10,'Engine Inputs'!$B$9)*$B$10,0)*'Engine Inputs'!$B$10/2)*(1-$B$8))/$B$10,'Engine Inputs'!$B$9)*($B$9-'Engine Inputs'!$B$5-'Engine Inputs'!$B$6-2*'Engine Inputs'!$B$7*SQRT(MIN((C19+(MIN(C19/$B$10,'Engine Inputs'!$B$9)*($B$9-'Engine Inputs'!$B$5-'Engine Inputs'!$B$6-2*'Engine Inputs'!$B$7*SQRT(MIN(C19/$B$10,'Engine Inputs'!$B$9)/'Engine Inputs'!$B$8))+MAX(C19-MIN(C19/$B$10,'Engine Inputs'!$B$9)*$B$10,0)*'Engine Inputs'!$B$10/2)*(1-$B$8))/$B$10,'Engine Inputs'!$B$9)/'Engine Inputs'!$B$8))+MAX((C19+(MIN(C19/$B$10,'Engine Inputs'!$B$9)*($B$9-'Engine Inputs'!$B$5-'Engine Inputs'!$B$6-2*'Engine Inputs'!$B$7*SQRT(MIN(C19/$B$10,'Engine Inputs'!$B$9)/'Engine Inputs'!$B$8))+MAX(C19-MIN(C19/$B$10,'Engine Inputs'!$B$9)*$B$10,0)*'Engine Inputs'!$B$10/2)*(1-$B$8))-MIN((C19+(MIN(C19/$B$10,'Engine Inputs'!$B$9)*($B$9-'Engine Inputs'!$B$5-'Engine Inputs'!$B$6-2*'Engine Inputs'!$B$7*SQRT(MIN(C19/$B$10,'Engine Inputs'!$B$9)/'Engine Inputs'!$B$8))+MAX(C19-MIN(C19/$B$10,'Engine Inputs'!$B$9)*$B$10,0)*'Engine Inputs'!$B$10/2)*(1-$B$8))/$B$10,'Engine Inputs'!$B$9)*$B$10,0)*'Engine Inputs'!$B$10/2)*(1-$B$8)-INDEX('Rebuilt Scenarios'!$C$11:$C$25,A20)*(1-$B$8),C19+(($B$6*C19-$B$7)*(12/18))*(1-$B$8)) -> 8.019278e+08 | D20: =MIN((D19+(MIN(D19/$B$10,'Engine Inputs'!$B$9)*($B$9-'Engine Inputs'!$B$5-'Engine Inputs'!$B$6-2*'Engine Inputs'!$B$7*SQRT(MIN(D19/$B$10,'Engine Inputs'!$B$9)/'Engine Inputs'!$B$8))+MAX(D19-MIN(D19/$B$10,'Engine Inputs'!$B$9)*$B$10,0)*'Engine Inputs'!$B$10/2)*(1-$B$8))+(MIN((D19+(MIN(D19/$B$10,'Engine Inputs'!$B$9)*($B$9-'Engine Inputs'!$B$5-'Engine Inputs'!$B$6-2*'Engine Inputs'!$B$7*SQRT(MIN(D19/$B$10,'Engine Inputs'!$B$9)/'Engine Inputs'!$B$8))+MAX(D19-MIN(D19/$B$10,'Engine Inputs'!$B$9)*$B$10,0)*'Engine Inputs'!$B$10/2)*(1-$B$8))/$B$10,'Engine Inputs'!$B$9)*($B$9-'Engine Inputs'!$B$5-'Engine Inputs'!$B$6-2*'Engine Inputs'!$B$7*SQRT(MIN((D19+(MIN(D19/$B$10,'Engine Inputs'!$B$9)*($B$9-'Engine Inputs'!$B$5-'Engine Inputs'!$B$6-2*'Engine Inputs'!$B$7*SQRT(MIN(D19/$B$10,'Engine Inputs'!$B$9)/'Engine Inputs'!$B$8))+MAX(D19-MIN(D19/$B$10,'Engine Inputs'!$B$9)*$B$10,0)*'Engine Inputs'!$B$10/2)*(1-$B$8))/$B$10,'Engine Inputs'!$B$9)/'Engine Inputs'!$B$8))+MAX((D19+(MIN(D19/$B$10,'Engine Inputs'!$B$9)*($B$9-'Engine Inputs'!$B$5-'Engine Inputs'!$B$6-2*'Engine Inputs'!$B$7*SQRT(MIN(D19/$B$10,'Engine Inputs'!$B$9)/'Engine Inputs'!$B$8))+MAX(D19-MIN(D19/$B$10,'Engine Inputs'!$B$9)*$B$10,0)*'Engine Inputs'!$B$10/2)*(1-$B$8))-MIN((D19+(MIN(D19/$B$10,'Engine Inputs'!$B$9)*($B$9-'Engine Inputs'!$B$5-'Engine Inputs'!$B$6-2*'Engine Inputs'!$B$7*SQRT(MIN(D19/$B$10,'Engine Inputs'!$B$9)/'Engine Inputs'!$B$8))+MAX(D19-MIN(D19/$B$10,'Engine Inputs'!$B$9)*$B$10,0)*'Engine Inputs'!$B$10/2)*(1-$B$8))/$B$10,'Engine Inputs'!$B$9)*$B$10,0)*'Engine Inputs'!$B$10/2)*(1-$B$8)-INDEX('Rebuilt Scenarios'!$C$11:$C$25,A20)*(1-$B$8),$B$5) -> 1000000000 | E20: =IF(E19>0,E19+(($B$6*E19-$B$7)*(12/18))*(1-$B$8),0)+MAX((D19+(MIN(D19/$B$10,'Engine Inputs'!$B$9)*($B$9-'Engine Inputs'!$B$5-'Engine Inputs'!$B$6-2*'Engine Inputs'!$B$7*SQRT(MIN(D19/$B$10,'Engine Inputs'!$B$9)/'Engine Inputs'!$B$8))+MAX(D19-MIN(D19/$B$10,'Engine Inputs'!$B$9)*$B$10,0)*'Engine Inputs'!$B$10/2)*(1-$B$8))+(MIN((D19+(MIN(D19/$B$10,'Engine Inputs'!$B$9)*($B$9-'Engine Inputs'!$B$5-'Engine Inputs'!$B$6-2*'Engine Inputs'!$B$7*SQRT(MIN(D19/$B$10,'Engine Inputs'!$B$9)/'Engine Inputs'!$B$8))+MAX(D19-MIN(D19/$B$10,'Engine Inputs'!$B$9)*$B$10,0)*'Engine Inputs'!$B$10/2)*(1-$B$8))/$B$10,'Engine Inputs'!$B$9)*($B$9-'Engine Inputs'!$B$5-'Engine Inputs'!$B$6-2*'Engine Inputs'!$B$7*SQRT(MIN((D19+(MIN(D19/$B$10,'Engine Inputs'!$B$9)*($B$9-'Engine Inputs'!$B$5-'Engine Inputs'!$B$6-2*'Engine Inputs'!$B$7*SQRT(MIN(D19/$B$10,'Engine Inputs'!$B$9)/'Engine Inputs'!$B$8))+MAX(D19-MIN(D19/$B$10,'Engine Inputs'!$B$9)*$B$10,0)*'Engine Inputs'!$B$10/2)*(1-$B$8))/$B$10,'Engine Inputs'!$B$9)/'Engine Inputs'!$B$8))+MAX((D19+(MIN(D19/$B$10,'Engine Inputs'!$B$9)*($B$9-'Engine Inputs'!$B$5-'Engine Inputs'!$B$6-2*'Engine Inputs'!$B$7*SQRT(MIN(D19/$B$10,'Engine Inputs'!$B$9)/'Engine Inputs'!$B$8))+MAX(D19-MIN(D19/$B$10,'Engine Inputs'!$B$9)*$B$10,0)*'Engine Inputs'!$B$10/2)*(1-$B$8))-MIN((D19+(MIN(D19/$B$10,'Engine Inputs'!$B$9)*($B$9-'Engine Inputs'!$B$5-'Engine Inputs'!$B$6-2*'Engine Inputs'!$B$7*SQRT(MIN(D19/$B$10,'Engine Inputs'!$B$9)/'Engine Inputs'!$B$8))+MAX(D19-MIN(D19/$B$10,'Engine Inputs'!$B$9)*$B$10,0)*'Engine Inputs'!$B$10/2)*(1-$B$8))/$B$10,'Engine Inputs'!$B$9)*$B$10,0)*'Engine Inputs'!$B$10/2)*(1-$B$8)-INDEX('Rebuilt Scenarios'!$C$11:$C$25,A20)*(1-$B$8)-$B$5,0) -> 1.4725825e+09 | F20: =D20+E20 -> 2.4725825e+09
A21: 7 | B21: =(B20+(MIN(B20/$B$10,'Engine Inputs'!$B$9)*($B$9-'Engine Inputs'!$B$5-'Engine Inputs'!$B$6-2*'Engine Inputs'!$B$7*SQRT(MIN(B20/$B$10,'Engine Inputs'!$B$9)/'Engine Inputs'!$B$8))+MAX(B20-MIN(B20/$B$10,'Engine Inputs'!$B$9)*$B$10,0)*'Engine Inputs'!$B$10/2)*(1-$B$8))+(MIN((B20+(MIN(B20/$B$10,'Engine Inputs'!$B$9)*($B$9-'Engine Inputs'!$B$5-'Engine Inputs'!$B$6-2*'Engine Inputs'!$B$7*SQRT(MIN(B20/$B$10,'Engine Inputs'!$B$9)/'Engine Inputs'!$B$8))+MAX(B20-MIN(B20/$B$10,'Engine Inputs'!$B$9)*$B$10,0)*'Engine Inputs'!$B$10/2)*(1-$B$8))/$B$10,'Engine Inputs'!$B$9)*($B$9-'Engine Inputs'!$B$5-'Engine Inputs'!$B$6-2*'Engine Inputs'!$B$7*SQRT(MIN((B20+(MIN(B20/$B$10,'Engine Inputs'!$B$9)*($B$9-'Engine Inputs'!$B$5-'Engine Inputs'!$B$6-2*'Engine Inputs'!$B$7*SQRT(MIN(B20/$B$10,'Engine Inputs'!$B$9)/'Engine Inputs'!$B$8))+MAX(B20-MIN(B20/$B$10,'Engine Inputs'!$B$9)*$B$10,0)*'Engine Inputs'!$B$10/2)*(1-$B$8))/$B$10,'Engine Inputs'!$B$9)/'Engine Inputs'!$B$8))+MAX((B20+(MIN(B20/$B$10,'Engine Inputs'!$B$9)*($B$9-'Engine Inputs'!$B$5-'Engine Inputs'!$B$6-2*'Engine Inputs'!$B$7*SQRT(MIN(B20/$B$10,'Engine Inputs'!$B$9)/'Engine Inputs'!$B$8))+MAX(B20-MIN(B20/$B$10,'Engine Inputs'!$B$9)*$B$10,0)*'Engine Inputs'!$B$10/2)*(1-$B$8))-MIN((B20+(MIN(B20/$B$10,'Engine Inputs'!$B$9)*($B$9-'Engine Inputs'!$B$5-'Engine Inputs'!$B$6-2*'Engine Inputs'!$B$7*SQRT(MIN(B20/$B$10,'Engine Inputs'!$B$9)/'Engine Inputs'!$B$8))+MAX(B20-MIN(B20/$B$10,'Engine Inputs'!$B$9)*$B$10,0)*'Engine Inputs'!$B$10/2)*(1-$B$8))/$B$10,'Engine Inputs'!$B$9)*$B$10,0)*'Engine Inputs'!$B$10/2)*(1-$B$8)-INDEX('Rebuilt Scenarios'!$C$11:$C$25,A21)*(1-$B$8) -> 3.8141024e+09 | C21: =IF(C20<'Engine Inputs'!$B$11,(C20+(MIN(C20/$B$10,'Engine Inputs'!$B$9)*($B$9-'Engine Inputs'!$B$5-'Engine Inputs'!$B$6-2*'Engine Inputs'!$B$7*SQRT(MIN(C20/$B$10,'Engine Inputs'!$B$9)/'Engine Inputs'!$B$8))+MAX(C20-MIN(C20/$B$10,'Engine Inputs'!$B$9)*$B$10,0)*'Engine Inputs'!$B$10/2)*(1-$B$8))+(MIN((C20+(MIN(C20/$B$10,'Engine Inputs'!$B$9)*($B$9-'Engine Inputs'!$B$5-'Engine Inputs'!$B$6-2*'Engine Inputs'!$B$7*SQRT(MIN(C20/$B$10,'Engine Inputs'!$B$9)/'Engine Inputs'!$B$8))+MAX(C20-MIN(C20/$B$10,'Engine Inputs'!$B$9)*$B$10,0)*'Engine Inputs'!$B$10/2)*(1-$B$8))/$B$10,'Engine Inputs'!$B$9)*($B$9-'Engine Inputs'!$B$5-'Engine Inputs'!$B$6-2*'Engine Inputs'!$B$7*SQRT(MIN((C20+(MIN(C20/$B$10,'Engine Inputs'!$B$9)*($B$9-'Engine Inputs'!$B$5-'Engine Inputs'!$B$6-2*'Engine Inputs'!$B$7*SQRT(MIN(C20/$B$10,'Engine Inputs'!$B$9)/'Engine Inputs'!$B$8))+MAX(C20-MIN(C20/$B$10,'Engine Inputs'!$B$9)*$B$10,0)*'Engine Inputs'!$B$10/2)*(1-$B$8))/$B$10,'Engine Inputs'!$B$9)/'Engine Inputs'!$B$8))+MAX((C20+(MIN(C20/$B$10,'Engine Inputs'!$B$9)*($B$9-'Engine Inputs'!$B$5-'Engine Inputs'!$B$6-2*'Engine Inputs'!$B$7*SQRT(MIN(C20/$B$10,'Engine Inputs'!$B$9)/'Engine Inputs'!$B$8))+MAX(C20-MIN(C20/$B$10,'Engine Inputs'!$B$9)*$B$10,0)*'Engine Inputs'!$B$10/2)*(1-$B$8))-MIN((C20+(MIN(C20/$B$10,'Engine Inputs'!$B$9)*($B$9-'Engine Inputs'!$B$5-'Engine Inputs'!$B$6-2*'Engine Inputs'!$B$7*SQRT(MIN(C20/$B$10,'Engine Inputs'!$B$9)/'Engine Inputs'!$B$8))+MAX(C20-MIN(C20/$B$10,'Engine Inputs'!$B$9)*$B$10,0)*'Engine Inputs'!$B$10/2)*(1-$B$8))/$B$10,'Engine Inputs'!$B$9)*$B$10,0)*'Engine Inputs'!$B$10/2)*(1-$B$8)-INDEX('Rebuilt Scenarios'!$C$11:$C$25,A21)*(1-$B$8),C20+(($B$6*C20-$B$7)*(12/18))*(1-$B$8)) -> 1.0994827e+09 | D21: =MIN((D20+(MIN(D20/$B$10,'Engine Inputs'!$B$9)*($B$9-'Engine Inputs'!$B$5-'Engine Inputs'!$B$6-2*'Engine Inputs'!$B$7*SQRT(MIN(D20/$B$10,'Engine Inputs'!$B$9)/'Engine Inputs'!$B$8))+MAX(D20-MIN(D20/$B$10,'Engine Inputs'!$B$9)*$B$10,0)*'Engine Inputs'!$B$10/2)*(1-$B$8))+(MIN((D20+(MIN(D20/$B$10,'Engine Inputs'!$B$9)*($B$9-'Engine Inputs'!$B$5-'Engine Inputs'!$B$6-2*'Engine Inputs'!$B$7*SQRT(MIN(D20/$B$10,'Engine Inputs'!$B$9)/'Engine Inputs'!$B$8))+MAX(D20-MIN(D20/$B$10,'Engine Inputs'!$B$9)*$B$10,0)*'Engine Inputs'!$B$10/2)*(1-$B$8))/$B$10,'Engine Inputs'!$B$9)*($B$9-'Engine Inputs'!$B$5-'Engine Inputs'!$B$6-2*'Engine Inputs'!$B$7*SQRT(MIN((D20+(MIN(D20/$B$10,'Engine Inputs'!$B$9)*($B$9-'Engine Inputs'!$B$5-'Engine Inputs'!$B$6-2*'Engine Inputs'!$B$7*SQRT(MIN(D20/$B$10,'Engine Inputs'!$B$9)/'Engine Inputs'!$B$8))+MAX(D20-MIN(D20/$B$10,'Engine Inputs'!$B$9)*$B$10,0)*'Engine Inputs'!$B$10/2)*(1-$B$8))/$B$10,'Engine Inputs'!$B$9)/'Engine Inputs'!$B$8))+MAX((D20+(MIN(D20/$B$10,'Engine Inputs'!$B$9)*($B$9-'Engine Inputs'!$B$5-'Engine Inputs'!$B$6-2*'Engine Inputs'!$B$7*SQRT(MIN(D20/$B$10,'Engine Inputs'!$B$9)/'Engine Inputs'!$B$8))+MAX(D20-MIN(D20/$B$10,'Engine Inputs'!$B$9)*$B$10,0)*'Engine Inputs'!$B$10/2)*(1-$B$8))-MIN((D20+(MIN(D20/$B$10,'Engine Inputs'!$B$9)*($B$9-'Engine Inputs'!$B$5-'Engine Inputs'!$B$6-2*'Engine Inputs'!$B$7*SQRT(MIN(D20/$B$10,'Engine Inputs'!$B$9)/'Engine Inputs'!$B$8))+MAX(D20-MIN(D20/$B$10,'Engine Inputs'!$B$9)*$B$10,0)*'Engine Inputs'!$B$10/2)*(1-$B$8))/$B$10,'Engine Inputs'!$B$9)*$B$10,0)*'Engine Inputs'!$B$10/2)*(1-$B$8)-INDEX('Rebuilt Scenarios'!$C$11:$C$25,A21)*(1-$B$8),$B$5) -> 1000000000 | E21: =IF(E20>0,E20+(($B$6*E20-$B$7)*(12/18))*(1-$B$8),0)+MAX((D20+(MIN(D20/$B$10,'Engine Inputs'!$B$9)*($B$9-'Engine Inputs'!$B$5-'Engine Inputs'!$B$6-2*'Engine Inputs'!$B$7*SQRT(MIN(D20/$B$10,'Engine Inputs'!$B$9)/'Engine Inputs'!$B$8))+MAX(D20-MIN(D20/$B$10,'Engine Inputs'!$B$9)*$B$10,0)*'Engine Inputs'!$B$10/2)*(1-$B$8))+(MIN((D20+(MIN(D20/$B$10,'Engine Inputs'!$B$9)*($B$9-'Engine Inputs'!$B$5-'Engine Inputs'!$B$6-2*'Engine Inputs'!$B$7*SQRT(MIN(D20/$B$10,'Engine Inputs'!$B$9)/'Engine Inputs'!$B$8))+MAX(D20-MIN(D20/$B$10,'Engine Inputs'!$B$9)*$B$10,0)*'Engine Inputs'!$B$10/2)*(1-$B$8))/$B$10,'Engine Inputs'!$B$9)*($B$9-'Engine Inputs'!$B$5-'Engine Inputs'!$B$6-2*'Engine Inputs'!$B$7*SQRT(MIN((D20+(MIN(D20/$B$10,'Engine Inputs'!$B$9)*($B$9-'Engine Inputs'!$B$5-'Engine Inputs'!$B$6-2*'Engine Inputs'!$B$7*SQRT(MIN(D20/$B$10,'Engine Inputs'!$B$9)/'Engine Inputs'!$B$8))+MAX(D20-MIN(D20/$B$10,'Engine Inputs'!$B$9)*$B$10,0)*'Engine Inputs'!$B$10/2)*(1-$B$8))/$B$10,'Engine Inputs'!$B$9)/'Engine Inputs'!$B$8))+MAX((D20+(MIN(D20/$B$10,'Engine Inputs'!$B$9)*($B$9-'Engine Inputs'!$B$5-'Engine Inputs'!$B$6-2*'Engine Inputs'!$B$7*SQRT(MIN(D20/$B$10,'Engine Inputs'!$B$9)/'Engine Inputs'!$B$8))+MAX(D20-MIN(D20/$B$10,'Engine Inputs'!$B$9)*$B$10,0)*'Engine Inputs'!$B$10/2)*(1-$B$8))-MIN((D20+(MIN(D20/$B$10,'Engine Inputs'!$B$9)*($B$9-'Engine Inputs'!$B$5-'Engine Inputs'!$B$6-2*'Engine Inputs'!$B$7*SQRT(MIN(D20/$B$10,'Engine Inputs'!$B$9)/'Engine Inputs'!$B$8))+MAX(D20-MIN(D20/$B$10,'Engine Inputs'!$B$9)*$B$10,0)*'Engine Inputs'!$B$10/2)*(1-$B$8))/$B$10,'Engine Inputs'!$B$9)*$B$10,0)*'Engine Inputs'!$B$10/2)*(1-$B$8)-INDEX('Rebuilt Scenarios'!$C$11:$C$25,A21)*(1-$B$8)-$B$5,0) -> 3.2992148e+09 | F21: =D21+E21 -> 4.2992148e+09
A22: 8 | B22: =(B21+(MIN(B21/$B$10,'Engine Inputs'!$B$9)*($B$9-'Engine Inputs'!$B$5-'Engine Inputs'!$B$6-2*'Engine Inputs'!$B$7*SQRT(MIN(B21/$B$10,'Engine Inputs'!$B$9)/'Engine Inputs'!$B$8))+MAX(B21-MIN(B21/$B$10,'Engine Inputs'!$B$9)*$B$10,0)*'Engine Inputs'!$B$10/2)*(1-$B$8))+(MIN((B21+(MIN(B21/$B$10,'Engine Inputs'!$B$9)*($B$9-'Engine Inputs'!$B$5-'Engine Inputs'!$B$6-2*'Engine Inputs'!$B$7*SQRT(MIN(B21/$B$10,'Engine Inputs'!$B$9)/'Engine Inputs'!$B$8))+MAX(B21-MIN(B21/$B$10,'Engine Inputs'!$B$9)*$B$10,0)*'Engine Inputs'!$B$10/2)*(1-$B$8))/$B$10,'Engine Inputs'!$B$9)*($B$9-'Engine Inputs'!$B$5-'Engine Inputs'!$B$6-2*'Engine Inputs'!$B$7*SQRT(MIN((B21+(MIN(B21/$B$10,'Engine Inputs'!$B$9)*($B$9-'Engine Inputs'!$B$5-'Engine Inputs'!$B$6-2*'Engine Inputs'!$B$7*SQRT(MIN(B21/$B$10,'Engine Inputs'!$B$9)/'Engine Inputs'!$B$8))+MAX(B21-MIN(B21/$B$10,'Engine Inputs'!$B$9)*$B$10,0)*'Engine Inputs'!$B$10/2)*(1-$B$8))/$B$10,'Engine Inputs'!$B$9)/'Engine Inputs'!$B$8))+MAX((B21+(MIN(B21/$B$10,'Engine Inputs'!$B$9)*($B$9-'Engine Inputs'!$B$5-'Engine Inputs'!$B$6-2*'Engine Inputs'!$B$7*SQRT(MIN(B21/$B$10,'Engine Inputs'!$B$9)/'Engine Inputs'!$B$8))+MAX(B21-MIN(B21/$B$10,'Engine Inputs'!$B$9)*$B$10,0)*'Engine Inputs'!$B$10/2)*(1-$B$8))-MIN((B21+(MIN(B21/$B$10,'Engine Inputs'!$B$9)*($B$9-'Engine Inputs'!$B$5-'Engine Inputs'!$B$6-2*'Engine Inputs'!$B$7*SQRT(MIN(B21/$B$10,'Engine Inputs'!$B$9)/'Engine Inputs'!$B$8))+MAX(B21-MIN(B21/$B$10,'Engine Inputs'!$B$9)*$B$10,0)*'Engine Inputs'!$B$10/2)*(1-$B$8))/$B$10,'Engine Inputs'!$B$9)*$B$10,0)*'Engine Inputs'!$B$10/2)*(1-$B$8)-INDEX('Rebuilt Scenarios'!$C$11:$C$25,A22)*(1-$B$8) -> 5.2486243e+09 | C22: =IF(C21<'Engine Inputs'!$B$11,(C21+(MIN(C21/$B$10,'Engine Inputs'!$B$9)*($B$9-'Engine Inputs'!$B$5-'Engine Inputs'!$B$6-2*'Engine Inputs'!$B$7*SQRT(MIN(C21/$B$10,'Engine Inputs'!$B$9)/'Engine Inputs'!$B$8))+MAX(C21-MIN(C21/$B$10,'Engine Inputs'!$B$9)*$B$10,0)*'Engine Inputs'!$B$10/2)*(1-$B$8))+(MIN((C21+(MIN(C21/$B$10,'Engine Inputs'!$B$9)*($B$9-'Engine Inputs'!$B$5-'Engine Inputs'!$B$6-2*'Engine Inputs'!$B$7*SQRT(MIN(C21/$B$10,'Engine Inputs'!$B$9)/'Engine Inputs'!$B$8))+MAX(C21-MIN(C21/$B$10,'Engine Inputs'!$B$9)*$B$10,0)*'Engine Inputs'!$B$10/2)*(1-$B$8))/$B$10,'Engine Inputs'!$B$9)*($B$9-'Engine Inputs'!$B$5-'Engine Inputs'!$B$6-2*'Engine Inputs'!$B$7*SQRT(MIN((C21+(MIN(C21/$B$10,'Engine Inputs'!$B$9)*($B$9-'Engine Inputs'!$B$5-'Engine Inputs'!$B$6-2*'Engine Inputs'!$B$7*SQRT(MIN(C21/$B$10,'Engine Inputs'!$B$9)/'Engine Inputs'!$B$8))+MAX(C21-MIN(C21/$B$10,'Engine Inputs'!$B$9)*$B$10,0)*'Engine Inputs'!$B$10/2)*(1-$B$8))/$B$10,'Engine Inputs'!$B$9)/'Engine Inputs'!$B$8))+MAX((C21+(MIN(C21/$B$10,'Engine Inputs'!$B$9)*($B$9-'Engine Inputs'!$B$5-'Engine Inputs'!$B$6-2*'Engine Inputs'!$B$7*SQRT(MIN(C21/$B$10,'Engine Inputs'!$B$9)/'Engine Inputs'!$B$8))+MAX(C21-MIN(C21/$B$10,'Engine Inputs'!$B$9)*$B$10,0)*'Engine Inputs'!$B$10/2)*(1-$B$8))-MIN((C21+(MIN(C21/$B$10,'Engine Inputs'!$B$9)*($B$9-'Engine Inputs'!$B$5-'Engine Inputs'!$B$6-2*'Engine Inputs'!$B$7*SQRT(MIN(C21/$B$10,'Engine Inputs'!$B$9)/'Engine Inputs'!$B$8))+MAX(C21-MIN(C21/$B$10,'Engine Inputs'!$B$9)*$B$10,0)*'Engine Inputs'!$B$10/2)*(1-$B$8))/$B$10,'Engine Inputs'!$B$9)*$B$10,0)*'Engine Inputs'!$B$10/2)*(1-$B$8)-INDEX('Rebuilt Scenarios'!$C$11:$C$25,A22)*(1-$B$8),C21+(($B$6*C21-$B$7)*(12/18))*(1-$B$8)) -> 1.5083708e+09 | D22: =MIN((D21+(MIN(D21/$B$10,'Engine Inputs'!$B$9)*($B$9-'Engine Inputs'!$B$5-'Engine Inputs'!$B$6-2*'Engine Inputs'!$B$7*SQRT(MIN(D21/$B$10,'Engine Inputs'!$B$9)/'Engine Inputs'!$B$8))+MAX(D21-MIN(D21/$B$10,'Engine Inputs'!$B$9)*$B$10,0)*'Engine Inputs'!$B$10/2)*(1-$B$8))+(MIN((D21+(MIN(D21/$B$10,'Engine Inputs'!$B$9)*($B$9-'Engine Inputs'!$B$5-'Engine Inputs'!$B$6-2*'Engine Inputs'!$B$7*SQRT(MIN(D21/$B$10,'Engine Inputs'!$B$9)/'Engine Inputs'!$B$8))+MAX(D21-MIN(D21/$B$10,'Engine Inputs'!$B$9)*$B$10,0)*'Engine Inputs'!$B$10/2)*(1-$B$8))/$B$10,'Engine Inputs'!$B$9)*($B$9-'Engine Inputs'!$B$5-'Engine Inputs'!$B$6-2*'Engine Inputs'!$B$7*SQRT(MIN((D21+(MIN(D21/$B$10,'Engine Inputs'!$B$9)*($B$9-'Engine Inputs'!$B$5-'Engine Inputs'!$B$6-2*'Engine Inputs'!$B$7*SQRT(MIN(D21/$B$10,'Engine Inputs'!$B$9)/'Engine Inputs'!$B$8))+MAX(D21-MIN(D21/$B$10,'Engine Inputs'!$B$9)*$B$10,0)*'Engine Inputs'!$B$10/2)*(1-$B$8))/$B$10,'Engine Inputs'!$B$9)/'Engine Inputs'!$B$8))+MAX((D21+(MIN(D21/$B$10,'Engine Inputs'!$B$9)*($B$9-'Engine Inputs'!$B$5-'Engine Inputs'!$B$6-2*'Engine Inputs'!$B$7*SQRT(MIN(D21/$B$10,'Engine Inputs'!$B$9)/'Engine Inputs'!$B$8))+MAX(D21-MIN(D21/$B$10,'Engine Inputs'!$B$9)*$B$10,0)*'Engine Inputs'!$B$10/2)*(1-$B$8))-MIN((D21+(MIN(D21/$B$10,'Engine Inputs'!$B$9)*($B$9-'Engine Inputs'!$B$5-'Engine Inputs'!$B$6-2*'Engine Inputs'!$B$7*SQRT(MIN(D21/$B$10,'Engine Inputs'!$B$9)/'Engine Inputs'!$B$8))+MAX(D21-MIN(D21/$B$10,'Engine Inputs'!$B$9)*$B$10,0)*'Engine Inputs'!$B$10/2)*(1-$B$8))/$B$10,'Engine Inputs'!$B$9)*$B$10,0)*'Engine Inputs'!$B$10/2)*(1-$B$8)-INDEX('Rebuilt Scenarios'!$C$11:$C$25,A22)*(1-$B$8),$B$5) -> 1000000000 | E22: =IF(E21>0,E21+(($B$6*E21-$B$7)*(12/18))*(1-$B$8),0)+MAX((D21+(MIN(D21/$B$10,'Engine Inputs'!$B$9)*($B$9-'Engine Inputs'!$B$5-'Engine Inputs'!$B$6-2*'Engine Inputs'!$B$7*SQRT(MIN(D21/$B$10,'Engine Inputs'!$B$9)/'Engine Inputs'!$B$8))+MAX(D21-MIN(D21/$B$10,'Engine Inputs'!$B$9)*$B$10,0)*'Engine Inputs'!$B$10/2)*(1-$B$8))+(MIN((D21+(MIN(D21/$B$10,'Engine Inputs'!$B$9)*($B$9-'Engine Inputs'!$B$5-'Engine Inputs'!$B$6-2*'Engine Inputs'!$B$7*SQRT(MIN(D21/$B$10,'Engine Inputs'!$B$9)/'Engine Inputs'!$B$8))+MAX(D21-MIN(D21/$B$10,'Engine Inputs'!$B$9)*$B$10,0)*'Engine Inputs'!$B$10/2)*(1-$B$8))/$B$10,'Engine Inputs'!$B$9)*($B$9-'Engine Inputs'!$B$5-'Engine Inputs'!$B$6-2*'Engine Inputs'!$B$7*SQRT(MIN((D21+(MIN(D21/$B$10,'Engine Inputs'!$B$9)*($B$9-'Engine Inputs'!$B$5-'Engine Inputs'!$B$6-2*'Engine Inputs'!$B$7*SQRT(MIN(D21/$B$10,'Engine Inputs'!$B$9)/'Engine Inputs'!$B$8))+MAX(D21-MIN(D21/$B$10,'Engine Inputs'!$B$9)*$B$10,0)*'Engine Inputs'!$B$10/2)*(1-$B$8))/$B$10,'Engine Inputs'!$B$9)/'Engine Inputs'!$B$8))+MAX((D21+(MIN(D21/$B$10,'Engine Inputs'!$B$9)*($B$9-'Engine Inputs'!$B$5-'Engine Inputs'!$B$6-2*'Engine Inputs'!$B$7*SQRT(MIN(D21/$B$10,'Engine Inputs'!$B$9)/'Engine Inputs'!$B$8))+MAX(D21-MIN(D21/$B$10,'Engine Inputs'!$B$9)*$B$10,0)*'Engine Inputs'!$B$10/2)*(1-$B$8))-MIN((D21+(MIN(D21/$B$10,'Engine Inputs'!$B$9)*($B$9-'Engine Inputs'!$B$5-'Engine Inputs'!$B$6-2*'Engine Inputs'!$B$7*SQRT(MIN(D21/$B$10,'Engine Inputs'!$B$9)/'Engine Inputs'!$B$8))+MAX(D21-MIN(D21/$B$10,'Engine Inputs'!$B$9)*$B$10,0)*'Engine Inputs'!$B$10/2)*(1-$B$8))/$B$10,'Engine Inputs'!$B$9)*$B$10,0)*'Engine Inputs'!$B$10/2)*(1-$B$8)-INDEX('Rebuilt Scenarios'!$C$11:$C$25,A22)*(1-$B$8)-$B$5,0) -> 5.8090194e+09 | F22: =D22+E22 -> 6.8090194e+09
A23: 9 | B23: =(B22+(MIN(B22/$B$10,'Engine Inputs'!$B$9)*($B$9-'Engine Inputs'!$B$5-'Engine Inputs'!$B$6-2*'Engine Inputs'!$B$7*SQRT(MIN(B22/$B$10,'Engine Inputs'!$B$9)/'Engine Inputs'!$B$8))+MAX(B22-MIN(B22/$B$10,'Engine Inputs'!$B$9)*$B$10,0)*'Engine Inputs'!$B$10/2)*(1-$B$8))+(MIN((B22+(MIN(B22/$B$10,'Engine Inputs'!$B$9)*($B$9-'Engine Inputs'!$B$5-'Engine Inputs'!$B$6-2*'Engine Inputs'!$B$7*SQRT(MIN(B22/$B$10,'Engine Inputs'!$B$9)/'Engine Inputs'!$B$8))+MAX(B22-MIN(B22/$B$10,'Engine Inputs'!$B$9)*$B$10,0)*'Engine Inputs'!$B$10/2)*(1-$B$8))/$B$10,'Engine Inputs'!$B$9)*($B$9-'Engine Inputs'!$B$5-'Engine Inputs'!$B$6-2*'Engine Inputs'!$B$7*SQRT(MIN((B22+(MIN(B22/$B$10,'Engine Inputs'!$B$9)*($B$9-'Engine Inputs'!$B$5-'Engine Inputs'!$B$6-2*'Engine Inputs'!$B$7*SQRT(MIN(B22/$B$10,'Engine Inputs'!$B$9)/'Engine Inputs'!$B$8))+MAX(B22-MIN(B22/$B$10,'Engine Inputs'!$B$9)*$B$10,0)*'Engine Inputs'!$B$10/2)*(1-$B$8))/$B$10,'Engine Inputs'!$B$9)/'Engine Inputs'!$B$8))+MAX((B22+(MIN(B22/$B$10,'Engine Inputs'!$B$9)*($B$9-'Engine Inputs'!$B$5-'Engine Inputs'!$B$6-2*'Engine Inputs'!$B$7*SQRT(MIN(B22/$B$10,'Engine Inputs'!$B$9)/'Engine Inputs'!$B$8))+MAX(B22-MIN(B22/$B$10,'Engine Inputs'!$B$9)*$B$10,0)*'Engine Inputs'!$B$10/2)*(1-$B$8))-MIN((B22+(MIN(B22/$B$10,'Engine Inputs'!$B$9)*($B$9-'Engine Inputs'!$B$5-'Engine Inputs'!$B$6-2*'Engine Inputs'!$B$7*SQRT(MIN(B22/$B$10,'Engine Inputs'!$B$9)/'Engine Inputs'!$B$8))+MAX(B22-MIN(B22/$B$10,'Engine Inputs'!$B$9)*$B$10,0)*'Engine Inputs'!$B$10/2)*(1-$B$8))/$B$10,'Engine Inputs'!$B$9)*$B$10,0)*'Engine Inputs'!$B$10/2)*(1-$B$8)-INDEX('Rebuilt Scenarios'!$C$11:$C$25,A23)*(1-$B$8) -> 6.7537711e+09 | C23: =IF(C22<'Engine Inputs'!$B$11,(C22+(MIN(C22/$B$10,'Engine Inputs'!$B$9)*($B$9-'Engine Inputs'!$B$5-'Engine Inputs'!$B$6-2*'Engine Inputs'!$B$7*SQRT(MIN(C22/$B$10,'Engine Inputs'!$B$9)/'Engine Inputs'!$B$8))+MAX(C22-MIN(C22/$B$10,'Engine Inputs'!$B$9)*$B$10,0)*'Engine Inputs'!$B$10/2)*(1-$B$8))+(MIN((C22+(MIN(C22/$B$10,'Engine Inputs'!$B$9)*($B$9-'Engine Inputs'!$B$5-'Engine Inputs'!$B$6-2*'Engine Inputs'!$B$7*SQRT(MIN(C22/$B$10,'Engine Inputs'!$B$9)/'Engine Inputs'!$B$8))+MAX(C22-MIN(C22/$B$10,'Engine Inputs'!$B$9)*$B$10,0)*'Engine Inputs'!$B$10/2)*(1-$B$8))/$B$10,'Engine Inputs'!$B$9)*($B$9-'Engine Inputs'!$B$5-'Engine Inputs'!$B$6-2*'Engine Inputs'!$B$7*SQRT(MIN((C22+(MIN(C22/$B$10,'Engine Inputs'!$B$9)*($B$9-'Engine Inputs'!$B$5-'Engine Inputs'!$B$6-2*'Engine Inputs'!$B$7*SQRT(MIN(C22/$B$10,'Engine Inputs'!$B$9)/'Engine Inputs'!$B$8))+MAX(C22-MIN(C22/$B$10,'Engine Inputs'!$B$9)*$B$10,0)*'Engine Inputs'!$B$10/2)*(1-$B$8))/$B$10,'Engine Inputs'!$B$9)/'Engine Inputs'!$B$8))+MAX((C22+(MIN(C22/$B$10,'Engine Inputs'!$B$9)*($B$9-'Engine Inputs'!$B$5-'Engine Inputs'!$B$6-2*'Engine Inputs'!$B$7*SQRT(MIN(C22/$B$10,'Engine Inputs'!$B$9)/'Engine Inputs'!$B$8))+MAX(C22-MIN(C22/$B$10,'Engine Inputs'!$B$9)*$B$10,0)*'Engine Inputs'!$B$10/2)*(1-$B$8))-MIN((C22+(MIN(C22/$B$10,'Engine Inputs'!$B$9)*($B$9-'Engine Inputs'!$B$5-'Engine Inputs'!$B$6-2*'Engine Inputs'!$B$7*SQRT(MIN(C22/$B$10,'Engine Inputs'!$B$9)/'Engine Inputs'!$B$8))+MAX(C22-MIN(C22/$B$10,'Engine Inputs'!$B$9)*$B$10,0)*'Engine Inputs'!$B$10/2)*(1-$B$8))/$B$10,'Engine Inputs'!$B$9)*$B$10,0)*'Engine Inputs'!$B$10/2)*(1-$B$8)-INDEX('Rebuilt Scenarios'!$C$11:$C$25,A23)*(1-$B$8),C22+(($B$6*C22-$B$7)*(12/18))*(1-$B$8)) -> 2.0702484e+09 | D23: =MIN((D22+(MIN(D22/$B$10,'Engine Inputs'!$B$9)*($B$9-'Engine Inputs'!$B$5-'Engine Inputs'!$B$6-2*'Engine Inputs'!$B$7*SQRT(MIN(D22/$B$10,'Engine Inputs'!$B$9)/'Engine Inputs'!$B$8))+MAX(D22-MIN(D22/$B$10,'Engine Inputs'!$B$9)*$B$10,0)*'Engine Inputs'!$B$10/2)*(1-$B$8))+(MIN((D22+(MIN(D22/$B$10,'Engine Inputs'!$B$9)*($B$9-'Engine Inputs'!$B$5-'Engine Inputs'!$B$6-2*'Engine Inputs'!$B$7*SQRT(MIN(D22/$B$10,'Engine Inputs'!$B$9)/'Engine Inputs'!$B$8))+MAX(D22-MIN(D22/$B$10,'Engine Inputs'!$B$9)*$B$10,0)*'Engine Inputs'!$B$10/2)*(1-$B$8))/$B$10,'Engine Inputs'!$B$9)*($B$9-'Engine Inputs'!$B$5-'Engine Inputs'!$B$6-2*'Engine Inputs'!$B$7*SQRT(MIN((D22+(MIN(D22/$B$10,'Engine Inputs'!$B$9)*($B$9-'Engine Inputs'!$B$5-'Engine Inputs'!$B$6-2*'Engine Inputs'!$B$7*SQRT(MIN(D22/$B$10,'Engine Inputs'!$B$9)/'Engine Inputs'!$B$8))+MAX(D22-MIN(D22/$B$10,'Engine Inputs'!$B$9)*$B$10,0)*'Engine Inputs'!$B$10/2)*(1-$B$8))/$B$10,'Engine Inputs'!$B$9)/'Engine Inputs'!$B$8))+MAX((D22+(MIN(D22/$B$10,'Engine Inputs'!$B$9)*($B$9-'Engine Inputs'!$B$5-'Engine Inputs'!$B$6-2*'Engine Inputs'!$B$7*SQRT(MIN(D22/$B$10,'Engine Inputs'!$B$9)/'Engine Inputs'!$B$8))+MAX(D22-MIN(D22/$B$10,'Engine Inputs'!$B$9)*$B$10,0)*'Engine Inputs'!$B$10/2)*(1-$B$8))-MIN((D22+(MIN(D22/$B$10,'Engine Inputs'!$B$9)*($B$9-'Engine Inputs'!$B$5-'Engine Inputs'!$B$6-2*'Engine Inputs'!$B$7*SQRT(MIN(D22/$B$10,'Engine Inputs'!$B$9)/'Engine Inputs'!$B$8))+MAX(D22-MIN(D22/$B$10,'Engine Inputs'!$B$9)*$B$10,0)*'Engine Inputs'!$B$10/2)*(1-$B$8))/$B$10,'Engine Inputs'!$B$9)*$B$10,0)*'Engine Inputs'!$B$10/2)*(1-$B$8)-INDEX('Rebuilt Scenarios'!$C$11:$C$25,A23)*(1-$B$8),$B$5) -> 1000000000 | E23: =IF(E22>0,E22+(($B$6*E22-$B$7)*(12/18))*(1-$B$8),0)+MAX((D22+(MIN(D22/$B$10,'Engine Inputs'!$B$9)*($B$9-'Engine Inputs'!$B$5-'Engine Inputs'!$B$6-2*'Engine Inputs'!$B$7*SQRT(MIN(D22/$B$10,'Engine Inputs'!$B$9)/'Engine Inputs'!$B$8))+MAX(D22-MIN(D22/$B$10,'Engine Inputs'!$B$9)*$B$10,0)*'Engine Inputs'!$B$10/2)*(1-$B$8))+(MIN((D22+(MIN(D22/$B$10,'Engine Inputs'!$B$9)*($B$9-'Engine Inputs'!$B$5-'Engine Inputs'!$B$6-2*'Engine Inputs'!$B$7*SQRT(MIN(D22/$B$10,'Engine Inputs'!$B$9)/'Engine Inputs'!$B$8))+MAX(D22-MIN(D22/$B$10,'Engine Inputs'!$B$9)*$B$10,0)*'Engine Inputs'!$B$10/2)*(1-$B$8))/$B$10,'Engine Inputs'!$B$9)*($B$9-'Engine Inputs'!$B$5-'Engine Inputs'!$B$6-2*'Engine Inputs'!$B$7*SQRT(MIN((D22+(MIN(D22/$B$10,'Engine Inputs'!$B$9)*($B$9-'Engine Inputs'!$B$5-'Engine Inputs'!$B$6-2*'Engine Inputs'!$B$7*SQRT(MIN(D22/$B$10,'Engine Inputs'!$B$9)/'Engine Inputs'!$B$8))+MAX(D22-MIN(D22/$B$10,'Engine Inputs'!$B$9)*$B$10,0)*'Engine Inputs'!$B$10/2)*(1-$B$8))/$B$10,'Engine Inputs'!$B$9)/'Engine Inputs'!$B$8))+MAX((D22+(MIN(D22/$B$10,'Engine Inputs'!$B$9)*($B$9-'Engine Inputs'!$B$5-'Engine Inputs'!$B$6-2*'Engine Inputs'!$B$7*SQRT(MIN(D22/$B$10,'Engine Inputs'!$B$9)/'Engine Inputs'!$B$8))+MAX(D22-MIN(D22/$B$10,'Engine Inputs'!$B$9)*$B$10,0)*'Engine Inputs'!$B$10/2)*(1-$B$8))-MIN((D22+(MIN(D22/$B$10,'Engine Inputs'!$B$9)*($B$9-'Engine Inputs'!$B$5-'Engine Inputs'!$B$6-2*'Engine Inputs'!$B$7*SQRT(MIN(D22/$B$10,'Engine Inputs'!$B$9)/'Engine Inputs'!$B$8))+MAX(D22-MIN(D22/$B$10,'Engine Inputs'!$B$9)*$B$10,0)*'Engine Inputs'!$B$10/2)*(1-$B$8))/$B$10,'Engine Inputs'!$B$9)*$B$10,0)*'Engine Inputs'!$B$10/2)*(1-$B$8)-INDEX('Rebuilt Scenarios'!$C$11:$C$25,A23)*(1-$B$8)-$B$5,0) -> 9.2578924e+09 | F23: =D23+E23 -> 1.0257892e+10
A24: 10 | B24: =(B23+(MIN(B23/$B$10,'Engine Inputs'!$B$9)*($B$9-'Engine Inputs'!$B$5-'Engine Inputs'!$B$6-2*'Engine Inputs'!$B$7*SQRT(MIN(B23/$B$10,'Engine Inputs'!$B$9)/'Engine Inputs'!$B$8))+MAX(B23-MIN(B23/$B$10,'Engine Inputs'!$B$9)*$B$10,0)*'Engine Inputs'!$B$10/2)*(1-$B$8))+(MIN((B23+(MIN(B23/$B$10,'Engine Inputs'!$B$9)*($B$9-'Engine Inputs'!$B$5-'Engine Inputs'!$B$6-2*'Engine Inputs'!$B$7*SQRT(MIN(B23/$B$10,'Engine Inputs'!$B$9)/'Engine Inputs'!$B$8))+MAX(B23-MIN(B23/$B$10,'Engine Inputs'!$B$9)*$B$10,0)*'Engine Inputs'!$B$10/2)*(1-$B$8))/$B$10,'Engine Inputs'!$B$9)*($B$9-'Engine Inputs'!$B$5-'Engine Inputs'!$B$6-2*'Engine Inputs'!$B$7*SQRT(MIN((B23+(MIN(B23/$B$10,'Engine Inputs'!$B$9)*($B$9-'Engine Inputs'!$B$5-'Engine Inputs'!$B$6-2*'Engine Inputs'!$B$7*SQRT(MIN(B23/$B$10,'Engine Inputs'!$B$9)/'Engine Inputs'!$B$8))+MAX(B23-MIN(B23/$B$10,'Engine Inputs'!$B$9)*$B$10,0)*'Engine Inputs'!$B$10/2)*(1-$B$8))/$B$10,'Engine Inputs'!$B$9)/'Engine Inputs'!$B$8))+MAX((B23+(MIN(B23/$B$10,'Engine Inputs'!$B$9)*($B$9-'Engine Inputs'!$B$5-'Engine Inputs'!$B$6-2*'Engine Inputs'!$B$7*SQRT(MIN(B23/$B$10,'Engine Inputs'!$B$9)/'Engine Inputs'!$B$8))+MAX(B23-MIN(B23/$B$10,'Engine Inputs'!$B$9)*$B$10,0)*'Engine Inputs'!$B$10/2)*(1-$B$8))-MIN((B23+(MIN(B23/$B$10,'Engine Inputs'!$B$9)*($B$9-'Engine Inputs'!$B$5-'Engine Inputs'!$B$6-2*'Engine Inputs'!$B$7*SQRT(MIN(B23/$B$10,'Engine Inputs'!$B$9)/'Engine Inputs'!$B$8))+MAX(B23-MIN(B23/$B$10,'Engine Inputs'!$B$9)*$B$10,0)*'Engine Inputs'!$B$10/2)*(1-$B$8))/$B$10,'Engine Inputs'!$B$9)*$B$10,0)*'Engine Inputs'!$B$10/2)*(1-$B$8)-INDEX('Rebuilt Scenarios'!$C$11:$C$25,A24)*(1-$B$8) -> 8.3330197e+09 | C24: =IF(C23<'Engine Inputs'!$B$11,(C23+(MIN(C23/$B$10,'Engine Inputs'!$B$9)*($B$9-'Engine Inputs'!$B$5-'Engine Inputs'!$B$6-2*'Engine Inputs'!$B$7*SQRT(MIN(C23/$B$10,'Engine Inputs'!$B$9)/'Engine Inputs'!$B$8))+MAX(C23-MIN(C23/$B$10,'Engine Inputs'!$B$9)*$B$10,0)*'Engine Inputs'!$B$10/2)*(1-$B$8))+(MIN((C23+(MIN(C23/$B$10,'Engine Inputs'!$B$9)*($B$9-'Engine Inputs'!$B$5-'Engine Inputs'!$B$6-2*'Engine Inputs'!$B$7*SQRT(MIN(C23/$B$10,'Engine Inputs'!$B$9)/'Engine Inputs'!$B$8))+MAX(C23-MIN(C23/$B$10,'Engine Inputs'!$B$9)*$B$10,0)*'Engine Inputs'!$B$10/2)*(1-$B$8))/$B$10,'Engine Inputs'!$B$9)*($B$9-'Engine Inputs'!$B$5-'Engine Inputs'!$B$6-2*'Engine Inputs'!$B$7*SQRT(MIN((C23+(MIN(C23/$B$10,'Engine Inputs'!$B$9)*($B$9-'Engine Inputs'!$B$5-'Engine Inputs'!$B$6-2*'Engine Inputs'!$B$7*SQRT(MIN(C23/$B$10,'Engine Inputs'!$B$9)/'Engine Inputs'!$B$8))+MAX(C23-MIN(C23/$B$10,'Engine Inputs'!$B$9)*$B$10,0)*'Engine Inputs'!$B$10/2)*(1-$B$8))/$B$10,'Engine Inputs'!$B$9)/'Engine Inputs'!$B$8))+MAX((C23+(MIN(C23/$B$10,'Engine Inputs'!$B$9)*($B$9-'Engine Inputs'!$B$5-'Engine Inputs'!$B$6-2*'Engine Inputs'!$B$7*SQRT(MIN(C23/$B$10,'Engine Inputs'!$B$9)/'Engine Inputs'!$B$8))+MAX(C23-MIN(C23/$B$10,'Engine Inputs'!$B$9)*$B$10,0)*'Engine Inputs'!$B$10/2)*(1-$B$8))-MIN((C23+(MIN(C23/$B$10,'Engine Inputs'!$B$9)*($B$9-'Engine Inputs'!$B$5-'Engine Inputs'!$B$6-2*'Engine Inputs'!$B$7*SQRT(MIN(C23/$B$10,'Engine Inputs'!$B$9)/'Engine Inputs'!$B$8))+MAX(C23-MIN(C23/$B$10,'Engine Inputs'!$B$9)*$B$10,0)*'Engine Inputs'!$B$10/2)*(1-$B$8))/$B$10,'Engine Inputs'!$B$9)*$B$10,0)*'Engine Inputs'!$B$10/2)*(1-$B$8)-INDEX('Rebuilt Scenarios'!$C$11:$C$25,A24)*(1-$B$8),C23+(($B$6*C23-$B$7)*(12/18))*(1-$B$8)) -> 2.8423581e+09 | D24: =MIN((D23+(MIN(D23/$B$10,'Engine Inputs'!$B$9)*($B$9-'Engine Inputs'!$B$5-'Engine Inputs'!$B$6-2*'Engine Inputs'!$B$7*SQRT(MIN(D23/$B$10,'Engine Inputs'!$B$9)/'Engine Inputs'!$B$8))+MAX(D23-MIN(D23/$B$10,'Engine Inputs'!$B$9)*$B$10,0)*'Engine Inputs'!$B$10/2)*(1-$B$8))+(MIN((D23+(MIN(D23/$B$10,'Engine Inputs'!$B$9)*($B$9-'Engine Inputs'!$B$5-'Engine Inputs'!$B$6-2*'Engine Inputs'!$B$7*SQRT(MIN(D23/$B$10,'Engine Inputs'!$B$9)/'Engine Inputs'!$B$8))+MAX(D23-MIN(D23/$B$10,'Engine Inputs'!$B$9)*$B$10,0)*'Engine Inputs'!$B$10/2)*(1-$B$8))/$B$10,'Engine Inputs'!$B$9)*($B$9-'Engine Inputs'!$B$5-'Engine Inputs'!$B$6-2*'Engine Inputs'!$B$7*SQRT(MIN((D23+(MIN(D23/$B$10,'Engine Inputs'!$B$9)*($B$9-'Engine Inputs'!$B$5-'Engine Inputs'!$B$6-2*'Engine Inputs'!$B$7*SQRT(MIN(D23/$B$10,'Engine Inputs'!$B$9)/'Engine Inputs'!$B$8))+MAX(D23-MIN(D23/$B$10,'Engine Inputs'!$B$9)*$B$10,0)*'Engine Inputs'!$B$10/2)*(1-$B$8))/$B$10,'Engine Inputs'!$B$9)/'Engine Inputs'!$B$8))+MAX((D23+(MIN(D23/$B$10,'Engine Inputs'!$B$9)*($B$9-'Engine Inputs'!$B$5-'Engine Inputs'!$B$6-2*'Engine Inputs'!$B$7*SQRT(MIN(D23/$B$10,'Engine Inputs'!$B$9)/'Engine Inputs'!$B$8))+MAX(D23-MIN(D23/$B$10,'Engine Inputs'!$B$9)*$B$10,0)*'Engine Inputs'!$B$10/2)*(1-$B$8))-MIN((D23+(MIN(D23/$B$10,'Engine Inputs'!$B$9)*($B$9-'Engine Inputs'!$B$5-'Engine Inputs'!$B$6-2*'Engine Inputs'!$B$7*SQRT(MIN(D23/$B$10,'Engine Inputs'!$B$9)/'Engine Inputs'!$B$8))+MAX(D23-MIN(D23/$B$10,'Engine Inputs'!$B$9)*$B$10,0)*'Engine Inputs'!$B$10/2)*(1-$B$8))/$B$10,'Engine Inputs'!$B$9)*$B$10,0)*'Engine Inputs'!$B$10/2)*(1-$B$8)-INDEX('Rebuilt Scenarios'!$C$11:$C$25,A24)*(1-$B$8),$B$5) -> 1000000000 | E24: =IF(E23>0,E23+(($B$6*E23-$B$7)*(12/18))*(1-$B$8),0)+MAX((D23+(MIN(D23/$B$10,'Engine Inputs'!$B$9)*($B$9-'Engine Inputs'!$B$5-'Engine Inputs'!$B$6-2*'Engine Inputs'!$B$7*SQRT(MIN(D23/$B$10,'Engine Inputs'!$B$9)/'Engine Inputs'!$B$8))+MAX(D23-MIN(D23/$B$10,'Engine Inputs'!$B$9)*$B$10,0)*'Engine Inputs'!$B$10/2)*(1-$B$8))+(MIN((D23+(MIN(D23/$B$10,'Engine Inputs'!$B$9)*($B$9-'Engine Inputs'!$B$5-'Engine Inputs'!$B$6-2*'Engine Inputs'!$B$7*SQRT(MIN(D23/$B$10,'Engine Inputs'!$B$9)/'Engine Inputs'!$B$8))+MAX(D23-MIN(D23/$B$10,'Engine Inputs'!$B$9)*$B$10,0)*'Engine Inputs'!$B$10/2)*(1-$B$8))/$B$10,'Engine Inputs'!$B$9)*($B$9-'Engine Inputs'!$B$5-'Engine Inputs'!$B$6-2*'Engine Inputs'!$B$7*SQRT(MIN((D23+(MIN(D23/$B$10,'Engine Inputs'!$B$9)*($B$9-'Engine Inputs'!$B$5-'Engine Inputs'!$B$6-2*'Engine Inputs'!$B$7*SQRT(MIN(D23/$B$10,'Engine Inputs'!$B$9)/'Engine Inputs'!$B$8))+MAX(D23-MIN(D23/$B$10,'Engine Inputs'!$B$9)*$B$10,0)*'Engine Inputs'!$B$10/2)*(1-$B$8))/$B$10,'Engine Inputs'!$B$9)/'Engine Inputs'!$B$8))+MAX((D23+(MIN(D23/$B$10,'Engine Inputs'!$B$9)*($B$9-'Engine Inputs'!$B$5-'Engine Inputs'!$B$6-2*'Engine Inputs'!$B$7*SQRT(MIN(D23/$B$10,'Engine Inputs'!$B$9)/'Engine Inputs'!$B$8))+MAX(D23-MIN(D23/$B$10,'Engine Inputs'!$B$9)*$B$10,0)*'Engine Inputs'!$B$10/2)*(1-$B$8))-MIN((D23+(MIN(D23/$B$10,'Engine Inputs'!$B$9)*($B$9-'Engine Inputs'!$B$5-'Engine Inputs'!$B$6-2*'Engine Inputs'!$B$7*SQRT(MIN(D23/$B$10,'Engine Inputs'!$B$9)/'Engine Inputs'!$B$8))+MAX(D23-MIN(D23/$B$10,'Engine Inputs'!$B$9)*$B$10,0)*'Engine Inputs'!$B$10/2)*(1-$B$8))/$B$10,'Engine Inputs'!$B$9)*$B$10,0)*'Engine Inputs'!$B$10/2)*(1-$B$8)-INDEX('Rebuilt Scenarios'!$C$11:$C$25,A24)*(1-$B$8)-$B$5,0) -> 1.3997196e+10 | F24: =D24+E24 -> 1.4997196e+10
A25: 11 | B25: =(B24+(MIN(B24/$B$10,'Engine Inputs'!$B$9)*($B$9-'Engine Inputs'!$B$5-'Engine Inputs'!$B$6-2*'Engine Inputs'!$B$7*SQRT(MIN(B24/$B$10,'Engine Inputs'!$B$9)/'Engine Inputs'!$B$8))+MAX(B24-MIN(B24/$B$10,'Engine Inputs'!$B$9)*$B$10,0)*'Engine Inputs'!$B$10/2)*(1-$B$8))+(MIN((B24+(MIN(B24/$B$10,'Engine Inputs'!$B$9)*($B$9-'Engine Inputs'!$B$5-'Engine Inputs'!$B$6-2*'Engine Inputs'!$B$7*SQRT(MIN(B24/$B$10,'Engine Inputs'!$B$9)/'Engine Inputs'!$B$8))+MAX(B24-MIN(B24/$B$10,'Engine Inputs'!$B$9)*$B$10,0)*'Engine Inputs'!$B$10/2)*(1-$B$8))/$B$10,'Engine Inputs'!$B$9)*($B$9-'Engine Inputs'!$B$5-'Engine Inputs'!$B$6-2*'Engine Inputs'!$B$7*SQRT(MIN((B24+(MIN(B24/$B$10,'Engine Inputs'!$B$9)*($B$9-'Engine Inputs'!$B$5-'Engine Inputs'!$B$6-2*'Engine Inputs'!$B$7*SQRT(MIN(B24/$B$10,'Engine Inputs'!$B$9)/'Engine Inputs'!$B$8))+MAX(B24-MIN(B24/$B$10,'Engine Inputs'!$B$9)*$B$10,0)*'Engine Inputs'!$B$10/2)*(1-$B$8))/$B$10,'Engine Inputs'!$B$9)/'Engine Inputs'!$B$8))+MAX((B24+(MIN(B24/$B$10,'Engine Inputs'!$B$9)*($B$9-'Engine Inputs'!$B$5-'Engine Inputs'!$B$6-2*'Engine Inputs'!$B$7*SQRT(MIN(B24/$B$10,'Engine Inputs'!$B$9)/'Engine Inputs'!$B$8))+MAX(B24-MIN(B24/$B$10,'Engine Inputs'!$B$9)*$B$10,0)*'Engine Inputs'!$B$10/2)*(1-$B$8))-MIN((B24+(MIN(B24/$B$10,'Engine Inputs'!$B$9)*($B$9-'Engine Inputs'!$B$5-'Engine Inputs'!$B$6-2*'Engine Inputs'!$B$7*SQRT(MIN(B24/$B$10,'Engine Inputs'!$B$9)/'Engine Inputs'!$B$8))+MAX(B24-MIN(B24/$B$10,'Engine Inputs'!$B$9)*$B$10,0)*'Engine Inputs'!$B$10/2)*(1-$B$8))/$B$10,'Engine Inputs'!$B$9)*$B$10,0)*'Engine Inputs'!$B$10/2)*(1-$B$8)-INDEX('Rebuilt Scenarios'!$C$11:$C$25,A25)*(1-$B$8) -> 9.9900182e+09 | C25: =IF(C24<'Engine Inputs'!$B$11,(C24+(MIN(C24/$B$10,'Engine Inputs'!$B$9)*($B$9-'Engine Inputs'!$B$5-'Engine Inputs'!$B$6-2*'Engine Inputs'!$B$7*SQRT(MIN(C24/$B$10,'Engine Inputs'!$B$9)/'Engine Inputs'!$B$8))+MAX(C24-MIN(C24/$B$10,'Engine Inputs'!$B$9)*$B$10,0)*'Engine Inputs'!$B$10/2)*(1-$B$8))+(MIN((C24+(MIN(C24/$B$10,'Engine Inputs'!$B$9)*($B$9-'Engine Inputs'!$B$5-'Engine Inputs'!$B$6-2*'Engine Inputs'!$B$7*SQRT(MIN(C24/$B$10,'Engine Inputs'!$B$9)/'Engine Inputs'!$B$8))+MAX(C24-MIN(C24/$B$10,'Engine Inputs'!$B$9)*$B$10,0)*'Engine Inputs'!$B$10/2)*(1-$B$8))/$B$10,'Engine Inputs'!$B$9)*($B$9-'Engine Inputs'!$B$5-'Engine Inputs'!$B$6-2*'Engine Inputs'!$B$7*SQRT(MIN((C24+(MIN(C24/$B$10,'Engine Inputs'!$B$9)*($B$9-'Engine Inputs'!$B$5-'Engine Inputs'!$B$6-2*'Engine Inputs'!$B$7*SQRT(MIN(C24/$B$10,'Engine Inputs'!$B$9)/'Engine Inputs'!$B$8))+MAX(C24-MIN(C24/$B$10,'Engine Inputs'!$B$9)*$B$10,0)*'Engine Inputs'!$B$10/2)*(1-$B$8))/$B$10,'Engine Inputs'!$B$9)/'Engine Inputs'!$B$8))+MAX((C24+(MIN(C24/$B$10,'Engine Inputs'!$B$9)*($B$9-'Engine Inputs'!$B$5-'Engine Inputs'!$B$6-2*'Engine Inputs'!$B$7*SQRT(MIN(C24/$B$10,'Engine Inputs'!$B$9)/'Engine Inputs'!$B$8))+MAX(C24-MIN(C24/$B$10,'Engine Inputs'!$B$9)*$B$10,0)*'Engine Inputs'!$B$10/2)*(1-$B$8))-MIN((C24+(MIN(C24/$B$10,'Engine Inputs'!$B$9)*($B$9-'Engine Inputs'!$B$5-'Engine Inputs'!$B$6-2*'Engine Inputs'!$B$7*SQRT(MIN(C24/$B$10,'Engine Inputs'!$B$9)/'Engine Inputs'!$B$8))+MAX(C24-MIN(C24/$B$10,'Engine Inputs'!$B$9)*$B$10,0)*'Engine Inputs'!$B$10/2)*(1-$B$8))/$B$10,'Engine Inputs'!$B$9)*$B$10,0)*'Engine Inputs'!$B$10/2)*(1-$B$8)-INDEX('Rebuilt Scenarios'!$C$11:$C$25,A25)*(1-$B$8),C24+(($B$6*C24-$B$7)*(12/18))*(1-$B$8)) -> 3.9033604e+09 | D25: =MIN((D24+(MIN(D24/$B$10,'Engine Inputs'!$B$9)*($B$9-'Engine Inputs'!$B$5-'Engine Inputs'!$B$6-2*'Engine Inputs'!$B$7*SQRT(MIN(D24/$B$10,'Engine Inputs'!$B$9)/'Engine Inputs'!$B$8))+MAX(D24-MIN(D24/$B$10,'Engine Inputs'!$B$9)*$B$10,0)*'Engine Inputs'!$B$10/2)*(1-$B$8))+(MIN((D24+(MIN(D24/$B$10,'Engine Inputs'!$B$9)*($B$9-'Engine Inputs'!$B$5-'Engine Inputs'!$B$6-2*'Engine Inputs'!$B$7*SQRT(MIN(D24/$B$10,'Engine Inputs'!$B$9)/'Engine Inputs'!$B$8))+MAX(D24-MIN(D24/$B$10,'Engine Inputs'!$B$9)*$B$10,0)*'Engine Inputs'!$B$10/2)*(1-$B$8))/$B$10,'Engine Inputs'!$B$9)*($B$9-'Engine Inputs'!$B$5-'Engine Inputs'!$B$6-2*'Engine Inputs'!$B$7*SQRT(MIN((D24+(MIN(D24/$B$10,'Engine Inputs'!$B$9)*($B$9-'Engine Inputs'!$B$5-'Engine Inputs'!$B$6-2*'Engine Inputs'!$B$7*SQRT(MIN(D24/$B$10,'Engine Inputs'!$B$9)/'Engine Inputs'!$B$8))+MAX(D24-MIN(D24/$B$10,'Engine Inputs'!$B$9)*$B$10,0)*'Engine Inputs'!$B$10/2)*(1-$B$8))/$B$10,'Engine Inputs'!$B$9)/'Engine Inputs'!$B$8))+MAX((D24+(MIN(D24/$B$10,'Engine Inputs'!$B$9)*($B$9-'Engine Inputs'!$B$5-'Engine Inputs'!$B$6-2*'Engine Inputs'!$B$7*SQRT(MIN(D24/$B$10,'Engine Inputs'!$B$9)/'Engine Inputs'!$B$8))+MAX(D24-MIN(D24/$B$10,'Engine Inputs'!$B$9)*$B$10,0)*'Engine Inputs'!$B$10/2)*(1-$B$8))-MIN((D24+(MIN(D24/$B$10,'Engine Inputs'!$B$9)*($B$9-'Engine Inputs'!$B$5-'Engine Inputs'!$B$6-2*'Engine Inputs'!$B$7*SQRT(MIN(D24/$B$10,'Engine Inputs'!$B$9)/'Engine Inputs'!$B$8))+MAX(D24-MIN(D24/$B$10,'Engine Inputs'!$B$9)*$B$10,0)*'Engine Inputs'!$B$10/2)*(1-$B$8))/$B$10,'Engine Inputs'!$B$9)*$B$10,0)*'Engine Inputs'!$B$10/2)*(1-$B$8)-INDEX('Rebuilt Scenarios'!$C$11:$C$25,A25)*(1-$B$8),$B$5) -> 1000000000 | E25: =IF(E24>0,E24+(($B$6*E24-$B$7)*(12/18))*(1-$B$8),0)+MAX((D24+(MIN(D24/$B$10,'Engine Inputs'!$B$9)*($B$9-'Engine Inputs'!$B$5-'Engine Inputs'!$B$6-2*'Engine Inputs'!$B$7*SQRT(MIN(D24/$B$10,'Engine Inputs'!$B$9)/'Engine Inputs'!$B$8))+MAX(D24-MIN(D24/$B$10,'Engine Inputs'!$B$9)*$B$10,0)*'Engine Inputs'!$B$10/2)*(1-$B$8))+(MIN((D24+(MIN(D24/$B$10,'Engine Inputs'!$B$9)*($B$9-'Engine Inputs'!$B$5-'Engine Inputs'!$B$6-2*'Engine Inputs'!$B$7*SQRT(MIN(D24/$B$10,'Engine Inputs'!$B$9)/'Engine Inputs'!$B$8))+MAX(D24-MIN(D24/$B$10,'Engine Inputs'!$B$9)*$B$10,0)*'Engine Inputs'!$B$10/2)*(1-$B$8))/$B$10,'Engine Inputs'!$B$9)*($B$9-'Engine Inputs'!$B$5-'Engine Inputs'!$B$6-2*'Engine Inputs'!$B$7*SQRT(MIN((D24+(MIN(D24/$B$10,'Engine Inputs'!$B$9)*($B$9-'Engine Inputs'!$B$5-'Engine Inputs'!$B$6-2*'Engine Inputs'!$B$7*SQRT(MIN(D24/$B$10,'Engine Inputs'!$B$9)/'Engine Inputs'!$B$8))+MAX(D24-MIN(D24/$B$10,'Engine Inputs'!$B$9)*$B$10,0)*'Engine Inputs'!$B$10/2)*(1-$B$8))/$B$10,'Engine Inputs'!$B$9)/'Engine Inputs'!$B$8))+MAX((D24+(MIN(D24/$B$10,'Engine Inputs'!$B$9)*($B$9-'Engine Inputs'!$B$5-'Engine Inputs'!$B$6-2*'Engine Inputs'!$B$7*SQRT(MIN(D24/$B$10,'Engine Inputs'!$B$9)/'Engine Inputs'!$B$8))+MAX(D24-MIN(D24/$B$10,'Engine Inputs'!$B$9)*$B$10,0)*'Engine Inputs'!$B$10/2)*(1-$B$8))-MIN((D24+(MIN(D24/$B$10,'Engine Inputs'!$B$9)*($B$9-'Engine Inputs'!$B$5-'Engine Inputs'!$B$6-2*'Engine Inputs'!$B$7*SQRT(MIN(D24/$B$10,'Engine Inputs'!$B$9)/'Engine Inputs'!$B$8))+MAX(D24-MIN(D24/$B$10,'Engine Inputs'!$B$9)*$B$10,0)*'Engine Inputs'!$B$10/2)*(1-$B$8))/$B$10,'Engine Inputs'!$B$9)*$B$10,0)*'Engine Inputs'!$B$10/2)*(1-$B$8)-INDEX('Rebuilt Scenarios'!$C$11:$C$25,A25)*(1-$B$8)-$B$5,0) -> 2.0509757e+10 | F25: =D25+E25 -> 2.1509757e+10
A26: 12 | B26: =(B25+(MIN(B25/$B$10,'Engine Inputs'!$B$9)*($B$9-'Engine Inputs'!$B$5-'Engine Inputs'!$B$6-2*'Engine Inputs'!$B$7*SQRT(MIN(B25/$B$10,'Engine Inputs'!$B$9)/'Engine Inputs'!$B$8))+MAX(B25-MIN(B25/$B$10,'Engine Inputs'!$B$9)*$B$10,0)*'Engine Inputs'!$B$10/2)*(1-$B$8))+(MIN((B25+(MIN(B25/$B$10,'Engine Inputs'!$B$9)*($B$9-'Engine Inputs'!$B$5-'Engine Inputs'!$B$6-2*'Engine Inputs'!$B$7*SQRT(MIN(B25/$B$10,'Engine Inputs'!$B$9)/'Engine Inputs'!$B$8))+MAX(B25-MIN(B25/$B$10,'Engine Inputs'!$B$9)*$B$10,0)*'Engine Inputs'!$B$10/2)*(1-$B$8))/$B$10,'Engine Inputs'!$B$9)*($B$9-'Engine Inputs'!$B$5-'Engine Inputs'!$B$6-2*'Engine Inputs'!$B$7*SQRT(MIN((B25+(MIN(B25/$B$10,'Engine Inputs'!$B$9)*($B$9-'Engine Inputs'!$B$5-'Engine Inputs'!$B$6-2*'Engine Inputs'!$B$7*SQRT(MIN(B25/$B$10,'Engine Inputs'!$B$9)/'Engine Inputs'!$B$8))+MAX(B25-MIN(B25/$B$10,'Engine Inputs'!$B$9)*$B$10,0)*'Engine Inputs'!$B$10/2)*(1-$B$8))/$B$10,'Engine Inputs'!$B$9)/'Engine Inputs'!$B$8))+MAX((B25+(MIN(B25/$B$10,'Engine Inputs'!$B$9)*($B$9-'Engine Inputs'!$B$5-'Engine Inputs'!$B$6-2*'Engine Inputs'!$B$7*SQRT(MIN(B25/$B$10,'Engine Inputs'!$B$9)/'Engine Inputs'!$B$8))+MAX(B25-MIN(B25/$B$10,'Engine Inputs'!$B$9)*$B$10,0)*'Engine Inputs'!$B$10/2)*(1-$B$8))-MIN((B25+(MIN(B25/$B$10,'Engine Inputs'!$B$9)*($B$9-'Engine Inputs'!$B$5-'Engine Inputs'!$B$6-2*'Engine Inputs'!$B$7*SQRT(MIN(B25/$B$10,'Engine Inputs'!$B$9)/'Engine Inputs'!$B$8))+MAX(B25-MIN(B25/$B$10,'Engine Inputs'!$B$9)*$B$10,0)*'Engine Inputs'!$B$10/2)*(1-$B$8))/$B$10,'Engine Inputs'!$B$9)*$B$10,0)*'Engine Inputs'!$B$10/2)*(1-$B$8)-INDEX('Rebuilt Scenarios'!$C$11:$C$25,A26)*(1-$B$8) -> 1.1728595e+10 | C26: =IF(C25<'Engine Inputs'!$B$11,(C25+(MIN(C25/$B$10,'Engine Inputs'!$B$9)*($B$9-'Engine Inputs'!$B$5-'Engine Inputs'!$B$6-2*'Engine Inputs'!$B$7*SQRT(MIN(C25/$B$10,'Engine Inputs'!$B$9)/'Engine Inputs'!$B$8))+MAX(C25-MIN(C25/$B$10,'Engine Inputs'!$B$9)*$B$10,0)*'Engine Inputs'!$B$10/2)*(1-$B$8))+(MIN((C25+(MIN(C25/$B$10,'Engine Inputs'!$B$9)*($B$9-'Engine Inputs'!$B$5-'Engine Inputs'!$B$6-2*'Engine Inputs'!$B$7*SQRT(MIN(C25/$B$10,'Engine Inputs'!$B$9)/'Engine Inputs'!$B$8))+MAX(C25-MIN(C25/$B$10,'Engine Inputs'!$B$9)*$B$10,0)*'Engine Inputs'!$B$10/2)*(1-$B$8))/$B$10,'Engine Inputs'!$B$9)*($B$9-'Engine Inputs'!$B$5-'Engine Inputs'!$B$6-2*'Engine Inputs'!$B$7*SQRT(MIN((C25+(MIN(C25/$B$10,'Engine Inputs'!$B$9)*($B$9-'Engine Inputs'!$B$5-'Engine Inputs'!$B$6-2*'Engine Inputs'!$B$7*SQRT(MIN(C25/$B$10,'Engine Inputs'!$B$9)/'Engine Inputs'!$B$8))+MAX(C25-MIN(C25/$B$10,'Engine Inputs'!$B$9)*$B$10,0)*'Engine Inputs'!$B$10/2)*(1-$B$8))/$B$10,'Engine Inputs'!$B$9)/'Engine Inputs'!$B$8))+MAX((C25+(MIN(C25/$B$10,'Engine Inputs'!$B$9)*($B$9-'Engine Inputs'!$B$5-'Engine Inputs'!$B$6-2*'Engine Inputs'!$B$7*SQRT(MIN(C25/$B$10,'Engine Inputs'!$B$9)/'Engine Inputs'!$B$8))+MAX(C25-MIN(C25/$B$10,'Engine Inputs'!$B$9)*$B$10,0)*'Engine Inputs'!$B$10/2)*(1-$B$8))-MIN((C25+(MIN(C25/$B$10,'Engine Inputs'!$B$9)*($B$9-'Engine Inputs'!$B$5-'Engine Inputs'!$B$6-2*'Engine Inputs'!$B$7*SQRT(MIN(C25/$B$10,'Engine Inputs'!$B$9)/'Engine Inputs'!$B$8))+MAX(C25-MIN(C25/$B$10,'Engine Inputs'!$B$9)*$B$10,0)*'Engine Inputs'!$B$10/2)*(1-$B$8))/$B$10,'Engine Inputs'!$B$9)*$B$10,0)*'Engine Inputs'!$B$10/2)*(1-$B$8)-INDEX('Rebuilt Scenarios'!$C$11:$C$25,A26)*(1-$B$8),C25+(($B$6*C25-$B$7)*(12/18))*(1-$B$8)) -> 5.3613473e+09 | D26: =MIN((D25+(MIN(D25/$B$10,'Engine Inputs'!$B$9)*($B$9-'Engine Inputs'!$B$5-'Engine Inputs'!$B$6-2*'Engine Inputs'!$B$7*SQRT(MIN(D25/$B$10,'Engine Inputs'!$B$9)/'Engine Inputs'!$B$8))+MAX(D25-MIN(D25/$B$10,'Engine Inputs'!$B$9)*$B$10,0)*'Engine Inputs'!$B$10/2)*(1-$B$8))+(MIN((D25+(MIN(D25/$B$10,'Engine Inputs'!$B$9)*($B$9-'Engine Inputs'!$B$5-'Engine Inputs'!$B$6-2*'Engine Inputs'!$B$7*SQRT(MIN(D25/$B$10,'Engine Inputs'!$B$9)/'Engine Inputs'!$B$8))+MAX(D25-MIN(D25/$B$10,'Engine Inputs'!$B$9)*$B$10,0)*'Engine Inputs'!$B$10/2)*(1-$B$8))/$B$10,'Engine Inputs'!$B$9)*($B$9-'Engine Inputs'!$B$5-'Engine Inputs'!$B$6-2*'Engine Inputs'!$B$7*SQRT(MIN((D25+(MIN(D25/$B$10,'Engine Inputs'!$B$9)*($B$9-'Engine Inputs'!$B$5-'Engine Inputs'!$B$6-2*'Engine Inputs'!$B$7*SQRT(MIN(D25/$B$10,'Engine Inputs'!$B$9)/'Engine Inputs'!$B$8))+MAX(D25-MIN(D25/$B$10,'Engine Inputs'!$B$9)*$B$10,0)*'Engine Inputs'!$B$10/2)*(1-$B$8))/$B$10,'Engine Inputs'!$B$9)/'Engine Inputs'!$B$8))+MAX((D25+(MIN(D25/$B$10,'Engine Inputs'!$B$9)*($B$9-'Engine Inputs'!$B$5-'Engine Inputs'!$B$6-2*'Engine Inputs'!$B$7*SQRT(MIN(D25/$B$10,'Engine Inputs'!$B$9)/'Engine Inputs'!$B$8))+MAX(D25-MIN(D25/$B$10,'Engine Inputs'!$B$9)*$B$10,0)*'Engine Inputs'!$B$10/2)*(1-$B$8))-MIN((D25+(MIN(D25/$B$10,'Engine Inputs'!$B$9)*($B$9-'Engine Inputs'!$B$5-'Engine Inputs'!$B$6-2*'Engine Inputs'!$B$7*SQRT(MIN(D25/$B$10,'Engine Inputs'!$B$9)/'Engine Inputs'!$B$8))+MAX(D25-MIN(D25/$B$10,'Engine Inputs'!$B$9)*$B$10,0)*'Engine Inputs'!$B$10/2)*(1-$B$8))/$B$10,'Engine Inputs'!$B$9)*$B$10,0)*'Engine Inputs'!$B$10/2)*(1-$B$8)-INDEX('Rebuilt Scenarios'!$C$11:$C$25,A26)*(1-$B$8),$B$5) -> 1000000000 | E26: =IF(E25>0,E25+(($B$6*E25-$B$7)*(12/18))*(1-$B$8),0)+MAX((D25+(MIN(D25/$B$10,'Engine Inputs'!$B$9)*($B$9-'Engine Inputs'!$B$5-'Engine Inputs'!$B$6-2*'Engine Inputs'!$B$7*SQRT(MIN(D25/$B$10,'Engine Inputs'!$B$9)/'Engine Inputs'!$B$8))+MAX(D25-MIN(D25/$B$10,'Engine Inputs'!$B$9)*$B$10,0)*'Engine Inputs'!$B$10/2)*(1-$B$8))+(MIN((D25+(MIN(D25/$B$10,'Engine Inputs'!$B$9)*($B$9-'Engine Inputs'!$B$5-'Engine Inputs'!$B$6-2*'Engine Inputs'!$B$7*SQRT(MIN(D25/$B$10,'Engine Inputs'!$B$9)/'Engine Inputs'!$B$8))+MAX(D25-MIN(D25/$B$10,'Engine Inputs'!$B$9)*$B$10,0)*'Engine Inputs'!$B$10/2)*(1-$B$8))/$B$10,'Engine Inputs'!$B$9)*($B$9-'Engine Inputs'!$B$5-'Engine Inputs'!$B$6-2*'Engine Inputs'!$B$7*SQRT(MIN((D25+(MIN(D25/$B$10,'Engine Inputs'!$B$9)*($B$9-'Engine Inputs'!$B$5-'Engine Inputs'!$B$6-2*'Engine Inputs'!$B$7*SQRT(MIN(D25/$B$10,'Engine Inputs'!$B$9)/'Engine Inputs'!$B$8))+MAX(D25-MIN(D25/$B$10,'Engine Inputs'!$B$9)*$B$10,0)*'Engine Inputs'!$B$10/2)*(1-$B$8))/$B$10,'Engine Inputs'!$B$9)/'Engine Inputs'!$B$8))+MAX((D25+(MIN(D25/$B$10,'Engine Inputs'!$B$9)*($B$9-'Engine Inputs'!$B$5-'Engine Inputs'!$B$6-2*'Engine Inputs'!$B$7*SQRT(MIN(D25/$B$10,'Engine Inputs'!$B$9)/'Engine Inputs'!$B$8))+MAX(D25-MIN(D25/$B$10,'Engine Inputs'!$B$9)*$B$10,0)*'Engine Inputs'!$B$10/2)*(1-$B$8))-MIN((D25+(MIN(D25/$B$10,'Engine Inputs'!$B$9)*($B$9-'Engine Inputs'!$B$5-'Engine Inputs'!$B$6-2*'Engine Inputs'!$B$7*SQRT(MIN(D25/$B$10,'Engine Inputs'!$B$9)/'Engine Inputs'!$B$8))+MAX(D25-MIN(D25/$B$10,'Engine Inputs'!$B$9)*$B$10,0)*'Engine Inputs'!$B$10/2)*(1-$B$8))/$B$10,'Engine Inputs'!$B$9)*$B$10,0)*'Engine Inputs'!$B$10/2)*(1-$B$8)-INDEX('Rebuilt Scenarios'!$C$11:$C$25,A26)*(1-$B$8)-$B$5,0) -> 2.9459058e+10 | F26: =D26+E26 -> 3.0459058e+10
A27: 13 | B27: =(B26+(MIN(B26/$B$10,'Engine Inputs'!$B$9)*($B$9-'Engine Inputs'!$B$5-'Engine Inputs'!$B$6-2*'Engine Inputs'!$B$7*SQRT(MIN(B26/$B$10,'Engine Inputs'!$B$9)/'Engine Inputs'!$B$8))+MAX(B26-MIN(B26/$B$10,'Engine Inputs'!$B$9)*$B$10,0)*'Engine Inputs'!$B$10/2)*(1-$B$8))+(MIN((B26+(MIN(B26/$B$10,'Engine Inputs'!$B$9)*($B$9-'Engine Inputs'!$B$5-'Engine Inputs'!$B$6-2*'Engine Inputs'!$B$7*SQRT(MIN(B26/$B$10,'Engine Inputs'!$B$9)/'Engine Inputs'!$B$8))+MAX(B26-MIN(B26/$B$10,'Engine Inputs'!$B$9)*$B$10,0)*'Engine Inputs'!$B$10/2)*(1-$B$8))/$B$10,'Engine Inputs'!$B$9)*($B$9-'Engine Inputs'!$B$5-'Engine Inputs'!$B$6-2*'Engine Inputs'!$B$7*SQRT(MIN((B26+(MIN(B26/$B$10,'Engine Inputs'!$B$9)*($B$9-'Engine Inputs'!$B$5-'Engine Inputs'!$B$6-2*'Engine Inputs'!$B$7*SQRT(MIN(B26/$B$10,'Engine Inputs'!$B$9)/'Engine Inputs'!$B$8))+MAX(B26-MIN(B26/$B$10,'Engine Inputs'!$B$9)*$B$10,0)*'Engine Inputs'!$B$10/2)*(1-$B$8))/$B$10,'Engine Inputs'!$B$9)/'Engine Inputs'!$B$8))+MAX((B26+(MIN(B26/$B$10,'Engine Inputs'!$B$9)*($B$9-'Engine Inputs'!$B$5-'Engine Inputs'!$B$6-2*'Engine Inputs'!$B$7*SQRT(MIN(B26/$B$10,'Engine Inputs'!$B$9)/'Engine Inputs'!$B$8))+MAX(B26-MIN(B26/$B$10,'Engine Inputs'!$B$9)*$B$10,0)*'Engine Inputs'!$B$10/2)*(1-$B$8))-MIN((B26+(MIN(B26/$B$10,'Engine Inputs'!$B$9)*($B$9-'Engine Inputs'!$B$5-'Engine Inputs'!$B$6-2*'Engine Inputs'!$B$7*SQRT(MIN(B26/$B$10,'Engine Inputs'!$B$9)/'Engine Inputs'!$B$8))+MAX(B26-MIN(B26/$B$10,'Engine Inputs'!$B$9)*$B$10,0)*'Engine Inputs'!$B$10/2)*(1-$B$8))/$B$10,'Engine Inputs'!$B$9)*$B$10,0)*'Engine Inputs'!$B$10/2)*(1-$B$8)-INDEX('Rebuilt Scenarios'!$C$11:$C$25,A27)*(1-$B$8) -> 1.3552765e+10 | C27: =IF(C26<'Engine Inputs'!$B$11,(C26+(MIN(C26/$B$10,'Engine Inputs'!$B$9)*($B$9-'Engine Inputs'!$B$5-'Engine Inputs'!$B$6-2*'Engine Inputs'!$B$7*SQRT(MIN(C26/$B$10,'Engine Inputs'!$B$9)/'Engine Inputs'!$B$8))+MAX(C26-MIN(C26/$B$10,'Engine Inputs'!$B$9)*$B$10,0)*'Engine Inputs'!$B$10/2)*(1-$B$8))+(MIN((C26+(MIN(C26/$B$10,'Engine Inputs'!$B$9)*($B$9-'Engine Inputs'!$B$5-'Engine Inputs'!$B$6-2*'Engine Inputs'!$B$7*SQRT(MIN(C26/$B$10,'Engine Inputs'!$B$9)/'Engine Inputs'!$B$8))+MAX(C26-MIN(C26/$B$10,'Engine Inputs'!$B$9)*$B$10,0)*'Engine Inputs'!$B$10/2)*(1-$B$8))/$B$10,'Engine Inputs'!$B$9)*($B$9-'Engine Inputs'!$B$5-'Engine Inputs'!$B$6-2*'Engine Inputs'!$B$7*SQRT(MIN((C26+(MIN(C26/$B$10,'Engine Inputs'!$B$9)*($B$9-'Engine Inputs'!$B$5-'Engine Inputs'!$B$6-2*'Engine Inputs'!$B$7*SQRT(MIN(C26/$B$10,'Engine Inputs'!$B$9)/'Engine Inputs'!$B$8))+MAX(C26-MIN(C26/$B$10,'Engine Inputs'!$B$9)*$B$10,0)*'Engine Inputs'!$B$10/2)*(1-$B$8))/$B$10,'Engine Inputs'!$B$9)/'Engine Inputs'!$B$8))+MAX((C26+(MIN(C26/$B$10,'Engine Inputs'!$B$9)*($B$9-'Engine Inputs'!$B$5-'Engine Inputs'!$B$6-2*'Engine Inputs'!$B$7*SQRT(MIN(C26/$B$10,'Engine Inputs'!$B$9)/'Engine Inputs'!$B$8))+MAX(C26-MIN(C26/$B$10,'Engine Inputs'!$B$9)*$B$10,0)*'Engine Inputs'!$B$10/2)*(1-$B$8))-MIN((C26+(MIN(C26/$B$10,'Engine Inputs'!$B$9)*($B$9-'Engine Inputs'!$B$5-'Engine Inputs'!$B$6-2*'Engine Inputs'!$B$7*SQRT(MIN(C26/$B$10,'Engine Inputs'!$B$9)/'Engine Inputs'!$B$8))+MAX(C26-MIN(C26/$B$10,'Engine Inputs'!$B$9)*$B$10,0)*'Engine Inputs'!$B$10/2)*(1-$B$8))/$B$10,'Engine Inputs'!$B$9)*$B$10,0)*'Engine Inputs'!$B$10/2)*(1-$B$8)-INDEX('Rebuilt Scenarios'!$C$11:$C$25,A27)*(1-$B$8),C26+(($B$6*C26-$B$7)*(12/18))*(1-$B$8)) -> 7.3648546e+09 | D27: =MIN((D26+(MIN(D26/$B$10,'Engine Inputs'!$B$9)*($B$9-'Engine Inputs'!$B$5-'Engine Inputs'!$B$6-2*'Engine Inputs'!$B$7*SQRT(MIN(D26/$B$10,'Engine Inputs'!$B$9)/'Engine Inputs'!$B$8))+MAX(D26-MIN(D26/$B$10,'Engine Inputs'!$B$9)*$B$10,0)*'Engine Inputs'!$B$10/2)*(1-$B$8))+(MIN((D26+(MIN(D26/$B$10,'Engine Inputs'!$B$9)*($B$9-'Engine Inputs'!$B$5-'Engine Inputs'!$B$6-2*'Engine Inputs'!$B$7*SQRT(MIN(D26/$B$10,'Engine Inputs'!$B$9)/'Engine Inputs'!$B$8))+MAX(D26-MIN(D26/$B$10,'Engine Inputs'!$B$9)*$B$10,0)*'Engine Inputs'!$B$10/2)*(1-$B$8))/$B$10,'Engine Inputs'!$B$9)*($B$9-'Engine Inputs'!$B$5-'Engine Inputs'!$B$6-2*'Engine Inputs'!$B$7*SQRT(MIN((D26+(MIN(D26/$B$10,'Engine Inputs'!$B$9)*($B$9-'Engine Inputs'!$B$5-'Engine Inputs'!$B$6-2*'Engine Inputs'!$B$7*SQRT(MIN(D26/$B$10,'Engine Inputs'!$B$9)/'Engine Inputs'!$B$8))+MAX(D26-MIN(D26/$B$10,'Engine Inputs'!$B$9)*$B$10,0)*'Engine Inputs'!$B$10/2)*(1-$B$8))/$B$10,'Engine Inputs'!$B$9)/'Engine Inputs'!$B$8))+MAX((D26+(MIN(D26/$B$10,'Engine Inputs'!$B$9)*($B$9-'Engine Inputs'!$B$5-'Engine Inputs'!$B$6-2*'Engine Inputs'!$B$7*SQRT(MIN(D26/$B$10,'Engine Inputs'!$B$9)/'Engine Inputs'!$B$8))+MAX(D26-MIN(D26/$B$10,'Engine Inputs'!$B$9)*$B$10,0)*'Engine Inputs'!$B$10/2)*(1-$B$8))-MIN((D26+(MIN(D26/$B$10,'Engine Inputs'!$B$9)*($B$9-'Engine Inputs'!$B$5-'Engine Inputs'!$B$6-2*'Engine Inputs'!$B$7*SQRT(MIN(D26/$B$10,'Engine Inputs'!$B$9)/'Engine Inputs'!$B$8))+MAX(D26-MIN(D26/$B$10,'Engine Inputs'!$B$9)*$B$10,0)*'Engine Inputs'!$B$10/2)*(1-$B$8))/$B$10,'Engine Inputs'!$B$9)*$B$10,0)*'Engine Inputs'!$B$10/2)*(1-$B$8)-INDEX('Rebuilt Scenarios'!$C$11:$C$25,A27)*(1-$B$8),$B$5) -> 1000000000 | E27: =IF(E26>0,E26+(($B$6*E26-$B$7)*(12/18))*(1-$B$8),0)+MAX((D26+(MIN(D26/$B$10,'Engine Inputs'!$B$9)*($B$9-'Engine Inputs'!$B$5-'Engine Inputs'!$B$6-2*'Engine Inputs'!$B$7*SQRT(MIN(D26/$B$10,'Engine Inputs'!$B$9)/'Engine Inputs'!$B$8))+MAX(D26-MIN(D26/$B$10,'Engine Inputs'!$B$9)*$B$10,0)*'Engine Inputs'!$B$10/2)*(1-$B$8))+(MIN((D26+(MIN(D26/$B$10,'Engine Inputs'!$B$9)*($B$9-'Engine Inputs'!$B$5-'Engine Inputs'!$B$6-2*'Engine Inputs'!$B$7*SQRT(MIN(D26/$B$10,'Engine Inputs'!$B$9)/'Engine Inputs'!$B$8))+MAX(D26-MIN(D26/$B$10,'Engine Inputs'!$B$9)*$B$10,0)*'Engine Inputs'!$B$10/2)*(1-$B$8))/$B$10,'Engine Inputs'!$B$9)*($B$9-'Engine Inputs'!$B$5-'Engine Inputs'!$B$6-2*'Engine Inputs'!$B$7*SQRT(MIN((D26+(MIN(D26/$B$10,'Engine Inputs'!$B$9)*($B$9-'Engine Inputs'!$B$5-'Engine Inputs'!$B$6-2*'Engine Inputs'!$B$7*SQRT(MIN(D26/$B$10,'Engine Inputs'!$B$9)/'Engine Inputs'!$B$8))+MAX(D26-MIN(D26/$B$10,'Engine Inputs'!$B$9)*$B$10,0)*'Engine Inputs'!$B$10/2)*(1-$B$8))/$B$10,'Engine Inputs'!$B$9)/'Engine Inputs'!$B$8))+MAX((D26+(MIN(D26/$B$10,'Engine Inputs'!$B$9)*($B$9-'Engine Inputs'!$B$5-'Engine Inputs'!$B$6-2*'Engine Inputs'!$B$7*SQRT(MIN(D26/$B$10,'Engine Inputs'!$B$9)/'Engine Inputs'!$B$8))+MAX(D26-MIN(D26/$B$10,'Engine Inputs'!$B$9)*$B$10,0)*'Engine Inputs'!$B$10/2)*(1-$B$8))-MIN((D26+(MIN(D26/$B$10,'Engine Inputs'!$B$9)*($B$9-'Engine Inputs'!$B$5-'Engine Inputs'!$B$6-2*'Engine Inputs'!$B$7*SQRT(MIN(D26/$B$10,'Engine Inputs'!$B$9)/'Engine Inputs'!$B$8))+MAX(D26-MIN(D26/$B$10,'Engine Inputs'!$B$9)*$B$10,0)*'Engine Inputs'!$B$10/2)*(1-$B$8))/$B$10,'Engine Inputs'!$B$9)*$B$10,0)*'Engine Inputs'!$B$10/2)*(1-$B$8)-INDEX('Rebuilt Scenarios'!$C$11:$C$25,A27)*(1-$B$8)-$B$5,0) -> 4.1756829e+10 | F27: =D27+E27 -> 4.2756829e+10
... A29: 15 | B29: =(B28+(MIN(B28/$B$10,'Engine Inputs'!$B$9)*($B$9-'Engine Inputs'!$B$5-'Engine Inputs'!$B$6-2*'Engine Inputs'!$B$7*SQRT(MIN(B28/$B$10,'Engine Inputs'!$B$9)/'Engine Inputs'!$B$8))+MAX(B28-MIN(B28/$B$10,'Engine Inputs'!$B$9)*$B$10,0)*'Engine Inputs'!$B$10/2)*(1-$B$8))+(MIN((B28+(MIN(B28/$B$10,'Engine Inputs'!$B$9)*($B$9-'Engine Inputs'!$B$5-'Engine Inputs'!$B$6-2*'Engine Inputs'!$B$7*SQRT(MIN(B28/$B$10,'Engine Inputs'!$B$9)/'Engine Inputs'!$B$8))+MAX(B28-MIN(B28/$B$10,'Engine Inputs'!$B$9)*$B$10,0)*'Engine Inputs'!$B$10/2)*(1-$B$8))/$B$10,'Engine Inputs'!$B$9)*($B$9-'Engine Inputs'!$B$5-'Engine Inputs'!$B$6-2*'Engine Inputs'!$B$7*SQRT(MIN((B28+(MIN(B28/$B$10,'Engine Inputs'!$B$9)*($B$9-'Engine Inputs'!$B$5-'Engine Inputs'!$B$6-2*'Engine Inputs'!$B$7*SQRT(MIN(B28/$B$10,'Engine Inputs'!$B$9)/'Engine Inputs'!$B$8))+MAX(B28-MIN(B28/$B$10,'Engine Inputs'!$B$9)*$B$10,0)*'Engine Inputs'!$B$10/2)*(1-$B$8))/$B$10,'Engine Inputs'!$B$9)/'Engine Inputs'!$B$8))+MAX((B28+(MIN(B28/$B$10,'Engine Inputs'!$B$9)*($B$9-'Engine Inputs'!$B$5-'Engine Inputs'!$B$6-2*'Engine Inputs'!$B$7*SQRT(MIN(B28/$B$10,'Engine Inputs'!$B$9)/'Engine Inputs'!$B$8))+MAX(B28-MIN(B28/$B$10,'Engine Inputs'!$B$9)*$B$10,0)*'Engine Inputs'!$B$10/2)*(1-$B$8))-MIN((B28+(MIN(B28/$B$10,'Engine Inputs'!$B$9)*($B$9-'Engine Inputs'!$B$5-'Engine Inputs'!$B$6-2*'Engine Inputs'!$B$7*SQRT(MIN(B28/$B$10,'Engine Inputs'!$B$9)/'Engine Inputs'!$B$8))+MAX(B28-MIN(B28/$B$10,'Engine Inputs'!$B$9)*$B$10,0)*'Engine Inputs'!$B$10/2)*(1-$B$8))/$B$10,'Engine Inputs'!$B$9)*$B$10,0)*'Engine Inputs'!$B$10/2)*(1-$B$8)-INDEX('Rebuilt Scenarios'!$C$11:$C$25,A29)*(1-$B$8) -> 1.7474952e+10 | C29: =IF(C28<'Engine Inputs'!$B$11,(C28+(MIN(C28/$B$10,'Engine Inputs'!$B$9)*($B$9-'Engine Inputs'!$B$5-'Engine Inputs'!$B$6-2*'Engine Inputs'!$B$7*SQRT(MIN(C28/$B$10,'Engine Inputs'!$B$9)/'Engine Inputs'!$B$8))+MAX(C28-MIN(C28/$B$10,'Engine Inputs'!$B$9)*$B$10,0)*'Engine Inputs'!$B$10/2)*(1-$B$8))+(MIN((C28+(MIN(C28/$B$10,'Engine Inputs'!$B$9)*($B$9-'Engine Inputs'!$B$5-'Engine Inputs'!$B$6-2*'Engine Inputs'!$B$7*SQRT(MIN(C28/$B$10,'Engine Inputs'!$B$9)/'Engine Inputs'!$B$8))+MAX(C28-MIN(C28/$B$10,'Engine Inputs'!$B$9)*$B$10,0)*'Engine Inputs'!$B$10/2)*(1-$B$8))/$B$10,'Engine Inputs'!$B$9)*($B$9-'Engine Inputs'!$B$5-'Engine Inputs'!$B$6-2*'Engine Inputs'!$B$7*SQRT(MIN((C28+(MIN(C28/$B$10,'Engine Inputs'!$B$9)*($B$9-'Engine Inputs'!$B$5-'Engine Inputs'!$B$6-2*'Engine Inputs'!$B$7*SQRT(MIN(C28/$B$10,'Engine Inputs'!$B$9)/'Engine Inputs'!$B$8))+MAX(C28-MIN(C28/$B$10,'Engine Inputs'!$B$9)*$B$10,0)*'Engine Inputs'!$B$10/2)*(1-$B$8))/$B$10,'Engine Inputs'!$B$9)/'Engine Inputs'!$B$8))+MAX((C28+(MIN(C28/$B$10,'Engine Inputs'!$B$9)*($B$9-'Engine Inputs'!$B$5-'Engine Inputs'!$B$6-2*'Engine Inputs'!$B$7*SQRT(MIN(C28/$B$10,'Engine Inputs'!$B$9)/'Engine Inputs'!$B$8))+MAX(C28-MIN(C28/$B$10,'Engine Inputs'!$B$9)*$B$10,0)*'Engine Inputs'!$B$10/2)*(1-$B$8))-MIN((C28+(MIN(C28/$B$10,'Engine Inputs'!$B$9)*($B$9-'Engine Inputs'!$B$5-'Engine Inputs'!$B$6-2*'Engine Inputs'!$B$7*SQRT(MIN(C28/$B$10,'Engine Inputs'!$B$9)/'Engine Inputs'!$B$8))+MAX(C28-MIN(C28/$B$10,'Engine Inputs'!$B$9)*$B$10,0)*'Engine Inputs'!$B$10/2)*(1-$B$8))/$B$10,'Engine Inputs'!$B$9)*$B$10,0)*'Engine Inputs'!$B$10/2)*(1-$B$8)-INDEX('Rebuilt Scenarios'!$C$11:$C$25,A29)*(1-$B$8),C28+(($B$6*C28-$B$7)*(12/18))*(1-$B$8)) -> 1.3901249e+10 | D29: =MIN((D28+(MIN(D28/$B$10,'Engine Inputs'!$B$9)*($B$9-'Engine Inputs'!$B$5-'Engine Inputs'!$B$6-2*'Engine Inputs'!$B$7*SQRT(MIN(D28/$B$10,'Engine Inputs'!$B$9)/'Engine Inputs'!$B$8))+MAX(D28-MIN(D28/$B$10,'Engine Inputs'!$B$9)*$B$10,0)*'Engine Inputs'!$B$10/2)*(1-$B$8))+(MIN((D28+(MIN(D28/$B$10,'Engine Inputs'!$B$9)*($B$9-'Engine Inputs'!$B$5-'Engine Inputs'!$B$6-2*'Engine Inputs'!$B$7*SQRT(MIN(D28/$B$10,'Engine Inputs'!$B$9)/'Engine Inputs'!$B$8))+MAX(D28-MIN(D28/$B$10,'Engine Inputs'!$B$9)*$B$10,0)*'Engine Inputs'!$B$10/2)*(1-$B$8))/$B$10,'Engine Inputs'!$B$9)*($B$9-'Engine Inputs'!$B$5-'Engine Inputs'!$B$6-2*'Engine Inputs'!$B$7*SQRT(MIN((D28+(MIN(D28/$B$10,'Engine Inputs'!$B$9)*($B$9-'Engine Inputs'!$B$5-'Engine Inputs'!$B$6-2*'Engine Inputs'!$B$7*SQRT(MIN(D28/$B$10,'Engine Inputs'!$B$9)/'Engine Inputs'!$B$8))+MAX(D28-MIN(D28/$B$10,'Engine Inputs'!$B$9)*$B$10,0)*'Engine Inputs'!$B$10/2)*(1-$B$8))/$B$10,'Engine Inputs'!$B$9)/'Engine Inputs'!$B$8))+MAX((D28+(MIN(D28/$B$10,'Engine Inputs'!$B$9)*($B$9-'Engine Inputs'!$B$5-'Engine Inputs'!$B$6-2*'Engine Inputs'!$B$7*SQRT(MIN(D28/$B$10,'Engine Inputs'!$B$9)/'Engine Inputs'!$B$8))+MAX(D28-MIN(D28/$B$10,'Engine Inputs'!$B$9)*$B$10,0)*'Engine Inputs'!$B$10/2)*(1-$B$8))-MIN((D28+(MIN(D28/$B$10,'Engine Inputs'!$B$9)*($B$9-'Engine Inputs'!$B$5-'Engine Inputs'!$B$6-2*'Engine Inputs'!$B$7*SQRT(MIN(D28/$B$10,'Engine Inputs'!$B$9)/'Engine Inputs'!$B$8))+MAX(D28-MIN(D28/$B$10,'Engine Inputs'!$B$9)*$B$10,0)*'Engine Inputs'!$B$10/2)*(1-$B$8))/$B$10,'Engine Inputs'!$B$9)*$B$10,0)*'Engine Inputs'!$B$10/2)*(1-$B$8)-INDEX('Rebuilt Scenarios'!$C$11:$C$25,A29)*(1-$B$8),$B$5) -> 1000000000 | E29: =IF(E28>0,E28+(($B$6*E28-$B$7)*(12/18))*(1-$B$8),0)+MAX((D28+(MIN(D28/$B$10,'Engine Inputs'!$B$9)*($B$9-'Engine Inputs'!$B$5-'Engine Inputs'!$B$6-2*'Engine Inputs'!$B$7*SQRT(MIN(D28/$B$10,'Engine Inputs'!$B$9)/'Engine Inputs'!$B$8))+MAX(D28-MIN(D28/$B$10,'Engine Inputs'!$B$9)*$B$10,0)*'Engine Inputs'!$B$10/2)*(1-$B$8))+(MIN((D28+(MIN(D28/$B$10,'Engine Inputs'!$B$9)*($B$9-'Engine Inputs'!$B$5-'Engine Inputs'!$B$6-2*'Engine Inputs'!$B$7*SQRT(MIN(D28/$B$10,'Engine Inputs'!$B$9)/'Engine Inputs'!$B$8))+MAX(D28-MIN(D28/$B$10,'Engine Inputs'!$B$9)*$B$10,0)*'Engine Inputs'!$B$10/2)*(1-$B$8))/$B$10,'Engine Inputs'!$B$9)*($B$9-'Engine Inputs'!$B$5-'Engine Inputs'!$B$6-2*'Engine Inputs'!$B$7*SQRT(MIN((D28+(MIN(D28/$B$10,'Engine Inputs'!$B$9)*($B$9-'Engine Inputs'!$B$5-'Engine Inputs'!$B$6-2*'Engine Inputs'!$B$7*SQRT(MIN(D28/$B$10,'Engine Inputs'!$B$9)/'Engine Inputs'!$B$8))+MAX(D28-MIN(D28/$B$10,'Engine Inputs'!$B$9)*$B$10,0)*'Engine Inputs'!$B$10/2)*(1-$B$8))/$B$10,'Engine Inputs'!$B$9)/'Engine Inputs'!$B$8))+MAX((D28+(MIN(D28/$B$10,'Engine Inputs'!$B$9)*($B$9-'Engine Inputs'!$B$5-'Engine Inputs'!$B$6-2*'Engine Inputs'!$B$7*SQRT(MIN(D28/$B$10,'Engine Inputs'!$B$9)/'Engine Inputs'!$B$8))+MAX(D28-MIN(D28/$B$10,'Engine Inputs'!$B$9)*$B$10,0)*'Engine Inputs'!$B$10/2)*(1-$B$8))-MIN((D28+(MIN(D28/$B$10,'Engine Inputs'!$B$9)*($B$9-'Engine Inputs'!$B$5-'Engine Inputs'!$B$6-2*'Engine Inputs'!$B$7*SQRT(MIN(D28/$B$10,'Engine Inputs'!$B$9)/'Engine Inputs'!$B$8))+MAX(D28-MIN(D28/$B$10,'Engine Inputs'!$B$9)*$B$10,0)*'Engine Inputs'!$B$10/2)*(1-$B$8))/$B$10,'Engine Inputs'!$B$9)*$B$10,0)*'Engine Inputs'!$B$10/2)*(1-$B$8)-INDEX('Rebuilt Scenarios'!$C$11:$C$25,A29)*(1-$B$8)-$B$5,0) -> 8.1878009e+10 | F29: =D29+E29 -> 8.2878009e+10
A31: Year-15 terminal (₹ Cr): | B31: =B29/10000000 -> 1747.4952 | C31: =C29/10000000 -> 1390.1249 | F31: =F29/10000000 -> 8287.8009
A32: Wealth destroyed by stubbornly staying vs hybrid (× factor): | B32: =F29/B29 -> 4.7426746

Sheet Global Shipping Tax & Exec
A1: GLOBAL SHIPPING · TAX & EXECUTION MODEL
A2: BDRY-focused stretched accumulation → SGX / ICE FFA handoff · all rupee figures in ₹ Crore · exit-leg capacity binding · fully reactive
A4: CONTROL BLOCK — blue cells are editable inputs
A5: Starting capital (₹ Cr) | B5: 2 | C5: Cycle 1 start
A6: Gross return per cycle | B6: 1.5 | C6: Macro trend capture (yours)
A7: Cycle length (months) | B7: 18 | C7: <24 ⇒ STCG slabs; ≥24 ⇒ LTCG 12.5%, surcharge cap 15%
A8: Corporate inflection threshold (₹ Cr) | B8: 20 | C8: TAX/FEMA wrapper switch only
A9: USD/INR | B9: 94.98
A10: Corporate tax rate (115BAA) | B10: 0.25168 | C10: IFSC s.80LA holiday possible — kept conservative
A11: Corporate expense per cycle (₹ Cr) | B11: 0.5 | C11: Deductible only in corporate phase
A12: BDRY safe $/day — CURRENT regime | B12: 82683 | C12: bdry_liquidity.csv, 90-day mean of tiered Safe Liquidity
A13: BDRY safe $/day — HOT regime | B13: 352235 | C13: Top-quartile rolling-90d windows since 2018
A14: BDRY safe $/day — PEAK (Jul-2021) | B14: 662516 | C14: Reference only
A15: Regime toggle (0=current, 1=hot) | B15: 0 | C15: Hot = freight upswing, volumes ~4× current
A16: Build window — entry (days) | B16: 45 | C16: 1–1.5 month stretched accumulation
A17: Exit window assumed similar (days) | B17: 45 | C17: Round trip ≈ 90 trading days exposure
A18: FFA capacity per position ($) | B18: 60000000 | C18: SGX/ICE Cape 5TC + Pmx 4TC — verify with FCM
A19: LTCG base (unlisted foreign ≥24m) | B19: 0.125
A20: STCG top base rate (slab) | B20: 0.3 | C20: New Tax Regime
A21: Cess | B21: 0.04
A23: DERIVED CAPACITY — reactive, computed from the control block
A24: BDRY safe $/day in force | B24: =IF(B15=1,B13,B12) -> 82683
A25: BDRY position capacity ($) | B25: =B24*B16 -> 3720735
A26: BDRY position capacity (₹ Cr) | B26: =B25*B9/10000000 -> 35.339541
A27: FFA position capacity (₹ Cr) | B27: =B18*B9/10000000 -> 569.88
A28: Idle-capital yield (NG engine link) | B28: ='Engine Inputs'!B10 -> 0.065
A29: ENTRY ceilings (exit leg binds): BDRY / FFA (₹ Cr) | B29: =B26/(1+B6) -> 14.135816 | C29: =B27/(1+B6) -> 227.952
A30: SURCHARGE TIERS — New Tax Regime (VLOOKUP on gain ₹ Cr)
A31: TAX PARAMETERS — New-Regime surcharge tiers · LTCG cap
A32: 0 | B32: 0 | C32: =$B$20*(1+B32)*(1+$B$21) -> 0.312
A33: 0.5 | B33: 0.1 | C33: =$B$20*(1+B33)*(1+$B$21) -> 0.3432
A34: 1 | B34: 0.15 | C34: =$B$20*(1+B34)*(1+$B$21) -> 0.3588
A35: 2 | B35: 0.25 | C35: =$B$20*(1+B35)*(1+$B$21) -> 0.39
A36: LTCG surcharge cap (s.112) | B36: 0.15
A38: CYCLE LEDGER (₹ Cr) — instrument switches when corpus clears the BDRY exit ceiling · wrapper at ₹20 Cr
A39: Cycle | B39: Start ₹Cr | C39: Wrapper (FEMA gate) | D39: Instrument | E39: Capacity ₹Cr | F39: Deployed ₹Cr | G39: Idle ₹Cr | H39: Gross gain ₹Cr | I39: Expense ₹Cr (corp) | J39: Taxable ₹Cr | K39: Regime | L39: Eff. tax rate | M39: Tax ₹Cr | N39: End ₹Cr | O39: End USD
A40: 1 | B40: =$B$5 -> 2 | C40: =IF(B40>=$B$8,"GIFT FIF (IFSC) Corp","Individual LRS") -> Individual LRS | D40: =IF(B40>$B$29,"SGX/ICE FFA blocks","BDRY (45-day iceberg)") -> BDRY (45-day iceberg) | E40: =IF(B40>$B$29,$C$29,$B$29) -> 14.135816 | F40: =MIN(B40,E40) -> 2 | G40: =B40-F40 -> 0 | H40: =F40*$B$6+G40*$B$28*$B$7/12 -> 3 | I40: =IF(B40>=$B$8,$B$11,0) -> 0 | J40: =MAX(H40-I40,0) -> 3 | K40: =IF(B40>=$B$8,"115BAA corp",IF($B$7>=24,"LTCG 112 (12.5%)","STCG @ slab")) -> STCG @ slab | L40: =IF(B40>=$B$8,$B$10,IF($B$7>=24,$B$19*(1+MIN(VLOOKUP(J40,$A$32:$B$35,2),$B$36))*(1+$B$21),$B$20*(1+VLOOKUP(J40,$A$32:$B$35,2))*(1+$B$21))) -> 0.39 | M40: =J40*L40 -> 1.17 | N40: =B40+H40-I40-M40 -> 3.83 | O40: =N40*10000000/$B$9 -> 403242.79
A41: 2 | B41: =N40 -> 3.83 | C41: =IF(B41>=$B$8,"GIFT FIF (IFSC) Corp","Individual LRS") -> Individual LRS | D41: =IF(B41>$B$29,"SGX/ICE FFA blocks","BDRY (45-day iceberg)") -> BDRY (45-day iceberg) | E41: =IF(B41>$B$29,$C$29,$B$29) -> 14.135816 | F41: =MIN(B41,E41) -> 3.83 | G41: =B41-F41 -> 0 | H41: =F41*$B$6+G41*$B$28*$B$7/12 -> 5.745 | I41: =IF(B41>=$B$8,$B$11,0) -> 0 | J41: =MAX(H41-I41,0) -> 5.745 | K41: =IF(B41>=$B$8,"115BAA corp",IF($B$7>=24,"LTCG 112 (12.5%)","STCG @ slab")) -> STCG @ slab | L41: =IF(B41>=$B$8,$B$10,IF($B$7>=24,$B$19*(1+MIN(VLOOKUP(J41,$A$32:$B$35,2),$B$36))*(1+$B$21),$B$20*(1+VLOOKUP(J41,$A$32:$B$35,2))*(1+$B$21))) -> 0.39 | M41: =J41*L41 -> 2.24055 | N41: =B41+H41-I41-M41 -> 7.33445 | O41: =N41*10000000/$B$9 -> 772209.94
A42: 3 | B42: =N41 -> 7.33445 | C42: =IF(B42>=$B$8,"GIFT FIF (IFSC) Corp","Individual LRS") -> Individual LRS | D42: =IF(B42>$B$29,"SGX/ICE FFA blocks","BDRY (45-day iceberg)") -> BDRY (45-day iceberg) | E42: =IF(B42>$B$29,$C$29,$B$29) -> 14.135816 | F42: =MIN(B42,E42) -> 7.33445 | G42: =B42-F42 -> 0 | H42: =F42*$B$6+G42*$B$28*$B$7/12 -> 11.001675 | I42: =IF(B42>=$B$8,$B$11,0) -> 0 | J42: =MAX(H42-I42,0) -> 11.001675 | K42: =IF(B42>=$B$8,"115BAA corp",IF($B$7>=24,"LTCG 112 (12.5%)","STCG @ slab")) -> STCG @ slab | L42: =IF(B42>=$B$8,$B$10,IF($B$7>=24,$B$19*(1+MIN(VLOOKUP(J42,$A$32:$B$35,2),$B$36))*(1+$B$21),$B$20*(1+VLOOKUP(J42,$A$32:$B$35,2))*(1+$B$21))) -> 0.39 | M42: =J42*L42 -> 4.2906533 | N42: =B42+H42-I42-M42 -> 14.045472 | O42: =N42*10000000/$B$9 -> 1478782
A43: 4 | B43: =N42 -> 14.045472 | C43: =IF(B43>=$B$8,"GIFT FIF (IFSC) Corp","Individual LRS") -> Individual LRS | D43: =IF(B43>$B$29,"SGX/ICE FFA blocks","BDRY (45-day iceberg)") -> BDRY (45-day iceberg) | E43: =IF(B43>$B$29,$C$29,$B$29) -> 14.135816 | F43: =MIN(B43,E43) -> 14.045472 | G43: =B43-F43 -> 0 | H43: =F43*$B$6+G43*$B$28*$B$7/12 -> 21.068208 | I43: =IF(B43>=$B$8,$B$11,0) -> 0 | J43: =MAX(H43-I43,0) -> 21.068208 | K43: =IF(B43>=$B$8,"115BAA corp",IF($B$7>=24,"LTCG 112 (12.5%)","STCG @ slab")) -> STCG @ slab | L43: =IF(B43>=$B$8,$B$10,IF($B$7>=24,$B$19*(1+MIN(VLOOKUP(J43,$A$32:$B$35,2),$B$36))*(1+$B$21),$B$20*(1+VLOOKUP(J43,$A$32:$B$35,2))*(1+$B$21))) -> 0.39 | M43: =J43*L43 -> 8.216601 | N43: =B43+H43-I43-M43 -> 26.897078 | O43: =N43*10000000/$B$9 -> 2831867.6
A44: 5 | B44: =N43 -> 26.897078 | C44: =IF(B44>=$B$8,"GIFT FIF (IFSC) Corp","Individual LRS") -> GIFT FIF (IFSC) Corp | D44: =IF(B44>$B$29,"SGX/ICE FFA blocks","BDRY (45-day iceberg)") -> SGX/ICE FFA blocks | E44: =IF(B44>$B$29,$C$29,$B$29) -> 227.952 | F44: =MIN(B44,E44) -> 26.897078 | G44: =B44-F44 -> 0 | H44: =F44*$B$6+G44*$B$28*$B$7/12 -> 40.345618 | I44: =IF(B44>=$B$8,$B$11,0) -> 0.5 | J44: =MAX(H44-I44,0) -> 39.845618 | K44: =IF(B44>=$B$8,"115BAA corp",IF($B$7>=24,"LTCG 112 (12.5%)","STCG @ slab")) -> 115BAA corp | L44: =IF(B44>=$B$8,$B$10,IF($B$7>=24,$B$19*(1+MIN(VLOOKUP(J44,$A$32:$B$35,2),$B$36))*(1+$B$21),$B$20*(1+VLOOKUP(J44,$A$32:$B$35,2))*(1+$B$21))) -> 0.25168 | M44: =J44*L44 -> 10.028345 | N44: =B44+H44-I44-M44 -> 56.714351 | O44: =N44*10000000/$B$9 -> 5971188.8
A45: 6 | B45: =N44 -> 56.714351 | C45: =IF(B45>=$B$8,"GIFT FIF (IFSC) Corp","Individual LRS") -> GIFT FIF (IFSC) Corp | D45: =IF(B45>$B$29,"SGX/ICE FFA blocks","BDRY (45-day iceberg)") -> SGX/ICE FFA blocks | E45: =IF(B45>$B$29,$C$29,$B$29) -> 227.952 | F45: =MIN(B45,E45) -> 56.714351 | G45: =B45-F45 -> 0 | H45: =F45*$B$6+G45*$B$28*$B$7/12 -> 85.071526 | I45: =IF(B45>=$B$8,$B$11,0) -> 0.5 | J45: =MAX(H45-I45,0) -> 84.571526 | K45: =IF(B45>=$B$8,"115BAA corp",IF($B$7>=24,"LTCG 112 (12.5%)","STCG @ slab")) -> 115BAA corp | L45: =IF(B45>=$B$8,$B$10,IF($B$7>=24,$B$19*(1+MIN(VLOOKUP(J45,$A$32:$B$35,2),$B$36))*(1+$B$21),$B$20*(1+VLOOKUP(J45,$A$32:$B$35,2))*(1+$B$21))) -> 0.25168 | M45: =J45*L45 -> 21.284962 | N45: =B45+H45-I45-M45 -> 120.00092 | O45: =N45*10000000/$B$9 -> 12634335
A46: 7 | B46: =N45 -> 120.00092 | C46: =IF(B46>=$B$8,"GIFT FIF (IFSC) Corp","Individual LRS") -> GIFT FIF (IFSC) Corp | D46: =IF(B46>$B$29,"SGX/ICE FFA blocks","BDRY (45-day iceberg)") -> SGX/ICE FFA blocks | E46: =IF(B46>$B$29,$C$29,$B$29) -> 227.952 | F46: =MIN(B46,E46) -> 120.00092 | G46: =B46-F46 -> 0 | H46: =F46*$B$6+G46*$B$28*$B$7/12 -> 180.00137 | I46: =IF(B46>=$B$8,$B$11,0) -> 0.5 | J46: =MAX(H46-I46,0) -> 179.50137 | K46: =IF(B46>=$B$8,"115BAA corp",IF($B$7>=24,"LTCG 112 (12.5%)","STCG @ slab")) -> 115BAA corp | L46: =IF(B46>=$B$8,$B$10,IF($B$7>=24,$B$19*(1+MIN(VLOOKUP(J46,$A$32:$B$35,2),$B$36))*(1+$B$21),$B$20*(1+VLOOKUP(J46,$A$32:$B$35,2))*(1+$B$21))) -> 0.25168 | M46: =J46*L46 -> 45.176906 | N46: =B46+H46-I46-M46 -> 254.32538 | O46: =N46*10000000/$B$9 -> 26776730
A47: 8 | B47: =N46 -> 254.32538 | C47: =IF(B47>=$B$8,"GIFT FIF (IFSC) Corp","Individual LRS") -> GIFT FIF (IFSC) Corp | D47: =IF(B47>$B$29,"SGX/ICE FFA blocks","BDRY (45-day iceberg)") -> SGX/ICE FFA blocks | E47: =IF(B47>$B$29,$C$29,$B$29) -> 227.952 | F47: =MIN(B47,E47) -> 227.952 | G47: =B47-F47 -> 26.373383 | H47: =F47*$B$6+G47*$B$28*$B$7/12 -> 344.4994 | I47: =IF(B47>=$B$8,$B$11,0) -> 0.5 | J47: =MAX(H47-I47,0) -> 343.9994 | K47: =IF(B47>=$B$8,"115BAA corp",IF($B$7>=24,"LTCG 112 (12.5%)","STCG @ slab")) -> 115BAA corp | L47: =IF(B47>=$B$8,$B$10,IF($B$7>=24,$B$19*(1+MIN(VLOOKUP(J47,$A$32:$B$35,2),$B$36))*(1+$B$21),$B$20*(1+VLOOKUP(J47,$A$32:$B$35,2))*(1+$B$21))) -> 0.25168 | M47: =J47*L47 -> 86.57777 | N47: =B47+H47-I47-M47 -> 511.74702 | O47: =N47*10000000/$B$9 -> 53879450
A48: 9 | B48: =N47 -> 511.74702 | C48: =IF(B48>=$B$8,"GIFT FIF (IFSC) Corp","Individual LRS") -> GIFT FIF (IFSC) Corp | D48: =IF(B48>$B$29,"SGX/ICE FFA blocks","BDRY (45-day iceberg)") -> SGX/ICE FFA blocks | E48: =IF(B48>$B$29,$C$29,$B$29) -> 227.952 | F48: =MIN(B48,E48) -> 227.952 | G48: =B48-F48 -> 283.79502 | H48: =F48*$B$6+G48*$B$28*$B$7/12 -> 369.59801 | I48: =IF(B48>=$B$8,$B$11,0) -> 0.5 | J48: =MAX(H48-I48,0) -> 369.09801 | K48: =IF(B48>=$B$8,"115BAA corp",IF($B$7>=24,"LTCG 112 (12.5%)","STCG @ slab")) -> 115BAA corp | L48: =IF(B48>=$B$8,$B$10,IF($B$7>=24,$B$19*(1+MIN(VLOOKUP(J48,$A$32:$B$35,2),$B$36))*(1+$B$21),$B$20*(1+VLOOKUP(J48,$A$32:$B$35,2))*(1+$B$21))) -> 0.25168 | M48: =J48*L48 -> 92.894588 | N48: =B48+H48-I48-M48 -> 787.95044 | O48: =N48*10000000/$B$9 -> 82959617
A49: 10 | B49: =N48 -> 787.95044 | C49: =IF(B49>=$B$8,"GIFT FIF (IFSC) Corp","Individual LRS") -> GIFT FIF (IFSC) Corp | D49: =IF(B49>$B$29,"SGX/ICE FFA blocks","BDRY (45-day iceberg)") -> SGX/ICE FFA blocks | E49: =IF(B49>$B$29,$C$29,$B$29) -> 227.952 | F49: =MIN(B49,E49) -> 227.952 | G49: =B49-F49 -> 559.99844 | H49: =F49*$B$6+G49*$B$28*$B$7/12 -> 396.52785 | I49: =IF(B49>=$B$8,$B$11,0) -> 0.5 | J49: =MAX(H49-I49,0) -> 396.02785 | K49: =IF(B49>=$B$8,"115BAA corp",IF($B$7>=24,"LTCG 112 (12.5%)","STCG @ slab")) -> 115BAA corp | L49: =IF(B49>=$B$8,$B$10,IF($B$7>=24,$B$19*(1+MIN(VLOOKUP(J49,$A$32:$B$35,2),$B$36))*(1+$B$21),$B$20*(1+VLOOKUP(J49,$A$32:$B$35,2))*(1+$B$21))) -> 0.25168 | M49: =J49*L49 -> 99.672289 | N49: =B49+H49-I49-M49 -> 1084.306 | O49: =N49*10000000/$B$9 -> 1.1416151e+08
A50: 11 | B50: =N49 -> 1084.306 | C50: =IF(B50>=$B$8,"GIFT FIF (IFSC) Corp","Individual LRS") -> GIFT FIF (IFSC) Corp | D50: =IF(B50>$B$29,"SGX/ICE FFA blocks","BDRY (45-day iceberg)") -> SGX/ICE FFA blocks | E50: =IF(B50>$B$29,$C$29,$B$29) -> 227.952 | F50: =MIN(B50,E50) -> 227.952 | G50: =B50-F50 -> 856.354 | H50: =F50*$B$6+G50*$B$28*$B$7/12 -> 425.42252 | I50: =IF(B50>=$B$8,$B$11,0) -> 0.5 | J50: =MAX(H50-I50,0) -> 424.92252 | K50: =IF(B50>=$B$8,"115BAA corp",IF($B$7>=24,"LTCG 112 (12.5%)","STCG @ slab")) -> 115BAA corp | L50: =IF(B50>=$B$8,$B$10,IF($B$7>=24,$B$19*(1+MIN(VLOOKUP(J50,$A$32:$B$35,2),$B$36))*(1+$B$21),$B$20*(1+VLOOKUP(J50,$A$32:$B$35,2))*(1+$B$21))) -> 0.25168 | M50: =J50*L50 -> 106.9445 | N50: =B50+H50-I50-M50 -> 1402.284 | O50: =N50*10000000/$B$9 -> 1.4763993e+08
A51: 12 | B51: =N50 -> 1402.284 | C51: =IF(B51>=$B$8,"GIFT FIF (IFSC) Corp","Individual LRS") -> GIFT FIF (IFSC) Corp | D51: =IF(B51>$B$29,"SGX/ICE FFA blocks","BDRY (45-day iceberg)") -> SGX/ICE FFA blocks | E51: =IF(B51>$B$29,$C$29,$B$29) -> 227.952 | F51: =MIN(B51,E51) -> 227.952 | G51: =B51-F51 -> 1174.332 | H51: =F51*$B$6+G51*$B$28*$B$7/12 -> 456.42537 | I51: =IF(B51>=$B$8,$B$11,0) -> 0.5 | J51: =MAX(H51-I51,0) -> 455.92537 | K51: =IF(B51>=$B$8,"115BAA corp",IF($B$7>=24,"LTCG 112 (12.5%)","STCG @ slab")) -> 115BAA corp | L51: =IF(B51>=$B$8,$B$10,IF($B$7>=24,$B$19*(1+MIN(VLOOKUP(J51,$A$32:$B$35,2),$B$36))*(1+$B$21),$B$20*(1+VLOOKUP(J51,$A$32:$B$35,2))*(1+$B$21))) -> 0.25168 | M51: =J51*L51 -> 114.7473 | N51: =B51+H51-I51-M51 -> 1743.4621 | O51: =N51*10000000/$B$9 -> 1.8356097e+08
